[{"Author":"Rienecker, Michele M. (GSFC-6101)","Content-Length":"3317176","Content-Type":"application/pdf","Creation-Date":"2012-11-23T21:17:44Z","Keywords":"","Last-Modified":"2012-11-23T21:17:44Z","Last-Save-Date":"2012-11-23T21:17:44Z","X-Parsed-By":["org.apache.tika.parser.CompositeParser","org.apache.tika.parser.journal.JournalParser"],"X-TIKA:content":"\u003chtml xmlns\u003d\"http://www.w3.org/1999/xhtml\"\u003e\n\u003chead\u003e\n\u003cmeta name\u003d\"date\" content\u003d\"2012-11-23T21:17:44Z\" /\u003e\n\u003cmeta name\u003d\"pdf:PDFVersion\" content\u003d\"1.4\" /\u003e\n\u003cmeta name\u003d\"xmp:CreatorTool\" content\u003d\"Word\" /\u003e\n\u003cmeta name\u003d\"grobid:header_Class\" content\u003d\"org.apache.tika.metadata.Metadata\" /\u003e\n\u003cmeta name\u003d\"Keywords\" content\u003d\"\" /\u003e\n\u003cmeta name\u003d\"access_permission:modify_annotations\" content\u003d\"true\" /\u003e\n\u003cmeta name\u003d\"access_permission:can_print_degraded\" content\u003d\"true\" /\u003e\n\u003cmeta name\u003d\"subject\" content\u003d\"\" /\u003e\n\u003cmeta name\u003d\"grobid:header_TEIJSONSource\" content\u003d\"{\u0026quot;TEI\u0026quot;:{\u0026quot;xmlns\u0026quot;:\u0026quot;http://www.tei-c.org/ns/1.0\u0026quot;,\u0026quot;teiHeader\u0026quot;:{\u0026quot;xml:lang\u0026quot;:\u0026quot;en\u0026quot;,\u0026quot;profileDesc\u0026quot;:{\u0026quot;abstract\u0026quot;:\u0026quot;\u0026quot;},\u0026quot;encodingDesc\u0026quot;:{\u0026quot;appInfo\u0026quot;:{\u0026quot;application\u0026quot;:{\u0026quot;ref\u0026quot;:{\u0026quot;content\u0026quot;:\u0026quot;GROBID - A machine learning software for extracting information from scholarly documents\u0026quot;,\u0026quot;target\u0026quot;:\u0026quot;https://github.com/kermitt2/grobid\u0026quot;},\u0026quot;ident\u0026quot;:\u0026quot;GROBID\u0026quot;,\u0026quot;version\u0026quot;:\u0026quot;0.4.1\u0026quot;,\u0026quot;when\u0026quot;:\u0026quot;2016-03-25T04:57+0000\u0026quot;}}},\u0026quot;fileDesc\u0026quot;:{\u0026quot;titleStmt\u0026quot;:{\u0026quot;title\u0026quot;:{\u0026quot;level\u0026quot;:\u0026quot;a\u0026quot;,\u0026quot;type\u0026quot;:\u0026quot;main\u0026quot;,\u0026quot;content\u0026quot;:\u0026quot;Earth System Modeling and Field Experiments in the Arctic-­\\u2010Boreal Zone NASA Workshop Report\u0026quot;}},\u0026quot;sourceDesc\u0026quot;:{\u0026quot;biblStruct\u0026quot;:{\u0026quot;analytic\u0026quot;:{\u0026quot;author\u0026quot;:[{\u0026quot;affiliation\u0026quot;:{\u0026quot;orgName\u0026quot;:{\u0026quot;type\u0026quot;:\u0026quot;laboratory\u0026quot;,\u0026quot;content\u0026quot;:\u0026quot;National Aeronautics and Space Administration\u0026quot;}},\u0026quot;persName\u0026quot;:{\u0026quot;forename\u0026quot;:{\u0026quot;type\u0026quot;:\u0026quot;first\u0026quot;,\u0026quot;content\u0026quot;:\u0026quot;Piers\u0026quot;},\u0026quot;surname\u0026quot;:\u0026quot;Sellers\u0026quot;}},{\u0026quot;affiliation\u0026quot;:{\u0026quot;orgName\u0026quot;:{\u0026quot;type\u0026quot;:\u0026quot;laboratory\u0026quot;,\u0026quot;content\u0026quot;:\u0026quot;National Aeronautics and Space Administration\u0026quot;}},\u0026quot;persName\u0026quot;:{\u0026quot;forename\u0026quot;:{\u0026quot;type\u0026quot;:\u0026quot;first\u0026quot;,\u0026quot;content\u0026quot;:\u0026quot;Michele\u0026quot;},\u0026quot;surname\u0026quot;:\u0026quot;Rienecker\u0026quot;}},{\u0026quot;affiliation\u0026quot;:{\u0026quot;orgName\u0026quot;:{\u0026quot;type\u0026quot;:\u0026quot;laboratory\u0026quot;,\u0026quot;content\u0026quot;:\u0026quot;National Aeronautics and Space Administration\u0026quot;}},\u0026quot;persName\u0026quot;:{\u0026quot;forename\u0026quot;:{\u0026quot;type\u0026quot;:\u0026quot;first\u0026quot;,\u0026quot;content\u0026quot;:\u0026quot;Steve\u0026quot;},\u0026quot;surname\u0026quot;:\u0026quot;Frolking\u0026quot;}},{\u0026quot;affiliation\u0026quot;:{\u0026quot;orgName\u0026quot;:{\u0026quot;type\u0026quot;:\u0026quot;laboratory\u0026quot;,\u0026quot;content\u0026quot;:\u0026quot;National Aeronautics and Space Administration\u0026quot;}},\u0026quot;persName\u0026quot;:{\u0026quot;forename\u0026quot;:{\u0026quot;type\u0026quot;:\u0026quot;first\u0026quot;,\u0026quot;content\u0026quot;:\u0026quot;David\u0026quot;},\u0026quot;surname\u0026quot;:\u0026quot;Randall\u0026quot;}}],\u0026quot;title\u0026quot;:{\u0026quot;level\u0026quot;:\u0026quot;a\u0026quot;,\u0026quot;type\u0026quot;:\u0026quot;main\u0026quot;,\u0026quot;content\u0026quot;:\u0026quot;Earth System Modeling and Field Experiments in the Arctic-­\\u2010Boreal Zone NASA Workshop Report\u0026quot;}},\u0026quot;monogr\u0026quot;:{\u0026quot;imprint\u0026quot;:{\u0026quot;date\u0026quot;:{\u0026quot;type\u0026quot;:\u0026quot;published\u0026quot;,\u0026quot;content\u0026quot;:\u0026quot;22-­\\u201024 May 2012 November 2012\u0026quot;}}}}},\u0026quot;publicationStmt\u0026quot;:{\u0026quot;date\u0026quot;:\u0026quot;22-­\\u201024 May 2012 November 2012\u0026quot;,\u0026quot;publisher\u0026quot;:\u0026quot;\u0026quot;,\u0026quot;availability\u0026quot;:{\u0026quot;licence\u0026quot;:\u0026quot;\u0026quot;,\u0026quot;status\u0026quot;:\u0026quot;unknown\u0026quot;}}}},\u0026quot;xsi:schemaLocation\u0026quot;:\u0026quot;http://www.tei-c.org/ns/1.0 /Users/Shashank/src/grobid/grobid-home/schemas/xsd/Grobid.xsd\u0026quot;,\u0026quot;xmlns:xlink\u0026quot;:\u0026quot;http://www.w3.org/1999/xlink\u0026quot;,\u0026quot;xmlns:xsi\u0026quot;:\u0026quot;http://www.w3.org/2001/XMLSchema-instance\u0026quot;,\u0026quot;text\u0026quot;:{\u0026quot;xml:lang\u0026quot;:\u0026quot;en\u0026quot;}}}\" /\u003e\n\u003cmeta name\u003d\"dc:creator\" content\u003d\"Rienecker, Michele M. (GSFC-6101)\" /\u003e\n\u003cmeta name\u003d\"dcterms:created\" content\u003d\"2012-11-23T21:17:44Z\" /\u003e\n\u003cmeta name\u003d\"Last-Modified\" content\u003d\"2012-11-23T21:17:44Z\" /\u003e\n\u003cmeta name\u003d\"dcterms:modified\" content\u003d\"2012-11-23T21:17:44Z\" /\u003e\n\u003cmeta name\u003d\"dc:format\" content\u003d\"application/pdf; version\u003d1.4\" /\u003e\n\u003cmeta name\u003d\"Last-Save-Date\" content\u003d\"2012-11-23T21:17:44Z\" /\u003e\n\u003cmeta name\u003d\"access_permission:fill_in_form\" content\u003d\"true\" /\u003e\n\u003cmeta name\u003d\"grobid:header_Title\" content\u003d\"Earth System Modeling and Field Experiments in the Arctic-­‐Boreal Zone NASA Workshop Report\" /\u003e\n\u003cmeta name\u003d\"meta:save-date\" content\u003d\"2012-11-23T21:17:44Z\" /\u003e\n\u003cmeta name\u003d\"grobid:header_Address\" content\u003d\"null, null null null \" /\u003e\n\u003cmeta name\u003d\"pdf:encrypted\" content\u003d\"false\" /\u003e\n\u003cmeta name\u003d\"dc:title\" content\u003d\"Microsoft Word - ABZ_Workshop_Report_Draft_Nov23.docx\" /\u003e\n\u003cmeta name\u003d\"modified\" content\u003d\"2012-11-23T21:17:44Z\" /\u003e\n\u003cmeta name\u003d\"grobid:header_FullAffiliations\" content\u003d\"[Affiliation {orgName\u003d, address\u003dnull, null null null}[Affiliation {orgName\u003d, address\u003dnull, null null null}]\" /\u003e\n\u003cmeta name\u003d\"Content-Length\" content\u003d\"3317176\" /\u003e\n\u003cmeta name\u003d\"Content-Type\" content\u003d\"application/pdf\" /\u003e\n\u003cmeta name\u003d\"X-Parsed-By\" content\u003d\"org.apache.tika.parser.CompositeParser\" /\u003e\n\u003cmeta name\u003d\"X-Parsed-By\" content\u003d\"org.apache.tika.parser.journal.JournalParser\" /\u003e\n\u003cmeta name\u003d\"grobid:header_Authors\" content\u003d\"Piers  Sellers 1 Michele  Rienecker 1 Steve  Frolking 1 David  Randall 1 \" /\u003e\n\u003cmeta name\u003d\"creator\" content\u003d\"Rienecker, Michele M. (GSFC-6101)\" /\u003e\n\u003cmeta name\u003d\"meta:author\" content\u003d\"Rienecker, Michele M. (GSFC-6101)\" /\u003e\n\u003cmeta name\u003d\"dc:subject\" content\u003d\"\" /\u003e\n\u003cmeta name\u003d\"grobid:header_Affiliation\" content\u003d\"1\" /\u003e\n\u003cmeta name\u003d\"meta:creation-date\" content\u003d\"2012-11-23T21:17:44Z\" /\u003e\n\u003cmeta name\u003d\"created\" content\u003d\"Fri Nov 23 13:17:44 PST 2012\" /\u003e\n\u003cmeta name\u003d\"access_permission:extract_for_accessibility\" content\u003d\"true\" /\u003e\n\u003cmeta name\u003d\"access_permission:assemble_document\" content\u003d\"true\" /\u003e\n\u003cmeta name\u003d\"xmpTPg:NPages\" content\u003d\"74\" /\u003e\n\u003cmeta name\u003d\"Creation-Date\" content\u003d\"2012-11-23T21:17:44Z\" /\u003e\n\u003cmeta name\u003d\"resourceName\" content\u003d\"DC83BF75177C2A4828762BA4E8362E24117BB624D8EC510CF56A2DF347450194\" /\u003e\n\u003cmeta name\u003d\"grobid:header_TEIXMLSource\" content\u003d\"\u0026lt;?xml version\u003d\u0026quot;1.0\u0026quot; encoding\u003d\u0026quot;UTF-8\u0026quot;?\u0026gt;\n\u0026lt;TEI xmlns\u003d\u0026quot;http://www.tei-c.org/ns/1.0\u0026quot; \nxmlns:xsi\u003d\u0026quot;http://www.w3.org/2001/XMLSchema-instance\u0026quot; \nxsi:schemaLocation\u003d\u0026quot;http://www.tei-c.org/ns/1.0 /Users/Shashank/src/grobid/grobid-home/schemas/xsd/Grobid.xsd\u0026quot;\n xmlns:xlink\u003d\u0026quot;http://www.w3.org/1999/xlink\u0026quot;\u0026gt;\n\t\u0026lt;teiHeader xml:lang\u003d\u0026quot;en\u0026quot;\u0026gt;\n\t\t\u0026lt;encodingDesc\u0026gt;\n\t\t\t\u0026lt;appInfo\u0026gt;\n\t\t\t\t\u0026lt;application version\u003d\u0026quot;0.4.1\u0026quot; ident\u003d\u0026quot;GROBID\u0026quot; when\u003d\u0026quot;2016-03-25T04:57+0000\u0026quot;\u0026gt;\n\t\t\t\t\t\u0026lt;ref target\u003d\u0026quot;https://github.com/kermitt2/grobid\u0026quot;\u0026gt;GROBID - A machine learning software for extracting information from scholarly documents\u0026lt;/ref\u0026gt;\n\t\t\t\t\u0026lt;/application\u0026gt;\n\t\t\t\u0026lt;/appInfo\u0026gt;\n\t\t\u0026lt;/encodingDesc\u0026gt;\n\t\t\u0026lt;fileDesc\u0026gt;\n\t\t\t\u0026lt;titleStmt\u0026gt;\n\t\t\t\t\u0026lt;title level\u003d\u0026quot;a\u0026quot; type\u003d\u0026quot;main\u0026quot;\u0026gt;Earth System Modeling and Field Experiments in the Arctic-­‐Boreal Zone NASA Workshop Report\u0026lt;/title\u0026gt;\n\t\t\t\u0026lt;/titleStmt\u0026gt;\n\t\t\t\u0026lt;publicationStmt\u0026gt;\n\t\t\t\t\u0026lt;publisher/\u0026gt;\n\t\t\t\t\u0026lt;availability status\u003d\u0026quot;unknown\u0026quot;\u0026gt;\u0026lt;licence/\u0026gt;\u0026lt;/availability\u0026gt;\n\t\t\t\t\u0026lt;date\u0026gt;22-­‐24 May 2012 November 2012\u0026lt;/date\u0026gt;\n\t\t\t\u0026lt;/publicationStmt\u0026gt;\n\t\t\t\u0026lt;sourceDesc\u0026gt;\n\t\t\t\t\u0026lt;biblStruct\u0026gt;\n\t\t\t\t\t\u0026lt;analytic\u0026gt;\n\t\t\t\t\t\t\u0026lt;author\u0026gt;\n\t\t\t\t\t\t\t\u0026lt;persName\u0026gt;\n\t\t\t\t\t\t\t\t\u0026lt;forename type\u003d\u0026quot;first\u0026quot;\u0026gt;Piers\u0026lt;/forename\u0026gt;\n\t\t\t\t\t\t\t\t\u0026lt;surname\u0026gt;Sellers\u0026lt;/surname\u0026gt;\n\t\t\t\t\t\t\t\u0026lt;/persName\u0026gt;\n\t\t\t\t\t\t\t\u0026lt;affiliation\u0026gt;\n\t\t\t\t\t\t\t\t\u0026lt;orgName type\u003d\u0026quot;laboratory\u0026quot;\u0026gt;National Aeronautics and Space Administration\u0026lt;/orgName\u0026gt;\n\t\t\t\t\t\t\t\u0026lt;/affiliation\u0026gt;\n\t\t\t\t\t\t\u0026lt;/author\u0026gt;\n\t\t\t\t\t\t\u0026lt;author\u0026gt;\n\t\t\t\t\t\t\t\u0026lt;persName\u0026gt;\n\t\t\t\t\t\t\t\t\u0026lt;forename type\u003d\u0026quot;first\u0026quot;\u0026gt;Michele\u0026lt;/forename\u0026gt;\n\t\t\t\t\t\t\t\t\u0026lt;surname\u0026gt;Rienecker\u0026lt;/surname\u0026gt;\n\t\t\t\t\t\t\t\u0026lt;/persName\u0026gt;\n\t\t\t\t\t\t\t\u0026lt;affiliation\u0026gt;\n\t\t\t\t\t\t\t\t\u0026lt;orgName type\u003d\u0026quot;laboratory\u0026quot;\u0026gt;National Aeronautics and Space Administration\u0026lt;/orgName\u0026gt;\n\t\t\t\t\t\t\t\u0026lt;/affiliation\u0026gt;\n\t\t\t\t\t\t\u0026lt;/author\u0026gt;\n\t\t\t\t\t\t\u0026lt;author\u0026gt;\n\t\t\t\t\t\t\t\u0026lt;persName\u0026gt;\n\t\t\t\t\t\t\t\t\u0026lt;forename type\u003d\u0026quot;first\u0026quot;\u0026gt;Steve\u0026lt;/forename\u0026gt;\n\t\t\t\t\t\t\t\t\u0026lt;surname\u0026gt;Frolking\u0026lt;/surname\u0026gt;\n\t\t\t\t\t\t\t\u0026lt;/persName\u0026gt;\n\t\t\t\t\t\t\t\u0026lt;affiliation\u0026gt;\n\t\t\t\t\t\t\t\t\u0026lt;orgName type\u003d\u0026quot;laboratory\u0026quot;\u0026gt;National Aeronautics and Space Administration\u0026lt;/orgName\u0026gt;\n\t\t\t\t\t\t\t\u0026lt;/affiliation\u0026gt;\n\t\t\t\t\t\t\u0026lt;/author\u0026gt;\n\t\t\t\t\t\t\u0026lt;author\u0026gt;\n\t\t\t\t\t\t\t\u0026lt;persName\u0026gt;\n\t\t\t\t\t\t\t\t\u0026lt;forename type\u003d\u0026quot;first\u0026quot;\u0026gt;David\u0026lt;/forename\u0026gt;\n\t\t\t\t\t\t\t\t\u0026lt;surname\u0026gt;Randall\u0026lt;/surname\u0026gt;\n\t\t\t\t\t\t\t\u0026lt;/persName\u0026gt;\n\t\t\t\t\t\t\t\u0026lt;affiliation\u0026gt;\n\t\t\t\t\t\t\t\t\u0026lt;orgName type\u003d\u0026quot;laboratory\u0026quot;\u0026gt;National Aeronautics and Space Administration\u0026lt;/orgName\u0026gt;\n\t\t\t\t\t\t\t\u0026lt;/affiliation\u0026gt;\n\t\t\t\t\t\t\u0026lt;/author\u0026gt;\n\t\t\t\t\t\t\u0026lt;title level\u003d\u0026quot;a\u0026quot; type\u003d\u0026quot;main\u0026quot;\u0026gt;Earth System Modeling and Field Experiments in the Arctic-­‐Boreal Zone NASA Workshop Report\u0026lt;/title\u0026gt;\n\t\t\t\t\t\u0026lt;/analytic\u0026gt;\n\t\t\t\t\t\u0026lt;monogr\u0026gt;\n\t\t\t\t\t\t\u0026lt;imprint\u0026gt;\n\t\t\t\t\t\t\t\u0026lt;date type\u003d\u0026quot;published\u0026quot;\u0026gt;22-­‐24 May 2012 November 2012\u0026lt;/date\u0026gt;\n\t\t\t\t\t\t\u0026lt;/imprint\u0026gt;\n\t\t\t\t\t\u0026lt;/monogr\u0026gt;\n\t\t\t\t\u0026lt;/biblStruct\u0026gt;\n\t\t\t\u0026lt;/sourceDesc\u0026gt;\n\t\t\u0026lt;/fileDesc\u0026gt;\n\t\t\u0026lt;profileDesc\u0026gt;\n\t\t\t\u0026lt;abstract/\u0026gt;\n\t\t\u0026lt;/profileDesc\u0026gt;\n\t\u0026lt;/teiHeader\u0026gt;\n\t\u0026lt;text xml:lang\u003d\u0026quot;en\u0026quot;\u0026gt;\n\t\u0026lt;/text\u0026gt;\n\u0026lt;/TEI\u0026gt;\n\" /\u003e\n\u003cmeta name\u003d\"access_permission:extract_content\" content\u003d\"true\" /\u003e\n\u003cmeta name\u003d\"access_permission:can_print\" content\u003d\"true\" /\u003e\n\u003cmeta name\u003d\"meta:keyword\" content\u003d\"\" /\u003e\n\u003cmeta name\u003d\"Author\" content\u003d\"Rienecker, Michele M. (GSFC-6101)\" /\u003e\n\u003cmeta name\u003d\"producer\" content\u003d\"Mac OS X 10.7.5 Quartz PDFContext\" /\u003e\n\u003cmeta name\u003d\"access_permission:can_modify\" content\u003d\"true\" /\u003e\n\u003ctitle\u003eMicrosoft Word - ABZ_Workshop_Report_Draft_Nov23.docx\u003c/title\u003e\n\u003c/head\u003e\n\u003cbody\u003e\u003cdiv class\u003d\"page\"\u003e\u003cp /\u003e\n\u003cp\u003e\t\r  \n\t\r  \n\u003c/p\u003e\n\u003cp\u003e\t\r  \t\r  \nEarth\t\r  System\t\r  Modeling\t\r  and\t\r  Field\t\r  Experiments\t\r  in\t\r  \nthe\t\r  Arctic-­‐Boreal\t\r  Zone\t\r  \n\u003c/p\u003e\n\u003cp\u003e\t\r  \nNASA\t\r  Workshop\t\r  Report\t\r  \n\u003c/p\u003e\n\u003cp\u003e22-­‐24\t\r  May\t\r  2012\t\r  \n\u003c/p\u003e\n\u003cp\u003e\t\r  \nPiers\t\r  Sellers,\t\r  Michele\t\r  Rienecker,\t\r  Steve\t\r  Frolking,\t\r  David\t\r  Randall\t\r  \t\r  \t\r  \t\r  \t\r  \t\r  \t\r  \t\r  \t\r  National\t\r  Aeronautics\t\r  and\t\r  Space\t\r  Administration\t\r   \t\r  \nNovember\t\r  2012\t\r  \n\u003c/p\u003e\n\u003cp\u003e\t\r  \u003c/p\u003e\n\u003cp /\u003e\n\u003c/div\u003e\n\u003cdiv class\u003d\"page\"\u003e\u003cp /\u003e\n\u003cp\u003e\t\r  \n\t\r  \n\t\r  \n\u003c/p\u003e\n\u003cp\u003e\t\r  \n\t\r   \t\r  \u003c/p\u003e\n\u003cp /\u003e\n\u003c/div\u003e\n\u003cdiv class\u003d\"page\"\u003e\u003cp /\u003e\n\u003cp\u003e\t\r  \nEarth\t\r  System\t\r  Modeling\t\r  and\t\r  Field\t\r  Experiments\t\r  in\t\r  \nthe\t\r  Arctic-­‐Boreal\t\r  Zone\t\r  \n\u003c/p\u003e\n\u003cp\u003e\t\r  \nNASA\t\r  Workshop\t\r  Report\t\r  \n\u003c/p\u003e\n\u003cp\u003e22-­‐24\t\r  May\t\r  2012\t\r  \n\u003c/p\u003e\n\u003cp\u003e\t\r  \nPiers\t\r  Sellers\t\r  \nNASA\t\r  Goddard\t\r  Space\t\r  Flight\t\r  Center,\t\r  Greenbelt,\t\r  Maryland\t\r  \n\u003c/p\u003e\n\u003cp\u003eMichele\t\r  Rienecker\t\r  \nNASA\t\r  Goddard\t\r  Space\t\r  Flight\t\r  Center,\t\r  Greenbelt,\t\r  Maryland\t\r  \n\u003c/p\u003e\n\u003cp\u003eSteve\t\r  Frolking\t\r  \nUniversity\t\r  of\t\r  New\t\r  Hampshire,\t\r  Durham,\t\r  New\t\r  Hampshire\t\r  \n\u003c/p\u003e\n\u003cp\u003eDavid\t\r  Randall\t\r  \nColorado\t\r  State\t\r  University,\t\r  Fort\t\r  Collins,\t\r  Colorado\t\r  \n\t\r  \n\u003c/p\u003e\n\u003cp\u003e\t\r  \t\r  \n\u003c/p\u003e\n\u003cp\u003e\t\r  \n\u003c/p\u003e\n\u003cp\u003e\t\r  \n\u003c/p\u003e\n\u003cp\u003e\t\r  National\t\r  Aeronautics\t\r  and\t\r  Space\t\r  Administration\t\r  \n\t\r  \t\r  \t\r  \nNovember\t\r  2012\t\r  \u003c/p\u003e\n\u003cp /\u003e\n\u003c/div\u003e\n\u003cdiv class\u003d\"page\"\u003e\u003cp /\u003e\n\u003cp\u003e\t\r  \u003c/p\u003e\n\u003cp\u003e\t\r   ii\t\r  \n\u003c/p\u003e\n\u003cp\u003e\t\r  \n\t\r  \n\t\r  \n\t\r  \n\t\r  \n\t\r  \n\t\r  \n\t\r  \n\t\r  \n\t\r  \n\t\r  \n\t\r  \n\t\r  \n\t\r  \n\t\r  \n\t\r  \n\t\r  \n\t\r  \n\t\r  \n\t\r  \n\t\r  \n\t\r  \n\t\r  \n \n \n\u003c/p\u003e\n\u003cp\u003eAvailable from: \n \n \n\u003c/p\u003e\n\u003cp\u003eNASA Center for AeroSpace Information                         National Technical Information Service \n7115 Standard Drive                                                                                      5285 Port Royal Road \nHanover, MD 21076-1320                                                                            Springfield, VA 22161\t\r    \u003c/p\u003e\n\u003cp /\u003e\n\u003c/div\u003e\n\u003cdiv class\u003d\"page\"\u003e\u003cp /\u003e\n\u003cp\u003e\t\r  \u003c/p\u003e\n\u003cp\u003e\t\r   iii\t\r  \n\u003c/p\u003e\n\u003cp\u003eTable\t\r  of\t\r  Contents\t\r  \nEXECUTIVE\t\r  SUMMARY\t\r  ........................................................................................................................................\t\r  V\t\r  \n1\t\r   INTRODUCTION\t\r  .............................................................................................................................................\t\r  1\t\r  1.1\t\r   WORKSHOP\t\r  ORGANIZATION\t\r  ........................................................................................................................................\t\r  3\t\r  \n2\t\r   PREDICTIVE\t\r  MODELS\t\r  \t\r  -­‐\t\r  STATUS\t\r  AND\t\r  GAPS\t\r  .........................................................................................\t\r  4\t\r  2.1\t\r   CLOUDS,\t\r  AEROSOLS,\t\r  RADIATION,\t\r  AND\t\r  THE\t\r  PLANETARY\t\r  BOUNDARY\t\r  LAYER\t\r  .....................................................\t\r  4\t\r  2.2\t\r   OCEAN\t\r  AND\t\r  SEA\t\r  ICE\t\r  –\t\r  PHYSICAL\t\r  CLIMATE\t\r  SYSTEM\t\r  ...............................................................................................\t\r  9\t\r  2.3\t\r   OCEAN\t\r  AND\t\r  SEA\t\r  ICE\t\r  –\t\r  BIOGEOCHEMISTRY\t\r  ............................................................................................................\t\r  10\t\r  2.4\t\r   LAND\t\r  SURFACE\t\r  –\t\r  CLIMATOLOGY\t\r  AND\t\r  HYDROLOGY\t\r  .............................................................................................\t\r  12\t\r  \n\u003c/p\u003e\n\u003cp\u003e2.4.1\t\r   Land\t\r  surface\t\r  energy\t\r  and\t\r  freshwater\t\r  budgets\t\r  .........................................................................................\t\r  12\t\r  \n2.4.2\t\r   Snow\t\r  ..........................................................................................................................................................................\t\r  13\t\r  \n2.4.3\t\r   Permafrost\t\r  ..............................................................................................................................................................\t\r  13\t\r  \n2.4.4\t\r   Lakes,\t\r  wetlands\t\r  and\t\r  rivers\t\r  ..............................................................................................................................\t\r  15\t\r  \n2.4.5\t\r   Sub-­‐grid\t\r  heterogeneity\t\r  ......................................................................................................................................\t\r  15\t\r  2.5\t\r   LAND\t\r  SURFACE\t\r  –\t\r  BIOGEOCHEMISTRY\t\r  .....................................................................................................................\t\r  16\t\r  \n2.5.1\t\r   Soils\t\r  ............................................................................................................................................................................\t\r  16\t\r  \n2.5.2\t\r   Disturbance\t\r  ............................................................................................................................................................\t\r  17\t\r  \n2.5.3\t\r   Ecosystem\t\r  dynamics\t\r  ...........................................................................................................................................\t\r  19\t\r  2.6\t\r   INTEGRATED\t\r  SYSTEMS,\t\r  CARBON\t\r  CYCLE,\t\r  AND\t\r  SCALING\t\r  METHODOLOGIES\t\r  ......................................................\t\r  20\t\r  \n2.6.1\t\r   Land\t\r  surface\t\r  hydrology\t\r  and\t\r  carbon\t\r  cycle\t\r  ................................................................................................\t\r  21\t\r  \n2.6.2\t\r   Marine\t\r  processes,\t\r  land-­‐ocean\t\r  exchanges\t\r  and\t\r  carbon\t\r  cycle\t\r  .............................................................\t\r  21\t\r  \n2.6.3\t\r   Trace\t\r  gas\t\r  concentrations\t\r  and\t\r  fluxes\t\r  ...........................................................................................................\t\r  22\t\r  \n2.6.4\t\r   Flux\t\r  estimation\t\r  and\t\r  evaluation:\t\r  inverse\t\r  modeling,\t\r  upscaling\t\r  and\t\r  downscaling\t\r  ....................\t\r  23\t\r  \n\u003c/p\u003e\n\u003cp\u003e3\t\r   KEY\t\r  QUESTIONS\t\r  TO\t\r  BE\t\r  ADDRESSED\t\r  ...................................................................................................\t\r  24\t\r  \n4\t\r   PROPOSED\t\r  FIELD\t\r  EXPERIMENTS\t\r  AND\t\r  STUDIES\t\r  .............................................................................\t\r  25\t\r  4.1\t\r   FIELD\t\r  CAMPAIGNS\t\r  –\t\r  REQUIREMENTS\t\r  AND\t\r  INITIAL\t\r  IDEAS\t\r  FOR\t\r  NEW\t\r  ACTIVITIES\t\r  .............................................\t\r  25\t\r  \n\u003c/p\u003e\n\u003cp\u003e4.1.1\t\r   Clouds,\t\r  aerosols\t\r  and\t\r  radiation\t\r  .......................................................................................................................\t\r  25\t\r  \n4.1.2\t\r   Ocean\t\r  circulation\t\r  and\t\r  sea\t\r  ice\t\r  .........................................................................................................................\t\r  25\t\r  \n4.1.3\t\r   Integrated\t\r  systems,\t\r  land\t\r  surface\t\r  hydrology,\t\r  and\t\r  carbon\t\r  cycle\t\r  .......................................................\t\r  26\t\r  \n4.1.4\t\r   Biogeochemical\t\r  cycles\t\r  .......................................................................................................................................\t\r  26\t\r  4.2\t\r   REMOTE\t\r  SENSING\t\r  CONTRIBUTIONS\t\r  .........................................................................................................................\t\r  28\t\r  4.3\t\r   PROPOSED\t\r  AND\t\r  RELATED\t\r  ONGOING\t\r  ACTIVITIES\t\r  AND\t\r  LEVERAGING\t\r  OPPORTUNITIES\t\r  ..................................\t\r  30\t\r  4.4\t\r   OTHER\t\r  ACTIVITIES\t\r  ......................................................................................................................................................\t\r  34\t\r  \n4.4.1\t\r   Model\t\r  development,\t\r  diagnostics,\t\r  and\t\r  assimilation\t\r  ...............................................................................\t\r  34\t\r  \n4.4.2\t\r   Observations:\t\r  analyses,\t\r  data\t\r  products\t\r  and\t\r  data\t\r  mining\t\r  ...................................................................\t\r  35\t\r  \n4.4.3\t\r   Model\t\r  input\t\r  to\t\r  planning\t\r  of\t\r  new\t\r  observations\t\r  and\t\r  field\t\r  campaigns\t\r  ..............................................\t\r  36\t\r  \n4.4.4\t\r   Integrative\t\r  assessments\t\r  ....................................................................................................................................\t\r  36\t\r  \n\u003c/p\u003e\n\u003cp\u003e5\t\r   NEXT\t\r  STEPS\t\r  .................................................................................................................................................\t\r  36\t\r  \n6\t\r   REFERENCES\t\r  ................................................................................................................................................\t\r  37\t\r  \nAPPENDIX\t\r  A:\t\r  ACRONYMS\t\r  ................................................................................................................................\t\r  46\t\r  \nAPPENDIX\t\r  B:\t\r  RELEVANT\t\r  FIELD\t\r  CAMPAIGNS\t\r  AND\t\r  MEASUREMENT\t\r  PROGRAMS\t\r  .........................\t\r  49\t\r  \nAPPENDIX\t\r  C:\t\r  CONTRIBUTORS\t\r  TO\t\r  THIS\t\r  REPORT\t\r  ....................................................................................\t\r  56\t\r  \nAPPENDIX\t\r  D:\t\r  WORKSHOP\t\r  AGENDA\t\r  ............................................................................................................\t\r  57\t\r  \nAPPENDIX\t\r  D:\t\r  WORKSHOP\t\r  ATTENDEES\t\r  .....................................................................................................\t\r  58\t\r  \u003c/p\u003e\n\u003cp /\u003e\n\u003c/div\u003e\n\u003cdiv class\u003d\"page\"\u003e\u003cp /\u003e\n\u003cp\u003e\t\r  \u003c/p\u003e\n\u003cp\u003e\t\r   iv\t\r  \n\u003c/p\u003e\n\u003cp\u003e\t\r  \t\r   \t\r  \u003c/p\u003e\n\u003cp /\u003e\n\u003c/div\u003e\n\u003cdiv class\u003d\"page\"\u003e\u003cp /\u003e\n\u003cp\u003e\t\r  \u003c/p\u003e\n\u003cp\u003e\t\r   v\t\r  \n\u003c/p\u003e\n\u003cp\u003eExecutive\t\r  Summary\t\r  Climate\t\r  model\t\r  calculations\t\r  performed\t\r  in\t\r  the\t\r  1980s\t\r  predicted\t\r  that\t\r  the\t\r  Arctic\t\r  Ocean\t\r  and\t\r  surrounding\t\r  circumpolar\t\r  land\t\r  masses\t\r  would\t\r  warm\t\r  earlier\t\r  and\t\r  faster\t\r  than\t\r  other\t\r  parts\t\r  of\t\r  the\t\r  planet\t\r  as\t\r  a\t\r  result\t\r  of\t\r  greenhouse\t\r  gas-­‐induced\t\r  climate\t\r  change,\t\r  augmented\t\r  by\t\r  the\t\r  sea-­‐ice\t\r  albedo\t\r  feedback\t\r  effect\t\r  (e.g.,\t\r  Manabe\t\r  and\t\r  Wetherald,\t\r  1975;\t\r  Hansen\t\r  et\t\r  al.,\t\r  1981;\t\r  1984).\t\r  These\t\r  predictions\t\r  have\t\r  been\t\r  largely\t\r  borne\t\r  out\t\r  by\t\r  observations\t\r  over\t\r  the\t\r  last\t\r  thirty\t\r  years\t\r  (e.g.,\t\r  Stroeve\t\r  et\t\r  al.,\t\r  2012;\t\r  Screen\t\r  and\t\r  Simmonds,\t\r  2010).\t\r  Nonetheless,\t\r  climate\t\r  models\t\r  vary\t\r  widely\t\r  in\t\r  their\t\r  warming\t\r  trajectories\t\r  over\t\r  the\t\r  21st\t\r  century.\t\r  \t\r  In\t\r  addition,\t\r  a\t\r  range\t\r  of\t\r  biogeochemical\t\r  cycle\t\r  (BGC)\t\r  models\t\r  indicate\t\r  that\t\r  Arctic-­‐Boreal\t\r  Zone\t\r  (ABZ)\t\r  warming\t\r  could\t\r  lead\t\r  to\t\r  widespread\t\r  permafrost\t\r  thaw,\t\r  which\t\r  could\t\r  contribute\t\r  around\t\r  90\t\r  ppm\t\r  CO2\t\r  to\t\r  the\t\r  atmospheric\t\r  CO2\t\r  burden\t\r  by\t\r  2100\t\r  (Schaefer\t\r  et\t\r  al.,\t\r  2011),\t\r  and\t\r  lead\t\r  to\t\r  significant\t\r  changes\t\r  in\t\r  the\t\r  vegetation\t\r  cover\t\r  in\t\r  the\t\r  ABZ\t\r  (e.g.,\t\r  Lawrence\t\r  and\t\r  Slater,\t\r  2005).\t\r  However,\t\r  the\t\r  uncertainties\t\r  associated\t\r  with\t\r  these\t\r  BGC\t\r  model\t\r  predictions\t\r  are\t\r  even\t\r  larger\t\r  than\t\r  those\t\r  associated\t\r  with\t\r  the\t\r  physical\t\r  climate\t\r  system\t\r  (PCS)\t\r  models\t\r  used\t\r  to\t\r  predict\t\r  climate\t\r  change.\t\r  A\t\r  workshop\t\r  was\t\r  held\t\r  at\t\r  NASA/GSFC,\t\r  May\t\r  22-­‐24\t\r  2012,\t\r  to\t\r  assess\t\r  the\t\r  predictive\t\r  capability\t\r  of\t\r  current\t\r  Earth\t\r  system\t\r  models\t\r  (ESMs),\t\r  prioritize\t\r  the\t\r  critical\t\r  science\t\r  questions\t\r  and\t\r  make\t\r  recommendations\t\r  regarding\t\r  new\t\r  field\t\r  experiments\t\r  that\t\r  would\t\r  contribute\t\r  to\t\r  important\t\r  improvements\t\r  in\t\r  model\t\r  subcomponents.\t\r  This\t\r  report\t\r  summarizes\t\r  the\t\r  findings\t\r  of\t\r  the\t\r  workshop\t\r  and\t\r  is\t\r  intended\t\r  to\t\r  provide\t\r  input\t\r  to\t\r  agency\t\r  program\t\r  managers\t\r  and\t\r  others\t\r  when\t\r  deciding\t\r  on\t\r  priorities\t\r  and\t\r  resource\t\r  allocations\t\r  for\t\r  field\t\r  experiments\t\r  in\t\r  the\t\r  ABZ\t\r  as\t\r  well\t\r  as\t\r  for\t\r  model\t\r  development\t\r  and\t\r  other\t\r  related\t\r  activities.\t\r  \nI. Key\t\r  Science\t\r  Questions\t\r  Critical\t\r  questions\t\r  to\t\r  guide\t\r  model\t\r  development\t\r  and\t\r  measurement\t\r  priorities\t\r  were\t\r  identified:\t\r  1. Clouds,\t\r  radiation\t\r  and\t\r  aerosols:\t\r  Are\t\r  the\t\r  observed\t\r  seasonal\t\r  changes\t\r  of\t\r  Arctic\t\r  clouds\t\r  primarily\t\r  determined\t\r  by\t\r  the\t\r  large-­‐scale\t\r  circulation\t\r  or\t\r  do\t\r  microphysical\t\r  and\t\r  surface\t\r  processes\t\r  play\t\r  a\t\r  key\t\r  role?\t\r  What\t\r  is\t\r  the\t\r  role\t\r  of\t\r  downwelling\t\r  infrared\t\r  radiation\t\r  in\t\r  the\t\r  surface\t\r  energy\t\r  budget\t\r  of\t\r  the\t\r  Arctic\t\r  Ocean\t\r  in\t\r  winter?\t\r  How\t\r  does\t\r  aerosol\t\r  forcing\t\r  affect\t\r  the\t\r  Arctic\t\r  climate,\t\r  and\t\r  how\t\r  will\t\r  aerosol\t\r  loadings\t\r  change\t\r  as\t\r  a\t\r  result\t\r  of\t\r  changes\t\r  in\t\r  land-­‐use,\t\r  industrial\t\r  emission,\t\r  desertification,\t\r  and\t\r  fire?\t\r  \t\r  2. Ocean\t\r  circulation\t\r  and\t\r  sea\t\r  ice:\t\r  What\t\r  are\t\r  the\t\r  processes\t\r  involved\t\r  in\t\r  melting\t\r  the\t\r  sea\t\r  ice\t\r  and\t\r  controlling\t\r  ocean\t\r  stratification\t\r  in\t\r  the\t\r  Beaufort\t\r  Sea?\t\r  3. Integrated\t\r  systems,\t\r  land\t\r  surface\t\r  hydrology,\t\r  and\t\r  carbon\t\r  cycle:\t\r  What\t\r  are\t\r  the\t\r  linkages\t\r  between\t\r  land\t\r  surface\t\r  hydrology,\t\r  vegetation\t\r  changes\t\r  and\t\r  the\t\r  surface\t\r  energy\t\r  budget\t\r  over\t\r  the\t\r  ABZ\t\r  and\t\r  how\t\r  will\t\r  these\t\r  influence\t\r  the\t\r  evolving\t\r  climate?\t\r  How,\t\r  and\t\r  how\t\r  rapidly,\t\r  is\t\r  the\t\r  ocean-­‐land\t\r  interface\t\r  changing\t\r  in\t\r  the\t\r  ABZ?\t\r  \t\r  4. Carbon\t\r  balance:\t\r  How\t\r  rapidly,\t\r  in\t\r  which\t\r  direction,\t\r  and\t\r  by\t\r  how\t\r  much\t\r  will\t\r  warming\t\r  and\t\r  changing\t\r  precipitation\t\r  modify\t\r  the\t\r  ABZ\t\r  net\t\r  carbon\t\r  balance?\t\r  Will\t\r  the\t\r  impact\t\r  on\t\r  net\t\r  CO2\t\r  exchange\t\r  be\t\r  smaller\t\r  or\t\r  larger\t\r  than\t\r  the\t\r  impact\t\r  on\t\r  net\t\r  CH4\t\r  exchange?\t\r  \t\r  \t\r  \nII. Model\t\r  Weaknesses\t\r  \n\u003c/p\u003e\n\u003cp\u003ePhysical\t\r  Climate\t\r  System\t\r  Clouds,\t\r  radiation\t\r  and\t\r  aerosols\t\r  (i) Poor\t\r  modeling\t\r  of\t\r  cloud\t\r  properties,\t\r  of\t\r  cloud\t\r  fraction\t\r  in\t\r  winter,\t\r  and\t\r  of\t\r  the\t\r  annual\t\r  cycle\t\r  of\t\r  cloudiness.\t\r  (ii) Poor\t\r  representation\t\r  of\t\r  mixed-­‐phase\t\r  clouds\t\r  in\t\r  the\t\r  Arctic,\t\r  leading\t\r  to\t\r  deficiencies\t\r  in\t\r  the\t\r  calculated\t\r  surface\t\r  radiation.\t\r  \u003c/p\u003e\n\u003cp /\u003e\n\u003c/div\u003e\n\u003cdiv class\u003d\"page\"\u003e\u003cp /\u003e\n\u003cp\u003e\t\r  \u003c/p\u003e\n\u003cp\u003e\t\r   vi\t\r  \n\u003c/p\u003e\n\u003cp\u003e(iii) Inadequate\t\r  modeling\t\r  of\t\r  microphysics,\t\r  particularly\t\r  ice\t\r  nucleation.\t\r  \t\r  (iv) Unreliable\t\r  modeling\t\r  of\t\r  the\t\r  seasonal\t\r  cycle\t\r  of\t\r  aerosols\t\r  due\t\r  to\t\r  inadequate\t\r  representation\t\r  of\t\r  wet\t\r  scavenging\t\r  as\t\r  well\t\r  as\t\r  poor\t\r  simulation\t\r  of\t\r  wintertime\t\r  low-­‐level\t\r  liquid\t\r  clouds.\t\r  \t\r  Oceans\t\r  and\t\r  Sea-­‐ice\t\r  (i) Models\t\r  have\t\r  inadequate\t\r  resolution\t\r  in\t\r  the\t\r  Arctic\t\r  Ocean,\t\r  with\t\r  resulting\t\r  impacts\t\r  on\t\r  the\t\r  accuracy\t\r  and\t\r  realism\t\r  of\t\r  the\t\r  calculated\t\r  circulation.\t\r  The\t\r  representation\t\r  of\t\r  narrow\t\r  coastal\t\r  currents\t\r  and\t\r  the\t\r  poleward\t\r  heat\t\r  and\t\r  freshwater\t\r  transports\t\r  are\t\r  particularly\t\r  affected.\t\r  Oceanic\t\r  mixing\t\r  and\t\r  heat\t\r  convergence\t\r  are\t\r  under-­‐represented.\t\r  (ii) Most\t\r  models\t\r  show\t\r  biases\t\r  in\t\r  atmospheric\t\r  circulation\t\r  and\t\r  precipitation,\t\r  impacting\t\r  the\t\r  representation\t\r  of\t\r  sea-­‐ice\t\r  distribution.\t\r  (iii) Parameterizations\t\r  of\t\r  surface\t\r  boundary\t\r  layers\t\r  and\t\r  air-­‐sea\t\r  interactions\t\r  are\t\r  deficient,\t\r  impacting\t\r  ice\t\r  melt\t\r  and\t\r  deep-­‐water\t\r  formation.\t\r  \t\r  Land\t\r  surface\t\r  climatology\t\r  and\t\r  hydrology\t\r  (i) The\t\r  representation\t\r  of\t\r  the\t\r  surface-­‐atmosphere\t\r  exchanges\t\r  of\t\r  energy,\t\r  momentum,\t\r  water\t\r  and\t\r  carbon\t\r  remain\t\r  unvalidated\t\r  at\t\r  intermediate\t\r  (1-­‐10km)\t\r  and\t\r  larger\t\r  \t\r  (ESM)\t\r  scales.\t\r  (ii) Snow\t\r  processes\t\r  could\t\r  be\t\r  represented\t\r  better.\t\r  In\t\r  particular,\t\r  wintertime\t\r  snowpack\t\r  simulations\t\r  are\t\r  too\t\r  deep,\t\r  over-­‐insulating\t\r  the\t\r  ground\t\r  below;\t\r  the\t\r  parameterized\t\r  relationships\t\r  between\t\r  unresolved\t\r  spatial\t\r  variability\t\r  and\t\r  snow\t\r  water\t\r  variables\t\r  are\t\r  very\t\r  crude;\t\r  and\t\r  albedo\t\r  parameterizations\t\r  do\t\r  not\t\r  adequately\t\r  treat\t\r  snow\t\r  aging\t\r  and\t\r  the\t\r  effects\t\r  of\t\r  deposited\t\r  constituents\t\r  (dust,\t\r  black\t\r  carbon).\t\r  \t\r  (iii) Permafrost\t\r  and\t\r  the\t\r  subgrid\t\r  distributions\t\r  of\t\r  freezing\t\r  soil\t\r  are\t\r  poorly\t\r  parameterized.\t\r  (iv) Lakes\t\r  are\t\r  represented\t\r  crudely.\t\r  (v) No\t\r  ESMs\t\r  have\t\r  incorporated\t\r  thermokarst\t\r  processes\t\r  as\t\r  yet.\t\r  \t\r  \t\r  \t\r  \nBiogeochemical\t\r  cycles\t\r  (i) The\t\r  representations\t\r  of\t\r  carbon\t\r  dynamics\t\r  in\t\r  BGC\t\r  models\t\r  have\t\r  large\t\r  uncertainties\t\r  in\t\r  their\t\r  parameter\t\r  values\t\r  and\t\r  they\t\r  lack\t\r  credible\t\r  methodologies\t\r  for\t\r  upscaling\t\r  from\t\r  the\t\r  local\t\r  scale\t\r  to\t\r  the\t\r  scales\t\r  appropriate\t\r  to\t\r  ESMs.\t\r  The\t\r  links\t\r  between\t\r  the\t\r  PCS\t\r  drivers\t\r  and\t\r  the\t\r  modeled\t\r  BGC\t\r  processes\t\r  need\t\r  to\t\r  be\t\r  verified.\t\r  (ii) Disturbance\t\r  is\t\r  not\t\r  represented\t\r  convincingly\t\r  in\t\r  any\t\r  ESM.\t\r  Few\t\r  models\t\r  consider\t\r  fire\t\r  emissions.\t\r  Others\t\r  do\t\r  so\t\r  in\t\r  simplistic\t\r  ways\t\r  that\t\r  do\t\r  not\t\r  capture\t\r  the\t\r  full\t\r  vulnerability\t\r  of\t\r  the\t\r  large\t\r  surface\t\r  carbon\t\r  stocks.\t\r  Disturbance\t\r  severity\t\r  needs\t\r  to\t\r  be\t\r  represented.\t\r  \t\r  (iii) The\t\r  use\t\r  of\t\r  vertically\t\r  integrated\t\r  soil\t\r  organic\t\r  matter\t\r  (SOM)\t\r  pools\t\r  with\t\r  first-­‐order\t\r  decay\t\r  in\t\r  ESM\t\r  soil\t\r  models\t\r  fails\t\r  to\t\r  capture\t\r  SOM\t\r  dynamics\t\r  at\t\r  high\t\r  latitudes.\t\r  (iv) Phenology\t\r  is\t\r  not\t\r  well\t\r  modeled,\t\r  nor\t\r  is\t\r  the\t\r  treeline.\t\r  The\t\r  dynamics\t\r  and\t\r  gradients\t\r  of\t\r  tree\t\r  canopy\t\r  density\t\r  may\t\r  need\t\r  to\t\r  be\t\r  addressed.\t\r  (v) No\t\r  ESM\t\r  has\t\r  permafrost\t\r  carbon\t\r  or\t\r  peatland\t\r  carbon\t\r  or\t\r  permafrost/peatland-­‐specific\t\r  processes\t\r  to\t\r  mineralize\t\r  their\t\r  carbon\t\r  pools;\t\r  few\t\r  include\t\r  nitrogen\t\r  availability\t\r  constraints\t\r  on\t\r  the\t\r  carbon\t\r  cycle;\t\r  very\t\r  few\t\r  credibly\t\r  simulate\t\r  CH4\t\r  or\t\r  N2O\t\r  fluxes.\t\r  (vi) The\t\r  source/sink\t\r  patterns\t\r  of\t\r  CO2\t\r  and\t\r  CH4\t\r  determined\t\r  from\t\r  ESM\t\r  inversions\t\r  are\t\r  very\t\r  poorly\t\r  constrained\t\r  by\t\r  in-­‐situ\t\r  atmospheric\t\r  concentration\t\r  measurements.\t\r  \t\r  \n\u003c/p\u003e\n\u003cp\u003eIII. Proposed\t\r  Experimental\t\r  Activities\t\r  \t\r  The\t\r  broad\t\r  goals\t\r  of\t\r  the\t\r  experiments\t\r  proposed\t\r  here\t\r  should\t\r  be\t\r  to\t\r  improve\t\r  our\t\r  understanding\t\r  of\t\r  the\t\r  governing\t\r  processes,\t\r  advance\t\r  our\t\r  interpretation\t\r  and\t\r  utilization\t\r  of\t\r  the\t\r  available\t\r  satellite\t\r  data,\t\r  and\t\r  use\t\r  these\t\r  gains\t\r  to\t\r  significantly\t\r  improve\t\r  ESM\t\r  performance.\t\r  \t\r  \u003c/p\u003e\n\u003cp /\u003e\n\u003c/div\u003e\n\u003cdiv class\u003d\"page\"\u003e\u003cp /\u003e\n\u003cp\u003e\t\r  \u003c/p\u003e\n\u003cp\u003e\t\r   vii\t\r  \n\u003c/p\u003e\n\u003cp\u003e\t\r  Some\t\r  specific\t\r  experimental\t\r  activities\t\r  were\t\r  recommended\t\r  to\t\r  address\t\r  the\t\r  model\t\r  weaknesses\t\r  and\t\r  key\t\r  science\t\r  questions\t\r  listed\t\r  above.\t\r  Note\t\r  that\t\r  in\t\r  some\t\r  cases\t\r  these\t\r  activities\t\r  could\t\r  greatly\t\r  benefit\t\r  from\t\r  coordination\t\r  between\t\r  PCS-­‐\t\r  and\t\r  BGC-­‐focused\t\r  experiments.\t\r  \t\r  \nPhysical\t\r  Climate\t\r  System\t\r  Clouds,\t\r  radiation\t\r  and\t\r  aerosols\t\r  (i) The\t\r  DOE\t\r  ARM\t\r  observations\t\r  should\t\r  be\t\r  extended,\t\r  with\t\r  an\t\r  emphasis\t\r  on\t\r  getting\t\r  better\t\r  observations\t\r  of\t\r  cloud\t\r  ice\t\r  properties\t\r  and\t\r  their\t\r  effects\t\r  on\t\r  the\t\r  radiation\t\r  budget.\t\r  (ii) \t\r  An\t\r  aircraft-­‐\t\r  and\t\r  ground-­‐based\t\r  field\t\r  campaign\t\r  should\t\r  be\t\r  conducted,\t\r  with\t\r  some\t\r  focus\t\r  on\t\r  the\t\r  Russian\t\r  Arctic-­‐boreal\t\r  zone\t\r  if\t\r  possible,\t\r  targeting\t\r  aerosol\t\r  wet\t\r  removal\t\r  by\t\r  super-­‐cooled\t\r  liquid,\t\r  mixed-­‐phase\t\r  and\t\r  ice\t\r  clouds.\t\r  \t\r  \t\r  \t\r  Oceans\t\r  and\t\r  Sea-­‐ice\t\r  (iii) A\t\r  field\t\r  campaign\t\r  should\t\r  be\t\r  conducted\t\r  in\t\r  the\t\r  western\t\r  Arctic\t\r  (Beaufort\t\r  Sea)\t\r  to\t\r  address\t\r  the\t\r  processes\t\r  involved\t\r  in\t\r  melting\t\r  sea-­‐ice\t\r  and\t\r  controlling\t\r  ocean\t\r  stratification.\t\r  \t\r  \t\r  (iv) A\t\r  long-­‐term\t\r  SHEBA\t\r  follow-­‐on\t\r  experiment,\t\r  like\t\r  the\t\r  proposed\t\r  multi-­‐year\t\r  MOSAiC\t\r  (Multi-­‐disciplinary\t\r  drifting\t\r  Observatory\t\r  for\t\r  the\t\r  Study\t\r  of\t\r  the\t\r  Arctic\t\r  Climate)\t\r  project,\t\r  should\t\r  be\t\r  conducted\t\r  with\t\r  21st\t\r  century\t\r  observing\t\r  capabilities\t\r  that\t\r  sample\t\r  many\t\r  different\t\r  thermodynamic\t\r  and\t\r  dynamic\t\r  environments,\t\r  clean\t\r  and\t\r  polluted\t\r  situations,\t\r  and\t\r  provide\t\r  insights\t\r  into\t\r  the\t\r  larger-­‐scale\t\r  controls\t\r  on\t\r  cloud\t\r  cover\t\r  and\t\r  cloud\t\r  properties.\t\r  \t\r  Integrated\t\r  systems,\t\r  land\t\r  surface\t\r  hydrology,\t\r  and\t\r  carbon\t\r  cycle\t\r  (v) Experiments,\t\r  using\t\r  flux\t\r  towers\t\r  and\t\r  aircraft\t\r  campaigns,\t\r  directed\t\r  at\t\r  validating\t\r  the\t\r  calculated\t\r  ESM\t\r  grid-­‐scale\t\r  surface-­‐atmosphere\t\r  exchanges\t\r  of\t\r  energy,\t\r  momentum,\t\r  water\t\r  and\t\r  carbon,\t\r  and\t\r  relating\t\r  these\t\r  fluxes\t\r  to\t\r  variables\t\r  that\t\r  are\t\r  amenable\t\r  to\t\r  satellite\t\r  remote\t\r  sensing\t\r  should\t\r  be\t\r  conducted.\t\r  These\t\r  should\t\r  be\t\r  integrated\t\r  with\t\r  the\t\r  experiments\t\r  proposed\t\r  in\t\r  section\t\r  (i)\t\r  and\t\r  (ii)\t\r  of\t\r  the\t\r  BGC\t\r  section\t\r  below.\t\r  \n\t\r  \nBiogeochemical\t\r  cycles\t\r  A\t\r  key\t\r  overall\t\r  goal\t\r  is\t\r  to\t\r  develop,\t\r  test,\t\r  and\t\r  validate\t\r  BGC\t\r  models\t\r  that\t\r  can\t\r  be\t\r  embedded\t\r  in\t\r  ESMs.\t\r  Most\t\r  of\t\r  the\t\r  surface\t\r  parameters\t\r  for\t\r  these\t\r  models\t\r  can\t\r  be\t\r  extracted\t\r  from\t\r  satellite\t\r  data\t\r  and\t\r  model\t\r  performance\t\r  should\t\r  be\t\r  validated\t\r  using\t\r  in-­‐situ\t\r  observations\t\r  (1\t\r  –\t\r  100\t\r  m),\t\r  local-­‐to-­‐regional\t\r  up-­‐scaling\t\r  work\t\r  (100\t\r  m\t\r  –\t\r  1000\t\r  km)\t\r  and\t\r  inversion\t\r  models\t\r  (1000\t\r  km\t\r  –\t\r  ABZ\t\r  scale).\t\r  \t\r  (i)\t\r   Integrated\t\r  surface-­‐atmosphere\t\r  and\t\r  surface\t\r  processes:\t\r  A\t\r  network\t\r  of\t\r  tower\t\r  and\t\r  surface\t\r  sites\t\r  is\t\r  needed\t\r  to\t\r  measure\t\r  surface-­‐atmosphere\t\r  fluxes\t\r  of\t\r  CO2\t\r  and\t\r  CH4\t\r  and\t\r  their\t\r  governing\t\r  processes,\t\r  in\t\r  addition\t\r  to\t\r  those\t\r  PCS\t\r  fluxes\t\r  described\t\r  above.\t\r  \t\r  (ii) Disturbance\t\r  and\t\r  carbon\t\r  cycle\t\r  dynamics:\t\r  A\t\r  combination\t\r  of\t\r  satellite\t\r  fire\t\r  mapping,\t\r  in-­‐situ\t\r  pre-­‐\t\r  and\t\r  post-­‐fire\t\r  inventories,\t\r  and\t\r  atmospheric\t\r  composition\t\r  (surface,\t\r  airborne,\t\r  satellite)\t\r  measurements\t\r  should\t\r  provide\t\r  the\t\r  constraints\t\r  to\t\r  support\t\r  disturbance\t\r  model\t\r  development.\t\r  \t\r  \t\r  Some\t\r  flux\t\r  towers\t\r  and\t\r  aircraft\t\r  campaigns\t\r  should\t\r  focus\t\r  on\t\r  abrupt\t\r  disturbance\t\r  impacts,\t\r  such\t\r  as\t\r  post-­‐fire\t\r  recovery\t\r  or\t\r  rapidly\t\r  warming\t\r  permafrost,\t\r  to\t\r  study\t\r  changes\t\r  in\t\r  surface\t\r  properties\t\r  and\t\r  associated\t\r  BGC\t\r  dynamics.\t\r  A\t\r  series\t\r  of\t\r  aircraft-­‐based\t\r  flux\t\r  measurements\t\r  of\t\r  CO2/CH4\t\r  and\t\r  Bowen\t\r  ratios\t\r  along\t\r  long\t\r  transects\t\r  would\t\r  provide\t\r  data\t\r  under\t\r  a\t\r  wide\t\r  range\t\r  of\t\r  environmental\t\r  conditions.\t\r  \t\r  (iii) Upscaling:\t\r  For\t\r  upscaling\t\r  from\t\r  site\t\r  to\t\r  region,\t\r  high-­‐precision\t\r  and\t\r  continuous\t\r  tower-­‐based\t\r  \u003c/p\u003e\n\u003cp /\u003e\n\u003c/div\u003e\n\u003cdiv class\u003d\"page\"\u003e\u003cp /\u003e\n\u003cp\u003e\t\r  \u003c/p\u003e\n\u003cp\u003e\t\r   viii\t\r  \n\u003c/p\u003e\n\u003cp\u003emeasurements\t\r  should\t\r  be\t\r  made\t\r  of\t\r  the\t\r  mixing\t\r  ratios,\t\r  and\t\r  fluxes\t\r  when\t\r  possible,\t\r  of\t\r  CO2,\t\r  CH4\t\r  and\t\r  other\t\r  gas\t\r  species.\t\r  Surface-­‐based\t\r  atmospheric\t\r  column\t\r  measurements\t\r  could\t\r  complement\t\r  these\t\r  tower\t\r  measurements\t\r  and\t\r  validate\t\r  satellite\t\r  trace\t\r  gas\t\r  retrievals.\t\r  Vertical\t\r  profiles\t\r  and\t\r  near-­‐surface\t\r  fluxes\t\r  of\t\r  these\t\r  gases\t\r  in\t\r  the\t\r  planetary\t\r  boundary\t\r  layer\t\r  could\t\r  be\t\r  sampled\t\r  by\t\r  aircraft\t\r  during\t\r  field\t\r  campaigns.\t\r  Satellite\t\r  and\t\r  aircraft\t\r  remote\t\r  sensing\t\r  data\t\r  at\t\r  various\t\r  spatial\t\r  resolutions\t\r  could\t\r  also\t\r  be\t\r  used\t\r  to\t\r  characterize\t\r  surface\t\r  heterogeneity\t\r  of\t\r  the\t\r  measurement\t\r  sites\t\r  and\t\r  the\t\r  pan-­‐ABZ.\t\r  In\t\r  combination,\t\r  these\t\r  measurements\t\r  could\t\r  be\t\r  used\t\r  to\t\r  directly\t\r  evaluate\t\r  process\t\r  models\t\r  over\t\r  the\t\r  range\t\r  of\t\r  local\t\r  to\t\r  regional\t\r  scales\t\r  as\t\r  well\t\r  as\t\r  to\t\r  constrain\t\r  downscaling\t\r  schemes.\t\r  \t\r   (iv)\t\r  \t\r   Downscaling:\t\r  A\t\r  comprehensive\t\r  effort\t\r  should\t\r  be\t\r  made\t\r  to\t\r  expand\t\r  the\t\r  network\t\r  of\t\r  atmospheric\t\r  CO2\t\r  and\t\r  CH4\t\r  concentration\t\r  measurements\t\r  in\t\r  the\t\r  ABZ,\t\r  preceded\t\r  and\t\r  accompanied\t\r  by\t\r  4DDA/OSSE\t\r  work\t\r  to\t\r  determine\t\r  the\t\r  optimal\t\r  deployment\t\r  pattern\t\r  and\t\r  schedule\t\r  for\t\r  inversion\t\r  studies.\t\r  This\t\r  network\t\r  should\t\r  directly\t\r  complement\t\r  the\t\r  surface,\t\r  tower\t\r  and\t\r  airborne\t\r  process\t\r  study\t\r  networks\t\r  listed\t\r  above\t\r  and\t\r  be\t\r  used\t\r  to\t\r  support\t\r  a\t\r  multi-­‐team\t\r  atmospheric\t\r  inversion\t\r  initiative\t\r  allied\t\r  to\t\r  satellite\t\r  trace\t\r  gas\t\r  algorithm\t\r  development.\t\r  All\t\r  of\t\r  these\t\r  studies\t\r  should\t\r  be\t\r  directly\t\r  linked\t\r  to\t\r  remote\t\r  sensing\t\r  investigations\t\r  with\t\r  a\t\r  view\t\r  to\t\r  scaling\t\r  up\t\r  the\t\r  improved\t\r  process\t\r  models\t\r  to\t\r  the\t\r  ESM\t\r  scale.\t\r  Previous,\t\r  current\t\r  and\t\r  proposed\t\r  experiment\t\r  sites\t\r  in\t\r  Alaska\t\r  and\t\r  Canada\t\r  (e.g.,\t\r  ABLE,\t\r  BOREAS,\t\r  BERMS,\t\r  NGEE,\t\r  etc.)\t\r  should\t\r  be\t\r  assessed\t\r  for\t\r  their\t\r  suitability\t\r  for\t\r  embedding\t\r  in\t\r  a\t\r  zonal-­‐scale\t\r  modeling\t\r  framework\t\r  to\t\r  support\t\r  this\t\r  work.\t\r  \t\r  \nIV. Preparatory\t\r  activities\t\r  and\t\r  next\t\r  steps\t\r  Satellite\t\r  data\t\r  and\t\r  other\t\r  data\t\r  sets\t\r  should\t\r  be\t\r  collected\t\r  and\t\r  consolidated\t\r  for\t\r  the\t\r  entire\t\r  ABZ.\t\r  \t\r  \t\r  Model\t\r  development\t\r  work,\t\r  especially\t\r  cloud\t\r  and\t\r  aerosol\t\r  microphysics\t\r  developments\t\r  for\t\r  mixed-­‐phase\t\r  and\t\r  ice\t\r  clouds,\t\r  improvements\t\r  in\t\r  surface\t\r  boundary\t\r  layer\t\r  parameterizations,\t\r  and\t\r  integration\t\r  of\t\r  many\t\r  new\t\r  elements\t\r  in\t\r  land\t\r  surface\t\r  modeling\t\r  of\t\r  hydrology\t\r  and\t\r  BGC,\t\r  should\t\r  be\t\r  a\t\r  priority.\t\r  \t\r  \t\r  Other\t\r  activities\t\r  recommended\t\r  for\t\r  early\t\r  attention\t\r  include\t\r  data\t\r  mining,\t\r  model\t\r  support\t\r  for\t\r  network\t\r  and\t\r  field\t\r  campaign\t\r  design,\t\r  and\t\r  some\t\r  integrative\t\r  work.\t\r  \t\r  Considerable\t\r  resources\t\r  and\t\r  organization\t\r  will\t\r  be\t\r  required\t\r  to\t\r  address\t\r  this\t\r  research\t\r  agenda.\t\r  Inter-­‐agency,\t\r  international\t\r  coordination\t\r  is\t\r  essential\t\r  in\t\r  order\t\r  to\t\r  span\t\r  the\t\r  physical\t\r  scales\t\r  and\t\r  scientific\t\r  disciplines\t\r  involved.\t\r  The\t\r  obvious\t\r  lead\t\r  players\t\r  are\t\r  the\t\r  US\t\r  and\t\r  Canadian\t\r  federal\t\r  agencies,\t\r  but\t\r  support\t\r  can\t\r  be\t\r  expected\t\r  from\t\r  state-­‐level\t\r  and\t\r  provincial\t\r  authorities,\t\r  and\t\r  the\t\r  academic\t\r  research\t\r  community.\t\r  \t\r  A\t\r  small\t\r  interdisciplinary,\t\r  interagency\t\r  team\t\r  should\t\r  be\t\r  formed\t\r  to\t\r  build\t\r  on\t\r  the\t\r  work\t\r  of\t\r  this\t\r  report\t\r  and:\t\r  1) Assess\t\r  current\t\r  and\t\r  planned\t\r  activities\t\r  in\t\r  the\t\r  context\t\r  of\t\r  this\t\r  and\t\r  other\t\r  study\t\r  reports;\t\r  and\t\r  2) Assess\t\r  priorities,\t\r  feasibility\t\r  and\t\r  resources\t\r  required\t\r  to\t\r  conduct\t\r  the\t\r  recommended\t\r  activities.\t\r  The\t\r  structure\t\r  of\t\r  this\t\r  report\t\r  roughly\t\r  follows\t\r  the\t\r  agenda\t\r  for\t\r  the\t\r  workshop.\t\r  Section\t\r  1\t\r  provides\t\r  an\t\r  overview\t\r  of\t\r  important\t\r  dynamical,\t\r  physical\t\r  and\t\r  biogeochemical\t\r  processes\t\r  in\t\r  the\t\r  ABZ.\t\r  Section\t\r  2\t\r  summarizes\t\r  the\t\r  status\t\r  of\t\r  the\t\r  predictive\t\r  models\t\r  and\t\r  lists\t\r  those\t\r  gaps\t\r  in\t\r  our\t\r  understanding\t\r  that\t\r  are\t\r  considered\t\r  to\t\r  lead\t\r  to\t\r  poor\t\r  predictive\t\r  performance.\t\r  Section\t\r  3\t\r  itemizes\t\r  the\t\r  key\t\r  science\t\r  questions\t\r  that\t\r  need\t\r  to\t\r  be\t\r  addressed\t\r  and\t\r  Section\t\r  4\t\r  lays\t\r  out\t\r  a\t\r  suggested\t\r  list\t\r  of\t\r  priority\t\r  experimental\t\r  activities\t\r  that\t\r  could\t\r  be\t\r  executed\t\r  to\t\r  address\t\r  those\t\r  questions.\t\r  A\t\r  table\t\r  in\t\r  Section\t\r  4\t\r  summarizes\t\r  previous,\t\r  existing\t\r  and\t\r  proposed\t\r  experimental\t\r  activities\t\r  in\t\r  the\t\r  ABZ.\t\r  \t\r  \u003c/p\u003e\n\u003cp /\u003e\n\u003c/div\u003e\n\u003cdiv class\u003d\"page\"\u003e\u003cp /\u003e\n\u003cp\u003e\t\r  \u003c/p\u003e\n\u003cp\u003e\t\r   ix\t\r  \n\u003c/p\u003e\n\u003cp\u003e\t\r   \t\r  \u003c/p\u003e\n\u003cp /\u003e\n\u003c/div\u003e\n\u003cdiv class\u003d\"page\"\u003e\u003cp /\u003e\n\u003cp\u003e\t\r  \u003c/p\u003e\n\u003cp\u003e\t\r   x\t\r  \n\u003c/p\u003e\n\u003cp\u003e\t\r  \t\r  \u003c/p\u003e\n\u003cp /\u003e\n\u003c/div\u003e\n\u003cdiv class\u003d\"page\"\u003e\u003cp /\u003e\n\u003cp\u003e\t\r  \u003c/p\u003e\n\u003cp\u003e\t\r   1\t\r  \n\u003c/p\u003e\n\u003cp\u003e1 Introduction\t\r  Early\t\r   climate\t\r   modeling\t\r   studies\t\r   indicated\t\r   that\t\r   the\t\r   Arctic\t\r   zone\t\r   would\t\r   be\t\r   a\t\r   bellweather\t\r   of\t\r  anthropogenic\t\r   global\t\r   warming\t\r   (e.g.,\t\r   Manabe\t\r   and\t\r   Wetherald,\t\r   1975;\t\r   Hansen\t\r   et\t\r   al.,\t\r   1981;\t\r   1984).\t\r  These\t\r   early\t\r  predictions\t\r   are\t\r  being\t\r   realized,\t\r   as\t\r   observations\t\r  now\t\r  show\t\r   that\t\r   the\t\r  Arctic\t\r   is\t\r  warming\t\r  more\t\r   than\t\r  twice\t\r  as\t\r   fast\t\r  as\t\r   the\t\r  rest\t\r  of\t\r   the\t\r  planet,\t\r   (e.g.,\t\r  Hansen\t\r  et\t\r  al.,\t\r  2010),\t\r  and\t\r  observations\t\r  and\t\r  models\t\r   indicate\t\r   that\t\r   a\t\r   late-­‐summer\t\r   ice-­‐free\t\r   Arctic\t\r   Ocean\t\r   could\t\r   be\t\r   a\t\r   reality\t\r   within\t\r   two\t\r   to\t\r   three\t\r  decades.\t\r  This\t\r  accelerated\t\r  warming,\t\r  often\t\r  referred\t\r  to\t\r  as\t\r  Polar\t\r  Amplification,\t\r  is\t\r  mainly\t\r  attributed\t\r  to\t\r  increased\t\r  solar\t\r  absorption\t\r  by\t\r  the\t\r  Arctic\t\r  Ocean\t\r  as\t\r  a\t\r  result\t\r  of\t\r  the\t\r  sea\t\r  ice-­‐albedo\t\r  feedback\t\r  effect\t\r  (e.g.,\t\r  Serreze\t\r   et\t\r   al.,\t\r   2009;\t\r   Serreze\t\r   and\t\r   Barry,\t\r   2011).\t\r   \t\r   State-­‐of-­‐the-­‐art\t\r   models\t\r   indicate\t\r   that\t\r   the\t\r   Boreal\t\r  region,\t\r   the\t\r   latitude\t\r   zone\t\r   immediately\t\r   to\t\r   the\t\r   south\t\r   of\t\r   the\t\r   Arctic,\t\r   is\t\r   next\t\r   in\t\r   line\t\r   for\t\r   accelerated\t\r  warming\t\r   due\t\r   to\t\r   mid-­‐continental\t\r   warming\t\r   and\t\r   drying,\t\r   reduced\t\r   snow\t\r   cover\t\r   and\t\r   hence\t\r   reduced\t\r  surface\t\r  albedo,\t\r  and\t\r  reduced\t\r  cold\t\r  advection\t\r  from\t\r  a\t\r  warming\t\r  Arctic.\t\r  \t\r  Changes\t\r  in\t\r  the\t\r  physical\t\r  climate,\t\r  biogeochemical\t\r  systems,\t\r  and\t\r  disturbance\t\r  regimes\t\r  are\t\r  expected\t\r  to\t\r  generate\t\r   changes\t\r   in\t\r   a\t\r  wide\t\r   range\t\r   of\t\r   land\t\r   surface\t\r   characteristics\t\r   that\t\r  will\t\r   in\t\r   turn\t\r   feed\t\r  back\t\r   onto\t\r  physical\t\r  climate\t\r  and\t\r  biogeochemical\t\r  processes.\t\r  The\t\r  combined\t\r  Arctic-­‐Boreal\t\r  Zone\t\r  (ABZ)\t\r  warming\t\r  could\t\r   have\t\r   significant\t\r   impacts\t\r   on\t\r   regional\t\r   biogeochemistry\t\r   and\t\r   ecology.\t\r   The\t\r   Arctic\t\r   land\t\r   areas\t\r  contain\t\r   deep\t\r   carbon\t\r   stores\t\r   in\t\r   the\t\r   permafrost,\t\r   and\t\r   the\t\r   Boreal\t\r   Zone\t\r   has\t\r   large\t\r   carbon\t\r   stores\t\r   in\t\r  saturated\t\r   organic\t\r   soils\t\r   (peatlands\t\r   and\t\r   discontinuous\t\r   permafrost),\t\r   mineral\t\r   soils\t\r   and\t\r   the\t\r   forest\t\r  biomass.\t\r   These\t\r   frozen\t\r   and\t\r   saturated\t\r   soils\t\r   are\t\r   expected\t\r   to\t\r   release\t\r   carbon\t\r   as\t\r  methane\t\r   (CH4)\t\r   and\t\r  carbon\t\r   dioxide\t\r   (CO2)\t\r   as\t\r   they\t\r   warm\t\r   and\t\r   dry.\t\r  Warming,\t\r   longer\t\r   growing\t\r   seasons,\t\r   and\t\r   permafrost\t\r  thawing\t\r  are\t\r  expected\t\r  to\t\r  cause\t\r  changes\t\r  in\t\r  ABZ\t\r  plant\t\r  community\t\r  composition,\t\r  photosynthesis,\t\r  and\t\r  net\t\r  primary\t\r  production\t\r  (e.g.,\t\r  Macias-­‐Fauria\t\r  et\t\r  al.,\t\r  2012).\t\r  \t\r  Changing\t\r  fire\t\r  frequency\t\r  and\t\r  intensity\t\r  will\t\r  impact\t\r  the\t\r  regional\t\r  carbon\t\r  balance\t\r  (e.g.,\t\r  Turetsky\t\r  et\t\r  al.,\t\r  2011;\t\r  Mack\t\r  et\t\r  al.,\t\r  2011).\t\r  The\t\r  net\t\r  impact\t\r  of\t\r  these\t\r  changes\t\r  in\t\r  productivity\t\r  and\t\r  decomposition\t\r  on\t\r  the\t\r  pan-­‐ABZ\t\r  carbon\t\r  balance\t\r  is\t\r  not\t\r  known,\t\r  and\t\r  system-­‐wide\t\r  feedbacks\t\r  are\t\r  poorly\t\r  understood\t\r  and\t\r  likely\t\r  to\t\r  be\t\r  complex\t\r  (e.g.,\t\r  Wookey\t\r  et\t\r  al.,\t\r  2009).\t\r  \t\r  For\t\r  CH4\t\r  emissions,\t\r  the\t\r  biggest\t\r  potential\t\r  increase\t\r  comes\t\r  from\t\r  permafrost\t\r  thaw,\t\r  but\t\r  the\t\r  magnitude\t\r  of\t\r  this\t\r  effect\t\r  is\t\r  quite\t\r  uncertain,\t\r  as\t\r  it\t\r  depends\t\r  on\t\r  whether\t\r  the\t\r  thawing/thawed\t\r  landscapes\t\r  become\t\r  wetter\t\r  or\t\r  drier\t\r  (Frolking\t\r  et\t\r  al.,\t\r  2011).\t\r  \t\r  \t\r  Despite\t\r   constant\t\r   improvement,\t\r   global\t\r   climate\t\r   models\t\r   have\t\r   greater\t\r   difficulty\t\r   in\t\r   reproducing\t\r   the\t\r  current\t\r   climate\t\r   in\t\r   the\t\r   Arctic\t\r   than\t\r   elsewhere\t\r   (Walsh\t\r   et\t\r   al.,\t\r   2002)\t\r   and\t\r   the\t\r   scatter\t\r   between\t\r  projections\t\r  from\t\r  different\t\r  climate\t\r  models\t\r   is\t\r  much\t\r  larger\t\r   in\t\r  the\t\r  Arctic\t\r  than\t\r  for\t\r  other\t\r  regions\t\r  (e.g.,\t\r  Prenni\t\r   et\t\r   al.,\t\r   2007).\t\r   \t\r   For\t\r   example,\t\r   although\t\r   all\t\r   models\t\r   participating\t\r   in\t\r   the\t\r   Fourth\t\r   Assessment\t\r  Report\t\r   for\t\r   the\t\r   Intergovernmental\t\r   Panel\t\r   on\t\r  Climate\t\r  Change\t\r   (IPCC\t\r  AR4)\t\r   show\t\r  declining\t\r  Arctic\t\r   ice\t\r  cover\t\r   from\t\r   1953\t\r   to\t\r   2006,\t\r   none\t\r   of\t\r   the\t\r  model\t\r   simulations\t\r   shows\t\r   decreases\t\r   as\t\r   large\t\r   as\t\r   observed.\t\r  Since\t\r  2006\t\r  the\t\r  precipitous\t\r  decrease\t\r  in\t\r  summer\t\r  sea\t\r  ice\t\r  extent\t\r  has\t\r  continued,\t\r  with\t\r  2007\t\r  and\t\r  2012\t\r  setting\t\r  new\t\r  records\t\r  (Comiso,\t\r  2012).\t\r  Current\t\r  observed\t\r  summer\t\r  minima\t\r  are\t\r  at\t\r  least\t\r  30\t\r  years\t\r  ahead\t\r  of\t\r   the\t\r  consensus\t\r  model\t\r   forecast.\t\r   If\t\r   these\t\r  observed\t\r  changes\t\r  are\t\r  due\t\r   to\t\r   the\t\r   increased\t\r  atmospheric\t\r  greenhouse\t\r  gas\t\r  (GHG)\t\r  loadings,\t\r  we\t\r  can\t\r  expect\t\r  an\t\r  essentially\t\r  ice-­‐free\t\r  Arctic\t\r  Ocean\t\r  in\t\r  20\t\r  to\t\r  30\t\r  years.\t\r  The\t\r  models\t\r  used\t\r  for\t\r  the\t\r  Fifth\t\r  Assessment\t\r  Report\t\r  (AR5)\t\r  show\t\r  a\t\r  similar\t\r  response.\t\r  Although\t\r  the\t\r  AR5\t\r  models\t\r   are\t\r   more\t\r   consistent\t\r   than\t\r   the\t\r   AR4\t\r   models\t\r   when\t\r   compared\t\r   with\t\r   observations\t\r   over\t\r   the\t\r  satellite\t\r  era\t\r  (1979–2011),\t\r  trends\t\r  from\t\r  most\t\r  models\t\r  remain\t\r  smaller\t\r  than\t\r  observed\t\r  (Stroeve\t\r  et\t\r  al.,\t\r  2012).\t\r   Recent\t\r   studies\t\r   (e.g.,\t\r   Kay\t\r   et\t\r   al.,\t\r   2011),\t\r   however,\t\r   suggest\t\r   that\t\r   some\t\r   of\t\r   the\t\r   summer\t\r   sea\t\r   ice\t\r  decline\t\r  in\t\r  recent\t\r  years\t\r  could\t\r  be\t\r  due\t\r  to\t\r  natural\t\r  decadal\t\r  variability.\t\r  Partly\t\r  because\t\r  of\t\r  this\t\r  and\t\r  partly\t\r  because\t\r   of\t\r   suspected\t\r   deficiencies\t\r   in\t\r   the\t\r   models’\t\r   atmospheric\t\r   parameterizations\t\r   and\t\r   their\t\r  treatment\t\r   of\t\r   sea\t\r   ice,\t\r   Stroeve\t\r   et\t\r   al.\t\r   (2012)\t\r   finds\t\r   that\t\r   “the\t\r   CMIP5\t\r  models\t\r   do\t\r   not\t\r   appear\t\r   to\t\r   have\t\r  appreciably\t\r  reduced\t\r  uncertainty\t\r  as\t\r  to\t\r  when\t\r  a\t\r  seasonally\t\r  ice-­‐free\t\r  Arctic\t\r  Ocean\t\r  will\t\r  be\t\r  realized.”\t\r  \u003c/p\u003e\n\u003cp /\u003e\n\u003c/div\u003e\n\u003cdiv class\u003d\"page\"\u003e\u003cp /\u003e\n\u003cp\u003e\t\r  \u003c/p\u003e\n\u003cp\u003e\t\r   2\t\r  \n\u003c/p\u003e\n\u003cp\u003e\t\r  Figure\t\r  1a:\t\r  \t\r  Arctic\t\r  September\t\r  sea\t\r  ice\t\r  extent\t\r  (x\t\r  106\t\r  km2)\t\r  from\t\r  observations\t\r  (thick\t\r  red\t\r  line)\t\r  and\t\r  13\t\r  IPCC\t\r  AR4\t\r  climate\t\r  models\t\r  using\t\r  the\t\r  SRES\t\r  A1B\t\r  scenario,\t\r  together\t\r  with\t\r  multi-­‐model\t\r  ensemble\t\r  mean\t\r  (solid\t\r  black\t\r  line)\t\r  and\t\r  standard\t\r  deviation\t\r  (dotted\t\r  black\t\r  line).\t\r  Insert\t\r  shows\t\r  9-­‐year\t\r  running\t\r  means.\t\r  [From\t\r  Stroeve\t\r  et\t\r  al.,\t\r  2007]\t\r  \t\r  \n\u003c/p\u003e\n\u003cp\u003e\t\r  Figure\t\r  2:\t\r  Pan-­‐Arctic\t\r  total\t\r  cumulative\t\r  Net\t\r  Ecosystem\t\r  Exchange\t\r  (NEE,\t\r  the\t\r  exchange\t\r  of\t\r  CO2\t\r  with\t\r  the\t\r  atmosphere,\t\r  where\t\r  a\t\r  positive\t\r  NEE\t\r  represents\t\r  a\t\r  loss\t\r  of\t\r  CO2\t\r  from\t\r  the\t\r  land\t\r  to\t\r  the\t\r  atmosphere)\t\r  for\t\r  low,\t\r  medium\t\r  and\t\r  high\t\r  warming\t\r  rates\t\r  without\t\r  permafrost\t\r  carbon\t\r  and\t\r  the\t\r  ensemble\t\r  mean\t\r  with\t\r  permafrost\t\r  carbon\t\r  flux.\t\r  The\t\r  grey\t\r  shading\t\r  represents\t\r  uncertainty\t\r  and\t\r  the\t\r  arrow\t\r  marks\t\r  the\t\r  pan-­‐Arctic\t\r  starting\t\r  point\t\r  of\t\r  2023\t\r  ±\t\r  4\t\r  years.\t\r  [From\t\r  Schaefer\t\r  et\t\r  al.\t\r  2011]\t\r  \t\r  The\t\r  prediction\t\r  of\t\r   likely\t\r  biogeochemical\t\r   cycle\t\r   (BGC)\t\r   responses\t\r   in\t\r   the\t\r  ABZ,\t\r  particularly\t\r   the\t\r   future\t\r  trajectory\t\r  of\t\r  CO2\t\r  and\t\r  CH4\t\r  emissions\t\r  from\t\r  the\t\r  thawing\t\r  permafrost\t\r  and\t\r  warming\t\r  and\t\r  drying\t\r  boreal\t\r  forest,\t\r   is\t\r   even\t\r  more\t\r   problematic.\t\r   Several\t\r  modeling\t\r   groups\t\r   have\t\r   used\t\r   BGC\t\r  models\t\r   in\t\r  which\t\r   they\t\r  have\t\r  varied\t\r  the\t\r   important\t\r  controlling\t\r  parameters\t\r  over\t\r  the\t\r   likely\t\r  range\t\r  of\t\r  values\t\r   in\t\r  an\t\r  attempt\t\r  to\t\r  bound\t\r   the\t\r   uncertainties\t\r   (e.g.,\t\r   Figure\t\r   2;\t\r   Schaefer\t\r   et\t\r   al.,\t\r   2011;\t\r   Koven\t\r   et\t\r   al.,\t\r   2011;\t\r   Schneider\t\r   von\t\r  \u003c/p\u003e\n\u003cp /\u003e\n\u003c/div\u003e\n\u003cdiv class\u003d\"page\"\u003e\u003cp /\u003e\n\u003cp\u003e\t\r  \u003c/p\u003e\n\u003cp\u003e\t\r   3\t\r  \n\u003c/p\u003e\n\u003cp\u003eDeimling\t\r   et\t\r   al.,\t\r   2012).\t\r   Most\t\r   of\t\r   these\t\r   studies\t\r   indicate\t\r   that\t\r   the\t\r   ABZ\t\r  will\t\r   switch\t\r   from\t\r   being\t\r   a\t\r   net\t\r  carbon\t\r   sink\t\r   to\t\r   a\t\r   source\t\r   over\t\r   the\t\r   next\t\r   few\t\r   decades\t\r   but\t\r   estimates\t\r   of\t\r   the\t\r   release\t\r   trajectories\t\r   vary\t\r  widely\t\r   (e.g.,\t\r   Qian\t\r   et\t\r   al.,\t\r   2010).\t\r   A\t\r   recent\t\r   study\t\r   suggests\t\r   the\t\r   evolved\t\r   CO2\t\r   from\t\r   thawing\t\r   Arctic\t\r  permafrost\t\r   alone\t\r   could\t\r   contribute\t\r   around\t\r   90\t\r   ppm\t\r   CO2\t\r   to\t\r   the\t\r   atmospheric\t\r   CO2\t\r   burden\t\r   by\t\r   2100\t\r  (Schaefer\t\r   et\t\r   al.,\t\r   2011).\t\r  To\t\r  date,\t\r   no\t\r   IPCC\t\r  model\t\r  has\t\r   accounted\t\r   for\t\r   this\t\r   or\t\r   similar\t\r   feedback\t\r  effects\t\r  associated\t\r  with\t\r  changes\t\r  in\t\r  the\t\r  ABZ\t\r  carbon\t\r  cycle.\t\r  Physical\t\r  Climate\t\r  System\t\r  (PCS)\t\r  models\t\r  are\t\r  becoming\t\r  more\t\r  realistic.\t\r  For\t\r  AR5,\t\r  several\t\r  models\t\r  aimed\t\r  to\t\r  improve\t\r  model\t\r  realism\t\r  by\t\r  including\t\r  advanced\t\r  cloud\t\r  microphysics\t\r  parameterizations\t\r  and\t\r  explicit\t\r  modeling\t\r  of\t\r  the\t\r  carbon\t\r  cycle,\t\r  i.e.,\t\r  the\t\r  emergence\t\r  of\t\r  Earth\t\r  System\t\r  Models\t\r  (ESMs)\t\r  with\t\r  the\t\r  coupling\t\r  of\t\r   PCS\t\r   and\t\r  BGC\t\r  models.\t\r   \t\r   \t\r   The\t\r  AR5\t\r  models\t\r   do\t\r   show\t\r   some\t\r   improvement\t\r   relative\t\r   to\t\r   AR4,\t\r   but\t\r   the\t\r  issues\t\r   noted\t\r   –\t\r   specifically\t\r   the\t\r   limited\t\r   capability\t\r   for\t\r   producing\t\r   reliable\t\r   quantitative\t\r   predictions,\t\r  especially\t\r   in\t\r   the\t\r  Arctic\t\r   –\t\r   are\t\r   still\t\r   present.\t\r   The\t\r  deficiencies\t\r   reflect,\t\r   at\t\r   least\t\r   in\t\r  part,\t\r   an\t\r   incomplete\t\r  understanding\t\r  of\t\r  the\t\r  Arctic\t\r  climate\t\r  system\t\r  and\t\r  can\t\r  be\t\r  related\t\r  to\t\r  inadequate\t\r  observational\t\r  data\t\r  or\t\r  to\t\r  inadequate\t\r  analysis\t\r  of\t\r  existing\t\r  data.\t\r  \t\r  Since\t\r   the\t\r   sensitivity\t\r   of\t\r   the\t\r   ABZ\t\r  may\t\r  well\t\r   be\t\r   greater\t\r   than\t\r   the\t\r  models\t\r   suggest,\t\r   improving\t\r  model\t\r  performance\t\r   is\t\r   essential\t\r   for\t\r   reliable\t\r   predictions\t\r   and\t\r   projections\t\r   of\t\r   the\t\r   future\t\r   and\t\r   for\t\r   reliable\t\r  attribution\t\r   of\t\r   natural\t\r   and\t\r   forced\t\r   changes.\t\r   How\t\r   can\t\r   we\t\r   improve\t\r   the\t\r   predictive\t\r   capabilities\t\r   of\t\r  models\t\r   further?\t\r   To\t\r   first\t\r   order,\t\r   we\t\r   need\t\r   observations\t\r   of\t\r   particular\t\r   processes:\t\r   those\t\r   related\t\r   to\t\r  surface\t\r  exchanges,\t\r  including\t\r  carbon\t\r  fluxes,\t\r  and\t\r  to\t\r  cloud\t\r  microphysics,\t\r  as\t\r  well\t\r  as\t\r  observations\t\r  that\t\r  help\t\r  upscale\t\r  point\t\r  observations\t\r  to\t\r  the\t\r  grid-­‐scale\t\r  of\t\r  models,\t\r  both\t\r  to\t\r  improve\t\r  parameterizations\t\r  and\t\r  for\t\r  appropriate\t\r  evaluation\t\r  of\t\r  model\t\r  performance.\t\r  The\t\r  modeling\t\r  community,\t\r  therefore,\t\r  recognized\t\r  the\t\r  urgent\t\r  need\t\r  to\t\r  improve\t\r  ESM\t\r  performance\t\r  and\t\r  to\t\r  develop\t\r  a\t\r  series\t\r  of\t\r  field\t\r  campaigns\t\r  to\t\r  support\t\r  this\t\r  goal.\t\r  This\t\r  idea\t\r  was\t\r  used\t\r  to\t\r  organize\t\r  and\t\r  task\t\r  this\t\r  workshop.\t\r  \n1.1 Workshop\t\r  Organization\t\r  The\t\r   workshop\t\r   was\t\r   held\t\r   at\t\r   NASA/GSFC,\t\r   May\t\r   22-­‐24\t\r   2012,\t\r   to\t\r   assess\t\r   the\t\r   predictive\t\r   capability\t\r   of\t\r  climate\t\r   models\t\r   in\t\r   the\t\r   ABZ,\t\r   identify\t\r   priorities\t\r   for\t\r   development,\t\r   and\t\r   make\t\r   recommendations\t\r  regarding\t\r  new\t\r  field\t\r  experiments\t\r  needed\t\r  to\t\r  improve\t\r  model\t\r  subcomponents.\t\r   \t\r  The\t\r  workshop\t\r  began\t\r  with\t\r  overview\t\r  presentations\t\r  of\t\r  the\t\r  current\t\r  state\t\r  of\t\r  the\t\r  PCS\t\r  and\t\r  BGC\t\r  models,\t\r  presentations\t\r  on\t\r  some\t\r  important\t\r  recent\t\r  and\t\r  planned\t\r  field\t\r  campaigns,\t\r  and\t\r  a\t\r  summary\t\r  of\t\r  the\t\r  2010\t\r  report\t\r  prepared\t\r  by\t\r  the\t\r  Arctic\t\r  research\t\r  community\t\r  for\t\r  NSF.\t\r  These\t\r  presentations\t\r  provided\t\r  a\t\r  focus\t\r  for\t\r  breakout\t\r  sessions\t\r  –\t\r  with\t\r  PCS\t\r  and\t\r  BGC\t\r  discussions\t\r  in\t\r  separate\t\r  groups.\t\r  The\t\r  breakout\t\r  groups\t\r  were\t\r  primarily\t\r  responsible\t\r  for\t\r   identifying\t\r   the\t\r   most\t\r   important\t\r   challenges\t\r   faced\t\r   by\t\r   the\t\r   model\t\r   developers\t\r   and\t\r   discuss\t\r   how\t\r  observations\t\r   could\t\r   help.\t\r   They\t\r   also\t\r   identified\t\r   some\t\r  priorities\t\r   that\t\r   should/could\t\r   be\t\r   pursued\t\r   even\t\r  without\t\r   new\t\r   observations,\t\r   such\t\r   as\t\r  model\t\r   developments\t\r   or\t\r   new\t\r   data\t\r   products.\t\r   Plenary\t\r   sessions\t\r  were\t\r  used\t\r  to\t\r  look\t\r  for\t\r  synergy\t\r  and\t\r  to\t\r  guide\t\r  further\t\r  breakout\t\r  group\t\r  discussions.\t\r  At\t\r  the\t\r  first\t\r  plenary\t\r  session,\t\r  it\t\r  was\t\r  decided\t\r  that\t\r  model\t\r  developments\t\r  and\t\r  associated\t\r  field\t\r  campaigns\t\r  should\t\r  be\t\r  focused\t\r  towards\t\r  some\t\r  key\t\r  science\t\r  questions\t\r  that\t\r  would\t\r  then\t\r  lead\t\r  to\t\r  an\t\r  improvement\t\r  in\t\r  predictive\t\r  capability.\t\r  These\t\r  questions\t\r  were\t\r  refined\t\r  at\t\r  the\t\r  end\t\r  of\t\r  the\t\r  workshop\t\r  with\t\r  a\t\r  smaller\t\r  group\t\r  who\t\r  were\t\r  also\t\r  tasked\t\r  to\t\r  provide\t\r  technical\t\r  material\t\r  summarizing\t\r  discussions\t\r  as\t\r  well\t\r  as\t\r  additional\t\r  material\t\r   on\t\r   the\t\r   status\t\r   of\t\r   current\t\r   climate\t\r  models\t\r   in\t\r   terms\t\r   of\t\r   the\t\r   priority\t\r   areas\t\r   identified\t\r   in\t\r   the\t\r  breakout\t\r  discussions.\t\r  This\t\r  report\t\r  summarizes\t\r  the\t\r  findings\t\r  of\t\r  the\t\r  workshop\t\r  as\t\r  well\t\r  as\t\r  comments\t\r  received\t\r  from\t\r  scientists\t\r  asked\t\r  to\t\r  review\t\r  the\t\r  report\t\r  draft.\t\r  \t\r  It\t\r  is\t\r  intended\t\r  to\t\r  provide\t\r  input\t\r  to\t\r  agency\t\r  program\t\r  managers\t\r  and\t\r  others\t\r  when\t\r  deciding\t\r  on\t\r  priorities\t\r  and\t\r  resource\t\r  allocations\t\r  for\t\r  field\t\r  experiments\t\r  in\t\r  the\t\r  ABZ.\t\r  Here,\t\r  the\t\r  ABZ\t\r  refers\t\r  to\t\r  the\t\r  high\t\r  northern\t\r  latitudes,\t\r  extending\t\r  from\t\r  the\t\r  North\t\r  Pole\t\r  down\t\r  to\t\r  the\t\r  southern\t\r  \u003c/p\u003e\n\u003cp /\u003e\n\u003c/div\u003e\n\u003cdiv class\u003d\"page\"\u003e\u003cp /\u003e\n\u003cp\u003e\t\r  \u003c/p\u003e\n\u003cp\u003e\t\r   4\t\r  \n\u003c/p\u003e\n\u003cp\u003elimit\t\r  of\t\r  the\t\r  boreal\t\r  forest\t\r  (~40-­‐50°N,\t\r  depending\t\r  on\t\r  geographical\t\r  location).\t\r  \n2 Predictive\t\r  Models\t\r  \t\r  -­‐\t\r  Status\t\r  and\t\r  Gaps\t\r  In\t\r  an\t\r  analysis\t\r  of\t\r   IPCC\t\r  AR4\t\r  models,\t\r  Eisenman\t\r  et\t\r  al.\t\r   (2007)\t\r   found\t\r   large\t\r   inter-­‐model\t\r  differences\t\r   in\t\r  simulating\t\r   the\t\r   current\t\r   climate\t\r   of\t\r   Arctic\t\r   cloud\t\r   cover\t\r   that\t\r   resulted\t\r   in\t\r   significant\t\r   differences\t\r   in\t\r  downwelling\t\r   long-­‐wave\t\r   radiation\t\r   and\t\r   equilibrium\t\r   ice\t\r   thickness\t\r   (Figure\t\r   3).\t\r   In\t\r   addition\t\r   to\t\r   having\t\r  difficulty\t\r   in\t\r   reproducing\t\r   the\t\r   current\t\r   climate\t\r   in\t\r   the\t\r   Arctic,\t\r   the\t\r   scatter\t\r   between\t\r   projections\t\r   from\t\r  different\t\r  climate\t\r  models\t\r  is\t\r  much\t\r  larger\t\r  in\t\r  the\t\r  Arctic\t\r  than\t\r  for\t\r  other\t\r  regions.\t\r  Much\t\r  of\t\r  this\t\r  uncertainty\t\r  is\t\r  related\t\r  to\t\r  the\t\r  inability\t\r  of\t\r  current\t\r  models\t\r  to\t\r  accurately\t\r  represent\t\r  many\t\r  of\t\r  the\t\r  physical\t\r  processes\t\r  and\t\r  feedbacks\t\r  involved,\t\r  especially\t\r  processes\t\r  related\t\r  to\t\r  Arctic\t\r  sea\t\r  ice\t\r  cover\t\r  (e.g.,\t\r  Zhang\t\r  and\t\r  Walsh,\t\r  2006;\t\r   Stroeve\t\r   et\t\r   al.,\t\r   2007;\t\r   Eisenman\t\r   et\t\r   al.,\t\r   2007),\t\r  mixed-­‐phase\t\r   clouds\t\r   (Prenni\t\r   et\t\r   al.,\t\r   2007),\t\r   and\t\r  near-­‐surface\t\r  temperature\t\r  (e.g.,\t\r  Holland\t\r  and\t\r  Bitz,\t\r  2003).\t\r  Rind\t\r  (2008)\t\r  emphasizes\t\r  the\t\r  importance\t\r  of\t\r  understanding\t\r  cryospheric\t\r  (both\t\r  sea\t\r  ice\t\r  and\t\r  snow\t\r  cover)\t\r  feedback\t\r  since\t\r  reduction\t\r  in\t\r  surface\t\r  snow\t\r  and\t\r   ice\t\r   cover,\t\r   and\t\r   the\t\r   corresponding\t\r   reduction\t\r   in\t\r   surface\t\r   albedo,\t\r   is\t\r   the\t\r   primary\t\r   reason\t\r   for\t\r   the\t\r  observed\t\r   high-­‐latitude\t\r   amplification\t\r   of\t\r   surface\t\r   air\t\r   temperature\t\r   (e.g.,\t\r   Serreze\t\r   et\t\r   al.,\t\r   2009;\t\r   Screen\t\r  and\t\r   Simmonds,\t\r   2010).\t\r   Screen\t\r   and\t\r   Simmonds\t\r   (2010)\t\r   argue\t\r   that\t\r   strong\t\r   positive\t\r   ice-­‐temperature\t\r  feedbacks\t\r  have\t\r  emerged\t\r  in\t\r  the\t\r  Arctic,\t\r  increasing\t\r  the\t\r  chances\t\r  of\t\r  further\t\r  rapid\t\r  warming\t\r  and\t\r  sea\t\r  ice\t\r  loss.\t\r  \t\r  \t\r  The\t\r  roles\t\r  of\t\r  changes\t\r  in\t\r  the\t\r  cryosphere\t\r  and\t\r  changes\t\r  in\t\r  atmospheric\t\r  and\t\r  oceanic\t\r  circulation,\t\r  cloud\t\r  cover\t\r  and\t\r  water\t\r  vapor\t\r  in\t\r  Arctic\t\r  amplification\t\r  are\t\r  still\t\r  matters\t\r  for\t\r  research.\t\r  A\t\r  better\t\r  understanding\t\r  of\t\r   the\t\r   processes\t\r   responsible\t\r   for\t\r   the\t\r   recent\t\r   amplified\t\r  warming\t\r   is\t\r   essential\t\r   for\t\r   ensuring\t\r   that\t\r   our\t\r  models\t\r  are\t\r  capable\t\r  of\t\r  predicting\t\r  any\t\r  future\t\r  rapid\t\r  Arctic\t\r  warming\t\r  and\t\r  sea\t\r  ice\t\r  loss.\t\r  \t\r   \t\r  \t\r  \t\r   Figure\t\r  3:\t\r  Simulated\t\r  Arctic\t\r  (70–90°N)\t\r  mean\t\r  seasonal\t\r  cycle\t\r  for\t\r  1980–1999\t\r  from\t\r  AR4\t\r  climate\t\r  model\t\r  simulations.\t\r  (a)\t\r  Total\t\r  vertically\t\r  integrated\t\r  cloudiness.\t\r  (b)\t\r  Surface\t\r  downward\t\r  LW\t\r  radiation.\t\r  Model\t\r  attributions\t\r  are\t\r  given\t\r  in\t\r  Eisenman\t\r  et\t\r  al.\t\r  (2007).\t\r  [Figure\t\r  \n\u003c/p\u003e\n\u003cp\u003ecourtesy\t\r  of\t\r  I.\t\r  Eisenman]\t\r  \n \t\r  \t\r  \t\r  \n2.1 Clouds,\t\r  Aerosols,\t\r  Radiation,\t\r  and\t\r  the\t\r  Planetary\t\r  Boundary\t\r  Layer\t\r  Clouds\t\r  remain\t\r  the\t\r  largest\t\r  source\t\r  of\t\r  uncertainty\t\r  in\t\r  climate\t\r  models\t\r  (IPCC,\t\r  2007).\t\r  They\t\r  determine\t\r  the\t\r  net\t\r  long-­‐wave\t\r  (LW)\t\r  radiation\t\r  at\t\r  the\t\r  surface\t\r  and\t\r  also\t\r  regulate\t\r  incoming\t\r  solar\t\r  radiation\t\r  in\t\r  summer.\t\r  Modeling\t\r   clouds\t\r   in\t\r   the\t\r   Arctic\t\r   presents\t\r   unique\t\r   challenges\t\r   because\t\r   of\t\r   the\t\r   frequent\t\r   occurrence\t\r   of\t\r  cloud\t\r  types\t\r  and\t\r  characteristics\t\r  that\t\r  are\t\r  not\t\r  as\t\r  common\t\r  at\t\r  lower\t\r  latitudes.\t\r  Low-­‐level\t\r  boundary\t\r  layer\t\r  (BL)\t\r  clouds\t\r  tend\t\r  to\t\r  dominate\t\r  in\t\r  the\t\r  Arctic\t\r  (Shupe\t\r  et\t\r  al.,\t\r  2011),\t\r  with\t\r  very\t\r  high\t\r  temporal\t\r  frequencies\t\r  \u003c/p\u003e\n\u003cp /\u003e\n\u003c/div\u003e\n\u003cdiv class\u003d\"page\"\u003e\u003cp /\u003e\n\u003cp\u003e\t\r  \u003c/p\u003e\n\u003cp\u003e\t\r   5\t\r  \n\u003c/p\u003e\n\u003cp\u003ein\t\r  all\t\r  seasons\t\r  (Intrieri\t\r  et\t\r  al.,\t\r  2002;\t\r  Vavrus\t\r  et\t\r  al.,\t\r  2009)\t\r  and\t\r  somewhat\t\r  uniform\t\r  spatial\t\r  distributions\t\r  (Vavrus,\t\r  2004).\t\r  Arctic\t\r  boundary\t\r  layer\t\r  clouds\t\r  are\t\r  often\t\r  characterized\t\r  by\t\r  the\t\r  presence\t\r  of\t\r  persistent\t\r  temperature\t\r   inversions,\t\r   humidity\t\r   inversions,\t\r   and\t\r   strong,\t\r   stably\t\r   stratified\t\r   layers\t\r   (Sedler\t\r   et\t\r   al.,\t\r  2012).\t\r  A\t\r  key\t\r  finding\t\r  from\t\r  Arctic\t\r  atmospheric\t\r  observatories\t\r  is\t\r  that\t\r  shallow,\t\r  near\t\r  surface\t\r  Arctic\t\r  clouds\t\r  are\t\r  commonly\t\r  mixed-­‐phase\t\r  (where\t\r  ice\t\r  and\t\r  liquid\t\r  are\t\r  present\t\r  between\t\r  about\t\r  -­‐35\t\r  and\t\r  -­‐5°C),\t\r  moderately\t\r  super-­‐cooled\t\r   and\t\r   very\t\r   long-­‐lived\t\r   (e.g.,\t\r   Shupe,\t\r   2011).\t\r   \t\r   Accurate\t\r  modeling\t\r   of\t\r   cloud\t\r  water\t\r  phase\t\r   is\t\r  particularly\t\r   important\t\r   for\t\r   determining\t\r   the\t\r   radiation\t\r   balance\t\r   at\t\r   the\t\r   surface:\t\r   water\t\r   phase\t\r   clouds\t\r  tend\t\r   to\t\r   be\t\r   optically\t\r   thicker\t\r   than\t\r   ice\t\r   clouds,\t\r   resulting\t\r   in\t\r   considerably\t\r   larger\t\r   downwelling\t\r   LW\t\r  radiative\t\r  fluxes\t\r  at\t\r  the\t\r  surface\t\r  (e.g.,\t\r  Shupe\t\r  and\t\r  Intrieri,\t\r  2004),\t\r  and\t\r  increases\t\r  in\t\r  both\t\r  the\t\r  surface\t\r  air\t\r  temperature\t\r  (SAT)\t\r  and\t\r  cloud\t\r  top\t\r  radiative\t\r  cooling\t\r  (e.g.,\t\r  Morrison\t\r  and\t\r  Pinto,\t\r  2006).\t\r  \t\r  Seasonal\t\r   variation\t\r   in\t\r   cloud\t\r   response\t\r   to\t\r   sea\t\r   ice\t\r   loss\t\r   is\t\r   due\t\r   to\t\r   changes\t\r   in\t\r   stability\t\r   and\t\r   air-­‐sea\t\r  temperature\t\r   gradients.\t\r   During\t\r   the\t\r   melt\t\r   season,\t\r   Arctic\t\r   cloud\t\r   cover\t\r   is\t\r   controlled\t\r   by\t\r   large-­‐scale\t\r  atmospheric\t\r   circulation\t\r   patterns,\t\r   near-­‐surface\t\r   static\t\r   stability,\t\r   and\t\r   surface\t\r   conditions\t\r   (Kay\t\r   and\t\r  Gettelman,\t\r   2009).\t\r   The\t\r   low-­‐cloud\t\r   increases\t\r   observed\t\r   by\t\r   MISR\t\r   and\t\r   CALIOP\t\r   support\t\r   the\t\r   positive\t\r  cloud-­‐temperature-­‐ice\t\r   feedback\t\r   hypothesis\t\r   that\t\r   has\t\r   been\t\r   proposed\t\r   as\t\r   a\t\r   cause\t\r   of\t\r   accelerated\t\r  surface\t\r  air\t\r  temperature\t\r  increase\t\r  in\t\r  the\t\r  past\t\r  decade\t\r  (Wu\t\r  and\t\r  Lee,\t\r  2012).\t\r  \t\r  \t\r  \n\u003c/p\u003e\n\u003cp\u003e\t\r  Figure\t\r  4:\t\r  Annual\t\r  cycle\t\r  of\t\r  simulated\t\r  mean\t\r  cloudiness\t\r  (thick\t\r  solid\t\r  lines)\t\r  and\t\r  intermodel\t\r  standard\t\r  deviation\t\r  (dashed)\t\r  areally\t\r  averaged\t\r  over\t\r  the\t\r  Arctic\t\r  (70°–90°N):\t\r  (left)\t\r  Total\t\r  cloud\t\r  amount,\t\r  (right)\t\r  Low,\t\r  medium,\t\r  and\t\r  high\t\r  cloud\t\r  amounts.\t\r  The\t\r  observations\t\r  (thin\t\r  line)\t\r  are\t\r  the\t\r  average\t\r  of\t\r  four\t\r  surface-­‐based\t\r  and\t\r  eight\t\r  satellite-­‐derived\t\r  data\t\r  sets\t\r  described\t\r  in\t\r  Vavrus\t\r  and\t\r  Waliser\t\r  (2008)\t\r  with\t\r  error\t\r  bars\t\r  representing\t\r  the\t\r  upper\t\r  and\t\r  lower\t\r  quartile\t\r  of\t\r  reported\t\r  values.\t\r  [From\t\r  Vavrus\t\r  et\t\r  al.,\t\r  2009] \t\r  Vavrus\t\r  et\t\r  al.\t\r   (2009)\t\r   found\t\r   that\t\r   the\t\r  AR4\t\r  models\t\r   correctly\t\r   simulated\t\r  Arctic\t\r   cloudiness\t\r  as\t\r  a\t\r   strong\t\r  function\t\r   of\t\r   surface\t\r   type.\t\r   Models\t\r   agree\t\r   on\t\r   simulating\t\r   very\t\r   cloudy\t\r   conditions\t\r   over\t\r   the\t\r   ice\t\r   pack\t\r  during\t\r   summer,\t\r   but\t\r  disagree\t\r   in\t\r   the\t\r   simulations\t\r  over\t\r  Greenland\t\r   in\t\r   all\t\r   seasons\t\r   and\t\r  during\t\r  winter\t\r  above\t\r   the\t\r   ice\t\r   pack\t\r   and\t\r   Canadian\t\r   Archipelago.\t\r   The\t\r   models\t\r   simulate\t\r   summertime\t\r   Arctic\t\r   cloud\t\r  amount\t\r  well,\t\r  but\t\r  perform\t\r  poorly\t\r   in\t\r   simulating\t\r  cloudiness\t\r  during\t\r  winter,\t\r  when\t\r   they\t\r  overproduce\t\r  clouds\t\r  and\t\r  exhibit\t\r  the\t\r  greatest\t\r  amount\t\r  of\t\r  inter-­‐model\t\r  spread\t\r  (Figure\t\r  4).\t\r  Low\t\r  clouds\t\r  are\t\r  correctly\t\r  modeled\t\r   as\t\r   the\t\r   prevailing\t\r   cloud\t\r   type\t\r   in\t\r   the\t\r   Arctic.\t\r   However,\t\r   models\t\r   disagree\t\r   in\t\r   the\t\r   simulated\t\r  magnitude\t\r  of\t\r   low\t\r  cloud\t\r  amount,\t\r  particularly\t\r  during\t\r  winter.\t\r  One-­‐third\t\r  of\t\r  the\t\r  models\t\r  simulated\t\r  an\t\r  inverted\t\r  annual\t\r  cycle\t\r  (more\t\r  clouds\t\r  in\t\r  winter\t\r  than\t\r  summer).\t\r  These\t\r  differences\t\r  may\t\r  relate\t\r  to\t\r  biases\t\r  in\t\r   the\t\r   sea\t\r   ice\t\r   distribution\t\r   or\t\r   circulation\t\r   patterns\t\r   and\t\r   are\t\r   clear\t\r   targets\t\r   for\t\r   model\t\r   improvement.\t\r  \u003c/p\u003e\n\u003cp /\u003e\n\u003c/div\u003e\n\u003cdiv class\u003d\"page\"\u003e\u003cp /\u003e\n\u003cp\u003e\t\r  \u003c/p\u003e\n\u003cp\u003e\t\r   6\t\r  \n\u003c/p\u003e\n\u003cp\u003eWhereas\t\r  the\t\r  models\t\r  consistently\t\r  simulate\t\r  similar\t\r   fairly\t\r  small\t\r   increases\t\r   in\t\r  summer\t\r  temperatures,\t\r  the\t\r  autumn\t\r  peak\t\r  in\t\r  low-­‐level\t\r  warming\t\r  is\t\r  not\t\r  represented\t\r  in\t\r  all\t\r  models\t\r  (Serreze\t\r  et\t\r  al.,\t\r  2009).\t\r  An\t\r  issue\t\r  for\t\r  observations\t\r  used\t\r  in\t\r  model\t\r  evaluations\t\r  is\t\r  that\t\r  cloud\t\r  detection\t\r  using\t\r  satellite\t\r  data\t\r  over\t\r  the\t\r   Arctic\t\r   can\t\r   be\t\r   difficult\t\r   because\t\r   of\t\r   the\t\r   poor\t\r   contrast\t\r   between\t\r   clouds\t\r   and\t\r   icy/snowy\t\r   surfaces.\t\r  Depending\t\r   on\t\r   the\t\r   threshold\t\r   being\t\r   used\t\r   to\t\r   identify\t\r   a\t\r   cloud\t\r   (e.g.,\t\r   the\t\r   minimum\t\r   optical\t\r   depth),\t\r   a\t\r  sensor\t\r   can\t\r   yield\t\r   a\t\r   number\t\r   of\t\r   possible\t\r   cloud\t\r   amounts,\t\r   especially\t\r   during\t\r   the\t\r   dry\t\r   winter\t\r   months\t\r  when\t\r   only\t\r   the\t\r   infrared\t\r   channels\t\r   can\t\r   be\t\r   used\t\r   for\t\r   cloud\t\r   characterization.\t\r   Inconsistencies\t\r   in\t\r   cloud\t\r  characterization\t\r   derived\t\r   from\t\r   different\t\r   cloud\t\r   sensors\t\r   (e.g.,\t\r   Aqua/MODIS,\t\r   CloudSat/CPR\t\r   and\t\r  CALIPSO/CALIOP)\t\r   have\t\r   also\t\r   been\t\r   reported\t\r   (Liu\t\r   et\t\r   al.,\t\r   2010;\t\r   Chan\t\r   and\t\r   Comiso,\t\r   2011).\t\r   Some\t\r  surface-­‐based\t\r  measurements\t\r  are\t\r  also\t\r  suspect\t\r  because\t\r  the\t\r  temperature\t\r  sensors\t\r  can\t\r  be\t\r  covered\t\r  by\t\r  snow.\t\r  \t\r  The\t\r  climate\t\r  model\t\r  community\t\r  has\t\r  more\t\r  recently\t\r  undertaken\t\r  comparisons,\t\r  not\t\r  only\t\r  in\t\r  terms\t\r  of\t\r   cloud\t\r   fraction\t\r   but\t\r   also\t\r   in\t\r   terms\t\r   of\t\r   more\t\r   direct\t\r   comparisons\t\r   with\t\r   measurements\t\r   through\t\r  simulators.\t\r   The\t\r   Cloud\t\r   Feedbacks\t\r  Model\t\r   Intercomparison\t\r   Project\t\r   (CFMIP)\t\r   Observation\t\r   Simulator\t\r  Package\t\r   (COSP)\t\r   produces\t\r   climate\t\r   model\t\r   diagnostics\t\r   that\t\r   can\t\r   be\t\r   compared\t\r   with\t\r   satellite\t\r   data\t\r  products\t\r   from\t\r   ISCCP,\t\r   MISR,\t\r   MODIS,\t\r   CloudSAT,\t\r   CALIPSO,\t\r   and\t\r   PARASOL.\t\r   Simulator-­‐facilitated\t\r  evaluation\t\r  of\t\r  cloud\t\r  properties,\t\r  such\t\r  as\t\r  amount\t\r  by\t\r  vertical\t\r  level\t\r  and\t\r  optical\t\r  depth,\t\r  can\t\r  expose\t\r  large,\t\r  and\t\r  at\t\r  times\t\r  radiatively-­‐compensating,\t\r  climate\t\r  model\t\r  cloud\t\r  biases\t\r  (e.g.,\t\r  Kay\t\r  et\t\r  al.,\t\r  2012).\t\r  \t\r  \n\u003c/p\u003e\n\u003cp\u003e\t\r  Figure\t\r  5:\t\r  Time\t\r  series\t\r  for\t\r  a\t\r  two-­‐day\t\r  simulation\t\r  plotted\t\r  over\t\r  Oliktok\t\r  Point\t\r  for\t\r  Standard\t\r  IN\t\r  and\t\r  M-­‐PACE\t\r  IN\t\r  concentrations:\t\r  (a)\t\r  liquid\t\r  water\t\r  path\t\r  (g\t\r  m-­‐2)\t\r  and\t\r  (b)\t\r  net\t\r  infrared\t\r  surface\t\r  flux\t\r  (W\t\r  m-­‐2,\t\r  negative\t\r  values\t\r  indicate\t\r  surface\t\r  cooling\t\r  by\t\r  infrared\t\r  emission).\t\r  The\t\r  solid\t\r  black\t\r  points\t\r  represent\t\r  observed\t\r  values:\t\r  (a)\t\r  microwave\t\r  radiometer\t\r  measurements,\t\r  and\t\r  (b)\t\r  surface\t\r  infrared\t\r  flux\t\r  measurements.\t\r  Multipliers\t\r  in\t\r  front\t\r  of\t\r  M-­‐PACE\t\r  IN\t\r  indicate\t\r  the\t\r  factor\t\r  by\t\r  which\t\r  the\t\r  M-­‐PACE\t\r  IN\t\r  concentrations\t\r  were\t\r  increased\t\r  in\t\r  the\t\r  model.\t\r  “Dep”\t\r  indicates\t\r  that\t\r  IN\t\r  were\t\r  depleted\t\r  by\t\r  ice\t\r  precipitation\t\r  whereas\t\r  “No\t\r  Dep”\t\r  indicates\t\r  that\t\r  IN\t\r  were\t\r  not\t\r  depleted.\t\r  [From\t\r  Prenni\t\r  et\t\r  al.\t\r  (2007)]\t\r  \t\r  Even\t\r  current\t\r  state-­‐of-­‐the-­‐art\t\r  cloud-­‐resolving\t\r  models\t\r  have\t\r  serious\t\r  difficulties\t\r  reproducing\t\r  observed\t\r  cloud\t\r   fields\t\r   from\t\r  field\t\r  campaigns\t\r  (Klein\t\r  et\t\r  al.,\t\r  2009;\t\r  Morrison\t\r  et\t\r  al.,\t\r  2011;\t\r  Avramov\t\r  et\t\r  al.,\t\r  2011).\t\r  Some\t\r   of\t\r   the\t\r   difficulties\t\r   in\t\r   modeling\t\r   Arctic\t\r   clouds\t\r   result\t\r   from\t\r   inaccuracies\t\r   in\t\r   microphysical\t\r  parameterizations,\t\r  particularly\t\r  ice\t\r  nucleation\t\r  parameterizations\t\r  (Figure\t\r  5;\t\r  Prenni\t\r  et\t\r  al.,\t\r  2007).\t\r  The\t\r  interaction\t\r  of\t\r  aerosols\t\r  and\t\r  clouds\t\r  is\t\r  critical\t\r  to\t\r  these\t\r  parameterizations.\t\r  \t\r  Aerosols\t\r   act\t\r   as\t\r   Cloud\t\r   Condensation\t\r   Nuclei\t\r   (CCN)\t\r   and\t\r   Ice\t\r   Nuclei\t\r   (IN),\t\r   affecting\t\r   the\t\r   formation\t\r   of\t\r  cloud\t\r  droplets\t\r  and\t\r  ice\t\r  crystals,\t\r  which\t\r  then\t\r  may\t\r  alter\t\r  cloud\t\r  radiative\t\r  processes\t\r  and\t\r  cloud\t\r  lifetime\t\r  by\t\r  changing\t\r  precipitation\t\r  processes.\t\r  Higher\t\r  concentrations\t\r  of\t\r   ice\t\r  particles\t\r  generally\t\r   lead\t\r  to\t\r  rapid\t\r  glaciation\t\r   of\t\r   a\t\r   mixed-­‐phase\t\r   cloud.\t\r   These\t\r   drastic\t\r   changes\t\r   in\t\r   microphysics\t\r   affect\t\r   the\t\r   radiation\t\r  balance\t\r   in\t\r   the\t\r   cloud\t\r   layer\t\r   as\t\r   well\t\r   as\t\r   at\t\r   the\t\r   surface,\t\r   but\t\r   they\t\r   also\t\r   alter\t\r   cloud\t\r   dynamics\t\r   and\t\r  \u003c/p\u003e\n\u003cp /\u003e\n\u003c/div\u003e\n\u003cdiv class\u003d\"page\"\u003e\u003cp /\u003e\n\u003cp\u003e\t\r  \u003c/p\u003e\n\u003cp\u003e\t\r   7\t\r  \n\u003c/p\u003e\n\u003cp\u003emacrostructure\t\r  (e.g.,\t\r  Ovchinnikov\t\r  et\t\r  al.,\t\r  2011).\t\r  \t\r  An\t\r   issue\t\r   for\t\r  modeling\t\r   Arctic\t\r   clouds\t\r   is\t\r   that\t\r   Arctic\t\r   aerosol\t\r   properties\t\r   are\t\r   different\t\r   from\t\r   those\t\r   at\t\r  lower\t\r   latitudes\t\r   (Prenni,\t\r   2007).\t\r   While\t\r   IN\t\r   only\t\r   represent\t\r   a\t\r   small\t\r   fraction\t\r   of\t\r   the\t\r   total\t\r   aerosol\t\r  population,\t\r  their\t\r  net\t\r  impact\t\r  on\t\r  clouds\t\r  remains\t\r  highly\t\r  uncertain.\t\r  To\t\r  improve\t\r  models,\t\r  it\t\r  is\t\r  important\t\r  to\t\r  understand\t\r  how\t\r  CCN\t\r  and\t\r  IN\t\r  together\t\r  impact\t\r  cloud\t\r  microphysical\t\r  properties,\t\r  phase\t\r  partitioning,\t\r  and\t\r  evolution.\t\r  Unfortunately,\t\r  the\t\r  measurements\t\r  of\t\r  ice\t\r  nucleus\t\r  properties\t\r  and\t\r  ice\t\r  crystal\t\r  properties\t\r  that\t\r  are\t\r  needed\t\r  are\t\r  not\t\r  yet\t\r  available\t\r  (Fridlind\t\r  et\t\r  al.,\t\r  2012).\t\r  Substantial\t\r  instrument\t\r  development\t\r  is\t\r  needed\t\r   to\t\r   measure\t\r   ice\t\r   nucleation\t\r   spectra\t\r   in\t\r   various\t\r   modes\t\r   and\t\r   to\t\r   measure\t\r   ice\t\r   single-­‐particle\t\r  properties\t\r   (McFarquhar\t\r   et\t\r   al.,\t\r   2007;\t\r   Fridlind\t\r   et\t\r   al.,\t\r   2007)\t\r   to\t\r   support\t\r   validation\t\r   of\t\r   their\t\r  representation\t\r  in\t\r  microphysics\t\r  parameterizations\t\r  (e.g.,\t\r  Barahona,\t\r  2012).\t\r  \t\r  \nDevelopment\t\r  of\t\r  cloud\t\r  microphysics\t\r  parameterizations\t\r  to\t\r  model\t\r  super-­‐cooled\t\r  liquid,\t\r  mixed-­‐phase\t\r  and\t\r  \nice\t\r  clouds\t\r  in\t\r  GCMs\t\r  is\t\r  a\t\r  priority.\t\r  Because\t\r  of\t\r  the\t\r  many\t\r  known\t\r  gaps\t\r  in\t\r  our\t\r  knowledge\t\r  of\t\r  cloud\t\r  processes,\t\r  \ncomprehensive\t\r  field\t\r  experiment\t\r  case\t\r  studies\t\r  are\t\r  required\t\r  to\t\r  evaluate\t\r  simulation\t\r  fidelity.\t\r  \t\r  Despite\t\r  some\t\r  local\t\r  seasonal\t\r  natural\t\r  and\t\r  anthropogenic\t\r  sources\t\r  (e.g.,\t\r  Law\t\r  and\t\r  Stohl,\t\r  2007),\t\r  aerosol\t\r  pollutants\t\r  in\t\r  the\t\r  Arctic\t\r  lower\t\r  troposphere\t\r  (Arctic\t\r  haze)\t\r  originate\t\r  from\t\r  a\t\r  mixture\t\r  of\t\r  lower-­‐latitude\t\r  forest\t\r   fires,\t\r   agricultural\t\r   fires\t\r   (e.g.,\t\r   Hegg\t\r   et\t\r   al.,\t\r   2010;\t\r  Wang\t\r   et\t\r   al.,\t\r   2011)\t\r   and\t\r   industrial\t\r   activities\t\r  (Rahn\t\r  et\t\r  al.,\t\r  1977).\t\r  During\t\r  winter\t\r  the\t\r  polar\t\r  front\t\r  expands\t\r  equatorward\t\r  as\t\r  far\t\r  as\t\r  40°N,\t\r  so\t\r  aerosols\t\r  from\t\r  major\t\r   source\t\r   regions\t\r   in\t\r  Asia,\t\r   Europe\t\r   and\t\r  North\t\r  America\t\r   can\t\r   be\t\r   rapidly\t\r   transported\t\r   to\t\r   the\t\r  Arctic\t\r   (e.g.,\t\r  Fisher\t\r  et\t\r  al.,\t\r  2011)\t\r  and\t\r   impact\t\r  Arctic\t\r   climatology\t\r   (Menon\t\r  et\t\r  al.,\t\r  2008)\t\r  and\t\r  ecological\t\r  systems\t\r  (Muir\t\r  et\t\r  al.,\t\r  1992).\t\r  They\t\r  perturb\t\r  solar\t\r  reflection\t\r  and\t\r  thermal\t\r  radiative\t\r  emission\t\r  by\t\r  clouds\t\r  and\t\r   they\t\r   directly\t\r   scatter\t\r   sunlight\t\r   back\t\r   to\t\r   space.\t\r   While\t\r   the\t\r   more\t\r   abundant\t\r   sulfate\t\r   and\t\r   organic\t\r  matter\t\r  particles\t\r  in\t\r  the\t\r  Arctic\t\r  haze\t\r  likely\t\r  cool\t\r  air\t\r  at\t\r  the\t\r  surface,\t\r  light-­‐absorbing\t\r  black\t\r  carbon\t\r  (BC),\t\r  a\t\r  minor\t\r  but\t\r  important\t\r  component\t\r  of\t\r  the\t\r  Arctic\t\r  haze\t\r  (Sharma\t\r  et\t\r  al.,\t\r  2006),\t\r  can\t\r  directly\t\r  heat\t\r  the\t\r  haze\t\r  layer\t\r  and\t\r  subsequently\t\r  warm\t\r  the\t\r  surface\t\r  through\t\r  enhanced\t\r  downward\t\r  LW\t\r  radiation\t\r  (Quinn\t\r  et\t\r  al.,\t\r  2007).\t\r   In\t\r  addition,\t\r  absorbing\t\r  aerosol\t\r  particles\t\r  deposited\t\r  onto\t\r  snow\t\r  and\t\r  ice\t\r  surfaces\t\r  can\t\r  enhance\t\r  absorption\t\r   of\t\r   shortwave\t\r   (SW)\t\r   radiation\t\r   at\t\r   the\t\r   surface,\t\r   resulting\t\r   in\t\r   a\t\r   warming\t\r   of\t\r   the\t\r   lower\t\r  atmosphere\t\r  and\t\r  more\t\r  rapid\t\r  melting\t\r  of\t\r  snow\t\r  and\t\r  ice\t\r  (Warren\t\r  and\t\r  Wiscombe,\t\r  1980;\t\r  Flanner\t\r  et\t\r  al.,\t\r  2009).\t\r  \t\r  \t\r  \t\r  \n\u003c/p\u003e\n\u003cp\u003e\t\r  \t\r  \n\u003c/p\u003e\n\u003cp\u003e\t\r   \t\r  \n\u003c/p\u003e\n\u003cp\u003e\t\r  \t\r  \n\t\r  \t\r  \n\u003c/p\u003e\n\u003cp\u003e\t\r   \t\r  \n\u003c/p\u003e\n\u003cp\u003e\t\r  Figure\t\r  6:\t\r  Observed\t\r  and\t\r  modeled\t\r  seasonal\t\r  cycles\t\r  of\t\r  CO\t\r  (upper)\t\r  and\t\r  BC\t\r  (lower)\t\r  surface\t\r  concentrations\t\r  at\t\r  Barrow\t\r  (left)\t\r  and\t\r  Alert\t\r  (right).\t\r  Results\t\r  from\t\r  17\t\r  models\t\r  are\t\r  in\t\r  grey.\t\r  Plots\t\r  for\t\r  CO\t\r  show\t\r  observations\t\r  from\t\r  the\t\r  NOAA\t\r  Global\t\r  Monitoring\t\r  Division,\t\r  with\t\r  1992-­‐2006\t\r  means\t\r  and\t\r  standard\t\r  deviations\t\r  in\t\r  red\t\r  and\t\r  2001\t\r  in\t\r  blue.\t\r  BC\t\r  data\t\r  are\t\r  from\t\r  Barrow\t\r  during\t\r  1996-­‐1998\t\r  (red),\t\r  and\t\r  from\t\r  Sharma\t\r  et\t\r  al.\t\r  (2006)\t\r  using\t\r  equivalent\t\r  BC\t\r  over\t\r  1989-­‐2003\t\r  (purple).\t\r  [From\t\r  Shindell\t\r  et\t\r  al.\t\r  (2008)]\t\r  \t\r  \u003c/p\u003e\n\u003cp /\u003e\n\u003c/div\u003e\n\u003cdiv class\u003d\"page\"\u003e\u003cp /\u003e\n\u003cp\u003e\t\r  \u003c/p\u003e\n\u003cp\u003e\t\r   8\t\r  \n\u003c/p\u003e\n\u003cp\u003eGarrett\t\r   et\t\r   al.\t\r   (2011)\t\r   showed\t\r   that\t\r   the\t\r   seasonal\t\r   cycle\t\r   of\t\r   Arctic\t\r   BC\t\r   is\t\r   primarily\t\r   driven\t\r   by\t\r   wet\t\r  scavenging\t\r  of\t\r   lower-­‐latitude\t\r  sources\t\r  en\t\r  route\t\r  to\t\r  the\t\r  Arctic\t\r  at\t\r  near-­‐freezing\t\r  temperatures.\t\r  Models\t\r  struggle\t\r   to\t\r   reproduce\t\r   the\t\r   observed\t\r   Arctic\t\r   aerosol\t\r   seasonality\t\r   (Figure\t\r   6),\t\r   perhaps\t\r   because\t\r   fast\t\r  processes\t\r   such\t\r   as\t\r   wet\t\r   scavenging\t\r   are\t\r   exceptionally\t\r   difficult\t\r   to\t\r   parameterize\t\r   within\t\r   the\t\r   coarse\t\r  spatial\t\r   grid\t\r   of\t\r   climate\t\r   models\t\r   (Shindell\t\r   et\t\r   al.,\t\r   2008).\t\r   In\t\r   addition,\t\r   climate\t\r   models\t\r   tend\t\r   to\t\r  overestimate\t\r   low\t\r  clouds\t\r   in\t\r   the\t\r  Arctic\t\r   region,\t\r  particularly\t\r  wintertime\t\r   low-­‐level\t\r   liquid\t\r  clouds\t\r  (e.g.,\t\r  Vavrus\t\r  and\t\r  Waliser,\t\r  2008;\t\r  Qian\t\r  et\t\r  al.,\t\r  2012).\t\r  This\t\r  can\t\r  be\t\r  a\t\r  potentially\t\r  important\t\r  contributor\t\r  to\t\r  the\t\r  under-­‐prediction\t\r  of\t\r  BC\t\r  and\t\r  other\t\r  aerosol\t\r  species\t\r  in\t\r  the\t\r  Arctic\t\r  by\t\r  climate\t\r  models\t\r  (e.g.,\t\r  Wang\t\r  et\t\r  al.,\t\r  2012;\t\r  Koch\t\r  et\t\r  al.,\t\r  2009).\t\r  \nA\t\r   field\t\r   campaign\t\r   targeting\t\r  aerosol\t\r  wet\t\r   removal\t\r  by\t\r   super-­‐cooled\t\r   liquid,\t\r  mixed-­‐phase\t\r  and\t\r   ice\t\r   clouds,\t\r  \nalong\t\r  with\t\r  observations\t\r  from\t\r  CloudSAT,\t\r  CALIPSO\t\r  and\t\r  other\t\r  A-­‐train\t\r  sensors,\t\r  would\t\r  be\t\r  very\t\r  helpful\t\r  to\t\r  \nincrease\t\r   the\t\r   understanding\t\r   of\t\r   aerosol\t\r   transport\t\r   to\t\r   the\t\r   Arctic\t\r   from\t\r   lower\t\r   latitudes\t\r   and\t\r   subsequent\t\r  \ndeposition\t\r  onto\t\r  snow\t\r  and\t\r  ice\t\r  within\t\r  the\t\r  Arctic,\t\r  and\t\r  to\t\r  improve\t\r  the\t\r  representation\t\r  of\t\r  these\t\r  processes\t\r  in\t\r  \nglobal\t\r  models.\t\r  \t\r  \t\r  Longwave\t\r   radiation\t\r  dominates\t\r   the\t\r   surface\t\r   energy\t\r  balance\t\r  of\t\r   the\t\r  Arctic\t\r  Ocean\t\r  during\t\r   all\t\r   seasons\t\r  and\t\r   plays\t\r   a\t\r   major\t\r   role\t\r   in\t\r   the\t\r   climate\t\r   feedback\t\r   (Curry\t\r   et\t\r   al.,\t\r   1996,\t\r   1997),\t\r   yet\t\r   downwelling\t\r   LW\t\r  radiation\t\r  is\t\r  still\t\r  poorly\t\r  known\t\r  over\t\r  both\t\r  land\t\r  and\t\r  ocean,\t\r  especially\t\r  in\t\r  winter.\t\r  Many\t\r  climate\t\r  models\t\r  overestimate\t\r  surface\t\r  absorption\t\r  of\t\r  solar\t\r  radiation\t\r  partly\t\r  due\t\r  to\t\r  problems\t\r  in\t\r  the\t\r  parameterizations\t\r  of\t\r   atmospheric\t\r   absorption,\t\r   clouds\t\r   and\t\r   aerosols\t\r   (Randall\t\r   et\t\r   al.,\t\r   2007).\t\r   Difficulties\t\r   in\t\r   simulating\t\r  absorbed\t\r   solar\t\r   and\t\r   infrared\t\r   radiation\t\r   at\t\r   the\t\r   surface\t\r   leads\t\r   inevitably\t\r   to\t\r   uncertainty\t\r   in\t\r   the\t\r  simulation\t\r  of\t\r  surface\t\r  sensible\t\r  and\t\r  latent\t\r  heat\t\r  fluxes.\t\r  \nThe\t\r  DOE\t\r  ARM\t\r  observations\t\r   should\t\r  be\t\r   extended,\t\r  with\t\r  an\t\r   emphasis\t\r   on\t\r  getting\t\r  better\t\r   observations\t\r  of\t\r  \ncloud\t\r  ice\t\r  properties\t\r  and\t\r  their\t\r  effects\t\r  on\t\r  the\t\r  radiation\t\r  budget.\t\r  The\t\r  satellite\t\r  remote\t\r  sensing\t\r  component\t\r  \nshould\t\r  be\t\r  well\t\r  supported.\t\r  A\t\r  long-­‐term\t\r  follow-­‐on\t\r  to\t\r  SHEBA\t\r  (Surface\t\r  Heat\t\r  Budget\t\r  of\t\r  the\t\r  Arctic\t\r  Ocean),\t\r  \nlike\t\r   the\t\r   proposed\t\r   multi-­‐year\t\r   MOSAiC\t\r   (Multi-­‐disciplinary\t\r   drifting\t\r   Observatory\t\r   for\t\r   the\t\r   Study\t\r   of\t\r   the\t\r  \nArctic\t\r   Climate)\t\r   project,\t\r   should\t\r   be\t\r   conducted\t\r   with\t\r   21st\t\r   century\t\r   observing\t\r   capabilities\t\r   that\t\r   sample\t\r  \nmany\t\r   different\t\r   thermodynamic\t\r   and\t\r   dynamic\t\r   environments\t\r   under\t\r   clean\t\r   and\t\r   polluted\t\r   situations,\t\r  \nproviding\t\r  insights\t\r  into\t\r  the\t\r  larger-­‐scale\t\r  controls\t\r  on\t\r  cloud\t\r  cover\t\r  and\t\r  cloud\t\r  properties.\t\r  In\t\r   addition\t\r   to\t\r   examination\t\r   of\t\r   Arctic\t\r   cloud\t\r   distributions,\t\r   climate\t\r   model\t\r   evaluations\t\r   have\t\r   also\t\r  considered\t\r   the\t\r   representation\t\r   of\t\r   surface\t\r   boundary\t\r   layer\t\r   temperature\t\r   inversions,\t\r   which\t\r   are\t\r  ubiquitous\t\r   in\t\r   the\t\r   lower\t\r   Arctic\t\r   atmosphere.\t\r   The\t\r   inversions\t\r   occur\t\r   frequently\t\r   in\t\r   the\t\r   lowest\t\r   few\t\r  hundred\t\r  meters\t\r   above\t\r   the\t\r   surface\t\r   throughout\t\r   all\t\r   seasons\t\r   and\t\r   are\t\r  most\t\r   persistent\t\r   and\t\r   strongest\t\r  during\t\r   the\t\r   winter\t\r   months\t\r   when\t\r   surface\t\r   solar\t\r   heating\t\r   is\t\r   minimal\t\r   or\t\r   absent.\t\r   Boé\t\r   et\t\r   al.\t\r   (2009)\t\r  demonstrated\t\r  that\t\r  temperature\t\r  inversions\t\r  in\t\r  the\t\r  lower-­‐Arctic\t\r  atmosphere\t\r  regulate\t\r  heat\t\r  content\t\r  of\t\r  the\t\r   upper-­‐Arctic\t\r   Ocean\t\r   through\t\r   modification\t\r   of\t\r   outgoing\t\r   LW\t\r   radiation.\t\r   CMIP3\t\r   models\t\r   over-­‐predicted\t\r  atmospheric\t\r   inversion\t\r  strength,\t\r  and\t\r  some\t\r  models\t\r  were\t\r   found\t\r   to\t\r  exaggerate\t\r   stable\t\r  and\t\r  underestimate\t\r   unstable\t\r   regimes\t\r   (Medeiros\t\r   et\t\r   al.,\t\r   2011).\t\r   An\t\r   examination\t\r   of\t\r   CCSM4\t\r   found\t\r   the\t\r  atmospheric\t\r  boundary\t\r   layer\t\r   in\t\r   the\t\r  model\t\r   is\t\r   too\t\r   stable\t\r   as\t\r   compared\t\r   to\t\r  ERA-­‐40\t\r  and\t\r  ERA-­‐Interim,\t\r  particularly\t\r  during\t\r  spring\t\r  over\t\r  both\t\r  land\t\r  and\t\r  ocean\t\r  surfaces.\t\r  The\t\r  surface\t\r  inversions\t\r  were\t\r  still\t\r  too\t\r  strong\t\r   (by\t\r   nearly\t\r   a\t\r   factor\t\r   of\t\r   two)\t\r   and\t\r   too\t\r   numerous.\t\r   Thus,\t\r   boundary\t\r   layers\t\r   continue\t\r   to\t\r   be\t\r  \nchallenging\t\r  for\t\r  models,\t\r  particularly\t\r  in\t\r  the\t\r  highly\t\r  stratified\t\r  Arctic,\t\r  and\t\r  should\t\r  be\t\r  a\t\r  priority\t\r  for\t\r  future\t\r  \nmodel\t\r  development.\t\r  Climate\t\r   sensitivity\t\r   to\t\r   planetary\t\r   boundary\t\r   layer\t\r   (PBL)\t\r   depth\t\r   has\t\r   been\t\r   shown\t\r   to\t\r   be\t\r   largest\t\r   for\t\r  shallow\t\r  stable\t\r  boundary\t\r  layer\t\r  regimes\t\r  (Knight\t\r  et\t\r  al.,\t\r  2007),\t\r  such\t\r  as\t\r  would\t\r  be\t\r  found\t\r  at\t\r  night\t\r  or\t\r  in\t\r  wintertime.\t\r   Model\t\r   overestimation\t\r   of\t\r   stable\t\r   PBL\t\r   heights\t\r   may\t\r   contribute\t\r   to\t\r   underestimation\t\r   of\t\r  climate\t\r  sensitivity\t\r  (Esau\t\r  et\t\r  al.,\t\r  2010).\t\r  In-­‐situ\t\r  measurements\t\r  of\t\r  PBL\t\r  height,\t\r  for\t\r  example\t\r  using\t\r  LIDAR,\t\r  \u003c/p\u003e\n\u003cp /\u003e\n\u003c/div\u003e\n\u003cdiv class\u003d\"page\"\u003e\u003cp /\u003e\n\u003cp\u003e\t\r  \u003c/p\u003e\n\u003cp\u003e\t\r   9\t\r  \n\u003c/p\u003e\n\u003cp\u003eover\t\r  an\t\r  expanded\t\r  area\t\r  are\t\r  needed\t\r  to\t\r  confirm\t\r  this\t\r  hypothesis.\t\r  To\t\r  identify\t\r  the\t\r  causes\t\r  for\t\r  the\t\r  apparent\t\r  \noverestimate\t\r   in\t\r   PBL\t\r   depth,\t\r   moisture\t\r   and\t\r   wind\t\r   profile\t\r   measurements\t\r   and\t\r   surface\t\r   enthalpy\t\r   flux\t\r  \nmeasurements\t\r  are\t\r  needed.\t\r  These\t\r  would\t\r  answer\t\r  questions\t\r  about\t\r  whether\t\r  models\t\r  respond\t\r  incorrectly\t\r  \nto\t\r   wind\t\r   shear\t\r   or\t\r   whether\t\r   the\t\r   surface\t\r   enthalpy\t\r   flux\t\r   is\t\r   overestimated.\t\r   Raman\t\r   LIDAR\t\r   for\t\r   moisture\t\r  \nprofiles\t\r  should\t\r  be\t\r  added\t\r  to\t\r  any\t\r  backscatter\t\r  lidar\t\r  measurements.\t\r  \n2.2 Ocean\t\r  and\t\r  Sea\t\r  Ice\t\r  –\t\r  Physical\t\r  Climate\t\r  System\t\r  Both\t\r  ocean\t\r  and\t\r  sea-­‐ice\t\r  processes\t\r  represent\t\r  critical\t\r  components\t\r  of\t\r  the\t\r  Arctic\t\r  and\t\r  the\t\r  global\t\r  climate\t\r  system.\t\r  The\t\r  formation\t\r  of\t\r  North\t\r  Atlantic\t\r  Deep\t\r  Water\t\r  (NADW)\t\r  is\t\r  an\t\r  important\t\r  factor\t\r  in\t\r  maintaining\t\r  the\t\r  thermohaline\t\r  circulation\t\r  that\t\r  transports\t\r  heat\t\r  from\t\r  the\t\r  tropics\t\r  through\t\r  the\t\r  Atlantic\t\r  Ocean\t\r  to\t\r  the\t\r  Arctic.\t\r  An\t\r  important\t\r  element\t\r  in\t\r  NADW\t\r  formation\t\r  is\t\r  the\t\r  freshwater\t\r  export\t\r  from\t\r  the\t\r  Arctic\t\r  Ocean\t\r  to\t\r  the\t\r  North\t\r  Atlantic\t\r  subpolar\t\r  seas,\t\r  where\t\r  a\t\r  freshwater\t\r  cap\t\r  can\t\r  effectively\t\r  stabilize\t\r  the\t\r  water\t\r  column.\t\r  \t\r  Sea\t\r  ice\t\r  cover\t\r  is\t\r  particularly\t\r  important\t\r  because\t\r  it\t\r  buffers\t\r  air-­‐sea\t\r  heat\t\r  fluxes\t\r  and\t\r  strongly\t\r  influences\t\r  Earth’s\t\r   absorption\t\r   of\t\r   solar\t\r   radiation\t\r   through\t\r   ice-­‐albedo\t\r   feedback.\t\r   As\t\r   the\t\r   climate\t\r   warms,\t\r   the\t\r  summer\t\r  melt\t\r  season\t\r  lengthens\t\r  and\t\r  intensifies,\t\r  leading\t\r  to\t\r  less\t\r  sea\t\r  ice\t\r  at\t\r  summer’s\t\r  end.\t\r  Summertime\t\r  absorption\t\r   of\t\r   solar\t\r   energy\t\r   in\t\r   open\t\r   water\t\r   areas\t\r   increases\t\r   the\t\r   heat\t\r   content\t\r   of\t\r   the\t\r   ocean.\t\r   Ice\t\r  formation\t\r   in\t\r   autumn\t\r   and\t\r   winter,\t\r   important\t\r   for\t\r   insulating\t\r   the\t\r   warm\t\r   ocean\t\r   from\t\r   the\t\r   cooling\t\r  atmosphere,\t\r  is\t\r  delayed.\t\r  This\t\r  promotes\t\r  enhanced\t\r  upward\t\r  heat\t\r  fluxes,\t\r  seen\t\r  as\t\r  strong\t\r  warming\t\r  at\t\r  the\t\r  surface\t\r  and\t\r  in\t\r  the\t\r  lower\t\r  troposphere.\t\r  \t\r  A\t\r  unique\t\r   feature\t\r  affecting\t\r   the\t\r   freshwater\t\r   content\t\r  within\t\r  and\t\r  export\t\r   from\t\r   the\t\r  Arctic\t\r  Ocean\t\r   is\t\r   the\t\r  Beaufort\t\r  Gyre\t\r   freshwater\t\r  reservoir,\t\r   comprising\t\r  a\t\r  set\t\r  of\t\r  specific\t\r  atmospheric,\t\r   sea\t\r   ice,\t\r  and\t\r  oceanic\t\r  conditions\t\r  and\t\r  interactions\t\r  that\t\r  have\t\r  significant\t\r  influence\t\r  on\t\r  Arctic\t\r  and\t\r  global\t\r  climate.\t\r  Besides\t\r  the\t\r  disappearing\t\r  sea\t\r  ice\t\r  cover,\t\r  the\t\r  Beaufort\t\r  Gyre\t\r  freshwater\t\r  reservoir\t\r  is\t\r  the\t\r  next\t\r  largest\t\r  entity\t\r  in\t\r  the\t\r  Arctic\t\r  Ocean\t\r  where\t\r  we\t\r  expect\t\r  to\t\r  find\t\r  sensitivity\t\r  to\t\r  global\t\r  climate\t\r  change.\t\r  \nInvestigation\t\r  of\t\r  Beaufort\t\r  Gyre\t\r  dynamics\t\r  and\t\r  change\t\r  requires\t\r  a\t\r  comprehensive\t\r   long-­‐term\t\r  measuring\t\r  \nand\t\r  monitoring\t\r  system\t\r  and\t\r  careful\t\r  analysis\t\r  of\t\r  both\t\r  observational\t\r  data\t\r  and\t\r  numerical\t\r  model\t\r  results\t\r  to\t\r  \nexamine\t\r   conditions,\t\r   mechanisms\t\r   and\t\r   variability\t\r   of\t\r   freshwater\t\r   accumulation\t\r   and\t\r   release.\t\r   A\t\r   field\t\r  \ncampaign\t\r  could\t\r  help\t\r  to\t\r  answer\t\r  the\t\r  question:\t\r  What\t\r  are\t\r  the\t\r  processes\t\r   involved\t\r   in\t\r  melting\t\r  the\t\r  sea-­‐ice\t\r  \nand\t\r  controlling\t\r  the\t\r  ocean\t\r  stratification,\t\r  especially\t\r  in\t\r  the\t\r  western\t\r  Arctic\t\r  (Beaufort\t\r  Sea)?\t\r  Unfortunately,\t\r   the\t\r  majority\t\r   of\t\r  models\t\r   used\t\r   for\t\r   climate\t\r   projections\t\r   have\t\r   significant\t\r   limitations\t\r   in\t\r  their\t\r   representation\t\r   of\t\r   past\t\r   and\t\r   present\t\r   sea\t\r   ice\t\r   variability\t\r   in\t\r   the\t\r   Arctic.\t\r   \t\r   Most\t\r   current\t\r   climate\t\r  models\t\r   do\t\r   not\t\r   reproduce\t\r   observed\t\r  multi-­‐decadal\t\r   sea\t\r   ice\t\r   variability\t\r   and\t\r   trends\t\r   in\t\r   the\t\r   pan-­‐Arctic\t\r  region\t\r  (Stroeve\t\r  et\t\r  al.,\t\r  2007;\t\r  Figure\t\r  1).\t\r  The\t\r  ensemble\t\r  multi-­‐model\t\r  mean\t\r  trend\t\r  in\t\r  September\t\r  Arctic\t\r  sea\t\r   ice\t\r   extent\t\r   from\t\r   1953\t\r   to\t\r   2006\t\r   is\t\r   much\t\r   too\t\r   conservative,\t\r   being\t\r   about\t\r   30\t\r   years\t\r   behind\t\r   the\t\r  observed\t\r  trend.\t\r  CMIP5\t\r  models\t\r  yield\t\r  similar,\t\r  yet\t\r  somewhat\t\r  more\t\r  conservative,\t\r  results\t\r  to\t\r  the\t\r  CMIP3\t\r  predictions\t\r  of\t\r  Arctic\t\r  sea\t\r  ice\t\r  decline\t\r  noted\t\r  above\t\r  (Maslowski\t\r  et\t\r  al.,\t\r  2012;\t\r  Stroeve\t\r  et\t\r  al.,\t\r  2012).\t\r  Some\t\r  of\t\r   the\t\r  models\t\r  have\t\r  quite\t\r  unrealistic\t\r  distributions\t\r  of\t\r  sea\t\r   ice\t\r   thickness\t\r   for\t\r   this\t\r  period;\t\r  others\t\r  have\t\r  unrealistic\t\r   extent.\t\r   Model\t\r   representation\t\r   of\t\r   sea\t\r   ice\t\r   thickness\t\r   presents\t\r   additional\t\r   challenges\t\r   as\t\r   it\t\r  involves\t\r   not\t\r   only\t\r   thermodynamic\t\r   interaction\t\r   with\t\r   the\t\r   ocean\t\r   below,\t\r   but\t\r   also\t\r   the\t\r   dynamic\t\r   and\t\r  thermodynamic\t\r   effects\t\r   from\t\r   the\t\r   atmosphere\t\r   above.\t\r   An\t\r   unrealistic\t\r   sea\t\r   ice–thickness\t\r   distribution\t\r  will\t\r   affect\t\r   the\t\r   modeled\t\r   ice\t\r   extent\t\r   and\t\r   area\t\r   as\t\r   well\t\r   as\t\r   volume,\t\r   which\t\r   in\t\r   turn\t\r   may\t\r   delay\t\r   (or\t\r  accelerate)\t\r   predicted\t\r   changes\t\r   in\t\r   seasonal\t\r   sea\t\r   ice\t\r   cover\t\r   in\t\r   the\t\r   Arctic\t\r   Ocean.\t\r  Detailed\t\r   analyses\t\r   of\t\r  \nchanges\t\r  in\t\r  sea\t\r  ice\t\r  thickness\t\r  and\t\r  volume\t\r  are\t\r  needed\t\r  to\t\r  determine\t\r  the\t\r  actual\t\r  melt\t\r  rate\t\r  of\t\r  Arctic\t\r  sea\t\r  ice.\t\r  \t\r  The\t\r  seasonal\t\r  evolution\t\r  of\t\r  Arctic\t\r  sea\t\r  ice\t\r  albedo\t\r  undergoes\t\r  a\t\r  number\t\r  of\t\r  distinct\t\r  phases\t\r  including\t\r  dry\t\r  snow,\t\r  melting\t\r  snow,\t\r  melt\t\r  pond\t\r  formation,\t\r  pond\t\r  evolution,\t\r  and\t\r  fall\t\r  freeze-­‐up\t\r  (Perovich\t\r  et\t\r  al.,\t\r  2002).\t\r  \u003c/p\u003e\n\u003cp /\u003e\n\u003c/div\u003e\n\u003cdiv class\u003d\"page\"\u003e\u003cp /\u003e\n\u003cp\u003e\t\r  \u003c/p\u003e\n\u003cp\u003e\t\r   10\t\r  \n\u003c/p\u003e\n\u003cp\u003eBecause\t\r   of\t\r   the\t\r   importance\t\r   of\t\r   surface\t\r   albedo\t\r   parameterizations,\t\r   CCSM4\t\r   (one\t\r   of\t\r   the\t\r   models\t\r   for\t\r  CMIP5/AR5)\t\r   included\t\r   a\t\r   parameterization\t\r   of\t\r  melt\t\r   pond\t\r   effects\t\r   and\t\r   the\t\r   deposition\t\r   and\t\r   cycling\t\r   of\t\r  aerosols\t\r  (e.g.,\t\r  Holland\t\r  et\t\r  al.,\t\r  2012).\t\r  Melt\t\r  ponds\t\r  can\t\r  form\t\r  and\t\r  expand\t\r  rapidly,\t\r  reducing\t\r  the\t\r  surface\t\r  albedo,\t\r   but\t\r   then\t\r   suddenly\t\r   drain\t\r   and\t\r   cause\t\r   the\t\r   surface\t\r   albedo\t\r   to\t\r   rise.\t\r   The\t\r   CCSM4\t\r   melt\t\r   pond\t\r  parameterization\t\r  is\t\r  simple\t\r  and\t\r  further\t\r  developments\t\r  are\t\r  needed.\t\r  \t\r  Distinguishing\t\r  large\t\r  melt\t\r  ponds\t\r  from\t\r  open\t\r  water\t\r   in\t\r   the\t\r  Arctic\t\r  using\t\r   satellites\t\r   is\t\r  not\t\r   trivial\t\r   (e.g.,\t\r   Steffen\t\r  et\t\r   al.,\t\r   1992),\t\r   so\t\r   the\t\r  most\t\r  detailed\t\r   assessment\t\r   of\t\r   melt\t\r   pond\t\r   evolution\t\r   over\t\r   the\t\r   summer\t\r   occurred\t\r   during\t\r   SHEBA.\t\r   Further\t\r  \nresearch\t\r  with\t\r  remote-­‐sensing\t\r  observations\t\r  and\t\r  a\t\r  SHEBA\t\r  follow-­‐on\t\r  campaign\t\r  (like\t\r  the\t\r  proposed\t\r  multi-­‐\nyear\t\r  MOSAiC)\t\r  are\t\r  needed\t\r  to\t\r  improve\t\r  the\t\r  melt\t\r  pond\t\r  parameterizations\t\r  and\t\r  support\t\r  model\t\r  evaluations.\t\r  Maslowski\t\r   et\t\r   al.\t\r   (2012)\t\r   list\t\r   critical\t\r   deficiencies\t\r   in\t\r   current\t\r   climate\t\r   models:\t\r   sea\t\r   ice\t\r   thickness\t\r  distribution,\t\r   deformation,\t\r   variability\t\r   and\t\r   export,\t\r   air-­‐ice-­‐sea\t\r   interactions,\t\r   northward\t\r   oceanic\t\r   and\t\r  atmospheric\t\r  heat\t\r  convergence,\t\r  and\t\r  freshwater\t\r  content\t\r  and\t\r  export\t\r   into\t\r  the\t\r  North\t\r  Atlantic.\t\r  Due\t\r  to\t\r  deficiencies\t\r  in\t\r  parameterizing\t\r  the\t\r  effect\t\r  of\t\r  ocean\t\r  eddies,\t\r  ocean\t\r  models\t\r  significantly\t\r  under-­‐estimate\t\r  oceanic\t\r  mixing\t\r   and\t\r  heat\t\r   convergence\t\r   in\t\r   the\t\r  Arctic\t\r  Ocean.\t\r   Atmospheric\t\r   biases\t\r   in\t\r   climate\t\r  models,\t\r  particularly\t\r   in\t\r   the\t\r   patterns\t\r   of\t\r   sea\t\r   level\t\r   pressure\t\r   and\t\r   precipitation,\t\r   are\t\r   key\t\r   contributors\t\r   to\t\r  deficiencies\t\r   in\t\r   sea-­‐ice\t\r   simulations.\t\r   Vavrus\t\r   et\t\r   al.\t\r   (2003)\t\r   infer\t\r   that\t\r   deficiencies\t\r   in\t\r   simulating\t\r   ice\t\r  cover\t\r   in\t\r   turn\t\r   impacts\t\r   the\t\r   simulation\t\r   of\t\r   high-­‐latitude\t\r   vegetation\t\r   by\t\r   affecting\t\r   the\t\r   atmospheric\t\r  circulation\t\r  and\t\r  thus\t\r  the\t\r  patterns\t\r  of\t\r  temperature\t\r  and\t\r  precipitation\t\r  over\t\r  land.\t\r  \t\r  Further\t\r   model\t\r   development\t\r   and\t\r   comparison\t\r   with\t\r   observations\t\r   are\t\r   needed.\t\r   Observations\t\r   of\t\r  thickness\t\r  distribution,\t\r  deformation\t\r  and\t\r  export\t\r  have\t\r   improved\t\r   in\t\r   recent\t\r  years\t\r  with\t\r   the\t\r  advent\t\r  of\t\r  ICESat\t\r   and\t\r   CryoSat\t\r   2\t\r   data\t\r   (Kwok,\t\r   2011).\t\r   \t\r   For\t\r   completeness,\t\r   model\t\r   development\t\r   should\t\r   also\t\r  \nemphasize\t\r   getting\t\r   the\t\r   right\t\r   distribution\t\r   of\t\r   sea\t\r   ice\t\r   that\t\r   survives\t\r   the\t\r   summer\t\r   and\t\r   of\t\r   multiyear\t\r   ice.\t\r  These\t\r  ice\t\r  types\t\r  are\t\r  measured\t\r  well\t\r  and\t\r  are\t\r  showing\t\r  large\t\r  interannual\t\r  declines\t\r  (Comiso,\t\r  2012).\t\r  \n2.3 Ocean\t\r  and\t\r  Sea\t\r  Ice\t\r  –\t\r  Biogeochemistry\t\r  The\t\r   workshop\t\r   did\t\r   not\t\r   address\t\r   ocean\t\r   and\t\r   sea-­‐ice\t\r   BGC\t\r   models.\t\r   However,\t\r   Drs\t\r   Kevin\t\r   Arrigo,\t\r   Jeff\t\r  Bowman,\t\r  Clara\t\r  Deal,\t\r  and\t\r  Scott\t\r  Elliott\t\r  provided\t\r  input\t\r  after\t\r  the\t\r  workshop.\t\r  \t\r  Marine\t\r  net\t\r  primary\t\r  productivity\t\r  (NPP)\t\r  is\t\r  a\t\r  key\t\r  process\t\r  in\t\r  the\t\r  global\t\r  carbon\t\r  cycle,\t\r  controlling\t\r  the\t\r  uptake\t\r   of\t\r   dissolved\t\r   inorganic\t\r   carbon\t\r   (DIC)\t\r   in\t\r   the\t\r   sunlit\t\r   surface\t\r   waters\t\r   of\t\r   the\t\r   ocean\t\r   and\t\r   its\t\r  transformation\t\r   into\t\r  organic\t\r  carbon\t\r  (OC).\t\r  However,\t\r  neither\t\r  absolute\t\r  values\t\r   for\t\r  global\t\r  annual\t\r  NPP\t\r  and\t\r  exported\t\r  particulate\t\r  OC\t\r   (EP)\t\r  nor\t\r   their\t\r   spatial\t\r   and\t\r   temporal\t\r   variability\t\r   are\t\r  well\t\r   known\t\r   from\t\r  direct\t\r   observations\t\r   (Schneider\t\r   et\t\r   al.,\t\r   2008).\t\r   Ocean\t\r   circulation\t\r   and\t\r   mixing,\t\r   which\t\r   transport\t\r  nutrients\t\r  into\t\r  the\t\r  euphotic\t\r  zone,\t\r  control\t\r  nutrient\t\r  availability\t\r  for\t\r  marine\t\r  biological\t\r  production.\t\r  The\t\r  melt\t\r  of\t\r  sea\t\r  ice\t\r  in\t\r  spring\t\r  and\t\r  summer\t\r  also\t\r  affects\t\r  the\t\r  occurrence\t\r  of\t\r  phytoplankton\t\r  blooms\t\r  near\t\r  the\t\r  ice\t\r   edges\t\r   since\t\r   low-­‐density\t\r   meltwater\t\r   provides\t\r   a\t\r   stable\t\r   environment\t\r   that\t\r   is\t\r   ideal\t\r   for\t\r  photosynthesis\t\r  because\t\r  of\t\r  the\t\r  presence\t\r  of\t\r  abundant\t\r  sunlight\t\r  (Smith\t\r  and\t\r  Comiso,\t\r  2008).\t\r  Current\t\r  estimates\t\r  of\t\r  NPP\t\r  on\t\r  Arctic\t\r  continental\t\r  shelves\t\r  may\t\r  be\t\r  drastically\t\r  underestimated\t\r  (Arrigo\t\r  et\t\r   al.,\t\r   2012).\t\r   Recent\t\r   observations\t\r   from\t\r   an\t\r   ICESCAPE\t\r   (Impacts\t\r   of\t\r   Climate\t\r   on\t\r   EcoSystems\t\r   and\t\r  Chemistry\t\r   of\t\r   the\t\r   Arctic\t\r   Pacific\t\r   Environment)\t\r   field\t\r   campaign\t\r   suggest\t\r   that\t\r   under-­‐ice\t\r   blooms\t\r   are\t\r  widespread,\t\r  consistent\t\r  with\t\r  earlier\t\r  observations\t\r  (e.g.,\t\r  Alexander\t\r  and\t\r  Niebauer,\t\r  1981).\t\r  Arrigo\t\r  and\t\r  van\t\r   Dijken\t\r   (2011)\t\r   showed\t\r   that\t\r   NPP\t\r   in\t\r   the\t\r   Arctic\t\r   has\t\r   increased\t\r   20%\t\r   over\t\r   the\t\r   last\t\r   decade\t\r   in\t\r  response\t\r   to\t\r   reduced\t\r   ice\t\r   cover\t\r   and\t\r   longer\t\r   open\t\r  water\t\r   seasons.\t\r   Processes\t\r   that\t\r   could\t\r   increase\t\r   the\t\r  availability\t\r  of\t\r  surface\t\r  nutrients\t\r  to\t\r  support\t\r  increased\t\r  NPP\t\r  include\t\r  increased\t\r  river\t\r  runoff,\t\r  increased\t\r  shelf\t\r  break\t\r  upwelling,\t\r  enhanced\t\r  eddy\t\r  activity,\t\r  and\t\r  greater\t\r  vertical\t\r  mixing\t\r  as\t\r   the\t\r  surface\t\r  ocean\t\r   is\t\r  increasingly\t\r   exposed\t\r   to\t\r   wind\t\r   forcing.\t\r   Unfortunately,\t\r   these\t\r   processes\t\r   are\t\r   poorly\t\r   represented\t\r   in\t\r  current\t\r  models\t\r  (Seferian\t\r  et\t\r  al.,\t\r  2012;\t\r  Popova\t\r  et\t\r  al.,\t\r  2012)\t\r  and\t\r  have\t\r  only\t\r  been\t\r  sampled\t\r  sporadically\t\r  \u003c/p\u003e\n\u003cp /\u003e\n\u003c/div\u003e\n\u003cdiv class\u003d\"page\"\u003e\u003cp /\u003e\n\u003cp\u003e\t\r  \u003c/p\u003e\n\u003cp\u003e\t\r   11\t\r  \n\u003c/p\u003e\n\u003cp\u003eduring\t\r  field\t\r  campaigns.\t\r  \t\r  Popova\t\r  et\t\r  al.\t\r  (2012)\t\r  compared\t\r  five\t\r  externally\t\r  forced\t\r  coupled\t\r  physical-­‐biological\t\r  ocean-­‐only\t\r  models\t\r  of\t\r  the\t\r  Arctic\t\r  domain\t\r  that\t\r  participated\t\r  in\t\r  the\t\r  Arctic\t\r  Ocean\t\r  Model\t\r  Intercomparison\t\r  Project\t\r  (AOMIP).\t\r  Whereas\t\r   the\t\r   models\t\r   showed\t\r   similar\t\r   distributions\t\r   of\t\r   present-­‐day\t\r   vertically\t\r   integrated\t\r   NPP\t\r   and\t\r  were\t\r  broadly\t\r   in\t\r  agreement\t\r  with\t\r   in-­‐situ\t\r  and\t\r  satellite-­‐derived\t\r  data,\t\r   the\t\r  physical\t\r   factors\t\r  controlling\t\r  this\t\r  distribution\t\r  differed\t\r  between\t\r  models.\t\r  There\t\r  was\t\r  substantial\t\r  variation\t\r   in\t\r   the\t\r  depth\t\r  of\t\r  winter\t\r  mixing,\t\r  one\t\r  of\t\r  the\t\r  main\t\r  mechanisms\t\r  supplying\t\r  inorganic\t\r  nutrients\t\r  over\t\r  the\t\r  majority\t\r  of\t\r  the\t\r  Arctic\t\r  Ocean.\t\r   Although\t\r   these\t\r   five\t\r  models\t\r  manifested\t\r   similar\t\r   levels\t\r   of\t\r   light\t\r   limitation\t\r   owing\t\r   to\t\r   general\t\r  agreement\t\r  on\t\r  the\t\r  ice\t\r  distribution,\t\r  the\t\r  amount\t\r  of\t\r  nutrients\t\r  available\t\r  for\t\r  plankton\t\r  utilization\t\r  differed\t\r  between\t\r  models.\t\r  Thus\t\r  the\t\r  participating\t\r  models\t\r  disagree\t\r  on\t\r  the\t\r   fundamental\t\r  question\t\r  of\t\r  whether\t\r  light\t\r  or\t\r  nutrient\t\r  availability\t\r  controls\t\r  present-­‐day\t\r  Arctic\t\r  productivity.\t\r  Evaluations\t\r   of\t\r   the\t\r   ocean\t\r   carbon\t\r   cycle\t\r   component\t\r   in\t\r   ESMs\t\r   show\t\r   discrepancies\t\r   from\t\r   available\t\r  observations,\t\r   primarily\t\r   remotely\t\r   sensed\t\r   ocean\t\r   color\t\r   observations\t\r   (Schneider\t\r   et\t\r   al.,\t\r   2008).\t\r   In\t\r   a\t\r  comparison\t\r   of\t\r   four\t\r   ESMs,\t\r   Steinacher\t\r   et\t\r   al.\t\r   (2010)\t\r   found\t\r   disagreement\t\r   among\t\r   the\t\r  models\t\r   in\t\r   the\t\r  Arctic\t\r  where\t\r  three\t\r  models\t\r  project\t\r  an\t\r  increase\t\r  in\t\r  NPP\t\r  over\t\r  the\t\r  21st\t\r  century,\t\r  while\t\r  one\t\r  model\t\r  (the\t\r  one\t\r   that\t\r   agrees\t\r   best\t\r  with\t\r   observations\t\r   on\t\r   a\t\r   global\t\r   basis)\t\r   projects\t\r   a\t\r   decrease\t\r   (Figure\t\r   7).\t\r   Results\t\r  from\t\r  the\t\r  Coupled\t\r  Climate–Carbon\t\r  Cycle\t\r  Model\t\r  Intercomparison\t\r  Project\t\r  (C4MIP)\t\r  (e.g.,\t\r  Friedlingstein\t\r  et\t\r  al.,\t\r  2006)\t\r  suggest\t\r  that\t\r  more\t\r  complete\t\r  treatments\t\r  of\t\r  ocean\t\r  ecosystems\t\r  (e.g.,\t\r  resolving\t\r  more\t\r  than\t\r  one\t\r   phytoplankton\t\r   functional\t\r   type),\t\r  micronutrient\t\r   limitation,\t\r   and\t\r   ocean\t\r   acidification\t\r   impacts\t\r   on\t\r  the\t\r  calcium\t\r  carbonate\t\r  cycle\t\r  are\t\r  needed.\t\r  In\t\r  addition\t\r  to\t\r  improvements\t\r  in\t\r  the\t\r  physical\t\r  climate\t\r  model,\t\r  ocean\t\r  and\t\r  sea-­‐ice\t\r  BGC\t\r  model\t\r  developments\t\r  under\t\r  consideration\t\r  include\t\r  the\t\r  nutrient-­‐sulfur\t\r  cycling\t\r  due\t\r  to\t\r  sea\t\r  ice\t\r  biology\t\r  (Elliott\t\r  et\t\r  al.,\t\r  2012)\t\r  to\t\r  improve\t\r  the\t\r  simulation\t\r  of\t\r  dimethylsuflide\t\r  (DMS),\t\r  an\t\r  important\t\r  aerosol\t\r  precursor.\t\r  \t\r  \n\u003c/p\u003e\n\u003cp\u003e\t\r  \t\r  \t\r  An\t\r   issue\t\r   for\t\r   model\t\r   development\t\r   and\t\r   evaluation\t\r   is\t\r   that\t\r   our\t\r   current\t\r   knowledge\t\r   of\t\r   Arctic\t\r   Ocean\t\r  ecosystems\t\r   is\t\r   limited\t\r   by\t\r   under-­‐sampling\t\r   since\t\r   existing\t\r   observations\t\r   are\t\r   very\t\r   sparse\t\r   and\t\r   biased\t\r  toward\t\r   summer.\t\r   Yet\t\r   it\t\r   is\t\r   during\t\r   the\t\r   spring\t\r   and\t\r   fall\t\r   transition\t\r   periods\t\r   that\t\r   ice-­‐ocean\t\r   exchange\t\r  processes\t\r  strongly\t\r   influence\t\r   ice\t\r  algae\t\r  and\t\r  phytoplankton\t\r  that\t\r  uptake\t\r  CO2,\t\r  as\t\r  well\t\r  as\t\r  zooplankton\t\r  and\t\r  bacteria\t\r  all\t\r  of\t\r  which\t\r  cycle\t\r  and\t\r  redistribute\t\r  C,\t\r  N\t\r  and\t\r  DMS.\t\r  \t\r  \nYear-­‐round\t\r   time\t\r   series\t\r   measurements\t\r   of\t\r   biological\t\r   and\t\r   chemical\t\r   concentrations,\t\r   parameters,\t\r   and\t\r  \ndistributions,\t\r   such\t\r   as\t\r   for\t\r   biomass,\t\r   nutrient\t\r   concentrations,\t\r   and\t\r   biological\t\r   rates\t\r   are\t\r   needed.\t\r  \nObservational\t\r  networks\t\r  and\t\r  multi-­‐scale\t\r  field\t\r  observations\t\r  should\t\r  be\t\r  coordinated\t\r  with\t\r  complementary\t\r  \nmodeling\t\r  to\t\r  facilitate\t\r  sampling\t\r  over\t\r  a\t\r  broad\t\r  range\t\r  of\t\r  scales\t\r  and\t\r  upscaling\t\r  information\t\r  from\t\r  fine-­‐scale\t\r  \nobservations\t\r  to\t\r  global-­‐scale\t\r  ESMs.\t\r  \n\u003c/p\u003e\n\u003cp\u003e-­‐30\t\r  -­‐20\t\r  \n-­‐10\t\r  0\t\r  \n10\t\r  20\t\r  \n30\t\r  40\t\r  \n\u003c/p\u003e\n\u003cp\u003eNPP\t\r   EP\t\r   PO4\t\r   NO3\t\r   FE\t\r  \n\u003c/p\u003e\n\u003cp\u003eFigure\t\r  7:\t\r  Long-­‐term\t\r  trends\t\r  of\t\r  NPP,\t\r  EP\t\r  and\t\r  related\t\r  properties\t\r  in\t\r  the\t\r  Arctic\t\r  as\t\r  projected\t\r  by\t\r  the\t\r  four\t\r  models\t\r  under\t\r  SRES\t\r  A2\t\r  in\t\r  Steinacher\t\r  et\t\r  al.\t\r  (2010).\t\r  The\t\r  projected\t\r  changes\t\r  are\t\r  with\t\r  respect\t\r  to\t\r  preindustrial\t\r  conditions\t\r  (average\t\r  2090–2099\t\r  minus\t\r  average\t\r  1860–1869).\t\r  Changes\t\r  in\t\r  NPP\t\r  and\t\r  EP\t\r  are\t\r  in\t\r  units\t\r  of\t\r  mgC\t\r  m-­‐2day-­‐1;\t\r  PO4\t\r  is\t\r  10\t\r  μ\t\r  mol\t\r  m-­‐3;\t\r  NO3\t\r  is\t\r  mmol\t\r  m-­‐3;\t\r  and\t\r  Fe\t\r  is\t\r  10\t\r  nmol\t\r  m-­‐3.\t\r  \t\r  \u003c/p\u003e\n\u003cp /\u003e\n\u003c/div\u003e\n\u003cdiv class\u003d\"page\"\u003e\u003cp /\u003e\n\u003cp\u003e\t\r  \u003c/p\u003e\n\u003cp\u003e\t\r   12\t\r  \n\u003c/p\u003e\n\u003cp\u003e2.4 Land\t\r  Surface\t\r  –\t\r  Climatology\t\r  and\t\r  Hydrology\t\r  ESMs\t\r  do\t\r  not\t\r  represent\t\r  the\t\r  energy\t\r  budget\t\r  over\t\r  the\t\r  Arctic\t\r  region\t\r  well,\t\r  and\t\r  variations\t\r   in\t\r  the\t\r  Arctic\t\r  freshwater\t\r   budget\t\r   are\t\r   not\t\r   well\t\r   understood\t\r   (e.g.,\t\r   Kattsov\t\r   et\t\r   al.,\t\r   2007).\t\r   Variations\t\r   in\t\r   hydrologic\t\r  processes\t\r  in\t\r  the\t\r  ABZ\t\r  impact\t\r  terrestrial\t\r  and\t\r  marine\t\r  ecosystems\t\r  as\t\r  well\t\r  as\t\r  the\t\r  cryosphere\t\r  and\t\r  ocean\t\r  circulation\t\r  through\t\r  the\t\r  impact\t\r  on\t\r  ocean\t\r  stratification.\t\r  Landscape\t\r  (soil)\t\r  moisture\t\r  status\t\r  appears\t\r  to\t\r  be\t\r  important\t\r  not\t\r  only\t\r  for\t\r  some\t\r  physical\t\r  climate\t\r  system\t\r  processes\t\r  but\t\r  also\t\r  to\t\r  the\t\r  generation\t\r  of\t\r  CO2\t\r  and\t\r  non-­‐CO2\t\r  GHGs\t\r  (e.g.,\t\r  Khvorostyanov\t\r  et\t\r  al.,\t\r  2008;\t\r  Qian\t\r  et\t\r  al.,\t\r  2010;\t\r  Grosse\t\r  et\t\r  al.,\t\r  2011).\t\r  \n2.4.1 Land\t\r  surface\t\r  energy\t\r  and\t\r  freshwater\t\r  budgets\t\r  The\t\r   range\t\r   of\t\r   historical\t\r   and\t\r   future\t\r   surface\t\r   temperature\t\r   increase\t\r   in\t\r   CMIP5\t\r   ESMs\t\r   is\t\r   similar\t\r   to\t\r   the\t\r  range\t\r  generated\t\r  by\t\r  the\t\r  CMIP3\t\r  coupled\t\r  general\t\r  circulation\t\r  models\t\r  (CGCMs).\t\r  Thus,\t\r  ESMs\t\r  still\t\r  have\t\r  significant\t\r  biases\t\r  in\t\r  the\t\r  prediction\t\r  of\t\r  ABZ\t\r  surface\t\r  climate\t\r  parameters,\t\r  such\t\r  as\t\r  seasonal\t\r  and\t\r  diurnal\t\r  temperature\t\r   and\t\r   precipitation\t\r   ranges\t\r   and\t\r   interannual\t\r   variability,\t\r   the\t\r   precipitation\t\r   distribution,\t\r  and\t\r  downwelling\t\r  LW\t\r  radiation\t\r  (e.g.,\t\r  Randall\t\r  et\t\r  al.,\t\r  2007;\t\r  Kattsov\t\r  et\t\r  al.,\t\r  2007;\t\r  Lawrence\t\r  et\t\r  al.,\t\r  2008,\t\r  2012).\t\r  The\t\r  implications\t\r  of\t\r  these\t\r  biases\t\r  for\t\r  ABZ\t\r  land\t\r  processes\t\r  need\t\r  to\t\r  be\t\r  assessed.\t\r  \t\r  Snow\t\r   cover\t\r   and\t\r   depth\t\r   play\t\r   a\t\r   significant\t\r   role\t\r   in\t\r   the\t\r   surface\t\r   energy\t\r   budget\t\r   due\t\r   to\t\r   albedo\t\r   and\t\r  thermal\t\r   insulation\t\r   effects\t\r   and\t\r   they\t\r   exert\t\r   a\t\r  major\t\r   control\t\r   over\t\r  permafrost\t\r  distribution\t\r  pattern\t\r   in\t\r  discontinuous\t\r  and\t\r  sporadic\t\r  permafrost\t\r  zones,\t\r  particularly\t\r   in\t\r  areas\t\r  of\t\r  complex\t\r  terrain.\t\r  Vegetation\t\r  influences\t\r   all\t\r   components\t\r   of\t\r   the\t\r   land-­‐surface\t\r   energy\t\r   budget.\t\r   In\t\r   winter,\t\r   the\t\r   presence\t\r   of\t\r   forest\t\r  reduces\t\r  albedo\t\r  by\t\r  at\t\r  least\t\r  60%\t\r  relative\t\r  to\t\r  nearby\t\r  snow-­‐covered\t\r  grassy\t\r  areas\t\r  (Betts\t\r  and\t\r  Ball,\t\r  1997)\t\r  and\t\r   thus\t\r   is\t\r   critical\t\r   in\t\r   determining\t\r   surface\t\r   albedo,\t\r   the\t\r   surface\t\r   energy\t\r   budget\t\r   and\t\r   planetary\t\r  boundary\t\r  layer\t\r  (PBL)\t\r  temperatures\t\r  and\t\r  depths.\t\r  In\t\r  summer,\t\r  vegetation\t\r  again\t\r  influences\t\r  the\t\r  surface\t\r  radiation\t\r  budgets,\t\r  but\t\r  latent\t\r  heat\t\r  fluxes\t\r  from\t\r  forest\t\r  have\t\r  been\t\r  observed\t\r  to\t\r  be\t\r  strongly\t\r  dependent\t\r  on\t\r  soil\t\r  temperatures\t\r  (e.g.,\t\r  the\t\r  so-­‐called\t\r  “green\t\r  desert”\t\r  observed\t\r  in\t\r  BOREAS-­‐94\t\r  \t\r  (Betts\t\r  et\t\r  al.,\t\r  2001)).\t\r  \nIn\t\r   general,\t\r   the\t\r   surface\t\r   energy\t\r   budgets\t\r   of\t\r   Arctic\t\r   and\t\r   Boreal\t\r   ecosystems\t\r   are\t\r   not\t\r  well\t\r   represented\t\r   in\t\r  \nESMs\t\r   owing\t\r   to\t\r   the\t\r   difficulties\t\r   in\t\r  modeling\t\r   fluxes\t\r   over\t\r   spatially\t\r   variable\t\r   landscapes.\t\r   This\t\r   issue\t\r  was\t\r  \naddressed\t\r  in\t\r  BOREAS\t\r  and\t\r  other\t\r  experiments\t\r  but\t\r  an\t\r  assessment\t\r  of\t\r  what\t\r  is\t\r  done\t\r  well\t\r  and\t\r  what\t\r  is\t\r  done\t\r  \npoorly\t\r  in\t\r  ESMs,\t\r  and\t\r  why,\t\r  is\t\r  warranted.\t\r  \n\u003c/p\u003e\n\u003cp\u003e\t\r  Figure\t\r  8:\t\r  P–E\t\r  linear\t\r  trends\t\r  (mm\t\r  day-­‐1\t\r  per\t\r  century)\t\r  in\t\r  CMIP3/AR4\t\r  models:\t\r  maximum\t\r  (MAX)\t\r  and\t\r  minimum\t\r  (MIN)\t\r  values\t\r  for\t\r  each\t\r  model\t\r  ensemble,\t\r  and\t\r  values\t\r  for\t\r  the\t\r  ensemble\t\r  means\t\r  (Mean)\t\r  over\t\r  the\t\r  entire\t\r  Arctic\t\r  Ocean\t\r  terrestrial\t\r  watershed\t\r  for\t\r  1965–99.\t\r  [From\t\r  Kattsov\t\r  et\t\r  al.\t\r  (2007)]\t\r  \t\r  \u003c/p\u003e\n\u003cp /\u003e\n\u003c/div\u003e\n\u003cdiv class\u003d\"page\"\u003e\u003cp /\u003e\n\u003cp\u003e\t\r  \u003c/p\u003e\n\u003cp\u003e\t\r   13\t\r  \n\u003c/p\u003e\n\u003cp\u003eIn\t\r  examining\t\r  the\t\r  Arctic\t\r  freshwater\t\r  budget\t\r  simulated\t\r  by\t\r  AR4\t\r  climate\t\r  models,\t\r  Kattsov\t\r  et\t\r  al.\t\r  (2007)\t\r  noted\t\r   that\t\r   evaluation\t\r   of\t\r   model\t\r   simulations\t\r   of\t\r   the\t\r   Arctic\t\r   hydrologic\t\r   variables\t\r   is\t\r   complicated\t\r   by\t\r  uncertainties\t\r   in\t\r   observational\t\r   estimates.\t\r   However,\t\r   they\t\r   found\t\r   that\t\r   the\t\r   biases\t\r   are\t\r   at\t\r   least\t\r   partly\t\r  attributable\t\r   to\t\r   the\t\r   spatial\t\r   variability\t\r   and\t\r   complexity\t\r   of\t\r   the\t\r   surface\t\r   and\t\r   to\t\r   biases\t\r   in\t\r   large-­‐scale\t\r  atmospheric\t\r   circulation\t\r   and\t\r   sea\t\r   ice\t\r   distribution.\t\r   There\t\r   was\t\r   significant\t\r   model\t\r   variability\t\r   in\t\r  simulated\t\r  trends\t\r  in\t\r  P-­‐E\t\r  over\t\r  the\t\r  Arctic\t\r  Ocean\t\r  terrestrial\t\r  watershed\t\r  for\t\r  1965-­‐1999\t\r  \t\r  (Figure\t\r  8).\t\r  The\t\r  models\t\r  were\t\r  more\t\r  similar\t\r  in\t\r  their\t\r  projected\t\r  21st\t\r  century\t\r  precipitation\t\r  increases,\t\r  with\t\r  a\t\r  17-­‐model\t\r  mean\t\r  annual\t\r  precipitation\t\r   increase\t\r  of\t\r  33%\t\r  in\t\r  the\t\r  Arctic,\t\r  much\t\r  higher\t\r  than\t\r  the\t\r  4.5%\t\r  global\t\r  mean\t\r  increase.\t\r  More\t\r   comprehensive\t\r   evaluations\t\r   of\t\r   the\t\r   terrestrial\t\r   surface\t\r  moisture\t\r   fluxes,\t\r   both\t\r   simulated\t\r  \nand\t\r   observed,\t\r   are\t\r   a\t\r   priority\t\r   for\t\r   assessments\t\r   of\t\r   the\t\r   robustness\t\r   of\t\r   the\t\r   projected\t\r   changes\t\r   of\t\r   the\t\r  \nhydrologic\t\r  budget\t\r  of\t\r  the\t\r  Arctic.\t\r  \n2.4.2 Snow\t\r  Virtually\t\r  all\t\r  the\t\r  ABZ\t\r  land\t\r  surface\t\r  is\t\r  snow-­‐covered\t\r  for\t\r  part\t\r  of\t\r  the\t\r  year.\t\r  \t\r  Land\t\r  surface\t\r  models,\t\r  which\t\r  are\t\r   forced\t\r   to\t\r   represent\t\r   the\t\r   large-­‐scale\t\r   behavior\t\r   of\t\r   snow\t\r   with\t\r   a\t\r   limited\t\r   number\t\r   of\t\r   prognostic\t\r  variables,\t\r   require\t\r   parameterizations\t\r   that\t\r   account\t\r   realistically\t\r   for\t\r   unresolved\t\r   snow\t\r   processes.\t\r   \t\r   A\t\r  key\t\r  example\t\r   is\t\r   the\t\r   impact\t\r  of\t\r   the\t\r  spatially\t\r  varying\t\r  snow\t\r  cover\t\r  extent\t\r  and\t\r  snow\t\r  water\t\r  equivalent,\t\r  which\t\r  can\t\r  strongly\t\r  affect\t\r  the\t\r  land\t\r  surface\t\r  energy\t\r  balance\t\r  through\t\r  their\t\r  impact\t\r  on\t\r  albedo.\t\r  \t\r  In\t\r  nature,\t\r  this\t\r   spatial\t\r   variability\t\r   is\t\r   controlled\t\r   by\t\r   topography\t\r   (e.g.,\t\r   due\t\r   to\t\r   altitudinal\t\r   temperature\t\r   effects),\t\r  wind\t\r   (e.g.,\t\r   the\t\r   build-­‐up\t\r  of\t\r  wind-­‐swept\t\r   snow\t\r   in\t\r   lowland\t\r   areas),\t\r   vegetation\t\r   (e.g.,\t\r   the\t\r   ability\t\r   of\t\r   tall\t\r  trees\t\r  to\t\r  stick\t\r  out\t\r  of\t\r  the\t\r  snow,\t\r  reducing\t\r  the\t\r  snow’s\t\r  impact\t\r  on\t\r  albedo),\t\r  and\t\r  by\t\r  other\t\r  factors,\t\r  such\t\r  as\t\r  the\t\r   spatial\t\r   variability\t\r   of\t\r   the\t\r   precipitation\t\r   itself.\t\r   Such\t\r   variation\t\r   in\t\r   snow\t\r   properties\t\r   leads\t\r   to\t\r  important\t\r   differences\t\r   in\t\r   permafrost\t\r   characteristics\t\r   and\t\r   potential\t\r   for\t\r   carbon\t\r   cycle\t\r   feedbacks\t\r  (Gouttevin\t\r  et\t\r  al.,\t\r  2012).\t\r  \t\r  \t\r  The\t\r  CMIP5\t\r  models\t\r  show\t\r  a\t\r  wide\t\r  range\t\r  of\t\r  snow\t\r  insulation\t\r  effects,\t\r  resulting\t\r  in\t\r  a\t\r  wide\t\r   range\t\r  of\t\r   simulated\t\r  distributions\t\r  of\t\r   current\t\r  permafrost.\t\r   Improved\t\r   treatment\t\r  of\t\r   thermal\t\r  insulation\t\r  by\t\r  snowpacks\t\r  (which\t\r  strongly\t\r  influences\t\r  soil\t\r  freeze-­‐thaw\t\r  processes)\t\r  is\t\r  needed.\t\r  \t\r  \t\r  \t\r  \nModels\t\r   require\t\r   parameterized\t\r   relationships\t\r   between\t\r   the\t\r   unresolved\t\r   spatial\t\r   variability\t\r   of\t\r   snow\t\r   and\t\r  \nthe\t\r  available\t\r  diagnostic\t\r  variables.\t\r  These\t\r  relationships\t\r  are\t\r  very\t\r  crude\t\r  in\t\r  current\t\r  models,\t\r  largely\t\r  due\t\r  to\t\r  \nthe\t\r   lack\t\r   of\t\r   adequate\t\r   surface\t\r   observations\t\r   to\t\r   support\t\r   the\t\r   development\t\r   of\t\r   more\t\r   sophisticated\t\r   (and\t\r  \npresumably\t\r   more\t\r   accurate)\t\r   parameterizations.\t\r   Satellite\t\r   data\t\r   are\t\r   mostly\t\r   adequate\t\r   for\t\r   the\t\r  characterization\t\r   of\t\r   snow\t\r   cover\t\r   extent\t\r   but\t\r   more\t\r   work\t\r   needs\t\r   to\t\r   be\t\r   done\t\r   to\t\r   retrieve\t\r   snow\t\r   water\t\r  \nequivalent\t\r  and\t\r  surface\t\r  albedo.\t\r   The\t\r   uncertainties\t\r   in\t\r   snow\t\r  water\t\r   equivalent\t\r   are\t\r   usually\t\r   associated\t\r  with\t\r  snow\t\r  aging\t\r  and\t\r  freeze-­‐thaw\t\r  processes\t\r  that\t\r  affect\t\r  the\t\r  dielectric\t\r  property\t\r  and\t\r  emissivity\t\r  of\t\r  the\t\r  surface.\t\r  \t\r  Albedo\t\r  is\t\r  also\t\r  affected\t\r  by\t\r  grain\t\r  size,\t\r  melt/thaw\t\r  processes\t\r  and\t\r  deposited\t\r  constituents\t\r  (dust,\t\r  black\t\r   carbon).\t\r   More\t\r   basic\t\r   research\t\r   with\t\r   in-­‐situ\t\r   measurements\t\r   targeted\t\r   towards\t\r   improvement\t\r   of\t\r  \nmacroscale\t\r  model\t\r  algorithms\t\r  is\t\r  needed.\t\r  \t\r  \n2.4.3 Permafrost\t\r  Permafrost\t\r  exerts\t\r  strong\t\r  controls\t\r  on\t\r  hydrologic\t\r  and\t\r  biophysical\t\r  processes\t\r  over\t\r  much\t\r  of\t\r  the\t\r  ABZ.\t\r  Processes\t\r   that\t\r   are\t\r   affected\t\r   include\t\r   surface\t\r   and\t\r   subsurface\t\r   runoff,\t\r   evapotranspiration\t\r   (especially\t\r  from\t\r  trees\t\r  with\t\r  roots\t\r  in\t\r  the\t\r  seasonally\t\r  thawed\t\r  active\t\r  layer)\t\r  and\t\r  surface\t\r  biogeochemical\t\r  fluxes,\t\r  e.g.\t\r  of\t\r   CH4\t\r   and\t\r  CO2,\t\r  which\t\r   are\t\r   strongly\t\r   temperature\t\r   dependent.\t\r   \t\r   Permafrost\t\r   also\t\r   represents\t\r   a\t\r  major\t\r  source\t\r   of\t\r   largely\t\r   immobile\t\r   stored\t\r   water,\t\r   the\t\r   availability\t\r   of\t\r   which\t\r   for\t\r   river\t\r   runoff\t\r   can\t\r   change\t\r   if\t\r  thawing\t\r  occurs.\t\r  \t\r  Permafrost\t\r  processes\t\r  are\t\r  strongly\t\r  linked\t\r  with\t\r  seasonal\t\r  snow\t\r  cover,\t\r  since\t\r  snow\t\r  is\t\r  a\t\r   strong\t\r   insulator.\t\r  The\t\r  active\t\r   layer\t\r  depth\t\r   is\t\r   influenced\t\r  by\t\r   the\t\r  date\t\r  of\t\r   first\t\r   snow\t\r  and\t\r  snow\t\r  depth\t\r  distribution\t\r  through\t\r  the\t\r  winter\t\r  season.\t\r  ESMs\t\r  will\t\r  require\t\r  careful\t\r  treatment\t\r  of\t\r  snowpack\t\r  properties\t\r  (depth,\t\r  density,\t\r  and\t\r  thermal\t\r  conductivity)\t\r  to\t\r  successfully\t\r  predict\t\r  changes\t\r  in\t\r  active\t\r  layer\t\r  depth\t\r  and\t\r  permafrost\t\r  thickness\t\r  and\t\r  distribution.\t\r  \t\r  \t\r  \t\r  \u003c/p\u003e\n\u003cp /\u003e\n\u003c/div\u003e\n\u003cdiv class\u003d\"page\"\u003e\u003cp /\u003e\n\u003cp\u003e\t\r  \u003c/p\u003e\n\u003cp\u003e\t\r   14\t\r  \n\u003c/p\u003e\n\u003cp\u003eClimate\t\r  warming\t\r  will\t\r   reduce\t\r   the\t\r   spatial\t\r   extent\t\r   of\t\r   permafrost\t\r   and\t\r  hence\t\r  modify\t\r   the\t\r   hydrological\t\r  regime\t\r  in\t\r  the\t\r  ABZ,\t\r  as\t\r  lateral\t\r  water\t\r  redistribution\t\r  driven\t\r  by\t\r  topographical\t\r  variation\t\r  can\t\r  be\t\r  greatly\t\r  enhanced\t\r  with\t\r   reduced\t\r  permafrost\t\r   areas\t\r   and\t\r   increased\t\r  active\t\r   layer\t\r   thickness.\t\r  This\t\r   lateral\t\r  water\t\r  redistribution\t\r   not\t\r   only\t\r   modifies\t\r   the\t\r   local\t\r   plant\t\r   growth,\t\r   grass-­‐shrub-­‐forest\t\r   distribution,\t\r  heterotrophic\t\r  respiration,\t\r  and\t\r  other\t\r  biogeochemical\t\r  processes,\t\r  but\t\r  also\t\r  the\t\r  landscape\t\r  averages\t\r  of\t\r  the\t\r  net\t\r  carbon\t\r  and\t\r  other\t\r  gas\t\r   fluxes\t\r  as\t\r  represented\t\r  at\t\r   the\t\r  ESM\t\r  grid\t\r  scale\t\r   (Sonnentag\t\r  et\t\r  al.,\t\r  2009;\t\r  Govind\t\r  et\t\r  al.,\t\r  2011).\t\r  \t\r  Most\t\r  modern\t\r  land\t\r  surface\t\r  models\t\r  (LSMs)\t\r  include\t\r  a\t\r  representation\t\r  of\t\r  frozen\t\r  soils\t\r  and\t\r  permafrost,\t\r  but,\t\r  in\t\r  climate\t\r  models,\t\r  these\t\r  are\t\r  applied\t\r  to\t\r  relatively\t\r  large\t\r  grid\t\r  cells\t\r  (~100\t\r  km),\t\r  and\t\r  hence\t\r  either\t\r  ignore\t\r  or\t\r  parameterize\t\r  spatial\t\r  variability.\t\r  While\t\r  the\t\r  thermodynamics\t\r  of\t\r  freezing\t\r  soil\t\r  moisture\t\r  are\t\r  relatively\t\r   straightforward,\t\r   representation\t\r   of\t\r   even\t\r   the\t\r   direct\t\r   thermodynamic\t\r   freezing\t\r   processes\t\r  differ\t\r  greatly\t\r  amongst\t\r  the\t\r  CMIP5\t\r  ESMs.\t\r  Furthermore,\t\r  large-­‐scale\t\r  model\t\r  treatments\t\r  are\t\r  necessarily\t\r  limited\t\r  by\t\r  their\t\r  inability\t\r  to\t\r  explicitly\t\r  resolve\t\r  subgrid\t\r  distributions\t\r  of\t\r  freezing\t\r  soil,\t\r  which\t\r  in\t\r  nature\t\r  are\t\r   controlled\t\r   by\t\r   variations\t\r   in\t\r   topography,\t\r   soil\t\r   type\t\r   (through\t\r   its\t\r   impact\t\r   on\t\r   water\t\r   transport),\t\r  vegetation,\t\r  topographic\t\r  aspect,\t\r  and\t\r  other\t\r  factors.\t\r  Local\t\r  subgrid\t\r  disturbances\t\r  such\t\r  as\t\r  thermokarst\t\r  are\t\r  not\t\r  incorporated\t\r  (Grosse\t\r  et\t\r  al.,\t\r  2011).\t\r  Attempts\t\r  have\t\r  been\t\r  made\t\r  to\t\r  base\t\r  parameterizations\t\r  on\t\r  comprehensive\t\r  in-­‐situ\t\r  measurements.\t\r  \t\r  However,\t\r  comparisons\t\r  of\t\r  model\t\r  predictions\t\r  of\t\r  permafrost-­‐related\t\r  variables\t\r  like\t\r  active\t\r  layer\t\r  depth\t\r  with\t\r  observations\t\r  (e.g.,\t\r  from\t\r  the\t\r  Circumpolar\t\r  Active\t\r  Layer\t\r  Monitoring\t\r   program\t\r   –\t\r   CALM)\t\r   usually\t\r   show\t\r   large\t\r   scatter\t\r   (Lawrence\t\r   et\t\r   al.,\t\r   2012;\t\r   Figure\t\r   9).\t\r   In\t\r  analogy\t\r  with\t\r  the\t\r  snow\t\r  problem,\t\r  models\t\r  may\t\r  need\t\r  to\t\r  parameterize\t\r  permafrost\t\r  spatial\t\r  variability\t\r  as\t\r  a\t\r  \nfunction\t\r  of\t\r  the\t\r  physical\t\r  characteristics\t\r  of\t\r  the\t\r  land\t\r  surface.\t\r  \t\r  \n\u003c/p\u003e\n\u003cp\u003e\t\r  \t\r  SMAP\t\r  freeze-­‐thaw\t\r  measurements\t\r  may\t\r  allow\t\r  the\t\r  generation\t\r  of\t\r  relevant\t\r  relationships\t\r  using\t\r  satellite\t\r  data,\t\r  at\t\r  least\t\r  for\t\r  the\t\r  upper\t\r  few\t\r  cm\t\r  of\t\r  the\t\r  soil\t\r  column.\t\r  Other\t\r  remote\t\r  sensing\t\r  techniques\t\r  may\t\r  prove\t\r  useful\t\r   for\t\r   large-­‐scale\t\r   monitoring\t\r   of\t\r   subsurface\t\r   freeze-­‐thaw\t\r   processes\t\r   as\t\r   well.\t\r   Liu\t\r   et\t\r   al.\t\r   (2012)\t\r  demonstrate\t\r   that\t\r   vertical\t\r   soil\t\r   displacements\t\r   due\t\r   to\t\r   seasonal\t\r   freeze-­‐thaw\t\r   processes,\t\r   detectable\t\r  through\t\r   InSAR,\t\r   can\t\r  be\t\r   related\t\r   to\t\r  active\t\r   layer\t\r   thickness,\t\r   although\t\r  key\t\r  parameters\t\r  needed\t\r   for\t\r   this\t\r  inversion,\t\r  such\t\r  as\t\r  soil\t\r  porosity,\t\r  currently\t\r  need\t\r  to\t\r  be\t\r  assumed.\t\r  Establishing\t\r  baseline\t\r  measurements\t\r  \nfor\t\r  longer-­‐term\t\r  monitoring\t\r  of\t\r  settling\t\r  due\t\r  to\t\r  permafrost\t\r  ice\t\r  loss\t\r  and\t\r  thermokarst\t\r  may\t\r  prove\t\r  a\t\r  crucial\t\r  \nway\t\r  of\t\r  detecting\t\r  changes\t\r  to\t\r  permafrost.\t\r   \t\r  Minsley\t\r  et\t\r  al.\t\r   (2012)\t\r  used\t\r  airborne\t\r  electromagnetic\t\r  (EM)\t\r  imaging\t\r  to\t\r  monitor\t\r  permafrost\t\r  distribution\t\r  in\t\r  a\t\r  zone\t\r  of\t\r  discontinuous\t\r  permafrost\t\r  in\t\r  Alaska.\t\r  \t\r  Such\t\r  \ntechniques,\t\r   or\t\r   other\t\r   ways\t\r   of\t\r   remotely\t\r   sensing\t\r   the\t\r   ABZ\t\r   subsurface\t\r   (or\t\r   extending\t\r   the\t\r   surface\t\r  \nmeasurements\t\r   to\t\r   infer\t\r   subsurface\t\r   properties\t\r   through\t\r   data\t\r   assimilation),\t\r   may\t\r   prove\t\r   critical\t\r   in\t\r   the\t\r  \nupscaling\t\r  of\t\r  permafrost\t\r  properties\t\r  from\t\r  point\t\r  measurements\t\r  to\t\r  regional\t\r  scales.\t\r  \n\u003c/p\u003e\n\u003cp\u003eFigure\t\r  9:\t\r  Scatterplot\t\r  of\t\r  active\t\r  layer\t\r  thickness\t\r  for\t\r  CALM\t\r  sites\t\r  vs\t\r  model\t\r  for\t\r  CLM4\t\r  and\t\r  CCSM4.\t\r  Model\t\r  data\t\r  are\t\r  from\t\r  ensemble\t\r  mean\t\r  climatological\t\r  average\t\r  for\t\r  the\t\r  period\t\r  1980–99.\t\r  CALM\t\r  site\t\r  data\t\r  are\t\r  climatological\t\r  average,\t\r  but\t\r  with\t\r  each\t\r  site\t\r  containing\t\r  a\t\r  different\t\r  number\t\r  of\t\r  years\t\r  of\t\r  data.\t\r  [From\t\r  Lawrence\t\r  et\t\r  al.\t\r  (2012)]\t\r  \u003c/p\u003e\n\u003cp /\u003e\n\u003c/div\u003e\n\u003cdiv class\u003d\"page\"\u003e\u003cp /\u003e\n\u003cp\u003e\t\r  \u003c/p\u003e\n\u003cp\u003e\t\r   15\t\r  \n\u003c/p\u003e\n\u003cp\u003e2.4.4 Lakes,\t\r  wetlands\t\r  and\t\r  rivers\t\r  Much\t\r  of\t\r  the\t\r  Arctic\t\r  land\t\r  area\t\r  has\t\r  a\t\r  relatively\t\r  high\t\r  density\t\r  of\t\r  lakes\t\r  and\t\r  wetlands\t\r  with\t\r  a\t\r  wide\t\r  range\t\r  in\t\r  size.\t\r  Lakes\t\r  represent\t\r  a\t\r  major\t\r  water\t\r  storage\t\r  reservoir\t\r  for\t\r  the\t\r  local\t\r  land\t\r  system,\t\r  helping\t\r  to\t\r  define\t\r  the\t\r  evaporative\t\r  regime.\t\r  Differences\t\r  in\t\r  lake\t\r  and\t\r  wetland\t\r  areas\t\r  are\t\r  thought\t\r  to\t\r  account\t\r  for\t\r  substantially\t\r  different\t\r   runoff\t\r   ratios\t\r   among\t\r   the\t\r   major\t\r   Arctic\t\r   rivers.\t\r   Hydrologically,\t\r   lakes,\t\r   wetlands\t\r   and\t\r  floodplains\t\r   are\t\r   a\t\r   complex\t\r   set\t\r   of\t\r   systems\t\r   that\t\r   have\t\r   very\t\r   different\t\r   properties\t\r   (e.g.\t\r   surface\t\r   versus\t\r  groundwater\t\r   dominated,\t\r   connected\t\r   versus\t\r   unconnected\t\r   to\t\r   river\t\r   systems,\t\r   thermally\t\r   stratified\t\r  versus\t\r  well-­‐mixed).\t\r  The\t\r   thermal\t\r  properties\t\r  and\t\r  surface\t\r   fluxes\t\r  of\t\r   lakes\t\r  are\t\r  usually\t\r  quite\t\r  different\t\r  from\t\r  those\t\r  of\t\r  the\t\r  surrounding\t\r  land\t\r  area.\t\r  \t\r  Surface\t\r  fluxes\t\r  over\t\r  frozen\t\r  lakes\t\r  are\t\r  usually\t\r  much\t\r  smaller\t\r  than\t\r  over\t\r   open\t\r  water,\t\r   so\t\r   the\t\r  dates\t\r   of\t\r   lake\t\r   freeze\t\r   and\t\r   thaw\t\r   can\t\r   exert\t\r   a\t\r   strong\t\r   influence\t\r   on\t\r   local\t\r  climate\t\r   (Samuelsson\t\r  et\t\r   al.,\t\r   2010;\t\r   Subin\t\r   et\t\r   al.,\t\r   2012a).\t\r   \t\r  During\t\r   summertime,\t\r  net\t\r   radiation\t\r   in\t\r  high\t\r  latitudes\t\r  is\t\r  high,\t\r  and\t\r  as\t\r  the\t\r  surrounding\t\r  landscape\t\r  dries\t\r  a\t\r  large\t\r  contrast\t\r  in\t\r  latent\t\r  heating\t\r  can\t\r  arise\t\r  (e.g.,\t\r  Subin\t\r  et\t\r  al.,\t\r  2012a).\t\r  \t\r  Most\t\r  climate\t\r  models\t\r  at\t\r  present\t\r  represent\t\r  lakes\t\r  only\t\r  crudely\t\r  and\t\r  typically\t\r  lump\t\r  multiple\t\r  lakes\t\r  into\t\r  an\t\r  “equivalent”\t\r  fractional\t\r  grid\t\r  cell\t\r   lake\t\r  with\t\r  a\t\r  static\t\r  area.\t\r   \t\r  Efforts\t\r  are\t\r  underway\t\r  to\t\r  refine\t\r  the\t\r  lake\t\r  model\t\r  components\t\r  included\t\r  in\t\r  climate\t\r  models\t\r  (e.g.,\t\r  Subin\t\r  et\t\r  al.,\t\r  2012b).\t\r  A\t\r  good\t\r  representation\t\r  of\t\r  surface\t\r   lakes,\t\r  wetlands\t\r  and\t\r   floodplain\t\r   inundation\t\r   in\t\r  ESMs\t\r  depends\t\r  on\t\r   the\t\r   incorporation\t\r  of\t\r  high-­‐resolution\t\r   topographic\t\r   data\t\r   into\t\r   the\t\r   lower-­‐resolution\t\r   structure\t\r   of\t\r   the\t\r   land\t\r   surface\t\r   model\t\r  (statistically\t\r  or\t\r  explicitly).\t\r  The\t\r  Arctic\t\r  contains\t\r  some\t\r  of\t\r  the\t\r  largest\t\r  rivers\t\r  and\t\r  watersheds\t\r  on\t\r  Earth\t\r  and\t\r  one-­‐half\t\r  to\t\r  two-­‐thirds\t\r  of\t\r  the\t\r  total\t\r  freshwater\t\r  flux\t\r  to\t\r  the\t\r  Arctic\t\r  Ocean\t\r  is\t\r  estimated\t\r  to\t\r  originate\t\r  as\t\r  river\t\r  runoff.\t\r  Most\t\r  GCMs\t\r  include\t\r  a\t\r  river\t\r  routing\t\r  scheme,\t\r  and\t\r  although\t\r  there\t\r  are\t\r  undoubtedly\t\r  improvements\t\r  that\t\r  are\t\r  needed,\t\r  the\t\r  primary\t\r  deficiency\t\r   in\t\r  modeling\t\r   the\t\r   freshwater\t\r   transport\t\r   to\t\r   the\t\r  Arctic\t\r  Ocean\t\r   lies\t\r   in\t\r  modeling\t\r  precipitation\t\r   and\t\r  other\t\r   inputs\t\r   rather\t\r   than\t\r   the\t\r   river\t\r   routing\t\r   scheme\t\r   itself.\t\r  Gravity\t\r  remote\t\r  sensing\t\r  \n(e.g.,\t\r  GRACE)\t\r  of\t\r  surface\t\r  water\t\r  dynamics\t\r  over\t\r  large\t\r  watersheds\t\r  could\t\r  help\t\r  detect\t\r  macroscale\t\r  changes\t\r  \nin\t\r  lake\t\r  storage\t\r  and\t\r  river\t\r  runoff\t\r  and\t\r  provide\t\r  some\t\r  validation\t\r  of\t\r  the\t\r  PCS\t\r  models.\t\r  \t\r  \n2.4.5 Sub-­‐grid\t\r  heterogeneity\t\r  Currently,\t\r  the\t\r  most\t\r  sophisticated\t\r  treatments\t\r  of\t\r  sub-­‐grid\t\r  heterogeneity\t\r  in\t\r  land\t\r  components\t\r  of\t\r  ESMs\t\r  assume\t\r   that\t\r   a\t\r   model\t\r   grid\t\r   cell\t\r   can\t\r   be\t\r   represented\t\r   as\t\r   fractional\t\r   areas\t\r   of\t\r   lake,\t\r   bare\t\r   ground,\t\r   and\t\r  multiple\t\r  plant\t\r  functional\t\r  types.\t\r  Sub-­‐grid\t\r  fractional\t\r  areas\t\r  are\t\r  combined\t\r  linearly\t\r  to\t\r  arrive\t\r  at\t\r  grid\t\r  cell\t\r  fluxes\t\r   and\t\r   states.\t\r   Many\t\r   LSMs\t\r   represent\t\r   processes\t\r   as\t\r   acting\t\r   in\t\r   independent\t\r   one-­‐dimensional\t\r  columns;\t\r   this\t\r   may\t\r   not\t\r   be\t\r   sufficient\t\r   to\t\r   deal\t\r   with\t\r   redistribution\t\r   of\t\r   water\t\r   and\t\r   energy\t\r   across\t\r  landscapes\t\r   (e.g.,\t\r   Koster\t\r   et\t\r   al.,\t\r   2000)\t\r   and\t\r   the\t\r   resulting\t\r   effects\t\r   on\t\r   soil\t\r   climate\t\r   and\t\r  biogeochemical\t\r  fluxes.\t\r  This\t\r  is\t\r  likely\t\r  to\t\r  be\t\r  particularly\t\r  important\t\r  in\t\r  environments\t\r  such\t\r  as\t\r  Arctic\t\r  polygonal\t\r  ground\t\r  and\t\r   peatland\t\r   microtopography.\t\r   DOE’s\t\r   Next\t\r   Generation\t\r   Ecosystem\t\r   Experiments\t\r   (NGEE)\t\r   project\t\r  aims\t\r  to\t\r  develop\t\r  a\t\r  high-­‐resolution\t\r  3-­‐D\t\r  LSM\t\r  that\t\r  includes\t\r  land\t\r  surface\t\r  deformation\t\r  for\t\r  the\t\r  Alaskan\t\r  North\t\r  Slope,\t\r   as\t\r  well\t\r   as\t\r   a\t\r   framework\t\r   for\t\r  bringing\t\r  a\t\r   statistical\t\r   treatment\t\r  of\t\r   these\t\r  dynamics\t\r   to\t\r   the\t\r  ESM\t\r  scale.\t\r  \t\r  NGEE\t\r  will\t\r  examine\t\r  whether\t\r  adequate\t\r  representation\t\r  of\t\r  biogeochemical\t\r  and\t\r  biophysical\t\r  dynamics\t\r   in\t\r   these\t\r   systems\t\r   depends\t\r   on\t\r   a\t\r   more\t\r   sophisticated\t\r   representation\t\r   of\t\r   the\t\r   fine-­‐scale\t\r  covariance\t\r   of\t\r   vegetation,\t\r   hydrology,\t\r   and\t\r   thermal\t\r   regime\t\r   as\t\r   structured\t\r   by\t\r   geomorphology\t\r   (e.g.,\t\r  Grosse\t\r  et\t\r  al.,\t\r  2011).\t\r  If\t\r  results\t\r  from\t\r  NGEE\t\r  over\t\r  limited\t\r  spatial\t\r  domains\t\r  confirm\t\r  the\t\r  hypothesis,\t\r  then\t\r  \na\t\r  more\t\r  extensive\t\r  effort\t\r  to\t\r  map\t\r  fine-­‐scale\t\r  geomorphological\t\r  variability\t\r  at\t\r  pan-­‐Arctic\t\r  scales\t\r  should\t\r  be\t\r  a\t\r  \npriority.\t\r  \t\r  \nA\t\r  critical\t\r  focus\t\r  should\t\r  be\t\r  on\t\r  the\t\r  testing\t\r  of\t\r  parameterizations\t\r  at\t\r  the\t\r  ESM\t\r  scale.\t\r  Surface\t\r  energy\t\r  budget\t\r  \ncalculations\t\r   based\t\r   on\t\r   statistical\t\r   representations\t\r   of\t\r   the\t\r   land\t\r   surface\t\r   variability\t\r   –\t\r   perhaps\t\r   best\t\r  \u003c/p\u003e\n\u003cp /\u003e\n\u003c/div\u003e\n\u003cdiv class\u003d\"page\"\u003e\u003cp /\u003e\n\u003cp\u003e\t\r  \u003c/p\u003e\n\u003cp\u003e\t\r   16\t\r  \n\u003c/p\u003e\n\u003cp\u003eobtained\t\r  from\t\r  remotely-­‐sensed\t\r  data\t\r  –\t\r  must\t\r  be\t\r  rigorously\t\r  evaluated\t\r  at\t\r  regional\t\r  (10\t\r  –\t\r  1000\t\r  km)\t\r  scales\t\r  \nas\t\r  well\t\r  as\t\r  at\t\r  the\t\r  scale\t\r  of\t\r   individual\t\r  process\t\r  study\t\r  sites\t\r  (10\t\r  m\t\r  –\t\r  10\t\r  km).\t\r  A\t\r  direct\t\r   additive\t\r   scaling-­‐up\t\r  approach\t\r  from\t\r  process\t\r  study\t\r  site\t\r  to\t\r  grid\t\r  area\t\r  is\t\r  not\t\r  feasible\t\r  as\t\r  almost\t\r  all\t\r  the\t\r  landscape\t\r  variability\t\r  is\t\r  expressed\t\r  at\t\r  length\t\r  scales\t\r  much\t\r  smaller\t\r  than\t\r  ESM\t\r  grid\t\r  areas.\t\r  \n2.5 Land\t\r  Surface\t\r  –\t\r  Biogeochemistry\t\r  \n\u003c/p\u003e\n\u003cp\u003e2.5.1 Soils\t\r  \t\r  About\t\r  one-­‐third\t\r  of\t\r  the\t\r  world’s\t\r  soil\t\r  organic\t\r  carbon\t\r  occurs\t\r  in\t\r  the\t\r  Arctic,\t\r  much\t\r  of\t\r  it\t\r  in\t\r  peatlands\t\r  and\t\r  in\t\r  the\t\r  deep\t\r  permafrost\t\r  soils\t\r  of\t\r  Siberia\t\r  (McGuire\t\r  et\t\r  al.,\t\r  2010).\t\r  Most\t\r  of\t\r  this\t\r  storage\t\r  has\t\r  accumulated\t\r  because\t\r   of\t\r  wet\t\r   and\t\r   cold\t\r   physical\t\r   conditions\t\r   that\t\r   are\t\r   not\t\r   conducive\t\r   to\t\r   the\t\r   decomposition\t\r   of\t\r   soil\t\r  organic\t\r  matter\t\r  (SOM).\t\r  The\t\r  biogeochemical\t\r  soil\t\r  models\t\r  in\t\r  ESMs\t\r  have\t\r  typically\t\r  been\t\r  conceptualized\t\r  as\t\r   vertically\t\r   integrated\t\r   box\t\r   models\t\r   with\t\r   first-­‐order\t\r   decay\t\r   of\t\r   SOM\t\r   and\t\r   transfer\t\r   among\t\r   multiple\t\r  pools\t\r  (e.g.,\t\r  Friedlingstein\t\r  et\t\r  al.,\t\r  2006).\t\r  \t\r  This\t\r  approach\t\r  fails\t\r  at\t\r  high\t\r  latitudes\t\r  for\t\r  a\t\r  variety\t\r  of\t\r  reasons:\t\r  \n• Steep\t\r  vertical\t\r  gradients\t\r  in\t\r  environmentally\t\r  determined\t\r  soil\t\r  turnover,\t\r  with\t\r  extremely\t\r  low\t\r  decomposition\t\r  in\t\r  permafrost\t\r  layers,\t\r  leads\t\r  to\t\r  buildup\t\r  of\t\r  labile\t\r  material\t\r  deep\t\r  in\t\r  mineral\t\r  soils.\t\r  \t\r  \n• Organic\t\r  layers,\t\r  which\t\r  build\t\r  up\t\r  in\t\r  saturated\t\r  and/or\t\r  cold\t\r  soils,\t\r  contain\t\r  large\t\r  amounts\t\r  of\t\r  carbon\t\r  that\t\r  could\t\r  be\t\r  mineralized\t\r  or\t\r  combusted\t\r  during\t\r  fires\t\r  under\t\r  changing\t\r  environmental\t\r  conditions.\t\r  \t\r  Since\t\r  organic\t\r  soils\t\r  have\t\r  very\t\r  different\t\r  physical\t\r  properties,\t\r  permafrost\t\r  organic\t\r  soils\t\r  are\t\r  likely\t\r  to\t\r  thaw\t\r  much\t\r  more\t\r  slowly\t\r  than\t\r  mineral\t\r  soils\t\r  with\t\r  climate\t\r  warming.\t\r  \n• Anoxic\t\r  decomposition,\t\r  and\t\r  the\t\r  production\t\r  and\t\r  consumption\t\r  of\t\r  CH4\t\r  and\t\r  N2O\t\r  are\t\r  poorly\t\r  or\t\r  not\t\r  represented\t\r  in\t\r  the\t\r  current\t\r  generation\t\r  of\t\r  ESMs.\t\r  \t\r  \t\r  \n• Microbial\t\r  dynamics\t\r  might\t\r  be\t\r  particularly\t\r  important\t\r  in\t\r  places\t\r  with\t\r  very\t\r  dynamic\t\r  changes\t\r  in\t\r  soil\t\r  microenvironment,\t\r  such\t\r  as\t\r  the\t\r  active\t\r  layer/permafrost\t\r  interface\t\r  or\t\r  oxic/anoxic\t\r  zones\t\r  in\t\r  saturated\t\r  soils.\t\r  To\t\r  address\t\r  these\t\r  issues,\t\r  models\t\r  need\t\r  to\t\r  use\t\r  sufficient\t\r  representation\t\r  of\t\r  the\t\r  vertical\t\r  structure\t\r  in\t\r  soil\t\r  biogeochemistry\t\r  to\t\r  assess\t\r  the\t\r  effects\t\r  of\t\r  permafrost\t\r  thaw\t\r  on\t\r  the\t\r  overall\t\r  soil\t\r  carbon\t\r  budget;\t\r  account\t\r  for\t\r  both\t\r  thermal\t\r  and\t\r  hydrologic\t\r  properties\t\r  of\t\r  SOM;\t\r  improve\t\r  the\t\r  treatment\t\r  of\t\r  shallow\t\r  water\t\r  tables,\t\r  and\t\r  the\t\r  production,\t\r  consumption,\t\r  and\t\r  transport\t\r  of\t\r  trace\t\r  gases;\t\r  and\t\r  include\t\r  microbial\t\r  dynamics.\t\r  Recent\t\r  modeling\t\r  studies\t\r  (Lawrence\t\r  et\t\r  al.,\t\r  2008;\t\r  Koven\t\r  et\t\r  al.,\t\r  2009,\t\r  2011;\t\r  Schneider\t\r  von\t\r  Deimling\t\r  et\t\r  al.,\t\r   2012)\t\r   used\t\r   a\t\r   vertically\t\r   discretized\t\r   soil\t\r   carbon\t\r   module,\t\r   where\t\r   decomposition\t\r   rates\t\r   are\t\r  calculated\t\r   for\t\r   each\t\r   soil\t\r   level,\t\r   to\t\r   dynamically\t\r   model\t\r   the\t\r   steep\t\r   vertical\t\r   gradient\t\r   in\t\r   soil\t\r   carbon\t\r  residence\t\r   time\t\r   that\t\r   occurs\t\r   at\t\r   the\t\r   permafrost\t\r   table\t\r   in\t\r   permafrost-­‐affected\t\r   soils.\t\r   Lawrence\t\r   et\t\r   al.\t\r  (2008)\t\r  account\t\r  for\t\r  both\t\r  thermal\t\r  and\t\r  hydrologic\t\r  properties\t\r  of\t\r  SOM\t\r  and\t\r  model\t\r  the\t\r  effect\t\r  of\t\r  SOM\t\r  on\t\r  active\t\r  layer\t\r  thickness.\t\r  These\t\r  model\t\r   improvements\t\r  lead\t\r  to\t\r  better\t\r  agreement\t\r  with\t\r  observations,\t\r  as\t\r  seen\t\r  in\t\r  the\t\r  comparison\t\r  from\t\r  Koven\t\r  et\t\r  al.\t\r  (2011)\t\r  (Figure\t\r  10).\t\r  However,\t\r  initial\t\r  carbon\t\r  stocks\t\r  are\t\r  still\t\r  substantially\t\r  underestimated,\t\r  particularly\t\r  those\t\r  in\t\r  western\t\r  Siberia\t\r  and\t\r  Canada,\t\r  because\t\r  the\t\r  model\t\r  does\t\r   not\t\r   include\t\r   the\t\r   buildup\t\r   of\t\r   organic\t\r   matter\t\r   peatlands\t\r   or\t\r   forests\t\r   on\t\r   sites\t\r   with\t\r   permafrost.\t\r  Khvorostyanov\t\r  et\t\r  al.\t\r  (2008a)\t\r  found\t\r  the\t\r  mobilization\t\r  of\t\r  frozen\t\r  carbon\t\r  to\t\r  be\t\r  particularly\t\r  sensitive\t\r  to\t\r  heat\t\r  produced\t\r  by\t\r  soil\t\r  microorganisms,\t\r  but\t\r  the\t\r  strength\t\r  of\t\r  this\t\r  feedback\t\r  mechanism\t\r  and\t\r  the\t\r  realism\t\r  of\t\r   the\t\r   simulations\t\r   remain\t\r   unclear\t\r   (Heimann\t\r   and\t\r   Reichstein,\t\r   2008).\t\r   \t\r   Harden\t\r   et\t\r   al.\t\r   (2012)\t\r   show\t\r  important\t\r  differences\t\r   in\t\r   carbon\t\r   form,\t\r   vertical\t\r   distribution,\t\r   content,\t\r   and\t\r  potential\t\r  mechanisms\t\r  of\t\r  vulnerability\t\r  across\t\r  different\t\r  permafrost\t\r  soil\t\r   types.\t\r  Mapable\t\r  soil\t\r  units\t\r  may\t\r  be\t\r  a\t\r  way\t\r  of\t\r  upscaling\t\r  from\t\r  point\t\r  measurements\t\r  to\t\r  regional\t\r  scales\t\r  to\t\r  address\t\r  these\t\r  issues.\t\r  \t\r  \u003c/p\u003e\n\u003cp /\u003e\n\u003c/div\u003e\n\u003cdiv class\u003d\"page\"\u003e\u003cp /\u003e\n\u003cp\u003e\t\r  \u003c/p\u003e\n\u003cp\u003e\t\r   17\t\r  \n\u003c/p\u003e\n\u003cp\u003e\t\r  \n\u003c/p\u003e\n\u003cp\u003e\t\r  Figure\t\r  10:\t\r  Maps\t\r  of\t\r  initial\t\r  soil\t\r  carbon\t\r  (kg\t\r  C\t\r  m-­‐2)\t\r  to\t\r  depths\t\r  of\t\r  1\t\r  m\t\r  and\t\r  3\t\r  m\t\r  for\t\r  sensitivity\t\r  experiments,\t\r  and\t\r  for\t\r  comparison,\t\r  observations\t\r  from\t\r  the\t\r  northern\t\r  circumpolar\t\r  soil\t\r  carbon\t\r  database\t\r  (NCSCD).\t\r  The\t\r  four\t\r  experiments\t\r  are\t\r  (i)\t\r  base,\t\r  in\t\r  which\t\r  soil\t\r  carbon\t\r  is\t\r  vertically\t\r  resolved\t\r  but\t\r  no\t\r  additional\t\r  processes\t\r  are\t\r  added;\t\r  (ii)\t\r  freeze,\t\r  inhibition\t\r  of\t\r  decomposition\t\r  in\t\r  seasonally\t\r  frozen\t\r  soil\t\r  layers,\t\r  but\t\r  no\t\r  soil\t\r  carbon\t\r  in\t\r  permafrost\t\r  soil\t\r  layers;\t\r  (iii)\t\r  permafrost,\t\r  inclusion\t\r  of\t\r  permafrost\t\r  carbon\t\r  through\t\r  vertical\t\r  mixing\t\r  and\t\r  soil\t\r  organic\t\r  insulation;\t\r  and\t\r  (iv)\t\r  heat,\t\r  inclusion\t\r  of\t\r  microbial\t\r  heat\t\r  release\t\r  by\t\r  decomposing\t\r  microbes\t\r  to\t\r  the\t\r  soil\t\r  thermal\t\r  budget.\t\r  [From\t\r  Koven\t\r  et\t\r  al.,\t\r  2011]\t\r  \t\r  \nPriority\t\r  should\t\r  be\t\r  given\t\r  to\t\r  mapping\t\r  permafrost\t\r  and\t\r  soil\t\r  properties\t\r  across\t\r  the\t\r  ABZ\t\r  using\t\r  satellite\t\r  data\t\r  \nand\t\r  available\t\r  in-­‐situ\t\r  data\t\r  sets,\t\r  with\t\r  a\t\r  significant\t\r  effort\t\r  to\t\r  correlate\t\r  soil,\t\r  vegetation\t\r  and\t\r  hydrological\t\r  \nattributes\t\r   to\t\r   remotely-­‐sensed\t\r   data\t\r   using\t\r   sophisticated\t\r   soil-­‐vegetation\t\r   models.\t\r   Field\t\r   campaigns\t\r  \ndesigned\t\r  to\t\r  investigate\t\r  surface\t\r  hydrology\t\r  and\t\r  land-­‐atmosphere\t\r  fluxes\t\r  should\t\r  consider\t\r  this\t\r  goal\t\r  when\t\r  \ndesigning\t\r   the\t\r   experiment.\t\r  A\t\r  key\t\r  aspect\t\r  will\t\r   be\t\r   to\t\r  use\t\r  observations\t\r  gathered\t\r  over\t\r  a\t\r   range\t\r  of\t\r   spatial\t\r  \nscales\t\r  –\t\r  surface\t\r  site,\t\r  airborne\t\r  sensors\t\r  and\t\r  satellite\t\r  sensors\t\r  –\t\r  to\t\r  credibly\t\r  account\t\r  for\t\r  scaling\t\r  effects.\t\r  \t\r  \n2.5.2 Disturbance\t\r  The\t\r  ABZ\t\r  will\t\r  be\t\r  subjected\t\r  to\t\r  both\t\r  press-­‐type\t\r  disturbance\t\r  (relatively\t\r  slow\t\r  but\t\r  persistent,\t\r  large\t\r  scale\t\r  impacts\t\r  like\t\r  warming-­‐induced\t\r  top-­‐down\t\r  permafrost\t\r  thaw,\t\r  gradual\t\r  climatic\t\r  drying,\t\r  pollution\t\r  or\t\r  N-­‐deposition),\t\r  and\t\r  pulse-­‐type\t\r  disturbances\t\r  (abrupt,\t\r  often\t\r  localized\t\r  impacts\t\r   like\t\r  fires,\t\r   flooding,\t\r   thaw\t\r  slumping)\t\r   (e.g.,\t\r   Grosse\t\r   et\t\r   al.\t\r   2011).\t\r   \t\r   These\t\r   disturbances\t\r   can\t\r   interact,\t\r   e.g.,\t\r   fire\t\r   leading\t\r   to\t\r   (multi-­‐year)\t\r  surface\t\r  warming\t\r  causing\t\r  accelerated\t\r  permafrost\t\r  thaw.\t\r  \t\r  Disturbance\t\r  varies\t\r  considerably\t\r  between\t\r  Arctic\t\r   tundra\t\r  and\t\r  boreal\t\r  biomes,\t\r  but\t\r   fire\t\r   is\t\r   common\t\r   to\t\r  both\t\r  and\t\r   is\t\r  ubiquitous\t\r   in\t\r   the\t\r   latter.\t\r   \t\r  The\t\r  disturbance\t\r   regime\t\r  has\t\r   intensified\t\r   in\t\r   recent\t\r  decades\t\r   in\t\r  both\t\r  North\t\r  America\t\r  and\t\r  northern\t\r  Eurasia\t\r  (e.g.,\t\r  Kasischke\t\r  and\t\r  Turetsky,\t\r  2006;\t\r  Goetz\t\r  et\t\r  al.,\t\r  2007).\t\r  Fires\t\r   of\t\r   anthropogenic\t\r   origin\t\r   account\t\r   for\t\r   a\t\r   portion\t\r   of\t\r   wildland\t\r   area\t\r   burned,\t\r   but\t\r   a\t\r   substantial\t\r  fraction\t\r  are\t\r  of\t\r  natural\t\r  origin.\t\r  Increased\t\r  convective\t\r  activity\t\r  in\t\r  the\t\r  ABZ\t\r  has\t\r  produced\t\r  more\t\r  frequent\t\r  lightning\t\r  strikes\t\r  in\t\r  both\t\r  tundra\t\r  and\t\r  boreal\t\r  zones,\t\r  increasing\t\r  the\t\r  likelihood\t\r  of\t\r  fire\t\r  ignition.\t\r  \t\r  Ignition\t\r  probability\t\r   is\t\r   amplified\t\r   in\t\r   the\t\r   boreal\t\r   zone\t\r   as\t\r   a\t\r   result\t\r   of\t\r   warmer\t\r   conditions\t\r   and\t\r   associated\t\r   tree\t\r  \u003c/p\u003e\n\u003cp /\u003e\n\u003c/div\u003e\n\u003cdiv class\u003d\"page\"\u003e\u003cp /\u003e\n\u003cp\u003e\t\r  \u003c/p\u003e\n\u003cp\u003e\t\r   18\t\r  \n\u003c/p\u003e\n\u003cp\u003emortality\t\r  from\t\r  drought\t\r  and\t\r  insect\t\r  pests.\t\r  \t\r  The\t\r  latter\t\r  are\t\r  highly\t\r  episodic\t\r  and\t\r  difficult\t\r  to\t\r  predict\t\r  but\t\r  are\t\r  typically\t\r  associated\t\r  with\t\r  stress\t\r  brought\t\r  on\t\r  by\t\r  drought\t\r  and\t\r  also\t\r  increased\t\r  pest\t\r  survival\t\r  during\t\r  warmer\t\r   winter\t\r   months.\t\r   Separation\t\r   of\t\r   longer-­‐term\t\r   disturbance\t\r   regimes\t\r   from\t\r   the\t\r   current,\t\r  intensifying\t\r   regime\t\r   has\t\r   a\t\r   high\t\r   level\t\r   of\t\r   uncertainty\t\r   and\t\r   needs\t\r   attention\t\r   for\t\r   realistic\t\r   model\t\r  evaluation.\t\r  \t\r  \t\r  Insects\t\r  and\t\r  pathogens\t\r  are\t\r  biotic\t\r  agents\t\r  of\t\r  disturbance\t\r   that\t\r  may\t\r  affect\t\r  up\t\r   to\t\r  45\t\r   times\t\r   the\t\r  area\t\r  of\t\r  wildfire.\t\r   Climate\t\r   is\t\r   an\t\r   important\t\r   driver\t\r   of\t\r   insect\t\r   and\t\r   disease\t\r   outbreaks\t\r   and\t\r   potential\t\r   feedbacks\t\r  exist\t\r  between\t\r  climate\t\r  change\t\r  and\t\r  biotic\t\r  disturbances\t\r  through\t\r  the\t\r  carbon\t\r  cycle.\t\r  According\t\r  to\t\r  Kurz\t\r  et\t\r  al.\t\r  (2008a,\t\r  b),\t\r  mountain\t\r  pine\t\r  beetle\t\r  outbreaks\t\r  in\t\r  western\t\r  Canada\t\r  have\t\r  had\t\r  a\t\r  dramatic\t\r  impact\t\r  on\t\r  carbon\t\r   cycling.\t\r   Hicke\t\r   et\t\r   al.\t\r   (2012)\t\r   found\t\r   that\t\r   biotic\t\r   disturbances\t\r   (insects,\t\r   disease,\t\r   and\t\r   forest\t\r  dieback)\t\r   can\t\r   have\t\r  major\t\r   impacts\t\r   on\t\r   forest\t\r   carbon\t\r   stocks\t\r   and\t\r   fluxes\t\r   and\t\r   can\t\r   be\t\r   large\t\r   enough\t\r   to\t\r  affect\t\r   regional\t\r   carbon\t\r   cycling.\t\r   They\t\r   identified\t\r   significant\t\r   knowledge\t\r   gaps,\t\r   including\t\r   a\t\r   limited\t\r  understanding\t\r   of\t\r   carbon\t\r   cycle\t\r   impacts\t\r   among\t\r   different\t\r   biotic\t\r   disturbance\t\r   types\t\r   (particularly\t\r  pathogens)\t\r  and\t\r  their\t\r  impacts\t\r  at\t\r  landscape\t\r  and\t\r  regional\t\r  scales.\t\r  The\t\r  capacity\t\r  to\t\r  predict\t\r  disturbance\t\r  events\t\r   and\t\r   their\t\r   consequences\t\r   for\t\r   carbon\t\r   cycling\t\r   is\t\r   limited\t\r   by\t\r   the\t\r   lack\t\r   of\t\r   knowledge\t\r   of\t\r   the\t\r   life\t\r  history,\t\r   traits\t\r   and\t\r   drivers\t\r   that\t\r   can\t\r   be\t\r   incorporated\t\r   into\t\r   predictive\t\r   modeling\t\r   and\t\r   the\t\r   lack\t\r   of\t\r   a\t\r  predictive\t\r   capability\t\r   for\t\r   invasions\t\r   by\t\r   exotic\t\r   species.\t\r   In\t\r   addition,\t\r   interactions\t\r   with\t\r   other\t\r  disturbances\t\r  are\t\r  not\t\r  well\t\r  quantified.\t\r  \t\r  Disturbance\t\r  processes\t\r  are\t\r  inadequately\t\r  incorporated\t\r  in\t\r  the\t\r  LSM-­‐BGC\t\r  component\t\r  of\t\r  ESMs.\t\r  Hicke\t\r  et\t\r  al.\t\r   (2012)\t\r   note\t\r   that\t\r   most\t\r   carbon\t\r   cycle\t\r   models\t\r   do\t\r   not\t\r   include\t\r   biotic\t\r   disturbances.\t\r   Removal\t\r   of\t\r  surface\t\r  organic\t\r  matter\t\r  by\t\r  fires\t\r  may\t\r  further\t\r  destabilize\t\r  permafrost,\t\r  exposing\t\r  underlying\t\r  carbon\t\r  to\t\r  further\t\r   fire\t\r   vulnerability\t\r   (positive\t\r   feedback).\t\r   These\t\r   processes\t\r   are\t\r   poorly\t\r   constrained\t\r   in\t\r   models\t\r  because\t\r   of\t\r   the\t\r   short\t\r   and\t\r   sparse\t\r   record\t\r   of\t\r   actual\t\r   fire\t\r   emissions\t\r   from\t\r   the\t\r   Arctic.\t\r   Therefore\t\r   few\t\r  models\t\r  consider\t\r  fire\t\r  emissions\t\r  or\t\r  do\t\r  so\t\r  in\t\r  simplistic\t\r  ways\t\r  that\t\r  do\t\r  not\t\r  capture\t\r  the\t\r  full\t\r  vulnerability\t\r  of\t\r   this\t\r   large\t\r  carbon\t\r  store.\t\r   \t\r  To\t\r  remedy\t\r  this,\t\r  a\t\r  combination\t\r  of\t\r  satellite\t\r  fire\t\r  mapping,\t\r  in-­‐situ\t\r  pre-­‐\t\r  and\t\r  \npost-­‐fire\t\r   inventories,\t\r   and\t\r   atmospheric\t\r   composition\t\r   (surface,\t\r   airborne,\t\r   satellite)\t\r   measurements\t\r   can\t\r  \nprovide\t\r  the\t\r  needed\t\r  constraints\t\r  to\t\r  allow\t\r  development\t\r  of\t\r  models\t\r  that\t\r  capture\t\r  the\t\r  current\t\r  situation\t\r  and\t\r  that\t\r   can\t\r   provide\t\r   predictions\t\r   of\t\r   future\t\r   carbon\t\r   emissions\t\r   from\t\r   this\t\r   important\t\r   carbon\t\r   stock.\t\r   Fire\t\r  observations\t\r   are\t\r   accurate\t\r   and\t\r   routine\t\r   from\t\r   satellites.\t\r   What\t\r   is\t\r   uncertain\t\r   is\t\r   the\t\r   amount\t\r   of\t\r   fuel\t\r  consumed.\t\r  \t\r  Recovery\t\r   from\t\r   disturbance\t\r   in\t\r   the\t\r   ABZ\t\r   is\t\r   also\t\r   highly\t\r   variable\t\r   and\t\r   strongly\t\r   influenced\t\r   by\t\r   the\t\r  intensity\t\r   of\t\r   disturbance\t\r   (e.g.,\t\r   Goetz\t\r   et\t\r   al.,\t\r   2012).\t\r   \t\r   Disturbance\t\r   intensity\t\r   produces\t\r   non-­‐linear\t\r  trajectories\t\r  of\t\r  post-­‐disturbance\t\r  carbon\t\r  and\t\r  energy\t\r  exchange.\t\r  \t\r  This\t\r  is\t\r  true\t\r  of\t\r  all\t\r  disturbance\t\r  types\t\r  -­‐\t\r  whether\t\r  fire,\t\r   insects,\t\r   logging\t\r  or\t\r  the\t\r  interaction\t\r  of\t\r  these\t\r  –\t\r  but\t\r  the\t\r  time\t\r  scale\t\r  of\t\r  their\t\r  legacy\t\r  effects\t\r  differ.\t\r  Progress\t\r  is\t\r  also\t\r  needed\t\r  with\t\r  respect\t\r  to\t\r  modeling\t\r  the\t\r  indirect\t\r  effects\t\r  of\t\r  disturbances\t\r  on\t\r  how\t\r  soil\t\r   hydrological,\t\r   thermal,\t\r   and\t\r   biogeochemical\t\r   dynamics\t\r   co-­‐vary\t\r   during\t\r   succession\t\r   following\t\r  disturbance.\t\r   In\t\r   addition\t\r   to\t\r   changing\t\r   post-­‐disturbance\t\r   vegetation\t\r   succession,\t\r   more\t\r   severe\t\r   fire\t\r  disturbance\t\r  produces\t\r  greater\t\r  microbial\t\r  respiration,\t\r  and\t\r  can\t\r  change\t\r  the\t\r  balance\t\r  of\t\r  the\t\r  components\t\r  of\t\r  net\t\r  exchange.\t\r  Better\t\r  remote\t\r  sensing\t\r  methods\t\r  are\t\r  needed\t\r  to\t\r  map\t\r  disturbance\t\r  severity\t\r  (e.g.\t\r  for\t\r  fire\t\r  \ndisturbance\t\r  this\t\r  is\t\r  defined\t\r  by\t\r  SOM\t\r  consumption),\t\r  and\t\r  disturbance\t\r  severity\t\r  needs\t\r  to\t\r  be\t\r  represented\t\r  in\t\r  \nLSM-­‐BGC\t\r   models.\t\r   Temporal\t\r   and\t\r   spatial\t\r   scaling\t\r   of\t\r   these\t\r   non-­‐linear\t\r   disturbance\t\r   effects\t\r   on\t\r   carbon,\t\r  \nenergy\t\r  and\t\r  water\t\r  is\t\r  a\t\r  high\t\r  priority\t\r  and\t\r  would\t\r  benefit\t\r  from\t\r  coordinated\t\r  and\t\r  focused\t\r  field\t\r  experiments.\t\r  Realistic\t\r  predictions\t\r  of\t\r  future\t\r  BGC\t\r  in\t\r  the\t\r  ABZ\t\r  requires\t\r  realistic\t\r  simulation\t\r  of\t\r  changes\t\r  in\t\r  vegetation\t\r  functional\t\r   types\t\r   as\t\r   mediated\t\r   by\t\r   disturbance\t\r   –\t\r   not\t\r   simply\t\r   climate\t\r   envelopes\t\r   of\t\r   species\t\r  presence/absence\t\r  projected\t\r  into\t\r  the\t\r  future.\t\r  \t\r  Better\t\r  records\t\r  of\t\r  past\t\r  disturbance\t\r  are\t\r  needed\t\r  –\t\r  perhaps\t\r  \nfrom\t\r  the\t\r  Landsat\t\r  record\t\r  –\t\r  particularly\t\r  for\t\r  northern\t\r  Eurasia.\t\r   \t\r   Ideally\t\r   these\t\r  should\t\r  be\t\r   “wall\t\r   to\t\r  wall”\t\r  rather\t\r  than\t\r  sampling-­‐based,\t\r  and\t\r  available\t\r  annually\t\r  as\t\r  far\t\r  back\t\r  as\t\r  possible.\t\r  \u003c/p\u003e\n\u003cp /\u003e\n\u003c/div\u003e\n\u003cdiv class\u003d\"page\"\u003e\u003cp /\u003e\n\u003cp\u003e\t\r  \u003c/p\u003e\n\u003cp\u003e\t\r   19\t\r  \n\u003c/p\u003e\n\u003cp\u003ePredictive\t\r  Disturbance\t\r  Modeling\t\r  and\t\r  ESMs:\t\r  ESMs\t\r  and\t\r  related\t\r  BGC\t\r  and/or\t\r  submodels\t\r  (e.g.,\t\r  Hicke\t\r  et\t\r  al.,\t\r  2012)\t\r  need\t\r  to\t\r  be\t\r  able\t\r  to\t\r  predict\t\r  how\t\r  climate\t\r  will\t\r  change\t\r  the\t\r  distribution,\t\r  frequency,\t\r  seasonal\t\r  timing,\t\r   and\t\r   severity\t\r   of\t\r   disturbances\t\r   common\t\r   to\t\r   the\t\r   ABZ\t\r   (e.g.,\t\r   fire,\t\r   thermokarst,\t\r   and\t\r   biological\t\r  disturbances\t\r  –\t\r  insects\t\r  and\t\r  pathogens).\t\r  Currently,\t\r  relationships\t\r  between\t\r  fire\t\r  frequency\t\r  and\t\r  climate\t\r  are\t\r  based\t\r  on\t\r  comparisons\t\r  of\t\r  burned\t\r  area\t\r  in\t\r  large\t\r  geographic\t\r  regions\t\r  and\t\r  variables\t\r  that\t\r  are\t\r  derived\t\r  from\t\r  weather\t\r   data,\t\r   including\t\r   a\t\r   set\t\r   of\t\r   fuel\t\r  moisture\t\r   indices\t\r   derived\t\r   from\t\r  weather\t\r   variables\t\r   (e.g.,\t\r  Balshi\t\r  et\t\r  al.,\t\r  2009a,\t\r  b).\t\r   \t\r  Further\t\r  research\t\r  is\t\r  needed\t\r  to\t\r  determine\t\r  how\t\r  variations\t\r  in\t\r  vegetation\t\r  cover,\t\r  \nfuel\t\r  amounts\t\r  and\t\r  fuel\t\r  conditions\t\r  influence\t\r  fire\t\r  occurrence\t\r  so\t\r  that\t\r  these\t\r  effects\t\r  can\t\r  be\t\r  included\t\r  in\t\r  ESMs.\t\r  \t\r  Liu\t\r  et\t\r  al.\t\r   (2011)\t\r  review\t\r  how\t\r  disturbances\t\r  and\t\r  their\t\r   impacts\t\r  are\t\r   treated\t\r  and\t\r  modeled\t\r   in\t\r  process-­‐based\t\r   state-­‐of-­‐the-­‐art\t\r   carbon\t\r   cycle\t\r   models\t\r   at\t\r   the\t\r   stand\t\r   level\t\r   and\t\r   how\t\r   disturbances\t\r   and\t\r   their\t\r  impacts\t\r   are\t\r   scaled\t\r   up\t\r   from\t\r   stand\t\r   to\t\r   continental\t\r   scales.\t\r   Grosse\t\r   et\t\r   al.\t\r   (2011)\t\r   noted\t\r   the\t\r   need\t\r   for\t\r  subgrid-­‐scale\t\r  processes\t\r  related\t\r  to\t\r  all\t\r  disturbances\t\r  to\t\r  be\t\r  meaningfully\t\r  integrated\t\r  with\t\r  macro-­‐scale\t\r  models.\t\r   To\t\r   model\t\r   the\t\r   stochastic\t\r   nature\t\r   of\t\r   disturbances,\t\r   probability\t\r   distributions\t\r   of\t\r   frequency,\t\r  severity,\t\r  and\t\r  spatial\t\r  coverage\t\r  for\t\r  different\t\r  types\t\r  of\t\r  disturbances\t\r  can\t\r  be\t\r  constructed\t\r  from\t\r  regional\t\r  databases.\t\r   The\t\r   challenge\t\r   is\t\r   to\t\r   upscale\t\r   these\t\r   relationships\t\r   to\t\r   the\t\r   continental\t\r   scale\t\r   of\t\r   ESMs\t\r   (e.g.,\t\r  Weng\t\r   et\t\r   al.,\t\r   2012).\t\r   In\t\r   order\t\r   to\t\r   capture\t\r   spatial\t\r   heterogeneity\t\r   of\t\r   landscape-­‐scale\t\r   processes,\t\r  more\t\r  detailed\t\r   spatial\t\r   scales\t\r   must\t\r   be\t\r   integrated\t\r   mathematically\t\r   into\t\r   the\t\r   coarser\t\r   scales\t\r   required\t\r   for\t\r  regional\t\r  and\t\r  global\t\r  models.\t\r  However,\t\r  it\t\r  is\t\r  not\t\r  clear\t\r  which\t\r  processes\t\r  and\t\r  properties\t\r  are\t\r  critical\t\r  at\t\r  a\t\r  given\t\r  temporal\t\r  or\t\r  spatial\t\r  scale,\t\r  and\t\r  which\t\r  can\t\r  be\t\r  simplified.\t\r  \t\r  It\t\r   is\t\r   probably\t\r   not\t\r   necessary,\t\r   or\t\r   efficient,\t\r   to\t\r   try\t\r   to\t\r   incorporate\t\r   a\t\r   coupled\t\r   mechanistic\t\r   climate-­‐vegetation-­‐fire\t\r  frequency\t\r  relationship\t\r  into\t\r  the\t\r  ESMs\t\r  themselves.\t\r  However,\t\r  one\t\r  approach\t\r  might\t\r  be\t\r  for\t\r  ESMs\t\r  to\t\r  generate\t\r  good\t\r  output\t\r  drivers\t\r  for\t\r  an\t\r  ensemble\t\r  of\t\r  disturbance/BGC\t\r  models\t\r  that\t\r  could\t\r  be\t\r  run\t\r  offline\t\r  to\t\r  get\t\r  a\t\r  good\t\r  statistical\t\r  set\t\r  of\t\r  model\t\r  outcomes.\t\r  The\t\r  results\t\r  could\t\r  then\t\r  be\t\r  summarized\t\r  to\t\r  calibrate\t\r  a\t\r  simpler\t\r  parameterization\t\r  that\t\r  could\t\r  be\t\r  integrated\t\r  into\t\r  the\t\r  ESM\t\r  itself.\t\r  \n2.5.3 Ecosystem\t\r  dynamics\t\r  Terrestrial\t\r  ecosystems\t\r  are\t\r  a\t\r  major\t\r  player\t\r  in\t\r  the\t\r  carbon-­‐climate\t\r  system:\t\r  they\t\r  can\t\r  release\t\r  or\t\r  absorb\t\r  globally\t\r   relevant\t\r   greenhouse\t\r   gases\t\r   such\t\r   as\t\r   CO2,\t\r   CH4\t\r   and\t\r   nitrous\t\r   oxide,\t\r   they\t\r   emit\t\r   aerosols\t\r   and\t\r  aerosol\t\r   precursors,\t\r   and\t\r   they\t\r   control\t\r   exchanges\t\r   of\t\r   energy,\t\r   water\t\r   and\t\r   momentum\t\r   between\t\r   the\t\r  atmosphere\t\r   and\t\r   the\t\r   land\t\r   surface.\t\r   A\t\r  multitude\t\r   of\t\r   climate–ecosystem\t\r   feedbacks\t\r  might\t\r   amplify\t\r   or\t\r  dampen\t\r   regional\t\r   and\t\r   global\t\r   climate\t\r   change.\t\r   The\t\r   rather\t\r   wide\t\r   spread\t\r   of\t\r   CO2\t\r   fluxes\t\r   among\t\r   ESM\t\r  models\t\r   in\t\r   both\t\r   historical\t\r   simulations\t\r   and\t\r   future\t\r   projections\t\r   of\t\r   carbon-­‐climate\t\r   feedbacks\t\r  (Friedlingstein\t\r  et\t\r  al.,\t\r  2006)\t\r  demonstrates\t\r  the\t\r  very\t\r  poor\t\r  understanding\t\r  of\t\r  processes\t\r  in\t\r  functioning\t\r  ecosystems\t\r  as\t\r  represented\t\r  in\t\r  these\t\r  models\t\r  (Heimann\t\r  and\t\r  Reichstein,\t\r  2008).\t\r  Dynamic\t\r   global\t\r   vegetation\t\r   models\t\r   (DGVMs)\t\r   were\t\r   developed\t\r   to\t\r   simulate\t\r   the\t\r   coupling\t\r   between\t\r  climate\t\r   and\t\r   vegetation\t\r   in\t\r   transient\t\r   simulations.\t\r   Levis\t\r   (2010)\t\r   summarizes\t\r   DGVMs\t\r   and\t\r   processes\t\r  (e.g.,\t\r  inclusion\t\r  of\t\r  fire\t\r  or\t\r  nitrogen\t\r  cycle,\t\r  the\t\r  level\t\r  of\t\r  complexity\t\r  of\t\r  the\t\r  representation\t\r  of\t\r  plants)\t\r  that\t\r  vary\t\r  between\t\r  them.\t\r  The\t\r  second-­‐generation\t\r  DGVMs\t\r  simulate\t\r  a\t\r  suite\t\r  of\t\r  ecosystem\t\r  properties,\t\r  from\t\r  half-­‐hourly\t\r  carbon\t\r  and\t\r  water\t\r  exchange,\t\r   through\t\r  daily\t\r  growth\t\r  and\t\r  tissue\t\r  turnover,\t\r   to\t\r   longer-­‐term\t\r  processes\t\r  of\t\r  reproduction,\t\r  competition,\t\r  and\t\r  mortality\t\r  (e.g.,\t\r  Fisher\t\r  et\t\r  al.,\t\r  2010).\t\r  Sitch\t\r  et\t\r  al.\t\r   (2008)\t\r  evaluated\t\r   five\t\r   DGVMs,\t\r   forced\t\r   with\t\r   observed\t\r   climatology\t\r   and\t\r   atmospheric\t\r   CO2.They\t\r   found\t\r   large\t\r  uncertainties\t\r   associated\t\r   with\t\r   the\t\r   response\t\r   of\t\r   boreal\t\r   ecosystems\t\r   to\t\r   elevated\t\r   temperatures\t\r   and\t\r  changing\t\r   soil\t\r   moisture\t\r   status.\t\r   For\t\r   the\t\r   most\t\r   extreme\t\r   emission\t\r   scenario\t\r   tested,\t\r   cumulative\t\r   land\t\r  uptake\t\r  over\t\r  the\t\r  21st\t\r  century\t\r  differed\t\r  among\t\r  DGVMs\t\r  by\t\r  494\t\r  Pg\t\r  C,\t\r  an\t\r  uncertainty\t\r  equivalent\t\r  to\t\r  over\t\r  50\t\r  years\t\r  of\t\r  anthropogenic\t\r  emissions\t\r  at\t\r  current\t\r  levels.\t\r  Ongoing\t\r   assessments\t\r   of\t\r   ecosystem\t\r  models\t\r   include\t\r   the\t\r   NACP-­‐led\t\r   MsTMIP\t\r   (Multi-­‐scale\t\r   Synthesis\t\r  \u003c/p\u003e\n\u003cp /\u003e\n\u003c/div\u003e\n\u003cdiv class\u003d\"page\"\u003e\u003cp /\u003e\n\u003cp\u003e\t\r  \u003c/p\u003e\n\u003cp\u003e\t\r   20\t\r  \n\u003c/p\u003e\n\u003cp\u003eand\t\r  Terrestrial\t\r  Model\t\r  Intercomparison\t\r  Project).\t\r  \t\r  Their\t\r  early\t\r  evaluations\t\r  show\t\r  that\t\r  there\t\r  is\t\r  a\t\r  lot\t\r  of\t\r  room\t\r  for\t\r  model\t\r  improvement.\t\r  \t\r  For\t\r  example,\t\r  Schaefer\t\r  et\t\r  al.\t\r  (2012)\t\r  showed\t\r  that\t\r  the\t\r  models\t\r  do\t\r  not\t\r  simulate\t\r  gross\t\r  primary\t\r  productivity\t\r  (GPP)\t\r  very\t\r  well,\t\r  with\t\r  none\t\r  of\t\r  the\t\r  models\t\r  included\t\r  in\t\r  the\t\r  study\t\r  matching\t\r  estimated\t\r  GPP\t\r  within\t\r  observational\t\r  uncertainty.\t\r  They\t\r  suggest\t\r  that\t\r  improving simulated \nGPP requires better leaf-to-canopy scaling and better values of model parameters that control \nthe maximum potential GPP (such as light use efficiency).\t\r  Richardson\t\r  et\t\r   al.\t\r   (2010,\t\r  2012)\t\r   reveal\t\r  several\t\r  other\t\r  deficiencies.\t\r  The\t\r  models\t\r  differ\t\r  in\t\r  the\t\r  calculated\t\r  magnitude\t\r  of\t\r  peak\t\r  fluxes,\t\r  phenology\t\r  (timing)\t\r   of\t\r   seasonal\t\r   changes,\t\r   and\t\r   high-­‐frequency\t\r   sensitivity\t\r   to\t\r   drivers\t\r   (Figure\t\r   11).\t\r   They\t\r   do\t\r   not\t\r  represent\t\r   interannual\t\r   variability\t\r   in\t\r   the\t\r   start/end\t\r   of\t\r   the\t\r   growing\t\r   season\t\r   and\t\r   show\t\r   large\t\r   model\t\r  biases\t\r   for\t\r  GPP\t\r  during\t\r  phenological\t\r   transition\t\r  periods.\t\r   \t\r  Multi-­‐year,\t\r  spatially\t\r  extensive\t\r  observations\t\r  \nare\t\r  needed\t\r  to\t\r  help\t\r  develop\t\r  better\t\r  phenological\t\r  models. \n\u003c/p\u003e\n\u003cp\u003e\t\r  \t\r  \t\r  \t\r  \t\r  \t\r  \t\r  \t\r  \t\r  \t\r  \t\r  \t\r  \t\r  \t\r  \t\r  \t\r  \t\r  \t\r  \t\r  \t\r  \t\r   \t\r  Invasion\t\r  of\t\r  shrubs\t\r  into\t\r  tussock\t\r  tundra\t\r  areas\t\r  is\t\r  widespread\t\r  in\t\r  northern\t\r  Alaska.\t\r  Tree\t\r  line\t\r  expansion\t\r  is\t\r  documented\t\r   for\t\r  northwestern\t\r  Alaska,\t\r  and\t\r   is\t\r  often\t\r  associated\t\r  with\t\r  permafrost\t\r  degradation\t\r  and\t\r  soil\t\r   drainage.\t\r   Expansion\t\r   of\t\r   forests\t\r   into\t\r   tundra\t\r   will\t\r   lead\t\r   to\t\r   significant\t\r   heating\t\r   of\t\r   the\t\r   lower\t\r  atmosphere\t\r  through\t\r  a\t\r  reduction\t\r  of\t\r  albedo,\t\r  especially\t\r  in\t\r  winter\t\r  (e.g.,\t\r  Betts\t\r  and\t\r  Ball,\t\r  1997;\t\r  Chapin\t\r  et\t\r  al.,\t\r  2000).\t\r   Jin\t\r  et\t\r  al.\t\r   (2012)\t\r  also\t\r  highlight\t\r  the\t\r   importance\t\r  of\t\r  vegetation\t\r  succession\t\r  and\t\r  snow\t\r  cover\t\r  duration\t\r   in\t\r   modulating\t\r   the\t\r   latitudinal\t\r   patterns\t\r   of\t\r   annual\t\r   albedo\t\r   change\t\r   and\t\r   surface\t\r   shortwave\t\r  forcing\t\r   averaged\t\r   over\t\r   the\t\r   decades\t\r   following\t\r   fire.\t\r   Neilson\t\r   et\t\r   al.\t\r   (2005)\t\r   discuss\t\r   many\t\r   of\t\r   the\t\r  challenges\t\r  associated\t\r  with\t\r   including\t\r  migration\t\r   in\t\r  DGVMs,\t\r  particularly\t\r   the\t\r   importance\t\r  of\t\r  sub-­‐grid\t\r  processes,\t\r  and\t\r  the\t\r  limitations\t\r  introduced\t\r  by\t\r  the\t\r  use\t\r  of\t\r  plant\t\r  functional\t\r  types.\t\r  \t\r  Perhaps\t\r  the\t\r  biggest\t\r  challenge\t\r  is\t\r  the\t\r  lack\t\r  of\t\r  useful\t\r  data\t\r  on\t\r  which\t\r  to\t\r  build\t\r  mechanistic\t\r  and\t\r  empirical\t\r  models.\t\r  \t\r  \nTo\t\r  understand\t\r  ABZ\t\r  ecosystem\t\r  transient\t\r   responses,\t\r   including\t\r  boundary\t\r   shifts,\t\r  a\t\r  better\t\r  description\t\r  of\t\r  \nthe\t\r  treeline\t\r  which\t\r  incorporates\t\r  gradients\t\r  of\t\r  tree\t\r  canopy\t\r  density\t\r  rather\t\r  than\t\r  discrete\t\r  class\t\r  boundaries,\t\r  \nis\t\r  needed\t\r  for\t\r  a\t\r  more\t\r  realistic\t\r  model\t\r  representation\t\r  of\t\r  the\t\r  biophysical\t\r  characteristics\t\r  of\t\r  the\t\r  transition\t\r  \nbetween\t\r  Arctic\t\r  tundra\t\r  and\t\r  the\t\r  boreal\t\r  biomes\t\r  and\t\r  associated\t\r  changes\t\r  in\t\r  albedo\t\r  and\t\r  radiative\t\r  forcings.\t\r  \nDGVMs\t\r  may\t\r  also\t\r  need\t\r  improved\t\r  treatment\t\r  of\t\r  plant\t\r  diversity\t\r  and\t\r  mechanistic\t\r  treatment\t\r  of\t\r  migration\t\r  \nand\t\r  competition\t\r  among\t\r  these\t\r  plants.\t\r  \n2.6 Integrated\t\r  Systems,\t\r  Carbon\t\r  Cycle,\t\r  and\t\r  Scaling\t\r  Methodologies\t\r  The\t\r   carbon\t\r   cycle\t\r   in\t\r   the\t\r   ABZ\t\r   has\t\r   the\t\r   potential\t\r   to\t\r   influence\t\r   the\t\r   climate\t\r   system\t\r   through\t\r   feedback\t\r  pathways\t\r   involving\t\r   responses\t\r   in\t\r   both\t\r   terrestrial\t\r   and\t\r   marine\t\r   systems.\t\r   Observational\t\r   and\t\r   model\t\r  component\t\r   enhancements\t\r   proposed\t\r   below\t\r   will\t\r   lead\t\r   to\t\r   increased\t\r   understanding\t\r   of\t\r   small-­‐scale\t\r  carbon\t\r   flux\t\r   processes\t\r   and\t\r   improve\t\r   the\t\r   ability\t\r   of\t\r   ESMs\t\r   to\t\r   integrate,\t\r   simulate\t\r   and\t\r   predict\t\r   such\t\r  processes.\t\r  \n\u003c/p\u003e\n\u003cp\u003eFigure\t\r  11:\t\r  The\t\r  10-­‐day\t\r  GPP\t\r  (g\t\r  C\t\r  m-­‐2\t\r  day-­‐1)\t\r  for\t\r  deciduous\t\r  broadleaf\t\r  forest\t\r  at\t\r  the\t\r  Old\t\r  Aspen\t\r  Site\t\r  in\t\r  Canada\t\r  from\t\r  14\t\r  ecosystem\t\r  models\t\r  participating\t\r  in\t\r  MsTMIP.\t\r  [From\t\r  \nRichardson\t\r  et\t\r  al.,\t\r  2010]\t\r  \t\r  \u003c/p\u003e\n\u003cp /\u003e\n\u003c/div\u003e\n\u003cdiv class\u003d\"page\"\u003e\u003cp /\u003e\n\u003cp\u003e\t\r  \u003c/p\u003e\n\u003cp\u003e\t\r   21\t\r  \n\u003c/p\u003e\n\u003cp\u003e2.6.1 Land\t\r  surface\t\r  hydrology\t\r  and\t\r  carbon\t\r  cycle\t\r  Processes\t\r  in\t\r  the\t\r  terrestrial\t\r  ABZ\t\r  that\t\r  are\t\r  sensitive\t\r  to\t\r  change\t\r  on\t\r  a\t\r  10-­‐\t\r  to\t\r  20-­‐year\t\r  timeframe\t\r  are\t\r  those\t\r  that\t\r   are\t\r   primarily\t\r   sensitive\t\r   to\t\r   changes\t\r   in\t\r   atmospheric\t\r   variables\t\r   (e.g.,\t\r   temperature,\t\r   precipitation,\t\r  CO2\t\r  concentration)\t\r  and\t\r  include\t\r  surface\t\r  hydrology,\t\r  photosynthesis\t\r  and\t\r  fire.\t\r  The\t\r  net\t\r  direction\t\r  of\t\r  the\t\r  photosynthesis\t\r   and\t\r   fire\t\r   feedbacks\t\r   depends\t\r   substantially\t\r   on\t\r   landscape\t\r  wetness\t\r   and\t\r   dryness.\t\r   For\t\r  example,\t\r  photosynthesis\t\r  may\t\r  be\t\r  decreased\t\r  more\t\r  by\t\r  dry\t\r  conditions\t\r   than\t\r   it\t\r  will\t\r  be\t\r  promoted\t\r  by\t\r  a\t\r  longer\t\r  growing\t\r  season.\t\r  Also,\t\r  dry\t\r  conditions\t\r  may\t\r  result\t\r  in\t\r  the\t\r  release\t\r  of\t\r  substantial\t\r  carbon\t\r  through\t\r  fire.\t\r  Riverine\t\r  chemistry\t\r  is\t\r  impacted\t\r  by\t\r  permafrost\t\r  thaw\t\r  due\t\r  to\t\r  large-­‐scale\t\r  fire\t\r  disturbance.\t\r  On\t\r  the\t\r  50-­‐to-­‐100-­‐year\t\r   timeframe,\t\r   processes\t\r   responding\t\r   slowly\t\r   to\t\r   climate\t\r   include\t\r   slow\t\r   ecological\t\r  processes\t\r   (e.g.,\t\r   increase\t\r   in\t\r   shrub\t\r   tundra,\t\r   changes\t\r   in\t\r   tree\t\r   species,\t\r   treeline\t\r   advance,\t\r   and\t\r   forest\t\r  degradation)\t\r   and\t\r   decomposition\t\r   responses\t\r   associated\t\r   with\t\r   the\t\r   thawing\t\r   of\t\r   permafrost.\t\r   Once\t\r  permafrost\t\r   thaws,\t\r   the\t\r  direction\t\r  of\t\r   feedbacks\t\r   to\t\r   the\t\r  climate\t\r  system\t\r  depends\t\r   largely\t\r  on\t\r   landscape\t\r  wetness\t\r  and\t\r  dryness.\t\r  To\t\r  facilitate\t\r  ESM\t\r  evaluation\t\r  and\t\r  improvements,\t\r  improved\t\r  characterization\t\r  and\t\r  \nreduced\t\r  uncertainty\t\r  in\t\r  ABZ\t\r  physical\t\r  (e.g.,\t\r  permafrost\t\r  distribution)\t\r  and\t\r  biogeochemical\t\r  (e.g.,\t\r  carbon\t\r  in\t\r  \npeatlands)\t\r  properties\t\r  are\t\r  needed.\t\r  In-­‐situ\t\r  measurements\t\r  of\t\r  riverine\t\r  chemistry\t\r  could\t\r  contribute\t\r  to\t\r  BGC\t\r  \nmodel\t\r  validation.\t\r  \n\u003c/p\u003e\n\u003cp\u003eSeveral\t\r   model\t\r   developments\t\r   are\t\r   needed\t\r   to\t\r   improve\t\r   representation\t\r   of\t\r   the\t\r   impact\t\r   of\t\r   land\t\r   surface\t\r  \nhydrology\t\r  on\t\r  the\t\r  carbon\t\r  cycle.\t\r   \t\r  For\t\r  example,\t\r  sub-­‐surface\t\r  leaching\t\r  and\t\r  surface\t\r  mobilization\t\r  of\t\r  C,\t\r  N,\t\r  sediments,\t\r  P,\t\r  etc.,\t\r   should\t\r  be\t\r  represented\t\r   in\t\r  ESMs.\t\r  This\t\r  requires\t\r  representation\t\r  of\t\r  complex\t\r  Arctic\t\r  soil\t\r  mineral\t\r  and\t\r  organic\t\r  properties,\t\r  explicit\t\r  representation\t\r  of\t\r  linked\t\r  nutrient-­‐carbon-­‐water\t\r  cycles,\t\r  and\t\r  improving\t\r  simulations\t\r  of\t\r  surface\t\r  and\t\r  sub-­‐surface\t\r  properties,\t\r  among\t\r  other\t\r  things.\t\r  The\t\r  physical\t\r  properties\t\r   of\t\r   lakes\t\r   and\t\r   wetlands,\t\r   especially\t\r   their\t\r   thermal\t\r   structure,\t\r   can\t\r   also\t\r   have\t\r   important\t\r  implications\t\r   for\t\r   biogeochemical\t\r   fluxes.\t\r   \t\r   For\t\r   instance,\t\r   there\t\r   is\t\r   some\t\r   evidence\t\r   that\t\r   lakes\t\r   are\t\r  responsible\t\r  for\t\r  much\t\r  of\t\r  the\t\r  flux\t\r  of\t\r  methane\t\r  from\t\r  western\t\r  Siberia\t\r  (Walter\t\r  et\t\r  al.,\t\r  2006).\t\r  Sub-­‐models\t\r  of\t\r   chemical\t\r   processes\t\r   (e.g.,\t\r   CH4)\t\r   need\t\r   to\t\r   be\t\r   linked\t\r   to\t\r   prognostic\t\r   hydrological\t\r   properties\t\r   (e.g.\t\r   T,\t\r  depth,\t\r   O2).\t\r   \t\r  Observations\t\r   are\t\r   needed\t\r   to\t\r   test\t\r   the\t\r   ability\t\r   of\t\r   the\t\r   simple\t\r   approaches\t\r   used\t\r   to\t\r   represent\t\r  \nlakes\t\r  and\t\r  wetlands\t\r  in\t\r  ESMs\t\r  to\t\r  capture\t\r  the\t\r  fluxes\t\r  of\t\r  greenhouse\t\r  gases\t\r  accurately.\t\r  \t\r  One\t\r   of\t\r   the\t\r   significant\t\r   uncertainties\t\r   in\t\r   ESMs\t\r   is\t\r   how\t\r   future\t\r   changes\t\r   to\t\r   peatland\t\r   hydrology\t\r   will\t\r  impact\t\r  these\t\r   large\t\r  carbon\t\r  reservoirs\t\r  (e.g.,\t\r  Wania\t\r  et\t\r  al.,\t\r  2009).\t\r  The\t\r  accumulation\t\r  of\t\r  peat,\t\r  which\t\r   is\t\r  partially\t\r  decomposed\t\r  organic\t\r  matter,\t\r   depends\t\r  on\t\r  water\t\r   table\t\r  position,\t\r   soil\t\r   temperature,\t\r   and\t\r  net\t\r  primary\t\r   production,\t\r   with\t\r   water\t\r   table\t\r   position\t\r   being\t\r   most\t\r   important\t\r   (Rouse\t\r   et\t\r   al.,\t\r   1997).\t\r  Permafrost\t\r   presence\t\r   in\t\r   peatlands\t\r   strongly\t\r   affects\t\r   vegetation\t\r   structure\t\r   and\t\r   soil\t\r   drainage\t\r  characteristics,\t\r  and\t\r  thus\t\r  SOC\t\r  accumulation\t\r  rates\t\r  (Robinson\t\r  and\t\r  Moore,\t\r  2000).\t\r  Whether\t\r  permafrost\t\r  thaw\t\r   in\t\r   peatlands\t\r   leads\t\r   to\t\r   a\t\r   positive\t\r   or\t\r   negative\t\r   feedback\t\r   to\t\r   atmospheric\t\r   greenhouse\t\r   gas\t\r  concentrations\t\r  will\t\r  depend\t\r  on\t\r  spatial\t\r  and\t\r  temporal\t\r  variation\t\r  in\t\r  water\t\r  table\t\r  position\t\r  as\t\r  well\t\r  as\t\r  soil\t\r  temperature,\t\r  which\t\r  both\t\r  serve\t\r  as\t\r  important\t\r  controls\t\r  on\t\r  methane\t\r  release\t\r  in\t\r  peatlands\t\r  (Grosse\t\r  et\t\r  al.,\t\r  2011).\t\r   Peatlands\t\r   in\t\r   some\t\r   situations\t\r   may\t\r   be\t\r   resistant\t\r   to\t\r   drought\t\r   due\t\r   to\t\r   the\t\r   high\t\r   water\t\r   holding\t\r  capacity\t\r  of\t\r   some\t\r  moss\t\r  species.\t\r  Hence\t\r   it\t\r  is\t\r  important\t\r  for\t\r  ESMs\t\r  to\t\r  have\t\r  explicitly\t\r  modeled\t\r  peatlands\t\r  \nand\t\r  peatland\t\r  hydrology\t\r  along\t\r  with\t\r  soil\t\r  freezing\t\r  and\t\r  thawing\t\r  and\t\r  permafrost\t\r  dynamics.\t\r  Thermokarst\t\r  \nand\t\r   other\t\r   disturbances\t\r   like\t\r   fire\t\r   and\t\r   cryoturbation\t\r   should\t\r   be\t\r   integrated\t\r   into\t\r   permafrost\t\r  models\t\r   to\t\r  \nbetter\t\r  quantify\t\r  and\t\r  predict\t\r  the\t\r  impact\t\r  of\t\r  disturbances\t\r  on\t\r  high\t\r  latitude\t\r  SOC\t\r  pools\t\r  (Grosse\t\r  et\t\r  al.,\t\r  2011).\t\r  \n2.6.2 Marine\t\r  processes,\t\r  land-­‐ocean\t\r  exchanges\t\r  and\t\r  carbon\t\r  cycle\t\r  For\t\r  marine\t\r  systems,\t\r  processes\t\r  sensitive\t\r  to\t\r  changes\t\r  in\t\r  surface\t\r  conditions\t\r  like\t\r  sea\t\r  ice\t\r  cover\t\r  and\t\r  near\t\r  surface\t\r   water\t\r   temperature\t\r   could\t\r   have\t\r   substantial\t\r   responses\t\r   on\t\r   the\t\r   10-­‐to-­‐20-­‐year\t\r   timeframe.\t\r  \t\r  Decreasing\t\r   sea\t\r   ice\t\r   cover\t\r   could\t\r   increase\t\r   CO2\t\r  sequestration\t\r   by\t\r   increasing\t\r   the\t\r   physical\t\r   transfer\t\r   of\t\r  dissolved\t\r  inorganic\t\r  Carbon\t\r  (DIC)\t\r  to\t\r  the\t\r  surface\t\r  layer\t\r  and\t\r  the\t\r  biological\t\r  uptake\t\r  of\t\r  CO2\t\r  in\t\r  the\t\r  surface\t\r  \u003c/p\u003e\n\u003cp /\u003e\n\u003c/div\u003e\n\u003cdiv class\u003d\"page\"\u003e\u003cp /\u003e\n\u003cp\u003e\t\r  \u003c/p\u003e\n\u003cp\u003e\t\r   22\t\r  \n\u003c/p\u003e\n\u003cp\u003elayer\t\r  through\t\r  more\t\r  light\t\r  and\t\r  nutrients.\t\r  It\t\r  could\t\r  also\t\r  decrease\t\r  CO2\t\r  uptake\t\r  through\t\r  the\t\r  creation\t\r  of\t\r  a\t\r  stable\t\r  photic\t\r  zone.\t\r  In\t\r  contrast,\t\r   increases\t\r  in\t\r  water\t\r  temperature\t\r  also\t\r  have\t\r  the\t\r  potential\t\r  to\t\r  enhance\t\r  the\t\r  release\t\r  of\t\r  CO2\t\r  and\t\r  CH4\t\r  through\t\r  enhanced\t\r  decomposition\t\r  and\t\r  methanogenesis\t\r  of\t\r  organic\t\r  carbon\t\r  in\t\r  the\t\r  water\t\r  column.\t\r  It\t\r  is\t\r  estimated\t\r  that\t\r  one-­‐half\t\r  to\t\r  two-­‐thirds\t\r  of\t\r  the\t\r  total\t\r  freshwater\t\r  flux\t\r  to\t\r  the\t\r  Arctic\t\r  Ocean\t\r  originates\t\r  as\t\r  river\t\r  runoff.\t\r  However,\t\r  there\t\r  are\t\r  major\t\r  uncertainties\t\r  in\t\r  riverine\t\r  fluxes\t\r  because\t\r  important\t\r  areas\t\r  of\t\r   the\t\r   Arctic\t\r   basin\t\r   are\t\r   essentially\t\r   without\t\r   gauges.\t\r  Measurement\t\r   of\t\r   riverine\t\r   fluxes\t\r   is\t\r   important\t\r   to\t\r  \nevaluate\t\r  the\t\r  model\t\r  estimates\t\r  of\t\r  land-­‐ocean\t\r  BGC\t\r  fluxes.\t\r  \t\r  The\t\r  Arctic\t\r   land-­‐ocean\t\r   interface\t\r   is\t\r   in\t\r  a\t\r  very\t\r  dynamic\t\r   transition.\t\r  Receding\t\r  sea\t\r   ice\t\r  has\t\r  changed\t\r   the\t\r  seasonal\t\r   climatology\t\r   of\t\r   the\t\r   coastal\t\r   zone\t\r   with\t\r   significant\t\r   consequences\t\r   for\t\r   both\t\r   land\t\r   and\t\r   ocean\t\r  ecosystems.\t\r   Ice-­‐free\t\r   conditions\t\r   have\t\r   resulted\t\r   in\t\r   the\t\r   generation\t\r   of\t\r   extreme\t\r   coastal\t\r   erosion\t\r   (e.g.,\t\r  Overeem\t\r   et\t\r   al.,\t\r   2011),\t\r   acceleration\t\r   of\t\r   permafrost\t\r   thaw,\t\r   and\t\r   other\t\r   changes\t\r   in\t\r   coastal\t\r   maritime\t\r  environments\t\r  and\t\r  upland\t\r  hydrologic\t\r  changes\t\r  in\t\r  the\t\r  major\t\r  deltaic\t\r  ecosystems\t\r  (e.g.,\t\r  Mackenzie\t\r  and\t\r  Yukon-­‐Kuskokwim\t\r  deltas).\t\r  With\t\r  an\t\r  anticipated\t\r  trend\t\r  toward\t\r  stronger\t\r  extreme\t\r  Arctic\t\r  cyclones,\t\r  the\t\r  associated\t\r  greater\t\r  wave\t\r  activity\t\r  would\t\r  promote\t\r  even\t\r  further\t\r  coastal\t\r  erosion\t\r  (Vavrus\t\r  et\t\r  al.,\t\r  2012).\t\r  \t\r  Key\t\r   questions\t\r   related\t\r   to\t\r   the\t\r   carbon\t\r   cycle\t\r   associated\t\r   with\t\r   marine\t\r   processes\t\r   and\t\r   land-­‐ocean\t\r  exchanges\t\r   include:\t\r   How\t\r   are\t\r   land-­‐to-­‐ocean\t\r   fluxes\t\r   of\t\r   water,\t\r   heat,\t\r   carbon,\t\r   nutrient,\t\r   and\t\r   sediment\t\r  fluxes\t\r  through\t\r  both\t\r  riverine\t\r  transport\t\r  and\t\r  coastal\t\r  erosion\t\r  changing?\t\r  How\t\r  will\t\r  ocean\t\r  trophic\t\r  levels\t\r  respond\t\r  to\t\r  reduced\t\r  ice\t\r  cover,\t\r  and,\t\r  coupled\t\r  with\t\r  changes\t\r  in\t\r  nutrient\t\r  runoff\t\r  from\t\r  the\t\r  land,\t\r  influence\t\r  the\t\r  Arctic\t\r  Ocean\t\r  carbon\t\r  budget?\t\r  Addressing\t\r  these\t\r  questions\t\r  requires\t\r  both\t\r  observations\t\r  and\t\r  model\t\r  developments\t\r  to\t\r  improve\t\r  representation\t\r  of\t\r  ocean\t\r  and\t\r  sea-­‐ice\t\r  processes\t\r  and\t\r  the\t\r  links\t\r  between\t\r  land\t\r  surface\t\r   processes\t\r   and\t\r   the\t\r   coastal\t\r   ocean.\t\r   As\t\r   mentioned\t\r   in\t\r   sections\t\r   2.2\t\r   and\t\r   2.3,\t\r  models\t\r   need\t\r   to\t\r  \nrepresent\t\r   sea-­‐ice\t\r   distributions\t\r   better\t\r   and\t\r   include\t\r   more\t\r   complete\t\r   treatments\t\r   of\t\r   ocean\t\r   ecosystems,\t\r  \nmicronutrient\t\r   limitation,\t\r  and\t\r  ocean\t\r  acidification\t\r   impacts\t\r  on\t\r   the\t\r   calcium\t\r  carbonate\t\r   cycle\t\r  as\t\r  well\t\r   as\t\r  \nimprovements\t\r  to\t\r  sea-­‐ice\t\r  biology.\t\r  \n2.6.3 Trace\t\r  gas\t\r  concentrations\t\r  and\t\r  fluxes\t\r  Comprehensive\t\r  atmospheric\t\r  measurements\t\r  of\t\r  CO2\t\r  and\t\r  CH4\t\r  are\t\r  needed\t\r  to\t\r  assess\t\r  ABZ\t\r  carbon\t\r  fluxes\t\r  and\t\r   their\t\r   representation\t\r   in\t\r   models.\t\r   The\t\r   current\t\r   observing\t\r   network\t\r   leaves\t\r   major\t\r   gaps\t\r   in\t\r  understanding\t\r  CO2\t\r  and\t\r  CH4\t\r  distributions\t\r  and\t\r  flux\t\r  processes\t\r  in\t\r  the\t\r  ABZ.\t\r  Comparison\t\r  of\t\r  surface-­‐only\t\r  CO2\t\r  and\t\r  CH4\t\r  measurements\t\r  with\t\r  atmospheric\t\r  transport\t\r  models\t\r  is\t\r  particularly\t\r  susceptible\t\r  to\t\r  errors\t\r  in\t\r  vertical\t\r  mixing\t\r  and\t\r  boundary\t\r   layer\t\r  processes,\t\r  which\t\r  remain\t\r  a\t\r  challenge\t\r   for\t\r  ESMs.\t\r  Column\t\r  CO2\t\r  measurement\t\r   comparisons\t\r   are\t\r   less\t\r   affected\t\r   by\t\r   these\t\r   types\t\r   of\t\r   model\t\r   error\t\r   but\t\r   lack\t\r   a\t\r   long\t\r   data\t\r  record\t\r   and\t\r   are\t\r   challenged\t\r   in\t\r   various\t\r   ways.\t\r   Ground-­‐based\t\r   operational\t\r   networks\t\r   provide\t\r  information\t\r   over\t\r   Europe\t\r   and\t\r   Canada\t\r   but\t\r   coverage\t\r   is\t\r   sparse\t\r   and\t\r   no\t\r   ground-­‐based\t\r   observations\t\r  exist\t\r  over\t\r  Eurasia.\t\r  \t\r  Satellite\t\r  data\t\r  from\t\r  AIRS\t\r  and\t\r  GOSAT\t\r  provide\t\r  the\t\r  most\t\r  comprehensive\t\r  available\t\r  regional\t\r  view\t\r  of\t\r  CO2\t\r  and\t\r  CH4\t\r  but\t\r   these\t\r  data\t\r   remain\t\r   limited\t\r  by\t\r  several\t\r   factors.\t\r  AIRS\t\r  observations\t\r  primarily\t\r   reflect\t\r   the\t\r  middle\t\r   and\t\r   upper\t\r   troposphere,\t\r   making\t\r   connection\t\r   to\t\r   small-­‐scale\t\r   surface\t\r   source/sink\t\r   processes\t\r  difficult.\t\r  GOSAT\t\r  observations\t\r  (and\t\r  planned\t\r  OCO-­‐2\t\r  measurements)\t\r  provide\t\r  sparse\t\r  sampling\t\r  of\t\r  CO2\t\r  in\t\r  the\t\r  ABZ\t\r  only\t\r  over\t\r  land\t\r  during\t\r  summer\t\r  months.\t\r  Future\t\r  satellite\t\r  missions,\t\r  such\t\r  as\t\r  ASCENDS,\t\r  will\t\r  employ\t\r   active\t\r   remote\t\r   sensing\t\r   techniques,\t\r   providing\t\r   improved\t\r   ability\t\r   to\t\r   observe\t\r   CO2\t\r   in\t\r   the\t\r  ABZ.\t\r  Because\t\r  of\t\r  the\t\r  limited\t\r  lifetimes\t\r  of\t\r  such\t\r  missions,\t\r  these\t\r  types\t\r  of\t\r  observations\t\r  will\t\r  be\t\r  most\t\r  useful\t\r  in\t\r  characterizing\t\r  variability\t\r  in\t\r  fluxes\t\r  on\t\r  seasonal\t\r  to\t\r  interannual\t\r  scales.\t\r  \nOverarching\t\r   measurement\t\r   needs\t\r   for\t\r   improved\t\r   characterization\t\r   of\t\r   ABZ\t\r   CO2\t\r   and\t\r   CH4\t\r   fluxes\t\r   are\t\r   (i)\t\r  \u003c/p\u003e\n\u003cp /\u003e\n\u003c/div\u003e\n\u003cdiv class\u003d\"page\"\u003e\u003cp /\u003e\n\u003cp\u003e\t\r  \u003c/p\u003e\n\u003cp\u003e\t\r   23\t\r  \n\u003c/p\u003e\n\u003cp\u003eimprovements\t\r   in\t\r   trace\t\r  gas\t\r  concentration\t\r  and\t\r   flux\t\r  measurements\t\r   through\t\r  a\t\r  combination\t\r  of\t\r  ground-­‐\nbased,\t\r   aircraft,\t\r   and\t\r   satellite\t\r   observations,\t\r   and\t\r   (ii)\t\r   improvements\t\r   in\t\r   understanding\t\r   local\t\r   scale\t\r  \nprocesses.\t\r  An\t\r  expansion\t\r  of\t\r  existing\t\r  ground-­‐based\t\r  networks\t\r  is\t\r  necessary\t\r  to\t\r  characterize\t\r  changes\t\r  in\t\r  the\t\r  \nregional\t\r   carbon\t\r   budget\t\r   on\t\r   longer\t\r   timescales.\t\r   Aircraft\t\r   field\t\r   campaigns\t\r   are\t\r   essential\t\r   for\t\r   validating\t\r  \nsatellite\t\r  observations\t\r  and\t\r  providing\t\r  the\t\r   link\t\r  between\t\r  surface\t\r  site\t\r  observations\t\r  and\t\r  inverse\t\r  modeling\t\r  \nretrievals.\t\r   Necessary\t\r   model\t\r   improvements\t\r   include\t\r   improved\t\r   surface\t\r   boundary\t\r   layers,\t\r   better\t\r  \ncharacterization\t\r  of\t\r  model\t\r  transport\t\r  error\t\r  in\t\r  the\t\r  ABZ\t\r  and\t\r  development\t\r  and\t\r  evaluation\t\r  of\t\r  improved\t\r  up-­‐\t\r  \nand\t\r  downscaling\t\r  techniques\t\r  appropriate\t\r  for\t\r  the\t\r  region\t\r  (see\t\r  section\t\r  2.6.5).\t\r  \t\r  \t\r  \n2.6.4 Flux\t\r  estimation\t\r  and\t\r  evaluation:\t\r  inverse\t\r  modeling,\t\r  upscaling\t\r  and\t\r  downscaling\t\r  \nInverse\t\r  modeling\t\r   techniques\t\r   are\t\r  used\t\r   to\t\r   estimate\t\r   surface\t\r   fluxes\t\r  using\t\r   information\t\r   contained\t\r   in\t\r  trace\t\r  gas\t\r  observations.\t\r  The\t\r  majority\t\r  of\t\r   inversion\t\r  studies\t\r   to\t\r  date\t\r  have\t\r  used\t\r  CO2\t\r  data\t\r  collected\t\r  by\t\r  the\t\r   NOAA\t\r   ground-­‐based\t\r   network\t\r   and\t\r   estimated\t\r   fluxes\t\r   for\t\r   large\t\r   areas\t\r   (e.g.\t\r   boreal\t\r   Asia\t\r   or\t\r   North\t\r  America,\t\r  ~5\t\r  or\t\r  10°\t\r  latitude\t\r  ×\t\r  longitude\t\r  boxes).\t\r  The\t\r  multi-­‐phase\t\r  TRANSCOM\t\r  experiment\t\r  has\t\r  helped\t\r  to\t\r  quantify\t\r  uncertainty\t\r  in\t\r  CO2\t\r  inversion\t\r  methods\t\r  using\t\r  a\t\r  number\t\r  of\t\r  global\t\r  atmospheric\t\r  transport\t\r  models;\t\r   results\t\r   indicate\t\r   large\t\r   differences\t\r   in\t\r   boreal\t\r   summer\t\r   flux\t\r   estimates\t\r   among\t\r  models\t\r   due\t\r   to\t\r  differences\t\r   in\t\r   the\t\r   timing\t\r   of\t\r   vegetation\t\r   CO2\t\r   uptake.\t\r   \t\r   Considerable\t\r   uncertainty\t\r   remains\t\r   regarding\t\r  total\t\r  CO2\t\r  flux\t\r  from\t\r  the\t\r  ABZ\t\r  and\t\r  few\t\r  attempts\t\r  have\t\r  been\t\r  made\t\r  to\t\r  apply\t\r  inversion\t\r  techniques\t\r  to\t\r  sub-­‐regional\t\r  scales\t\r  in\t\r  this\t\r  area.\t\r  Efforts\t\r  to\t\r  use\t\r  GOSAT\t\r  CO2\t\r  observations\t\r  in\t\r  inversions\t\r  are\t\r  underway\t\r  by\t\r  a\t\r  number\t\r  of\t\r  groups.\t\r  Chevallier\t\r  et\t\r  al.\t\r   (2011)\t\r  used\t\r  ground-­‐based\t\r  remote\t\r  sensing\t\r  data\t\r   from\t\r  a\t\r  sparse\t\r  network\t\r  to\t\r  estimate\t\r  CO2\t\r  fluxes\t\r  globally,\t\r  but\t\r  were\t\r  not\t\r  able\t\r  to\t\r  reduce\t\r  flux\t\r  uncertainty\t\r  over\t\r  the\t\r  North\t\r  American\t\r  boreal\t\r  region\t\r  due\t\r  to\t\r  a\t\r  lack\t\r  of\t\r  data.\t\r  Results\t\r  for\t\r  CH4\t\r  are\t\r  less\t\r  advanced\t\r  than\t\r  those\t\r  for\t\r  CO2.\t\r  \t\r  In\t\r   recent\t\r   years,\t\r   considerable\t\r   effort\t\r  has\t\r   focused\t\r  on\t\r  estimating\t\r  CO2\t\r   fluxes\t\r  over\t\r   a\t\r  densely\t\r   sampled\t\r  region\t\r   (e.g.,\t\r   North\t\r   America)\t\r   on\t\r   finer\t\r   resolution\t\r   spatial\t\r   resolutions\t\r   (e.g.,\t\r   4-­‐12\t\r   km,\t\r   up\t\r   to\t\r   50\t\r   km)\t\r  using\t\r   regional\t\r   transport\t\r   models\t\r   (e.g.,\t\r   Göckede\t\r   et\t\r   al.,\t\r   2010;\t\r   Gourdji\t\r   et\t\r   al.\t\r   2010).\t\r   These\t\r   efforts\t\r  combine\t\r   regional\t\r   models\t\r   with\t\r   Lagrangian\t\r   particle\t\r   dispersion\t\r   models\t\r   to\t\r   diagnose\t\r   upstream\t\r  influence\t\r  on\t\r  atmospheric\t\r  measurement\t\r  locations.\t\r  Such\t\r  methods\t\r  provide\t\r  a\t\r  promising\t\r  path\t\r  forward\t\r  for\t\r   estimating\t\r   ABZ\t\r   fluxes\t\r   at\t\r   sub-­‐regional\t\r   scales\t\r   but\t\r   require\t\r   a\t\r   denser\t\r   observing\t\r   network\t\r   than\t\r  currently\t\r  exists.\t\r  In\t\r  addition,\t\r  inversions\t\r  at\t\r  both\t\r  regional\t\r  and\t\r  global\t\r  scales\t\r  are\t\r  still\t\r  challenged\t\r  by\t\r  the\t\r  difficulty\t\r   in\t\r   estimating\t\r   atmospheric\t\r   transport\t\r   model\t\r   error;\t\r   lack\t\r   of\t\r   accurate\t\r   transport\t\r   model\t\r  characterization\t\r   contributes\t\r   to\t\r   continuing\t\r   flux\t\r   uncertainty\t\r   and\t\r   can\t\r   cause\t\r   errors\t\r   in\t\r   source/sink\t\r  attribution\t\r  if\t\r  not\t\r  properly\t\r  quantified\t\r  in\t\r  the\t\r  inversion\t\r  framework.\t\r  Work\t\r  is\t\r  ongoing\t\r  to\t\r  develop\t\r  better\t\r  transport\t\r  model\t\r  error\t\r  estimates.\t\r  \nUpscaling\t\r  methods\t\r  extrapolate\t\r  knowledge\t\r  of\t\r  fluxes\t\r  gained\t\r  from\t\r  high-­‐resolution\t\r  process\t\r  models\t\r  or\t\r  direct\t\r  observations\t\r  over\t\r  limited\t\r  areas\t\r  (10\t\r  m\t\r  –\t\r  1\t\r  km)\t\r  to\t\r  larger\t\r  scales\t\r  (1\t\r  –\t\r  1000\t\r  km)\t\r  using\t\r  models\t\r  in\t\r  which\t\r   the\t\r   land\t\r  surface\t\r  or\t\r  ecosystem\t\r  properties\t\r  are\t\r  derived\t\r   from\t\r  remotely\t\r  sensed\t\r  data.\t\r  Airborne\t\r  eddy\t\r   correlation\t\r  measurements\t\r   (e.g.,\t\r   Desjardins\t\r   et\t\r   al.,\t\r   1997)\t\r   provide\t\r   a\t\r   very\t\r   powerful\t\r   means\t\r   of\t\r  bridging\t\r   the\t\r   scale\t\r   interval\t\r   between\t\r   flux\t\r   towers,\t\r   regional\t\r   surface/atmosphere\t\r   models,\t\r   and\t\r   the\t\r  retrievals\t\r  provided\t\r  by\t\r  ESM\t\r  inversions.\t\r  These\t\r  “bottom-­‐up”\t\r  spatially\t\r  coherent\t\r  flux\t\r  estimates\t\r  can\t\r  be\t\r  compared\t\r  with\t\r   the\t\r   fluxes\t\r   retrieved\t\r   from\t\r   ESM\t\r   inversions,\t\r  which\t\r  would\t\r   be\t\r   anchored\t\r   by\t\r   a\t\r   sparse\t\r  network\t\r  of\t\r  trace\t\r  gas\t\r  concentration\t\r  measurements.\t\r  \t\r  Techniques\t\r  are\t\r  being\t\r  developed\t\r  to\t\r  estimate\t\r  large-­‐scale\t\r  land\t\r  biosphere\t\r  CO2\t\r  fluxes\t\r  from\t\r  sparse\t\r  flux\t\r  tower\t\r   observations\t\r   but\t\r   the\t\r   results\t\r   remain\t\r   subject\t\r   to\t\r   large\t\r   uncertainties.\t\r   \t\r   While\t\r   regional-­‐scale\t\r  fluxes\t\r  appear\t\r  reasonable,\t\r  in\t\r  some\t\r  cases\t\r  these\t\r  techniques\t\r  lead\t\r  to\t\r  global\t\r  net\t\r  flux\t\r  estimates\t\r  that\t\r  are\t\r  inconsistent\t\r  with\t\r  atmospheric\t\r  CO2\t\r  concentration\t\r  observations.\t\r   In\t\r  order\t\r   to\t\r  apply\t\r  such\t\r   techniques\t\r  successfully\t\r   to\t\r   the\t\r   ABZ,\t\r   improvements\t\r   in\t\r   local\t\r   carbon\t\r   flux\t\r   estimates\t\r   are\t\r   needed\t\r   through\t\r  improvements\t\r  in\t\r  process\t\r  models,\t\r  increases\t\r  in\t\r  the\t\r  flux\t\r  tower\t\r  network\t\r  density\t\r  and/or\t\r  increased\t\r  use\t\r  \u003c/p\u003e\n\u003cp /\u003e\n\u003c/div\u003e\n\u003cdiv class\u003d\"page\"\u003e\u003cp /\u003e\n\u003cp\u003e\t\r  \u003c/p\u003e\n\u003cp\u003e\t\r   24\t\r  \n\u003c/p\u003e\n\u003cp\u003eof\t\r   airborne\t\r   eddy\t\r   correlation.\t\r   \t\r   Improved\t\r   characterization\t\r   of\t\r   spatial\t\r   heterogeneity\t\r   of\t\r   land\t\r   surface\t\r  and\t\r  ecosystem\t\r  properties\t\r   in\t\r  the\t\r  ABZ\t\r  is\t\r  also\t\r  needed\t\r  for\t\r  proper\t\r  extrapolation\t\r  to\t\r   larger\t\r  scales;\t\r   it\t\r   is\t\r  expected\t\r   that\t\r   planned\t\r   and\t\r   proposed\t\r   field\t\r   campaigns\t\r   and\t\r   analysis\t\r   of\t\r   relevant\t\r   remote\t\r   sensing\t\r  observations\t\r  can\t\r  contribute\t\r  significantly\t\r  to\t\r  this\t\r  goal.\t\r  \t\r  \t\r  \nForward\t\r   model\t\r   scaling\t\r   approach:\t\r   Spatial\t\r   heterogeneity\t\r   in\t\r   ABZ\t\r   landscapes\t\r   and\t\r   coupling\t\r   of\t\r  physical,\t\r   biological,\t\r   and\t\r   BGC\t\r   processes\t\r   at\t\r   multiple\t\r   spatial\t\r   scales\t\r   present\t\r   special\t\r   problems\t\r   for\t\r  climate-­‐scale\t\r   predictive\t\r   modeling.\t\r   The\t\r   lack\t\r   of\t\r   a\t\r   solid\t\r   theoretical\t\r   foundation\t\r   to\t\r   address\t\r   these\t\r  scaling\t\r  problems\t\r  is\t\r  one\t\r  reason\t\r  for\t\r  the\t\r  diversity\t\r  in\t\r  model\t\r  formulation\t\r  and\t\r  parameterization\t\r  and\t\r  the\t\r  resulting\t\r   scatter\t\r   in\t\r   large-­‐scale\t\r   predictions\t\r   of\t\r   permafrost\t\r   dynamics\t\r   for\t\r   the\t\r   21st\t\r   century.\t\r   One\t\r  approach\t\r  for\t\r  reducing\t\r  prediction\t\r  uncertainty\t\r  at\t\r  the\t\r  climate-­‐modeling\t\r  scale\t\r  is\t\r  to\t\r  construct,\t\r  initialize,\t\r  and\t\r  execute\t\r  fine-­‐scale\t\r  models\t\r  that\t\r  represent\t\r  Arctic\t\r  landscape\t\r  processes\t\r  explicitly,\t\r  and\t\r  to\t\r  use\t\r  these\t\r  process-­‐resolving\t\r   high-­‐resolution\t\r   models\t\r   as\t\r   a\t\r   basis\t\r   for\t\r   parameterizing\t\r   implicit\t\r   or\t\r   statistical\t\r  representations\t\r  of\t\r  important\t\r  processes\t\r  at\t\r  larger\t\r  spatial\t\r  scales.\t\r  This\t\r  concept\t\r  is\t\r  the\t\r  basis\t\r  for\t\r  NGEE.\t\r  \nDownscaling\t\r   techniques\t\r   translate\t\r   larger\t\r   scale\t\r   flux\t\r   estimates\t\r   produced\t\r   by\t\r   global\t\r   models\t\r   or\t\r  inversions\t\r  to\t\r  finer\t\r  spatial\t\r  scales,\t\r  using\t\r  information\t\r  about\t\r  surface\t\r  properties\t\r  or\t\r  statistics\t\r  about\t\r  high\t\r  resolution\t\r   variability\t\r   from\t\r  higher\t\r   resolution\t\r  models\t\r   or\t\r   dense\t\r   observations\t\r   (satellite\t\r   or\t\r   aircraft).\t\r  These\t\r   methods\t\r   are\t\r   essential\t\r   for\t\r   evaluation\t\r   of\t\r   coarse\t\r   resolution\t\r   flux\t\r   estimates\t\r   with\t\r   the\t\r   higher\t\r  resolution\t\r  estimates\t\r  described\t\r  above.\t\r  Such\t\r  methods\t\r  could\t\r  be\t\r  applied\t\r  to\t\r  existing\t\r  observations\t\r  and\t\r  models\t\r   to\t\r   estimate\t\r   small-­‐scale\t\r   variability\t\r   for\t\r   planning\t\r   future\t\r   field\t\r   campaigns\t\r   and\t\r  measurement\t\r  network\t\r  deployments.\t\r  Knowledge\t\r  of\t\r  realistic\t\r  regional\t\r  flux\t\r  estimates\t\r  and\t\r  variability\t\r  in\t\r  the\t\r  context\t\r  of\t\r  global\t\r   flux\t\r  estimates\t\r  could\t\r  require\t\r  a\t\r  hierarchical\t\r  model\t\r  approach\t\r  that\t\r   integrates\t\r  contributions\t\r  with\t\r  small-­‐scale\t\r  process\t\r  models\t\r  (~\t\r  1\t\r  km)\t\r  with\t\r  regional\t\r  (~10\t\r  km)\t\r  and\t\r  global\t\r  models\t\r  (~100\t\r  km).\t\r  \t\r  \t\r  \n3 Key\t\r  questions\t\r  to\t\r  be\t\r  addressed\t\r  The\t\r  critical\t\r  questions\t\r  that\t\r  should\t\r  guide\t\r  model\t\r  development\t\r  and\t\r  measurement\t\r  priorities\t\r  are\t\r  summarized\t\r  from\t\r  Section\t\r  2\t\r  as\t\r  follows:\t\r  1. Clouds,\t\r  radiation\t\r  and\t\r  aerosols:\t\r  Are\t\r  the\t\r  observed\t\r  seasonal\t\r  changes\t\r  of\t\r  Arctic\t\r  clouds\t\r  primarily\t\r  determined\t\r  by\t\r  the\t\r  large-­‐scale\t\r  circulation\t\r  or\t\r  do\t\r  microphysical\t\r  and\t\r  surface\t\r  processes\t\r  play\t\r  a\t\r  key\t\r  role?\t\r  What\t\r  is\t\r  the\t\r  role\t\r  of\t\r  downwelling\t\r  infrared\t\r  radiation\t\r  in\t\r  the\t\r  surface\t\r  energy\t\r  budget\t\r  of\t\r  the\t\r  Arctic\t\r  Ocean\t\r  in\t\r  winter?\t\r  How\t\r  does\t\r  aerosol\t\r  forcing\t\r  affect\t\r  the\t\r  Arctic\t\r  climate,\t\r  and\t\r  how\t\r  will\t\r  aerosol\t\r  loadings\t\r  change\t\r  as\t\r  a\t\r  result\t\r  of\t\r  changes\t\r  in\t\r  land-­‐use,\t\r  industrial\t\r  emission,\t\r  desertification,\t\r  and\t\r  fire?\t\r  \t\r  2. Ocean\t\r  circulation\t\r  and\t\r  sea\t\r  ice:\t\r  What\t\r  are\t\r  the\t\r  processes\t\r  involved\t\r  in\t\r  melting\t\r  the\t\r  sea\t\r  ice\t\r  and\t\r  controlling\t\r  ocean\t\r  stratification\t\r  in\t\r  the\t\r  Beaufort\t\r  Sea?\t\r  3. Integrated\t\r  systems,\t\r  land\t\r  surface\t\r  hydrology,\t\r  and\t\r  carbon\t\r  cycle:\t\r  What\t\r  are\t\r  the\t\r  linkages\t\r  between\t\r  land\t\r  surface\t\r  hydrology,\t\r  vegetation\t\r  changes\t\r  and\t\r  the\t\r  surface\t\r  energy\t\r  budget\t\r  over\t\r  the\t\r  ABZ\t\r  and\t\r  how\t\r  will\t\r  these\t\r  influence\t\r  the\t\r  evolving\t\r  climate?\t\r  How,\t\r  and\t\r  how\t\r  rapidly,\t\r  is\t\r  the\t\r  ocean-­‐land\t\r  interface\t\r  changing\t\r  in\t\r  the\t\r  ABZ?\t\r  \t\r  4. Carbon\t\r  balance:\t\r  How\t\r  rapidly,\t\r  in\t\r  which\t\r  direction,\t\r  and\t\r  by\t\r  how\t\r  much\t\r  will\t\r  warming\t\r  and\t\r  changing\t\r  precipitation\t\r  modify\t\r  the\t\r  ABZ\t\r  net\t\r  carbon\t\r  balance?\t\r  Will\t\r  the\t\r  impact\t\r  on\t\r  net\t\r  CO2\t\r  exchange\t\r  be\t\r  smaller\t\r  or\t\r  larger\t\r  than\t\r  the\t\r  impact\t\r  on\t\r  net\t\r  CH4\t\r  exchange?\t\r  \t\r  \t\r  \u003c/p\u003e\n\u003cp /\u003e\n\u003c/div\u003e\n\u003cdiv class\u003d\"page\"\u003e\u003cp /\u003e\n\u003cp\u003e\t\r  \u003c/p\u003e\n\u003cp\u003e\t\r   25\t\r  \n\u003c/p\u003e\n\u003cp\u003e4 Proposed\t\r  Field\t\r  Experiments\t\r  and\t\r  Studies\t\r  The\t\r  discussion\t\r  in\t\r  Sections\t\r  1\t\r  and\t\r  2\t\r  and\t\r  the\t\r  key\t\r  science\t\r  questions\t\r  of\t\r  Section\t\r  3\t\r  provided\t\r  the\t\r  basis\t\r  for\t\r  laying\t\r   out\t\r   a\t\r   set\t\r   of\t\r   recommended\t\r   field\t\r   experiment\t\r   activities.\t\r   Each\t\r   activity\t\r   is\t\r   designed\t\r   to\t\r   address\t\r  important\t\r   weaknesses\t\r   in\t\r   the\t\r   process\t\r   models\t\r   that\t\r   make\t\r   up\t\r   the\t\r   subcomponents\t\r   of\t\r   ESMs.\t\r   The\t\r  problem\t\r  of\t\r  scaling,\t\r   that\t\r   is,\t\r   the\t\r  development\t\r  and\t\r  validation\t\r  of\t\r  process\t\r  models\t\r  and\t\r  global\t\r  ESMs,\t\r   is\t\r  also\t\r  addressed.\t\r  \t\r  \n4.1 Field\t\r  campaigns\t\r  –\t\r  requirements\t\r  and\t\r  initial\t\r  ideas\t\r  for\t\r  new\t\r  activities\t\r  \n\u003c/p\u003e\n\u003cp\u003e4.1.1 \t\r  Clouds,\t\r  aerosols\t\r  and\t\r  radiation\t\r  (i) Cloud\t\r  ice\t\r  properties\t\r  and\t\r  the\t\r  radiation\t\r  budget:\t\r  Development\t\r  of\t\r  cloud\t\r  microphysics\t\r  parameterizations\t\r  to\t\r  model\t\r  mixed-­‐phase\t\r  and\t\r  ice\t\r  clouds\t\r  in\t\r  global\t\r  climate\t\r  models\t\r  is\t\r  a\t\r  priority.\t\r  Because\t\r  of\t\r  the\t\r  many\t\r  known\t\r  gaps\t\r  in\t\r  our\t\r  knowledge\t\r  of\t\r  cloud\t\r  processes,\t\r  comprehensive\t\r  field\t\r  experiment\t\r  case\t\r  studies\t\r  are\t\r  required\t\r  to\t\r  evaluate\t\r  simulation\t\r  fidelity.\t\r  Participation\t\r  in\t\r  and\t\r  extension\t\r  of\t\r  DOE\t\r  ARM\t\r  observations,\t\r  with\t\r  an\t\r  emphasis\t\r  on\t\r  getting\t\r  better\t\r  observations\t\r  of\t\r  CCN\t\r  and\t\r  cloud\t\r  ice\t\r  properties\t\r  and\t\r  their\t\r  effects\t\r  on\t\r  the\t\r  radiation\t\r  budget,\t\r  is\t\r  recommended.\t\r  \t\r   (ii) Aerosols:\t\r  A\t\r  field\t\r  campaign\t\r  targeting\t\r  aerosol\t\r  wet\t\r  removal\t\r  by\t\r  super-­‐cooled\t\r  liquid,\t\r  mixed-­‐phase\t\r  and\t\r  ice\t\r  clouds,\t\r  along\t\r  with\t\r  observations\t\r  from\t\r  CloudSat,\t\r  CALIPSO,\t\r  MODIS,\t\r  and\t\r  MISR,\t\r  is\t\r  recommended\t\r  to\t\r  increase\t\r  scientific\t\r  understanding\t\r  of\t\r  aerosol\t\r  transport\t\r  to\t\r  the\t\r  Arctic\t\r  from\t\r  lower\t\r  latitudes\t\r  and\t\r  deposition\t\r  onto\t\r  snow\t\r  and\t\r  ice\t\r  within\t\r  the\t\r  Arctic,\t\r  and\t\r  to\t\r  improve\t\r  the\t\r  representation\t\r  of\t\r  these\t\r  processes\t\r  in\t\r  global\t\r  models.\t\r  \t\r  \t\r  Previous\t\r  field\t\r  campaigns\t\r  in\t\r  the\t\r  Arctic\t\r  have\t\r  focused\t\r  on\t\r  the\t\r  North\t\r  American\t\r  and\t\r  European\t\r  sectors.\t\r  Whereas\t\r  there\t\r  is\t\r  value\t\r  in\t\r  additional\t\r  campaigns\t\r  in\t\r  those\t\r  regions,\t\r  an\t\r  aircraft-­‐\t\r  and\t\r  ground-­‐based\t\r  field\t\r  campaign\t\r  from\t\r  bases\t\r  in\t\r  Siberia\t\r  would\t\r  be\t\r  of\t\r  considerable\t\r  value\t\r  for\t\r  better\t\r  understanding\t\r  aerosol-­‐climate\t\r  interactions\t\r  and\t\r  biogeochemical\t\r  processes\t\r  of\t\r  critical\t\r  relevance\t\r  for\t\r  the\t\r  Arctic.\t\r  However,\t\r  since\t\r  field\t\r  observations\t\r  in\t\r  the\t\r  Russian\t\r  Arctic\t\r  will\t\r  likely\t\r  remain\t\r  limited\t\r  in\t\r  the\t\r  future\t\r  because\t\r  of\t\r  the\t\r  difficulty\t\r  of\t\r  access,\t\r  satellite\t\r  observations\t\r  will\t\r  play\t\r  a\t\r  crucial\t\r  role\t\r  for\t\r  monitoring\t\r  the\t\r  future\t\r  evolution\t\r  of\t\r  this\t\r  critical\t\r  region.\t\r  Opportunities\t\r  for\t\r  participating\t\r  in\t\r  field\t\r  campaigns\t\r  there\t\r  should\t\r  nevertheless\t\r  be\t\r  explored.\t\r  \n4.1.2 Ocean\t\r  circulation\t\r  and\t\r  sea\t\r  ice\t\r  (iii) Sea-­‐ice\t\r  melt\t\r  in\t\r  the\t\r  Western\t\r  Arctic\t\r  and\t\r  surface\t\r  energy\t\r  budget\t\r  of\t\r  the\t\r  Arctic\t\r  Ocean:\t\r  Climate\t\r  models\t\r  melt\t\r  the\t\r  ice\t\r  in\t\r  the\t\r  eastern\t\r  Arctic\t\r  (Laptev\t\r  Sea)\t\r  rather\t\r  than\t\r  the\t\r  western\t\r  Arctic\t\r  (Canadian\t\r  Basin,\t\r  Beaufort\t\r  Sea).\t\r  A\t\r  field\t\r  campaign\t\r  should\t\r  be\t\r  conducted\t\r  to\t\r  address\t\r  the\t\r  processes\t\r  involved\t\r  in\t\r  melting\t\r  the\t\r  sea-­‐ice\t\r  and\t\r  controlling\t\r  the\t\r  ocean\t\r  stratification\t\r  in\t\r  the\t\r  western\t\r  Arctic\t\r  (Beaufort\t\r  Sea).\t\r  \t\r  (iv) A\t\r  long-­‐term\t\r  experiment\t\r  like\t\r  SHEBA\t\r  is\t\r  needed\t\r  (but\t\r  with\t\r  21st\t\r  century\t\r  observing\t\r  capability)\t\r  that\t\r  samples\t\r  many\t\r  different\t\r  thermodynamic\t\r  and\t\r  dynamic\t\r  environments,\t\r  clean\t\r  and\t\r  polluted\t\r  situations,\t\r  and\t\r  gives\t\r  us\t\r  insights\t\r  into\t\r  the\t\r  larger-­‐scale\t\r  controls\t\r  on\t\r  cloud\t\r  cover\t\r  and\t\r  cloud\t\r  properties.\t\r  If\t\r  an\t\r  icebreaker\t\r  were\t\r  used\t\r  as\t\r  an\t\r  observational\t\r  platform,\t\r  as\t\r  in\t\r  SHEBA,\t\r  it\t\r  would\t\r  be\t\r  possible\t\r  to\t\r  operate\t\r  instrumented\t\r  unmanned\t\r  aerial\t\r  vehicles\t\r  (UAVs)\t\r  from\t\r  the\t\r  ship,\t\r  providing\t\r  greatly\t\r  extended\t\r  areal\t\r  coverage\t\r  of\t\r  measurements\t\r  over\t\r  the\t\r  central\t\r  Arctic\t\r  Ocean.\t\r  This\t\r  would\t\r  be\t\r  a\t\r  major\t\r  advance\t\r  over\t\r  what\t\r  \u003c/p\u003e\n\u003cp /\u003e\n\u003c/div\u003e\n\u003cdiv class\u003d\"page\"\u003e\u003cp /\u003e\n\u003cp\u003e\t\r  \u003c/p\u003e\n\u003cp\u003e\t\r   26\t\r  \n\u003c/p\u003e\n\u003cp\u003ecould\t\r  be\t\r  achieved\t\r  during\t\r  the\t\r  1990s.\t\r  Participation\t\r  in\t\r  MOSAiC\t\r  (Multi-­‐disciplinary\t\r  drifting\t\r  Observatory\t\r  for\t\r  the\t\r  Study\t\r  of\t\r  the\t\r  Arctic\t\r  Climate),\t\r  a\t\r  proposed\t\r  activity\t\r  under\t\r  the\t\r  auspices\t\r  of\t\r  the\t\r  International\t\r  Arctic\t\r  Science\t\r  Committee\t\r  (IASC),\t\r  would\t\r  be\t\r  an\t\r  effective\t\r  way\t\r  to\t\r  meet\t\r  this\t\r  observational\t\r  need.\t\r  \n4.1.3 Integrated\t\r  systems,\t\r  land\t\r  surface\t\r  hydrology,\t\r  and\t\r  carbon\t\r  cycle\t\r  \t\r  (i) Surface-­‐Atmosphere\t\r  Interactions:\t\r  Experiments\t\r  should\t\r  be\t\r  designed\t\r  and\t\r  conducted\t\r  to\t\r  validate\t\r  the\t\r  calculated\t\r  ESM\t\r  grid-­‐scale\t\r  surface-­‐atmosphere\t\r  exchanges\t\r  of\t\r  energy,\t\r  momentum,\t\r  water\t\r  and\t\r  carbon,\t\r  and\t\r  to\t\r  relate\t\r  these\t\r  fluxes\t\r  to\t\r  variables\t\r  that\t\r  are\t\r  amenable\t\r  to\t\r  satellite\t\r  remote\t\r  sensing.\t\r  This\t\r  will\t\r  require\t\r  in-­‐situ\t\r  measurements\t\r  of\t\r  radiation\t\r  components,\t\r  momentum,\t\r  sensible\t\r  heat,\t\r  latent\t\r  heat,\t\r  CO2\t\r  and\t\r  CH4\t\r  (where\t\r  possible)\t\r  preferably\t\r  measured\t\r  at\t\r  multiple\t\r  nested\t\r  scales,\t\r  by\t\r  short\t\r  and\t\r  tall\t\r  towers,\t\r  and\t\r  from\t\r  aircraft.\t\r  As\t\r  part\t\r  of\t\r  this,\t\r  the\t\r  data\t\r  collected\t\r  over\t\r  the\t\r  “heritage”\t\r  ABZ\t\r  sites\t\r  -­‐\t\r  Hudson\t\r  Bay\t\r  Lowland\t\r  (1990),\t\r  BOREAS\t\r  (1994\t\r  \u0026amp;\t\r  1996),\t\r  BERMS\t\r  and\t\r  Mackenzie\t\r  Basin\t\r  (1999),\t\r  etc.\t\r  –\t\r  should\t\r  be\t\r  re-­‐examined,\t\r  and\t\r  some\t\r  of\t\r  these\t\r  data\t\r  should\t\r  be\t\r  revisited\t\r  to\t\r  ascertain\t\r  how\t\r  the\t\r  land\t\r  surface\t\r  climatology,\t\r  hydrology\t\r  and\t\r  carbon\t\r  cycle\t\r  have\t\r  changed.\t\r  \n4.1.4 Biogeochemical\t\r  cycles\t\r  The\t\r  overall\t\r  goal\t\r   is\t\r   to\t\r  develop,\t\r   test\t\r  and\t\r  validate\t\r  zonal-­‐scale\t\r  BGC\t\r  models\t\r   that\t\r  can\t\r  be\t\r  embedded\t\r   in\t\r  ESMs.\t\r  Most\t\r  of\t\r  the\t\r  surface\t\r  parameters\t\r  for\t\r  these\t\r  models\t\r  are\t\r  to\t\r  be\t\r  extracted\t\r  from\t\r  satellite\t\r  data\t\r  and\t\r  model\t\r   performance\t\r   is\t\r   to\t\r   be\t\r   validated\t\r   by\t\r   in-­‐situ\t\r   observations\t\r   (1\t\r   –\t\r   100\t\r  m),\t\r   local-­‐to-­‐regional\t\r   up-­‐scaling\t\r   work\t\r   (100\t\r   m\t\r   –\t\r   1000\t\r   km)\t\r   and\t\r   inversion\t\r   models\t\r   (1000\t\r   km\t\r   –\t\r   ABZ\t\r   scale).\t\r   The\t\r   specific\t\r  experimental\t\r  activities\t\r  that\t\r  are\t\r  considered\t\r  to\t\r  be\t\r  most\t\r  useful\t\r  are\t\r  outlined\t\r  below.\t\r  \t\r  (i) Integrated\t\r  surface-­‐atmosphere\t\r  and\t\r  surface\t\r  processes:\t\r  A\t\r  network\t\r  of\t\r  tower\t\r  and\t\r  surface\t\r  process\t\r  study\t\r  sites\t\r  is\t\r  needed\t\r  to\t\r  measure\t\r  surface-­‐atmosphere\t\r  fluxes\t\r  of\t\r  CO2\t\r  and\t\r  CH4\t\r  and\t\r  their\t\r  governing\t\r  processes,\t\r  in\t\r  addition\t\r  to\t\r  those\t\r  PCS\t\r  fluxes\t\r  described\t\r  above.\t\r  Processes\t\r  and\t\r  pools\t\r  that\t\r  dominate\t\r  short-­‐term\t\r  BGC\t\r  response\t\r  (i.e.,\t\r  fast\t\r  flux\t\r  pools)\t\r  may\t\r  be\t\r  different\t\r  from\t\r  those\t\r  that\t\r  dominate\t\r  long-­‐term\t\r  responses\t\r  (large,\t\r  slow\t\r  flux\t\r  pools,\t\r  permafrost,\t\r  ecosystem\t\r  shifts\t\r  or\t\r  state\t\r  changes),\t\r  and\t\r  these\t\r  will\t\r  likely\t\r  require\t\r  different\t\r  observations.\t\r  Expanded\t\r  ground-­‐based\t\r  monitoring\t\r  capabilities\t\r  would\t\r  support\t\r  observations\t\r  of\t\r  long-­‐term\t\r  changes\t\r  needed\t\r  for\t\r  model\t\r  validation\t\r  and\t\r  source/sink\t\r  inversion\t\r  studies.\t\r  Clearly,\t\r  PCS\t\r  and\t\r  BGC\t\r  requirements\t\r  can\t\r  and\t\r  should\t\r  be\t\r  meshed\t\r  at\t\r  some\t\r  sites.\t\r  These\t\r  studies\t\r  should\t\r  be\t\r  directly\t\r  linked\t\r  to\t\r  remote\t\r  sensing\t\r  investigations\t\r  with\t\r  a\t\r  view\t\r  to\t\r  scaling\t\r  up\t\r  the\t\r  improved\t\r  process\t\r  models\t\r  to\t\r  the\t\r  ESM\t\r  scale.\t\r  \t\r  As\t\r  in\t\r  subsection\t\r  4.1.3,\t\r  the\t\r  data\t\r  collected\t\r  over\t\r  the\t\r  “heritage”\t\r  sites\t\r  should\t\r  be\t\r  re-­‐examined.\t\r  Some\t\r  of\t\r  these\t\r  sites\t\r  could\t\r  be\t\r  revived\t\r  to\t\r  ascertain\t\r  how\t\r  the\t\r  hydrological\t\r  properties\t\r  and\t\r  associated\t\r  surface-­‐atmosphere\t\r  energy,\t\r  momentum,\t\r  water\t\r  and\t\r  carbon\t\r  fluxes\t\r  have\t\r  changed.\t\r  \t\r  This\t\r  effort\t\r  should\t\r  be\t\r  meshed\t\r  with\t\r  any\t\r  proposed\t\r  work\t\r  to\t\r  be\t\r  conducted\t\r  at\t\r  “new”\t\r  sites.\t\r  New\t\r  measurements\t\r  that\t\r  would\t\r  be\t\r  useful\t\r  include\t\r  response\t\r  of\t\r  vegetation\t\r  growth\t\r  and\t\r  heterotrophic\t\r  respiration\t\r  to\t\r  changes\t\r  in\t\r  temperature\t\r  and\t\r  soil\t\r  moisture,\t\r  allocation\t\r  of\t\r  plant\t\r  growth\t\r  above\t\r  and\t\r  below\t\r  ground,\t\r  and\t\r  response\t\r  of\t\r  allocation\t\r  to\t\r  changes\t\r  in\t\r  temperature,\t\r  moisture,\t\r  and\t\r  vegetation\t\r  community\t\r  structure.\t\r  \t\r  Data\t\r  on\t\r  stable\t\r  isotope\t\r  content\t\r  (e.g.,\t\r  13C)\t\r  of\t\r  vegetation\t\r  and\t\r  soil\t\r  organic\t\r  matter\t\r  will\t\r  be\t\r  useful\t\r  in\t\r  evaluating\t\r  predicted\t\r  water\t\r  use\t\r  efficiency.\t\r  \t\r  The\t\r  development\t\r  of\t\r  new\t\r  CH4\t\r  sensors\t\r  has\t\r  made\t\r  it\t\r  feasible\t\r  to\t\r  measure\t\r  CO2/CH4\t\r  fluxes\t\r  from\t\r  an\t\r  airborne\t\r  platform,\t\r  thus\t\r  increasing\t\r  the\t\r  flux\t\r  footprint\t\r  of\t\r  tower-­‐and\t\r  chamber-­‐\u003c/p\u003e\n\u003cp /\u003e\n\u003c/div\u003e\n\u003cdiv class\u003d\"page\"\u003e\u003cp /\u003e\n\u003cp\u003e\t\r  \u003c/p\u003e\n\u003cp\u003e\t\r   27\t\r  \n\u003c/p\u003e\n\u003cp\u003ebased\t\r  CO2/CH4\t\r  measurements.\t\r  This\t\r  represents\t\r  an\t\r  important\t\r  step\t\r  between\t\r  very\t\r  small-­‐scale\t\r  (process\t\r  study,\t\r  flux\t\r  tower)\t\r  measurements\t\r  and\t\r  the\t\r  very\t\r  large\t\r  scale\t\r  relevant\t\r  to\t\r  ESMs.\t\r  Flux\t\r  measurements\t\r  should\t\r  be\t\r  obtained\t\r  with\t\r  aircraft-­‐based\t\r  systems\t\r  along\t\r  several\t\r  transects\t\r  as\t\r  well\t\r  as\t\r  during\t\r  grid\t\r  flights.\t\r  The\t\r  field\t\r  campaigns\t\r  augmented\t\r  with\t\r  CO2\t\r  and\t\r  CH4\t\r  measurement\t\r  capabilities\t\r  and\t\r  future\t\r  satellite\t\r  missions\t\r  would\t\r  provide\t\r  a\t\r  more\t\r  comprehensive\t\r  regional\t\r  picture\t\r  of\t\r  trace\t\r  gases\t\r  to\t\r  complement\t\r  the\t\r  long-­‐term\t\r  record\t\r  provided\t\r  by\t\r  ground-­‐based\t\r  networks.\t\r  \t\r  \t\r  \t\r  Cooperation\t\r  with\t\r  Siberian\t\r  work\t\r  for\t\r  validation\t\r  purposes\t\r  and\t\r  to\t\r  anchor\t\r  some\t\r  model\t\r  predictions\t\r  for\t\r  this\t\r  part\t\r  of\t\r  the\t\r  ABZ\t\r  should\t\r  be\t\r  continued.\t\r  \t\r  The\t\r  West\t\r  Siberian\t\r  Lowlands\t\r  are\t\r  the\t\r  largest\t\r  boreal\t\r  wetland\t\r  ecosystem\t\r  in\t\r  the\t\r  world\t\r  and\t\r  could\t\r  play\t\r  an\t\r  important\t\r  role\t\r  in\t\r  the\t\r  global\t\r  emission\t\r  of\t\r  CH4,\t\r  but\t\r  we\t\r  presently\t\r  have\t\r  no\t\r  direct\t\r  observations\t\r  of\t\r  such\t\r  emissions\t\r  from\t\r  this\t\r  region.\t\r  \t\r  \t\r  (ii) Disturbance\t\r  and\t\r  carbon\t\r  cycle\t\r  dynamics:\t\r  A\t\r  combination\t\r  of\t\r  satellite\t\r  fire\t\r  mapping,\t\r  in-­‐situ\t\r  pre-­‐\t\r  and\t\r  post-­‐fire\t\r  inventories,\t\r  and\t\r  atmospheric\t\r  composition\t\r  (surface,\t\r  airborne,\t\r  satellite)\t\r  measurements\t\r  should\t\r  provide\t\r  the\t\r  constraints\t\r  to\t\r  support\t\r  disturbance\t\r  model\t\r  development.\t\r  \t\r  Short-­‐term\t\r  processes\t\r  (including\t\r  interannual\t\r  variability)\t\r  need\t\r  to\t\r  be\t\r  studied\t\r  with\t\r  observations\t\r  such\t\r  as\t\r  flux\t\r  towers\t\r  and\t\r  aircraft\t\r  campaigns\t\r  with\t\r  a\t\r  focus\t\r  on\t\r  abrupt\t\r  disturbance\t\r  impacts\t\r  such\t\r  as\t\r  post-­‐fire.\t\r  Aircraft-­‐based\t\r  flux\t\r  measurements\t\r  along\t\r  several\t\r  long\t\r  transects\t\r  (200\t\r  km)\t\r  with\t\r  a\t\r  substantial\t\r  temperature\t\r  gradient\t\r  would\t\r  be\t\r  useful.\t\r  A\t\r  series\t\r  of\t\r  aircraft-­‐based\t\r  flux\t\r  measurements\t\r  of\t\r  CO2/CH4\t\r  and\t\r  Bowen\t\r  ratios\t\r  along\t\r  long\t\r  transects,\t\r  with\t\r  a\t\r  wide\t\r  range\t\r  of\t\r  environmental\t\r  conditions,\t\r  have\t\r  the\t\r  potential\t\r  to\t\r  provide\t\r  the\t\r  data\t\r  necessary\t\r  to\t\r  evaluate\t\r  whether\t\r  the\t\r  physical,\t\r  chemical\t\r  and\t\r  biological\t\r  mechanisms\t\r  in\t\r  the\t\r  ESMs\t\r  are\t\r  accurately\t\r  modeled.\t\r  Decadal/century\t\r  trends\t\r  need\t\r  to\t\r  be\t\r  investigated\t\r  through\t\r  analysis\t\r  of\t\r  long-­‐term\t\r  data\t\r  records\t\r  (stream\t\r  gauges,\t\r  remote\t\r  sensing\t\r  records,\t\r  Long\t\r  Term\t\r  Ecological\t\r  Research\t\r  (LTER)\t\r  data,\t\r  etc.).\t\r  Field\t\r  sites\t\r  studied\t\r  one\t\r  or\t\r  more\t\r  decades\t\r  ago\t\r  (as\t\r  noted\t\r  above)\t\r  should\t\r  be\t\r  revisited\t\r  using\t\r  a\t\r  combination\t\r  of\t\r  flux\t\r  tower\t\r  and\t\r  aircraft-­‐based\t\r  flux\t\r  measurements\t\r  to\t\r  identify\t\r  the\t\r  significance\t\r  of\t\r  any\t\r  changes\t\r  in\t\r  ecosystem\t\r  properties.\t\r  In\t\r  addition,\t\r  processes\t\r  associated\t\r  with\t\r  post-­‐fire\t\r  recovery\t\r  can\t\r  be\t\r  studied\t\r  using\t\r  the\t\r  aircraft\t\r  to\t\r  measure\t\r  CO2\t\r  exchange\t\r  1,\t\r  10,\t\r  20,\t\r  30\t\r  years\t\r  after\t\r  a\t\r  fire.\t\r  (iii) Upscaling:\t\r  A\t\r  combination\t\r  of\t\r  flux\t\r  towers,\t\r  flux\t\r  aircraft\t\r  and\t\r  remote\t\r  sensing\t\r  data\t\r  collection\t\r  and\t\r  validation\t\r  efforts\t\r  should\t\r  all\t\r  be\t\r  used\t\r  to\t\r  address\t\r  the\t\r  scale\t\r  gap\t\r  between\t\r  the\t\r  in-­‐situ\t\r  process\t\r  studies\t\r  and\t\r  the\t\r  ESM\t\r  scales.\t\r  For\t\r  the\t\r  purpose\t\r  of\t\r  upscaling\t\r  from\t\r  site\t\r  to\t\r  region,\t\r  high-­‐precision\t\r  and\t\r  continuous\t\r  tower-­‐based\t\r  measurements\t\r  should\t\r  be\t\r  made\t\r  of\t\r  the\t\r  mixing\t\r  ratios,\t\r  and\t\r  fluxes\t\r  when\t\r  possible,\t\r  of\t\r  CO2,\t\r  CH4\t\r  and\t\r  other\t\r  gas\t\r  species.\t\r  Surface-­‐based\t\r  atmospheric\t\r  column\t\r  measurements\t\r  will\t\r  complement\t\r  these\t\r  tower\t\r  measurements\t\r  and\t\r  validate\t\r  satellite\t\r  trace\t\r  gas\t\r  retrievals.\t\r  Vertical\t\r  profiles\t\r  and\t\r  near-­‐surface\t\r  fluxes\t\r  of\t\r  these\t\r  gases\t\r  in\t\r  the\t\r  PBL\t\r  can\t\r  be\t\r  sampled\t\r  by\t\r  aircraft\t\r  during\t\r  field\t\r  campaigns.\t\r  Satellite\t\r  and\t\r  aircraft\t\r  remote\t\r  sensing\t\r  data\t\r  at\t\r  various\t\r  spatial\t\r  resolutions\t\r  can\t\r  also\t\r  be\t\r  used\t\r  to\t\r  characterize\t\r  surface\t\r  heterogeneity\t\r  of\t\r  the\t\r  measurement\t\r  sites\t\r  and\t\r  the\t\r  global\t\r  ABZ.\t\r  In\t\r  combination,\t\r  these\t\r  measurements\t\r  can\t\r  be\t\r  used\t\r  to\t\r  evaluate\t\r  process\t\r  models\t\r  directly\t\r  over\t\r  the\t\r  range\t\r  of\t\r  local\t\r  to\t\r  regional\t\r  scales\t\r  and\t\r  can\t\r  help\t\r  to\t\r  constrain\t\r  the\t\r  atmospheric\t\r  inversion\t\r  work\t\r  described\t\r  in\t\r  (iv)\t\r  below.\t\r  \t\r   (iv)\t\r  \t\r   Downscaling:\t\r  A\t\r  comprehensive\t\r  effort\t\r  should\t\r  be\t\r  made\t\r  to\t\r  expand\t\r  the\t\r  network\t\r  of\t\r  atmospheric\t\r  CO2\t\r  and\t\r  CH4\t\r  concentration\t\r  measurements\t\r  in\t\r  the\t\r  ABZ,\t\r  preceded\t\r  and\t\r  \u003c/p\u003e\n\u003cp /\u003e\n\u003c/div\u003e\n\u003cdiv class\u003d\"page\"\u003e\u003cp /\u003e\n\u003cp\u003e\t\r  \u003c/p\u003e\n\u003cp\u003e\t\r   28\t\r  \n\u003c/p\u003e\n\u003cp\u003eaccompanied\t\r  by\t\r  four-­‐dimensional\t\r  data\t\r  assimilation\t\r  (4DDA)\t\r  and\t\r  observing\t\r  system\t\r  simulation\t\r  experiments\t\r  (OSSEs)\t\r  to\t\r  determine\t\r  the\t\r  optimal\t\r  deployment\t\r  pattern\t\r  and\t\r  schedule\t\r  for\t\r  inversion\t\r  studies.\t\r  This\t\r  network\t\r  should\t\r  directly\t\r  complement\t\r  the\t\r  surface,\t\r  tower\t\r  and\t\r  airborne\t\r  process\t\r  study\t\r  networks\t\r  listed\t\r  above\t\r  and\t\r  be\t\r  used\t\r  to\t\r  support\t\r  a\t\r  multi-­‐team\t\r  atmospheric\t\r  inversion\t\r  initiative\t\r  allied\t\r  to\t\r  satellite\t\r  trace\t\r  gas\t\r  algorithm\t\r  development.\t\r  All\t\r  of\t\r  these\t\r  studies\t\r  should\t\r  be\t\r  directly\t\r  linked\t\r  to\t\r  remote\t\r  sensing\t\r  investigations\t\r  with\t\r  a\t\r  view\t\r  to\t\r  scaling\t\r  up\t\r  the\t\r  improved\t\r  process\t\r  models\t\r  to\t\r  the\t\r  ESM\t\r  scale.\t\r  Previous,\t\r  current\t\r  and\t\r  proposed\t\r  experiment\t\r  sites\t\r  in\t\r  Alaska\t\r  and\t\r  Canada\t\r  (e.g.,\t\r  ABLE,\t\r  BOREAS,\t\r  BERMS,\t\r  NGEE,\t\r  etc.)\t\r   should\t\r  be\t\r  assessed\t\r  for\t\r  zonal-­‐scale\t\r  embedding.\t\r  \t\r  \n4.2 Remote\t\r  sensing\t\r  contributions\t\r  Remote\t\r  sensing\t\r  provides\t\r  the\t\r  only\t\r  viable\t\r  option\t\r  for\t\r  obtaining\t\r  high\t\r  spatial\t\r  and\t\r  temporal\t\r  sampling\t\r  in\t\r  the\t\r   remote\t\r   regions\t\r  of\t\r   the\t\r  ABZ.\t\r  Many\t\r  observations\t\r   are\t\r   available\t\r   almost\t\r   contemporaneously\t\r   from\t\r  the\t\r  A-­‐train\t\r  sensors\t\r  and\t\r  the\t\r  operational\t\r  NOAA\t\r  satellites\t\r  to\t\r  help\t\r  improve\t\r  climate\t\r  models.\t\r  Much\t\r  work\t\r  remains\t\r  to\t\r  be\t\r  done\t\r  to\t\r  use\t\r  these\t\r  observations\t\r  effectively.\t\r  A\t\r  more\t\r  complete\t\r  picture\t\r  of\t\r  the\t\r  ABZ\t\r  meteorology\t\r  can\t\r  be\t\r  obtained\t\r  by\t\r  integrating\t\r  in-­‐situ\t\r  and\t\r  satellite\t\r  observations\t\r  through\t\r  model\t\r  reanalysis\t\r  (4DDA).\t\r  The\t\r  satellite\t\r  sounding\t\r  measurements\t\r  of\t\r  humidity\t\r  and\t\r   temperature\t\r   (AIRS,\t\r   AMSU,\t\r   AMSR,\t\r   CrIS,\t\r   ATMS,\t\r   etc.)\t\r   are\t\r   particularly\t\r   important.\t\r   The\t\r   EOS\t\r  platforms,\t\r  and\t\r  the\t\r  A-­‐Train\t\r  in\t\r  particular,\t\r  have\t\r  provided\t\r  unprecedented\t\r  observations\t\r  of\t\r  clouds\t\r  and\t\r  aerosols\t\r  (CloudSat,\t\r  CALIPSO,\t\r  PARASOL).\t\r  Observations\t\r  of\t\r  cloudiness\t\r  and\t\r  the\t\r  atmospheric\t\r  radiation\t\r  budget\t\r  are\t\r  provided\t\r  by\t\r  AVHRR,\t\r  MODIS,\t\r  VIIRS,\t\r  MISR\t\r  and\t\r  CERES\t\r  to\t\r  give\t\r  a\t\r  record\t\r  from\t\r  the\t\r  late\t\r  1970s\t\r  onward.\t\r  MISR\t\r  measurements\t\r  are\t\r  particularly\t\r  valuable\t\r  for\t\r  cloud\t\r  observations\t\r  over\t\r  the\t\r  Arctic\t\r  Ocean\t\r  where\t\r   icy\t\r   and\t\r   snowy\t\r   surfaces\t\r   are\t\r   problematic\t\r   to\t\r   other\t\r   sensors\t\r   that\t\r   are\t\r   sensitive\t\r   to\t\r  radiometric/thermal\t\r   calibration\t\r   and\t\r   the\t\r   contrast\t\r   between\t\r   surface\t\r   and\t\r   cloud\t\r   radiances\t\r   (Wu\t\r   and\t\r  Lee,\t\r  2012).\t\r  MISR\t\r  has\t\r  been\t\r  operating\t\r  almost\t\r  continuously\t\r  since\t\r  March\t\r  2000\t\r  except\t\r  for\t\r  a\t\r  ~16-­‐day\t\r  gap\t\r   in\t\r   October\t\r   2008.\t\r   However,\t\r   high\t\r   optically\t\r   thick\t\r   clouds\t\r   prevent\t\r   satellite\t\r   sensors\t\r   from\t\r   seeing\t\r  lower\t\r   clouds,\t\r   and\t\r   the\t\r   vertical\t\r   resolution\t\r   of\t\r   MISR\t\r   prohibits\t\r   it\t\r   from\t\r   detecting\t\r   clouds\t\r   lower\t\r   than\t\r  ~500\t\r  m\t\r  from\t\r  the\t\r  surface.\t\r  Whereas\t\r  the\t\r  lidar\t\r  active\t\r  remote\t\r  sensing\t\r  technique\t\r  used\t\r  for\t\r  CALIPSO\t\r  has\t\r  advantages\t\r   in\t\r  vertical\t\r  accuracy\t\r  and\t\r   insensitivity\t\r   to\t\r   lack\t\r  of\t\r   sunlight\t\r  or\t\r   thermal\t\r  contrast,\t\r   the\t\r  main\t\r  disadvantage\t\r  is\t\r  its\t\r  limited\t\r  spatial\t\r  coverage\t\r  (e.g.,\t\r  Palm\t\r  et\t\r  al.,\t\r  2010).\t\r  CALIPSO,\t\r  MODIS\t\r  and\t\r  MISR\t\r  provide\t\r  information\t\r  on\t\r  aerosol\t\r  profiles\t\r  and\t\r  column-­‐integrated\t\r  aerosol\t\r  optical\t\r   depth,\t\r   respectively.\t\r   \t\r   With\t\r   data\t\r   assimilation\t\r   systems,\t\r   these\t\r   observations\t\r   can\t\r   provide\t\r  constraints\t\r   on\t\r   aerosol\t\r   transports\t\r   from\t\r   lower\t\r   latitudes\t\r   to\t\r   the\t\r  ABZ.\t\r   \t\r   Field\t\r   campaigns\t\r   can\t\r   then\t\r   be\t\r  used\t\r   to\t\r   evaluate\t\r   those\t\r   estimates\t\r   and\t\r   provide\t\r   details\t\r   on\t\r   their\t\r   distribution\t\r   within\t\r   the\t\r   ABZ.\t\r   The\t\r  combination\t\r   of\t\r   field\t\r   campaign\t\r   and\t\r   satellite\t\r   data\t\r   is\t\r   then\t\r   useful\t\r   for\t\r   evaluating\t\r   model\t\r   transport\t\r  estimates,\t\r  including\t\r  wet\t\r  deposition\t\r  during\t\r  transport.\t\r  In\t\r  conjunction\t\r  with\t\r  in-­‐situ\t\r  observations\t\r  from\t\r  the\t\r   ARM\t\r   program,\t\r   the\t\r   combination\t\r   of\t\r   CloudSat\t\r   and\t\r   CALIPSO\t\r   data,\t\r   with\t\r   their\t\r   high-­‐resolution\t\r  representation\t\r   of\t\r   cloud\t\r   and\t\r   aerosol\t\r   structures,\t\r   will\t\r   provide\t\r   important\t\r   metrics\t\r   to\t\r   evaluate\t\r   new\t\r  parameterizations\t\r  of\t\r  ice\t\r  and\t\r  mixed-­‐phase\t\r  cloud\t\r  microphysics\t\r  Large-­‐scale\t\r   information\t\r  about\t\r  the\t\r  sea\t\r   ice\t\r  cover,\t\r  water\t\r  vapor\t\r  and\t\r  precipitation\t\r  has\t\r  been\t\r  available\t\r  almost\t\r   continuously\t\r   from\t\r   passive\t\r  microwave\t\r   data\t\r   (ESMR,\t\r   SMMR,\t\r   SSM/I\t\r   and\t\r   AMSR-­‐E)\t\r   since\t\r   the\t\r  1970s.\t\r   \t\r  Seasonal\t\r  and\t\r  interannual\t\r  variability\t\r  in\t\r  the\t\r  extent\t\r  and\t\r  distribution\t\r  of\t\r  ice\t\r  has\t\r  been\t\r  derived\t\r  primarily\t\r   from\t\r   these\t\r   data.\t\r   \t\r   Radarsat\t\r   and\t\r   other\t\r   radar\t\r   satellites\t\r   launched\t\r   since\t\r   the\t\r   mid-­‐1990s\t\r  provide\t\r   information\t\r   on\t\r   surface\t\r   type,\t\r   sea\t\r   ice\t\r   cover\t\r   and\t\r   freeze-­‐thaw\t\r   extent.\t\r   The\t\r   SMAP\t\r   mission\t\r  includes\t\r  a\t\r  freeze/thaw\t\r  component\t\r  that\t\r  could\t\r  be\t\r  highly\t\r  relevant\t\r  to\t\r  an\t\r  ABZ\t\r  field\t\r  experiment.\t\r  \t\r  SMAP\t\r  is\t\r  slated\t\r  for\t\r  launch\t\r  in\t\r  late\t\r  2014\t\r  and,\t\r  for\t\r  at\t\r  least\t\r  three\t\r  years,\t\r  will\t\r  provide\t\r  binary\t\r  freeze/thaw\t\r  state\t\r  \u003c/p\u003e\n\u003cp /\u003e\n\u003c/div\u003e\n\u003cdiv class\u003d\"page\"\u003e\u003cp /\u003e\n\u003cp\u003e\t\r  \u003c/p\u003e\n\u003cp\u003e\t\r   29\t\r  \n\u003c/p\u003e\n\u003cp\u003einformation\t\r   at\t\r   a\t\r   resolution\t\r   of\t\r   3\t\r   km\t\r   every\t\r   two\t\r   days,\t\r   with\t\r   a\t\r   classification\t\r   accuracy\t\r   of\t\r   80%.\t\r   Pilot\t\r  investigations,\t\r   using\t\r   airborne\t\r  microwave\t\r   instruments,\t\r   should\t\r   be\t\r   conducted\t\r   over\t\r   the\t\r  ABZ\t\r   before\t\r  and\t\r  during\t\r  the\t\r  SMAP\t\r  mission.\t\r  Gravity\t\r  remote\t\r  sensing\t\r  (e.g.,\t\r  GRACE)\t\r  of\t\r  surface\t\r  water\t\r  dynamics\t\r  over\t\r  large\t\r   watersheds\t\r   could\t\r   help\t\r   in\t\r   detecting\t\r   macroscale\t\r   changes\t\r   in\t\r   permafrost\t\r   thaw,\t\r   active\t\r   layer\t\r  thickness,\t\r  soil\t\r  water\t\r  storage,\t\r  and\t\r  runoff.\t\r  \t\r  Satellite\t\r  data\t\r  from\t\r  AIRS,\t\r  IASI\t\r  and\t\r  GOSAT\t\r  provide\t\r  the\t\r  most\t\r  comprehensive\t\r  available\t\r  regional\t\r  view\t\r  of\t\r  CO2\t\r  and\t\r  CH4\t\r  but\t\r  these\t\r  data\t\r  remain\t\r  limited\t\r  by\t\r  several\t\r  factors.\t\r  AIRS\t\r  observations\t\r  primarily\t\r  reflect\t\r  the\t\r  middle\t\r  and\t\r  upper\t\r  troposphere,\t\r  making\t\r  connection\t\r  to\t\r  small-­‐scale\t\r  surface\t\r  source/sink\t\r  processes\t\r  difficult.\t\r  GOSAT\t\r  observations\t\r  provide\t\r   sparse\t\r   sampling\t\r  of\t\r   CO2\t\r   columns\t\r   in\t\r   the\t\r  ABZ\t\r  only\t\r  over\t\r   land\t\r  during\t\r   summer\t\r   months.\t\r   OCO-­‐2,\t\r   scheduled\t\r   for\t\r   launch\t\r   in\t\r   December\t\r   2014,\t\r   will\t\r   provide\t\r   CO2\t\r  measurements\t\r   in\t\r  the\t\r  ABZ\t\r  from\t\r  spring\t\r  to\t\r   fall.\t\r   \t\r  AIRS,\t\r   IASI,\t\r  and\t\r  TES\t\r  provide\t\r  observations\t\r  of\t\r  partial\t\r  columns\t\r  of\t\r  CO\t\r  and\t\r  MLS\t\r  upper\t\r  tropospheric\t\r  CO.\t\r  Making\t\r  most\t\r  use\t\r  of\t\r  these\t\r  observations\t\r  requires\t\r  the\t\r  use\t\r   of\t\r   data\t\r   assimilation\t\r   systems.\t\r   The\t\r   advantage\t\r   of\t\r   using\t\r   these\t\r   observations\t\r   in\t\r   an\t\r   assimilation\t\r  framework\t\r   is\t\r   that\t\r  a\t\r  view\t\r  of\t\r  atmospheric\t\r   trace\t\r  gases\t\r   that\t\r   is\t\r   consistent\t\r  across\t\r  platforms,\t\r  and\t\r  also\t\r  consistent\t\r   with\t\r   the\t\r   concurrent\t\r   meteorology,\t\r   emerges.\t\r   Field\t\r   campaigns\t\r   provide\t\r   invaluable\t\r  evaluation\t\r  metrics.\t\r  Satellite\t\r   observations\t\r   of\t\r   ocean\t\r   color\t\r   (SeaWiFS,\t\r  MODIS,\t\r   VIIRS)\t\r   have\t\r   been\t\r   important\t\r   to\t\r   studies\t\r   of\t\r  phytoplankton\t\r   abundance\t\r   and\t\r   net\t\r   primary\t\r   production,\t\r   including\t\r   model\t\r   evaluation.\t\r   These\t\r  observations\t\r  can\t\r  be\t\r  difficult\t\r  to\t\r  use\t\r  in\t\r  the\t\r  Arctic\t\r  because\t\r  of\t\r  the\t\r  large\t\r  solar\t\r  zenith\t\r  angles,\t\r  persistent\t\r  cloud\t\r  cover,\t\r  and\t\r  high\t\r  riverine\t\r  fluxes\t\r  into\t\r  its\t\r  coastal\t\r  margins\t\r  (Arrigo\t\r  et\t\r  al.,\t\r  2011).\t\r  In\t\r  addition,\t\r  depth-­‐integrated\t\r   rates\t\r   of\t\r   NPP\t\r   that\t\r   are\t\r   calculated\t\r   from\t\r   satellite-­‐based\t\r   measurements\t\r   will\t\r   be\t\r  underestimated\t\r   in\t\r   regions\t\r  of\t\r   the\t\r  Arctic\t\r  Ocean\t\r   that\t\r  have\t\r  a\t\r  well-­‐developed\t\r  subsurface\t\r   chlorophyll\t\r  maximum.\t\r   In-­‐situ\t\r   observations\t\r   are\t\r   essential\t\r   to\t\r   quantify\t\r   the\t\r   uncertainties\t\r   in\t\r   remote\t\r   sensing\t\r  estimates;\t\r  comparisons\t\r  and\t\r  uncertainty\t\r  quantification\t\r  should\t\r  be\t\r  pursued\t\r  whenever\t\r  possible.\t\r  Grosse\t\r   et\t\r   al.\t\r   (2011)\t\r   enumerate\t\r  many\t\r  ways\t\r   that\t\r   remote\t\r   sensing\t\r   data\t\r   can\t\r   be\t\r   used\t\r   to\t\r   improve\t\r   or\t\r  evaluate\t\r  land\t\r  surface\t\r  disturbance\t\r  models.\t\r  Spatial\t\r  monitoring\t\r  of\t\r  aboveground\t\r  organic\t\r  carbon\t\r  stocks\t\r  and\t\r   vegetation-­‐soil-­‐water\t\r   interactions\t\r   using\t\r   remote\t\r   sensing\t\r   including\t\r   hyperspectral,\t\r   SAR\t\r   and\t\r  LIDAR\t\r  sensors,\t\r  coupled\t\r  with\t\r  dedicated\t\r  field\t\r  campaigns,\t\r  could\t\r  greatly\t\r   improve\t\r  our\t\r  understanding\t\r  of\t\r   SOC\t\r   input\t\r   dynamics\t\r   related\t\r   to\t\r   terrestrial\t\r   land\t\r   surface\t\r   dynamics\t\r   under\t\r   disturbance\t\r   regimes.\t\r  Since\t\r   thermal\t\r  and\t\r  hydrological\t\r   regimes\t\r  are\t\r  critical\t\r   to\t\r  vulnerability\t\r  and\t\r  resilience\t\r  of\t\r  SOC,\t\r   remote\t\r  sensing\t\r  applications\t\r  aimed\t\r  at\t\r  quantifying\t\r  these\t\r  regimes\t\r  in\t\r  the\t\r  ABZ\t\r  would\t\r  enhance\t\r  our\t\r  capability\t\r  to\t\r  characterize,\t\r  quantify,\t\r  and\t\r  potentially\t\r  predict\t\r  disturbances\t\r  and\t\r  their\t\r  impacts\t\r  on\t\r  SOC\t\r  at\t\r  large\t\r  scales.\t\r  Relevant\t\r  existing\t\r  or\t\r  upcoming\t\r  missions\t\r  include\t\r  soil\t\r  moisture\t\r  and\t\r  surface\t\r  water\t\r  satellite\t\r  missions\t\r  (e.g.,\t\r  SMOS,\t\r  SMAP,\t\r  SWOT\t\r  (2020\t\r  launch)),\t\r  spaceborne\t\r  SAR\t\r  missions\t\r  to\t\r  detect\t\r  aboveground\t\r  biomass,\t\r  and\t\r  existing\t\r  thermal\t\r  satellite\t\r  measurements\t\r  (e.g.,\t\r  AVHRR,\t\r  MODIS,\t\r  VIIRS).\t\r  Several\t\r  optical\t\r  (Visible,\t\r  NIR)\t\r  satellite\t\r  data\t\r  sets\t\r  have\t\r  been\t\r  used\t\r  to\t\r  study\t\r  land\t\r  surface\t\r  changes\t\r  and\t\r  processes\t\r   in\t\r   the\t\r   ABZ\t\r   (e.g.,\t\r   Frolking\t\r   et\t\r   al.,\t\r   2009).\t\r   These\t\r   data\t\r   could\t\r   also\t\r   be\t\r   used\t\r   to\t\r   characterize\t\r  surface\t\r   variability\t\r   and\t\r   specify\t\r   surface\t\r   parameter\t\r   fields\t\r   for\t\r   models.\t\r   The\t\r   AVHRR\t\r   archive\t\r   extends\t\r  back\t\r  to\t\r  1979\t\r  and\t\r  is\t\r  currently\t\r  being\t\r  used\t\r  to\t\r  study\t\r  the\t\r  progressive\t\r  “green-­‐up”\t\r  of\t\r  the\t\r  Arctic\t\r  tundra\t\r  over\t\r  the\t\r  last\t\r  30\t\r  years\t\r  (Bhatt\t\r  et\t\r  al.,\t\r  2010;\t\r  Raynolds\t\r  et\t\r  al.,\t\r  2012).\t\r  Landsat\t\r  data,\t\r  extending\t\r  from\t\r  the\t\r  1970’s\t\r  onwards,\t\r  has\t\r  been\t\r  used\t\r  to\t\r  track\t\r  disturbance\t\r  in\t\r  several\t\r  ABZ\t\r  regions\t\r  (e.g.,\t\r  Hall\t\r  et\t\r  al.,\t\r  1991;\t\r  Kasischke\t\r  et\t\r  al.,\t\r  2010).\t\r  MODIS\t\r  data,\t\r  starting\t\r  from\t\r  1998,\t\r  offers\t\r  great\t\r  enhancements\t\r  over\t\r  the\t\r  AVHRR\t\r  data\t\r  set,\t\r  and\t\r  VIIRS\t\r  will\t\r  extend\t\r  the\t\r  MODIS\t\r  data\t\r  set\t\r  forward.\t\r   \t\r  \u003c/p\u003e\n\u003cp /\u003e\n\u003c/div\u003e\n\u003cdiv class\u003d\"page\"\u003e\u003cp /\u003e\n\u003cp\u003e\t\r  \u003c/p\u003e\n\u003cp\u003e\t\r   30\t\r  \n\u003c/p\u003e\n\u003cp\u003e4.3 Proposed\t\r  and\t\r  Related\t\r  Ongoing\t\r  Activities\t\r  and\t\r  Leveraging\t\r  Opportunities\t\r  \n\u003c/p\u003e\n\u003cp\u003eAtmosphere\t\r  \n\u003c/p\u003e\n\u003cp\u003eObservational\t\r  \nActivity\t\r   Details\t\r  \n\u003c/p\u003e\n\u003cp\u003eProposed\t\r  Supplements\t\r  \n(shown\t\r  in\t\r  blue)\t\r  and\t\r  New\t\r  \nActivities\t\r  (shown\t\r  in\t\r  red)\t\r  \n\u003c/p\u003e\n\u003cp\u003eReference\t\r  \n\u003c/p\u003e\n\u003cp\u003eClouds-­‐Aerosols-­‐Radiation\t\r  \n\u003c/p\u003e\n\u003cp\u003eDOE\t\r  ARM\t\r  Program\t\r  \nARM\t\r  Climate\t\r  Research\t\r  Facilities\t\r  at\t\r  Barrow\t\r  (coastal)\t\r  and\t\r  Atqasuk\t\r  (inland).\t\r  \nCampaigns:\t\r  Barrow\t\r  Black\t\r  Carbon\t\r  Source\t\r  and\t\r  Impact\t\r  Study,\t\r  July\t\r  2012\t\r  –\t\r  June\t\r  2013:\t\r  combination\t\r  of\t\r  air\t\r  monitoring,\t\r  snow\t\r  collection\t\r  and\t\r  radiative\t\r  measurements.\t\r  \t\r  \n\u003c/p\u003e\n\u003cp\u003eConduct\t\r  analyses\t\r  of\t\r  existing\t\r  observations\t\r  of\t\r  CCN\t\r  and\t\r  IN\t\r  to\t\r  characterize\t\r  the\t\r  probability\t\r  distribution\t\r  of\t\r  ice\t\r  particle\t\r  properties.\t\r  \t\r  Obtain\t\r  more\t\r  observations\t\r  (including\t\r  at\t\r  new\t\r  sites\t\r  in\t\r  the\t\r  ABZ)\t\r  of\t\r  CCN\t\r  and\t\r  cloud\t\r  ice\t\r  properties\t\r  and\t\r  their\t\r  effects\t\r  on\t\r  the\t\r  radiation\t\r  budget.\t\r  \t\r  Spring\t\r  aircraft\t\r  campaign;\t\r  add\t\r  aerosol\t\r  component\t\r  targeting\t\r  aerosol\t\r  wet\t\r  removal.\t\r  \t\r  \n\u003c/p\u003e\n\u003cp\u003e§2.1\t\r  §4.4.1\t\r  \t\r  \t\r  \t\r  \t\r  \t\r  \t\r  \t\r  \t\r  \t\r  \t\r  §2.1\t\r  §4.1.1\t\r  \t\r  \nICECAPS\t\r  (NSF\t\r  AON)\t\r  \n\u003c/p\u003e\n\u003cp\u003eA\t\r  field\t\r  campaign\t\r  adding\t\r  cloud,\t\r  atmosphere,\t\r  and\t\r  precipitation\t\r  measurements,\t\r  and\t\r  associated\t\r  higher-­‐order\t\r  data\t\r  products,\t\r  to\t\r  Summit,\t\r  Greenland\t\r  at\t\r  the\t\r  top\t\r  of\t\r  the\t\r  Greenland\t\r  Icesheet.\t\r  \t\r  CALIPSO,\t\r  CloudSAT,\t\r  MISR,\t\r  MODIS\t\r   Cloud\t\r  and\t\r  aerosol\t\r  profiles;\t\r  column-­‐integrated\t\r  AOD.\t\r   Conduct\t\r  analyses\t\r  related\t\r  to\t\r  ABZ.\t\r   §2.1\t\r  §4.2\t\r  AEROCAN\t\r   19\t\r  sites\t\r  across\t\r  Canada\t\r  –\t\r  part\t\r  of\t\r  AERONET.\t\r   Augment\t\r  network\t\r  in\t\r  ABZ.\t\r   §2.1\t\r  \nCO2,\t\r  CH4\t\r   \t\r  \n\u003c/p\u003e\n\u003cp\u003eNOAA\t\r  ESRL\t\r  surface\t\r  observatories\t\r  \nGround-­‐based\t\r  observing\t\r  network\t\r  for\t\r  surface\t\r  observations\t\r  of\t\r  CO2,\t\r  CH4,\t\r  etc.;\t\r  10\t\r  locations\t\r  (6\t\r  in\t\r  Canada\t\r  and\t\r  Alaska,\t\r  1\t\r  in\t\r  Greenland,\t\r  and\t\r  3\t\r  in\t\r  Europe\t\r  north\t\r  of\t\r  60°N\t\r  (Iceland,\t\r  Finland,\t\r  and\t\r  Sweden/Norway).\t\r  \n\u003c/p\u003e\n\u003cp\u003eAugment\t\r  network\t\r  with\t\r  new\t\r  surface\t\r  observations\t\r  (~10-­‐20\t\r  stations).\t\r  \t\r  Use\t\r  4DDA/OSSE\t\r  to\t\r  define\t\r  the\t\r  network.\t\r  Assess\t\r  other\t\r  cheaper\t\r  methods\t\r  for\t\r  measuring\t\r  concentrations\t\r  and\t\r  columns\t\r  in\t\r  the\t\r  ABZ.\t\r  \n§2.6.1\t\r  §2.6.5\t\r  §4.5.3\t\r  \n\u003c/p\u003e\n\u003cp\u003eTCCON\t\r  \t\r  \nGround-­‐based\t\r  Fourier\t\r  Transform\t\r  Spectrometers\t\r  recording\t\r  direct\t\r  solar\t\r  spectra\t\r  in\t\r  the\t\r  near-­‐IR\t\r  for\t\r  column-­‐averaged\t\r  CO2,\t\r  CH4,\t\r  CO,\t\r  etc.\t\r  Three\t\r  sites\t\r  are\t\r  north\t\r  of\t\r  60°N,\t\r  but\t\r  only\t\r  2\t\r  are\t\r  operational.\t\r  \n\u003c/p\u003e\n\u003cp\u003eABoVE\t\r  \nRS\t\r  and\t\r  field-­‐based\t\r  measurements\t\r  to\t\r  understand\t\r  how\t\r  land\t\r  surface\t\r  processes\t\r  interact\t\r  to\t\r  regulate\t\r  the\t\r  atmospheric\t\r  GHGs;\t\r  will\t\r  add\t\r  eddy\t\r  covariance\t\r  towers,\t\r  and\t\r  provide\t\r  the\t\r  opportunity\t\r  to\t\r  extend\t\r  CARVE.\t\r  CO2\t\r  and\t\r  CH4\t\r  flux\t\r  measurements\t\r  using\t\r  flux\t\r  auto\t\r  chambers.\t\r  \n\u003c/p\u003e\n\u003cp\u003eEmbed\t\r  ABoVE\t\r  within\t\r  US-­‐Canadian\t\r  downscaling\t\r  effort.\t\r  \t\r  Evaluate\t\r  requirements\t\r  for\t\r  US\t\r  airborne\t\r  flux\t\r  measurement\t\r  capability\t\r  for\t\r  CO2\t\r  and\t\r  CH4.\t\r  \n§2.6.5\t\r  §4.1.4\t\r  \t\r  \u003c/p\u003e\n\u003cp /\u003e\n\u003c/div\u003e\n\u003cdiv class\u003d\"page\"\u003e\u003cp /\u003e\n\u003cp\u003e\t\r  \u003c/p\u003e\n\u003cp\u003e\t\r   31\t\r  \n\u003c/p\u003e\n\u003cp\u003eCARVE\t\r  (2012-­‐2015) \nAirborne\t\r  mission\t\r  to\t\r  quantify\t\r  correlations\t\r  between\t\r  atmospheric\t\r  concentrations\t\r  of\t\r  CO2\t\r  and\t\r  CH4\t\r  with\t\r  surface-­‐atmosphere\t\r  carbon\t\r  fluxes\t\r  and\t\r  surface\t\r  state\t\r  control\t\r  variables.\t\r  \n\u003c/p\u003e\n\u003cp\u003eAugment\t\r  coverage,\t\r  extend\t\r  duration.\t\r  Assess\t\r  adding\t\r  airborne\t\r  flux\t\r  measurement\t\r  capability\t\r  to\t\r  follow-­‐on\t\r  campaigns.\t\r  \n§2.6.1\t\r  §2.6.5\t\r  §4.1.3\t\r  §4.1.4\t\r  \t\r  \n\u003c/p\u003e\n\u003cp\u003eSatellites\t\r  (AIRS,\t\r  IASI,\t\r  MLS,\t\r  GOSAT,\t\r  OCO-­‐2)\t\r   Combined\t\r  with\t\r  4DDA\t\r  provides\t\r  information\t\r  on\t\r  transport\t\r  into\t\r  ABZ.\t\r  \nUse\t\r  4DDA/OSSE\t\r  to\t\r  contribute\t\r  to\t\r  future\t\r  mission\t\r  (ASCENDS)\t\r  planning\t\r  to\t\r  ensure\t\r  the\t\r  measurements\t\r  meet\t\r  requirements\t\r  for\t\r  ABZ.\t\r  \n\u003c/p\u003e\n\u003cp\u003e§2.6.5\t\r  §4.2\t\r  \n\t\r  \nLand\t\r  Surface\t\r  \n\u003c/p\u003e\n\u003cp\u003eObservational\t\r  \nActivity\t\r   Details\t\r  \n\u003c/p\u003e\n\u003cp\u003eProposed\t\r  Supplements\t\r  \n(shown\t\r  in\t\r  blue)\t\r  and\t\r  New\t\r  \nActivities\t\r  (shown\t\r  in\t\r  red)\t\r  \n\u003c/p\u003e\n\u003cp\u003eReference\t\r  \n\u003c/p\u003e\n\u003cp\u003ePermafrost and thermokarst scaling studies  \n\u003c/p\u003e\n\u003cp\u003eNGEE\t\r   \nPhase\t\r  1\t\r  –\t\r  field\t\r  observations,\t\r  lab\t\r  experiments,\t\r  modeling\t\r  activities\t\r  –\t\r  Permafrost\t\r  degradation\t\r  and\t\r  its\t\r  impact\t\r  on\t\r  water,\t\r  N,\t\r  C,\t\r  and\t\r  energy-­‐related\t\r  processes\t\r  across\t\r  a\t\r  hierarchy\t\r  of\t\r  scales.\t\r  Locations:\t\r  North\t\r  Slope\t\r  (Barrow)\t\r  and\t\r  Seward\t\r  Peninsula\t\r  (Council).\t\r  \n\u003c/p\u003e\n\u003cp\u003eAugment\t\r  upscaling\t\r  approach\t\r  using\t\r  flux\t\r  aircraft\t\r  and\t\r  additional\t\r  remote\t\r  sensing\t\r  studies.\t\r   §2.4.5 \n\u003c/p\u003e\n\u003cp\u003eABoVE\t\r  \nField\t\r  measurements\t\r  to\t\r  understand\t\r  driving\t\r  processes\t\r  and\t\r  agents\t\r  to\t\r  develop\t\r  inputs\t\r  to\t\r  physical\t\r  models\t\r  to\t\r  predict\t\r  spatial\t\r  and\t\r  temporal\t\r  patterns\t\r  and\t\r  future\t\r  conditions\t\r  for\t\r  soil\t\r  active\t\r  layer\t\r  depth\t\r  and\t\r  permafrost\t\r  status.\t\r  \n\u003c/p\u003e\n\u003cp\u003eCoordination\t\r  with\t\r  NGEE,\t\r  extending\t\r  the\t\r  domain,\t\r  incorporating\t\r  heritage\t\r  sites\t\r  and\t\r  scaling\t\r  studies.\t\r   §2.4.3\t\r  \nNSF\t\r  AON\t\r   Long-­‐term\t\r  permafrost\t\r  temperature\t\r  observations\t\r  and\t\r  active\t\r  layer\t\r  thickness\t\r  in\t\r  the\t\r  NH;\t\r  over\t\r  300\t\r  sites.\t\r   Conduct\t\r  analyses\t\r  of\t\r  existing\t\r  observations\t\r   §2.4.3\t\r  \nADAPT\t\r  (2011-­‐2015)\t\r  \n\u003c/p\u003e\n\u003cp\u003eMany\t\r  observational\t\r  sites\t\r  across\t\r  northern\t\r  Canada\t\r  to\t\r  identify\t\r  the\t\r  impacts\t\r  of\t\r  rapid\t\r  environmental\t\r  changes\t\r  underway\t\r  in\t\r  the\t\r  North\t\r  caused\t\r  by\t\r  thawing\t\r  permafrost.\t\r  \t\r  \nConduct\t\r  analyses\t\r  of\t\r  existing\t\r  and\t\r  new\t\r  observations.\t\r   §2.4.3\t\r  \n\u003c/p\u003e\n\u003cp\u003eHydrology\t\r  \n\u003c/p\u003e\n\u003cp\u003eDOE\t\r  ARM\t\r  Program\t\r   Campaign:\t\r  Barrow\t\r  Webcam\t\r  for\t\r  ITEX,\t\r  Sept\t\r  2009-­‐Aug\t\r  2012:\t\r  Daily\t\r  ground\t\r  views\t\r  to\t\r  observe\t\r  seasonal\t\r  surface\t\r  changes\t\r  such\t\r  as\t\r  onset\t\r  and\t\r  melt\t\r  of\t\r  snow\t\r  cover.\t\r   Conduct\t\r  data\t\r  analyses.\t\r   §2.4.2\t\r  \u003c/p\u003e\n\u003cp /\u003e\n\u003c/div\u003e\n\u003cdiv class\u003d\"page\"\u003e\u003cp /\u003e\n\u003cp\u003e\t\r  \u003c/p\u003e\n\u003cp\u003e\t\r   32\t\r  \n\u003c/p\u003e\n\u003cp\u003eABoVE\t\r  \nField\t\r  measurements,\t\r  watershed\t\r  scale:\t\r  soil\t\r  moisture,\t\r  precipitation,\t\r  snow\t\r  depth\t\r  and\t\r  SWE;\t\r  tower\t\r  eddy\t\r  covariance\t\r  measurements\t\r  of\t\r  land-­‐atmosphere\t\r  water/energy\t\r  fluxes;\t\r  water\t\r  isotopes;\t\r  stream\t\r  flow;\t\r  fine\t\r  scale\t\r  topography;\t\r  vertical\t\r  and\t\r  lateral\t\r  runoff\t\r  and\t\r  groundwater\t\r  flows;\t\r  water\t\r  chemistry.\t\r  \n\u003c/p\u003e\n\u003cp\u003eUpscale\t\r  with\t\r  remote\t\r  sensing\t\r  (RS)\t\r  and\t\r  flux\t\r  aircraft.\t\r   §4.1.3\t\r  \n\u003c/p\u003e\n\u003cp\u003eSatellite-­‐retrieved\t\r  Snow\t\r  products\t\r  (MODIS)\t\r   Products\t\r  available\t\r  from\t\r  NSIDC.\t\r  \nUpscale\t\r  characteristics\t\r  (density,\t\r  spatial\t\r  variability).\t\r  Develop\t\r  better\t\r  estimates\t\r  of\t\r  SWE.\t\r   §2.4.2\t\r  \n\u003c/p\u003e\n\u003cp\u003eSMAP\t\r  (2014)\t\r   Soil\t\r  moisture,\t\r  freeze/thaw\t\r  state\t\r   Use\t\r  observations\t\r  to\t\r  help\t\r  derive\t\r  parameterizations\t\r  of\t\r  permafrost\t\r  spatial\t\r  variability\t\r  as\t\r  a\t\r  function\t\r  of\t\r  the\t\r  physical\t\r  characteristics\t\r  of\t\r  the\t\r  land\t\r  surface.\t\r   §2.4.3\t\r  \nBiogeochemistry\t\r  \n\u003c/p\u003e\n\u003cp\u003eNGEE\t\r  \nExamining\t\r  whether\t\r  adequate\t\r  representation\t\r  of\t\r  biogeochemical\t\r  and\t\r  biophysical\t\r  processes\t\r  requires\t\r  sophisticated\t\r  representation\t\r  of\t\r  fine-­‐scale\t\r  covariance\t\r  of\t\r  vegetation,\t\r  hydrology,\t\r  and\t\r  thermal\t\r  regime\t\r  as\t\r  structured\t\r  by\t\r  geomorphology.\t\r  \n\u003c/p\u003e\n\u003cp\u003eUpscale,\t\r  high-­‐resolution\t\r  as\t\r  function\t\r  of\t\r  plant\t\r  type.\t\r  If\t\r  results\t\r  from\t\r  NGEE\t\r  over\t\r  limited\t\r  spatial\t\r  domains\t\r  confirm\t\r  their\t\r  hypothesis,\t\r  extend\t\r  effort\t\r  to\t\r  map\t\r  fine-­‐scale\t\r  geomorphological\t\r  variability.\t\r  \t\r  \n§2.4.5\t\r  \n\u003c/p\u003e\n\u003cp\u003eABoVE\t\r  \nLIDAR\t\r  and\t\r  SAR\t\r  characterize\t\r  vegetation\t\r  structure\t\r  and\t\r  biomass\t\r  changes\t\r  following\t\r  disturbance.\t\r  Field\t\r  measurements\t\r  study\t\r  factors\t\r  controlling\t\r  plant\t\r  community\t\r  structure\t\r  and\t\r  response\t\r  to\t\r  variations\t\r  in\t\r  permafrost\t\r  and\t\r  surface\t\r  hydrology.\t\r  Regional\t\r  soil\t\r  mapping;\t\r  use\t\r  RS\t\r  to\t\r  quantify\t\r  linkages\t\r  between\t\r  in\t\r  situ\t\r  soil\t\r  C\t\r  patterns\t\r  and\t\r  overlying\t\r  vegetation,\t\r  terrain\t\r  and\t\r  microclimate.\t\r  \n\u003c/p\u003e\n\u003cp\u003eCouple\t\r  to\t\r  pan-­‐ABZ\t\r  RS\t\r  effort\t\r  to\t\r  characterize\t\r  ABZ\t\r  vegetation,\t\r  soils,\t\r  hydrology,\t\r  etc.,\t\r  in\t\r  ESMs.\t\r   §2.4.5\t\r  \n\u003c/p\u003e\n\u003cp\u003eHeritage\t\r  sites\t\r  (e.g.,\t\r  BOREAS,\t\r  BERMS,\t\r  ABLE-­‐3A,\t\r  3B)\t\r   Previous\t\r  field\t\r  experiment\t\r  sites\t\r  in\t\r  Canada\t\r  and\t\r  Alaska\t\r  \nRevisit\t\r  using\t\r  a\t\r  combination\t\r  of\t\r  flux\t\r  tower\t\r  and\t\r  aircraft-­‐based\t\r  flux\t\r  measurements;\t\r  add\t\r  some\t\r  “new”\t\r  sites\t\r  -­‐\t\r  determine\t\r  how\t\r  to\t\r  do\t\r  temporal\t\r  and\t\r  spatial\t\r  scaling\t\r  of\t\r  non-­‐linear\t\r  disturbance\t\r  effects\t\r  on\t\r  carbon,\t\r  energy\t\r  and\t\r  water.\t\r  Assess\t\r  changes\t\r  since\t\r  previous\t\r  studies.\t\r  \n\u003c/p\u003e\n\u003cp\u003e§4.1.3\t\r  §4.1.4\t\r  \n\t\r  \t\r  \u003c/p\u003e\n\u003cp /\u003e\n\u003c/div\u003e\n\u003cdiv class\u003d\"page\"\u003e\u003cp /\u003e\n\u003cp\u003e\t\r  \u003c/p\u003e\n\u003cp\u003e\t\r   33\t\r  \n\u003c/p\u003e\n\u003cp\u003eOcean\t\r  \u0026amp;\t\r  Sea\t\r  Ice\t\r  \n\u003c/p\u003e\n\u003cp\u003eObservational\t\r  \nActivity\t\r   Details\t\r  \n\u003c/p\u003e\n\u003cp\u003eProposed\t\r  Supplements\t\r  \n(shown\t\r  in\t\r  blue)\t\r  and\t\r  New\t\r  \nActivities\t\r  (shown\t\r  in\t\r  red)\t\r  \n\u003c/p\u003e\n\u003cp\u003eReference\t\r  \n\u003c/p\u003e\n\u003cp\u003eSHEBA\t\r  (1997-­‐1998)\t\r   Concurrent\t\r  measurement\t\r  of\t\r  the\t\r  atmosphere,\t\r  sea\t\r  ice\t\r  and\t\r  upper\t\r  ocean,\t\r  including\t\r  air-­‐ice,\t\r  ice-­‐ocean,\t\r  and\t\r  air-­‐ocean\t\r  fluxes.\t\r   Contribute\t\r  to\t\r  MOSAiC,\t\r  particularly\t\r  with\t\r  observations\t\r  focused\t\r  on\t\r  the\t\r  Western\t\r  Arctic.\t\r  \t\r  Coordinate\t\r  multi-­‐scale\t\r  ecosystem\t\r  observations\t\r  with\t\r  complementary\t\r  modeling\t\r  to\t\r  facilitate\t\r  upscaling\t\r  information\t\r  from\t\r  small-­‐scale\t\r  observations.\t\r  \n\u003c/p\u003e\n\u003cp\u003e§2.1\t\r  §2.3\t\r  \t\r  §4.1.1\t\r  §4.1.2\t\r  §4.1.3\t\r  MOSAiC\t\r  (~\t\r  2017)\t\r  (Follow-­‐up\t\r  to\t\r  SHEBA)\t\r  \n\u003c/p\u003e\n\u003cp\u003eScientific\t\r  emphasis:\t\r  processes\t\r  that\t\r  transfer\t\r  heat,\t\r  moisture,\t\r  density,\t\r  and\t\r  momentum\t\r  through\t\r  the\t\r  system.\t\r  Proposed\t\r  observations:\t\r  a\t\r  manned,\t\r  transpolar\t\r  drifting\t\r  observatory\t\r  for\t\r  intensive\t\r  observations\t\r  of\t\r  atmospheric,\t\r  oceanic,\t\r  and\t\r  sea-­‐ice\t\r  properties\t\r  over\t\r  1-­‐2-­‐year\t\r  timeframe.\t\r  \t\r  Expand\t\r  to\t\r  larger\t\r  spatial\t\r  scales\t\r  with\t\r  a\t\r  network\t\r  of\t\r  buoys,\t\r  unmanned\t\r  aerial\t\r  systems,\t\r  autonomous\t\r  underwater\t\r  vehicles,\t\r  ships,\t\r  aircraft,\t\r  and\t\r  satellites.\t\r  Satellite-­‐derived\t\r  sea-­‐ice\t\r  extent\t\r  (AMSR-­‐E;\t\r  SSMI/S)\t\r   Products\t\r  available\t\r  from\t\r  NSIDC.\t\r   4DDA\t\r  products\t\r  for\t\r  integrated\t\r  view\t\r  of\t\r  variations\t\r  and\t\r  surface\t\r  flux\t\r  estimates.\t\r   §4.5.1\t\r  §4.5.4\t\r  CryoSAT-­‐2,\t\r  IceSAT-­‐2\t\r  (2016)\t\r   Satellite-­‐derived\t\r  sea-­‐ice\t\r  thickness.\t\r   Use\t\r  IceBridge\t\r  measurements\t\r  of\t\r  opportunity\t\r  for\t\r  validation.\t\r   §2.2\t\r  \t\r  \nIntegrated\t\r  Systems\t\r  \n\u003c/p\u003e\n\u003cp\u003eObservational\t\r  \nActivity\t\r   Details\t\r  \n\u003c/p\u003e\n\u003cp\u003eProposed\t\r  Supplements\t\r  \n(shown\t\r  in\t\r  blue)\t\r  and\t\r  New\t\r  \nActivities\t\r  (shown\t\r  in\t\r  red)\t\r  \n\u003c/p\u003e\n\u003cp\u003eReference\t\r  \n\u003c/p\u003e\n\u003cp\u003eGlobal\t\r  Rivers\t\r  Project\t\r  \nCharacterize\t\r  the\t\r  sources,\t\r  pathways\t\r  and\t\r  timescales\t\r  of\t\r  riverine\t\r  export\t\r  of\t\r  organic\t\r  and\t\r  inorganic\t\r  carbon\t\r  from\t\r  land\t\r  to\t\r  ocean.\t\r  Two\t\r  rivers\t\r  (Lena,\t\r  Kolyma)\t\r  in\t\r  Arctic\t\r  basin.\t\r  \n\u003c/p\u003e\n\u003cp\u003eExtend\t\r  to\t\r  rivers\t\r  in\t\r  Canadian\t\r  Basin.\t\r   §4.4\t\r  \t\r  \nNSF-­‐OPP\t\r  Soil\t\r  fluxes\t\r  \t\r  \t\r  (water,\t\r  C,\t\r  N…)\t\r   Fluxes\t\r  of\t\r  water,\t\r  carbon,\t\r  nutrients\t\r  from\t\r  soils\t\r  as\t\r  function\t\r  of\t\r  climate\t\r  and\t\r  land\t\r  surface\t\r  \t\r   Upscale\t\r  with\t\r  RS/flux\t\r  aircraft.\t\r   §2.6.2\t\r  \nDOE\t\r  ARM\t\r  Program\t\r   Campaign:\t\r  Sea\t\r  Ice\t\r  Effect\t\r  on\t\r  Arctic\t\r  Precipitation,\t\r  2011-­‐2013:\t\r  oxygen\t\r  and\t\r  hydrogen\t\r  isotopic\t\r  compositions\t\r  in\t\r  precipitation\t\r  collected\t\r  at\t\r  Barrow\t\r  and\t\r  Atqasuk.\t\r  \n\u003c/p\u003e\n\u003cp\u003eCompare\t\r  with\t\r  integrative\t\r  reanalyses.\t\r   §4.5.4\t\r  \t\r  \u003c/p\u003e\n\u003cp /\u003e\n\u003c/div\u003e\n\u003cdiv class\u003d\"page\"\u003e\u003cp /\u003e\n\u003cp\u003e\t\r  \u003c/p\u003e\n\u003cp\u003e\t\r   34\t\r  \n\u003c/p\u003e\n\u003cp\u003e4.4 Other\t\r  Activities\t\r  \n\u003c/p\u003e\n\u003cp\u003e4.4.1 Model\t\r  development,\t\r  diagnostics,\t\r  and\t\r  assimilation\t\r  Even\t\r   before\t\r   targeted\t\r   field\t\r   campaigns\t\r   are\t\r   planned,\t\r   it\t\r   is\t\r   important\t\r   to\t\r   recognize\t\r   that\t\r   there\t\r   are\t\r  deficiencies\t\r   in\t\r   models\t\r   that\t\r   can\t\r   and\t\r   should\t\r   be\t\r   addressed\t\r   with\t\r   model\t\r   development\t\r   activities.\t\r  Examples\t\r   include\t\r   the\t\r   development\t\r   of\t\r   cloud\t\r   microphysics\t\r   parameterizations,\t\r   the\t\r   better\t\r  representation\t\r   and\t\r   parameterization\t\r   of\t\r   small\t\r   scale\t\r   terrestrial\t\r   geomorphology\t\r   for\t\r   the\t\r   relatively\t\r  larger\t\r  scale\t\r  atmospheric\t\r  model\t\r  grids,\t\r   improvements\t\r  of\t\r  old\t\r  parameterizations\t\r  or\t\r   the\t\r   introduction\t\r  of\t\r   new\t\r   parameterizations\t\r   to\t\r   keep\t\r   up\t\r   with\t\r   the\t\r   continuing\t\r   evolution\t\r   of\t\r   models\t\r   toward\t\r   higher\t\r  horizontal\t\r  and\t\r  vertical\t\r  resolution,\t\r  and\t\r  the\t\r  need\t\r  for\t\r  improvements\t\r  in\t\r  the\t\r  representation\t\r  of\t\r  both\t\r  the\t\r  atmospheric\t\r  and\t\r  oceanic\t\r  planetary\t\r  boundary\t\r  layer.\t\r  The\t\r  models\t\r  undoubtedly\t\r  need\t\r  much\t\r  increased\t\r  vertical\t\r  resolution,\t\r  but\t\r  this\t\r  will\t\r  only\t\r  be\t\r  useful\t\r  with\t\r  improved\t\r  parameterizations\t\r  of\t\r  turbulence\t\r  and\t\r  clouds.\t\r  \nCloud\t\r  and\t\r  aerosol\t\r  microphysics\t\r  Development\t\r   of\t\r   cloud\t\r   microphysics\t\r   parameterizations\t\r   to\t\r   represent\t\r   super-­‐cooled\t\r   liquid,\t\r   mixed-­‐phase\t\r  and\t\r  ice\t\r  clouds,\t\r  and\t\r  of\t\r  cloud-­‐aerosol\t\r  interactions\t\r  at\t\r  the\t\r  microphysical\t\r  level\t\r  is\t\r  a\t\r  priority.\t\r  The\t\r  ARM\t\r   program\t\r   aims\t\r   to\t\r   get\t\r   better\t\r   observations\t\r   of\t\r   ice\t\r   properties\t\r   (see\t\r   draft\t\r   white\t\r   paper\t\r   on\t\r   Ice\t\r  Physical\t\r   and\t\r   Radiative\t\r   Properties\t\r   focus\t\r   group\t\r   at\t\r   http://asr.science.energy.gov/science/working-­‐groups/focus-­‐groups).\t\r  As\t\r   a\t\r   first\t\r   step,\t\r   they\t\r   plan\t\r   analysis\t\r   of\t\r   existing\t\r   observations,\t\r   including\t\r   new\t\r  observations\t\r   at\t\r   Barrow,\t\r   to\t\r   characterize\t\r   the\t\r   probability\t\r   distribution\t\r   of\t\r   ice\t\r   particle\t\r   properties\t\r   in\t\r  terms\t\r  of\t\r  other\t\r  properties\t\r  (such\t\r  as\t\r  temperature,\t\r  cloud\t\r  type,\t\r  etc.).\t\r  Activities\t\r  like\t\r  this\t\r  need\t\r  to\t\r  be\t\r  given\t\r  priority\t\r  and\t\r  new\t\r  observational\t\r  needs\t\r  must\t\r  be\t\r  identified.\t\r  \nLand\t\r  Surface\t\r  Model\t\r  Developments\t\r  Land\t\r   surface\t\r  models\t\r   aim\t\r   to\t\r   produce\t\r   an\t\r   accurate\t\r   large-­‐scale\t\r   description\t\r   of\t\r   snow\t\r   behavior\t\r   using\t\r  only\t\r  a\t\r  handful\t\r  of\t\r  snow\t\r  variables;\t\r  this\t\r  is\t\r  made\t\r  difficult\t\r  by\t\r  the\t\r  fact\t\r  that\t\r  in\t\r  nature,\t\r  the\t\r  evolution\t\r  of\t\r  a\t\r  snowpack\t\r   is\t\r   strongly\t\r   affected\t\r   by\t\r   spatial\t\r   variability\t\r   in\t\r   snow\t\r   at\t\r   scales\t\r   not\t\r   resolved\t\r   by\t\r   the\t\r  model.\t\r  \t\r  Similarly,\t\r   land\t\r  models\t\r  attempt\t\r   to\t\r   reproduce\t\r   the\t\r   surface\t\r  and\t\r  energy\t\r  water\t\r  balances\t\r  accurately\t\r  at\t\r  the\t\r   large\t\r   scale\t\r   without\t\r   resolving\t\r   explicitly\t\r   key\t\r   spatial\t\r   variations\t\r   in\t\r   soil\t\r   water\t\r   and\t\r   temperature\t\r  variables.\t\r  \t\r  In\t\r  principle,\t\r  the\t\r  models\t\r  can\t\r  function\t\r  adequately\t\r  with\t\r  their\t\r  coarse\t\r  resolution\t\r  by\t\r  properly\t\r  parameterizing\t\r   the\t\r   effects\t\r   of\t\r   the\t\r  unresolved\t\r   variability.\t\r   \t\r   The\t\r  parameterizations\t\r   in\t\r  models\t\r   today,\t\r  however,\t\r   are\t\r   very\t\r   crude,\t\r   largely\t\r   due\t\r   to\t\r   a\t\r   paucity\t\r   of\t\r   the\t\r   surface\t\r   observations\t\r   needed\t\r   to\t\r   support\t\r  their\t\r   development.\t\r   More\t\r   basic\t\r   research\t\r   based\t\r   on\t\r   in-­‐situ\t\r   measurements\t\r   is\t\r   needed\t\r   to\t\r   improve\t\r  macroscale\t\r   land\t\r  surface\t\r  model\t\r  representations\t\r  of\t\r  energy,\t\r  water,\t\r  and\t\r  snow\t\r  processes.\t\r  Better\t\r  BGC\t\r  component\t\r   models\t\r   are\t\r   also\t\r   needed,\t\r   e.g.,\t\r   a\t\r   better\t\r   phenological\t\r   model\t\r   and\t\r   improved\t\r   ability\t\r   to\t\r  represent\t\r   the\t\r   treeline.\t\r  DVGMs\t\r  may\t\r  also\t\r  need\t\r   improved\t\r   treatment\t\r  of\t\r  plant\t\r  diversity\t\r   and\t\r  a\t\r  better\t\r  mechanistic\t\r   treatment\t\r   of\t\r   migration\t\r   and\t\r   competition\t\r   among\t\r   plant\t\r   types.\t\r   Fire\t\r   emissions\t\r   and\t\r  disturbance\t\r   severity\t\r   need\t\r   to\t\r   be\t\r   represented.\t\r   Improving\t\r   permafrost\t\r   models\t\r   by\t\r   integrating\t\r  thermokarst\t\r   and\t\r   other\t\r   disturbances\t\r   is\t\r   necessary\t\r   to\t\r   better\t\r   quantify\t\r   and\t\r   predict\t\r   the\t\r   impact\t\r   of\t\r  disturbances\t\r   on\t\r   northern\t\r   high-­‐latitude\t\r   SOC\t\r   pools.\t\r   Several\t\r   model\t\r   developments\t\r   are\t\r   needed\t\r   to\t\r  improve\t\r   the\t\r   representation\t\r   of\t\r   the\t\r   impact\t\r   of\t\r   land\t\r   surface\t\r   hydrology\t\r   on\t\r   the\t\r   carbon\t\r   cycle.\t\r   Surface\t\r  lakes/wetlands/floodplain\t\r  inundation\t\r  should\t\r  also\t\r  be\t\r  included\t\r  in\t\r  the\t\r  land\t\r  models.\t\r  \nVertical\t\r  resolution\t\r  in\t\r  AGCMs\t\r  Observations\t\r   show\t\r   that\t\r   the\t\r  Arctic\t\r   atmosphere\t\r   has\t\r  many\t\r   important\t\r   structures\t\r   that\t\r   are\t\r   very\t\r   thin\t\r  vertically.\t\r  These\t\r   include\t\r   the\t\r   turbulent\t\r  boundary\t\r   layer,\t\r   cloud\t\r   layers,\t\r   and\t\r   inversions.\t\r  High\t\r  vertical\t\r  resolution\t\r   is\t\r  needed\t\r   in\t\r  a\t\r  model\t\r   that\t\r  resolves\t\r   these\t\r   features,\t\r  but\t\r  high\t\r  vertical\t\r   resolution\t\r   is\t\r  useful\t\r  \u003c/p\u003e\n\u003cp /\u003e\n\u003c/div\u003e\n\u003cdiv class\u003d\"page\"\u003e\u003cp /\u003e\n\u003cp\u003e\t\r  \u003c/p\u003e\n\u003cp\u003e\t\r   35\t\r  \n\u003c/p\u003e\n\u003cp\u003eonly\t\r   when\t\r   the\t\r   physical\t\r   parameterizations\t\r   are\t\r   sufficiently\t\r   realistic.\t\r   Therefore\t\r   increasing\t\r   vertical\t\r  resolution\t\r  should\t\r  be\t\r  accompanied\t\r  by\t\r  improvements\t\r  in\t\r  parameterizations.\t\r  \nHorizontal\t\r  resolution\t\r  in\t\r  OGCMs\t\r  and\t\r  Sea-­‐Ice\t\r  Models\t\r  Maslowski\t\r   et\t\r   al.\t\r   (2008)\t\r   show\t\r   that\t\r   significant\t\r   improvements\t\r   in\t\r   ocean\t\r   and\t\r   sea-­‐ice\t\r   models\t\r   are\t\r  realized\t\r   by\t\r   increasing\t\r   resolution.\t\r   Better\t\r   representation\t\r   of\t\r   bathymetry\t\r   due\t\r   to\t\r   higher\t\r   resolution\t\r  both\t\r  in\t\r  the\t\r  horizontal\t\r  and\t\r  vertical\t\r  improves\t\r  the\t\r  simulation\t\r  of\t\r  topographically\t\r  steered\t\r  flows,\t\r  which\t\r  in\t\r   the\t\r   case\t\r   of\t\r   the\t\r   Barents\t\r   Sea\t\r   and\t\r   other\t\r   coastal\t\r   areas\t\r   can\t\r   change\t\r   the\t\r   representation\t\r   of\t\r   ocean\t\r  circulation\t\r  as\t\r  well\t\r  as\t\r  regional\t\r  distribution\t\r  and\t\r  transformation\t\r  of\t\r  water\t\r  masses.\t\r  Validation\t\r  of\t\r  model\t\r  results\t\r  against\t\r  observations\t\r   (Maslowski\t\r  and\t\r  Walczowski;\t\r  2002;\t\r  McGeehan\t\r  and\t\r  Maslowski,\t\r  2012)\t\r  indicate\t\r  that\t\r  high\t\r  horizontal\t\r  resolution\t\r  is\t\r  required\t\r  to\t\r  properly\t\r  represent\t\r  buoyancy-­‐driven\t\r  narrow\t\r  coastal\t\r   currents\t\r   (e.g.,\t\r   Alaska\t\r   Coastal\t\r   Current\t\r   or\t\r   Norwegian\t\r   Coastal\t\r   Current),\t\r   small-­‐scale\t\r  bathymetry\t\r   (e.g.,\t\r   Bering\t\r   Strait\t\r   Barrow\t\r   Canyon),\t\r   and\t\r   land\t\r   futures\t\r   (e.g.,\t\r   passages\t\r   through\t\r   the\t\r  Canadian\t\r  Arctic\t\r  Archipelago).\t\r  \t\r  \n4DDA\t\r  Analyses\t\r  Analyses\t\r  generated\t\r   through\t\r  data\t\r  assimilation\t\r  are\t\r  an\t\r   important\t\r  part\t\r  of\t\r   the\t\r   tool\t\r   set\t\r   for\t\r  advancing\t\r  understanding\t\r   of\t\r   the\t\r   Arctic\t\r   region.\t\r   With\t\r   adequate\t\r   observations,\t\r   assimilation\t\r   analyses\t\r   help\t\r   to\t\r  characterize\t\r  the\t\r  state\t\r  of\t\r  the\t\r  ABZ\t\r  and\t\r  provide\t\r  an\t\r  assessment\t\r  of\t\r  the\t\r  quality\t\r  and\t\r  consistency\t\r  of\t\r  model\t\r  components\t\r   with\t\r   respect\t\r   to\t\r   the\t\r   observations.\t\r   Through\t\r   the\t\r   direct\t\r   confrontation\t\r   of\t\r   models\t\r   with\t\r  observations,\t\r   assimilation\t\r   also\t\r   has\t\r   the\t\r   potential\t\r   for\t\r   guiding\t\r   model\t\r   development\t\r   or\t\r   improving\t\r  parameter\t\r  choices.\t\r  It\t\r  can\t\r  also\t\r  help\t\r  determine\t\r  the\t\r  optimal\t\r  choice\t\r  of\t\r  field\t\r  experiments\t\r  (surface\t\r  and\t\r  aircraft\t\r  observations)\t\r  to\t\r  help\t\r  evaluate\t\r  and\t\r  constrain\t\r  the\t\r  uncertain\t\r  model\t\r  processes.\t\r  \n4.4.2 Observations:\t\r  analyses,\t\r  data\t\r  products\t\r  and\t\r  data\t\r  mining\t\r  A\t\r  comprehensive\t\r  satellite\t\r  collection\t\r  and\t\r  analysis\t\r  effort\t\r  should\t\r  be\t\r  implemented\t\r  for\t\r  the\t\r  entire\t\r  ABZ.\t\r  These\t\r   data\t\r   (including\t\r   the\t\r   complete\t\r   available\t\r   historical\t\r   data\t\r   archive)\t\r   will\t\r   be\t\r   used\t\r   for\t\r   a\t\r   better\t\r  characterization\t\r  of\t\r  PCS\t\r  and\t\r  BGC\t\r  parameters\t\r  in\t\r  ESMs\t\r  and\t\r  for\t\r  experimental\t\r  validation.\t\r  \t\r  This\t\r  applies\t\r  particularly\t\r  to\t\r  land\t\r  surface\t\r  parameters.\t\r  \t\r  \t\r  A\t\r  survey\t\r  of\t\r  other\t\r  available\t\r  data\t\r  sets\t\r  should\t\r  be\t\r  a\t\r  priority,\t\r  with\t\r  provision\t\r  of\t\r  a\t\r  central\t\r  access\t\r  site\t\r  to\t\r  those\t\r  data\t\r  that\t\r  will\t\r  be\t\r  used\t\r  by\t\r  models\t\r  either\t\r  for\t\r  ingestion\t\r  or\t\r  validation.\t\r  New\t\r  data\t\r  products\t\r  as\t\r  well\t\r  as\t\r   analyses\t\r   of\t\r   existing\t\r   products\t\r   should\t\r   be\t\r   undertaken\t\r   to\t\r   bring\t\r   new\t\r   insight\t\r   to\t\r   ABZ\t\r   questions.\t\r  Providing\t\r  easy\t\r  access\t\r  to\t\r  model\t\r  output\t\r  for\t\r  analysis\t\r  or\t\r  comparison\t\r  by\t\r  interested\t\r  parties\t\r  will\t\r  also\t\r  be\t\r  necessary.\t\r   A\t\r   valuable\t\r   addition\t\r  would\t\r   be\t\r   a\t\r   data\t\r   repository\t\r   specifically\t\r   for\t\r  model\t\r   calibration\t\r   and\t\r  validation\t\r  with\t\r  site-­‐specific\t\r  data\t\r  in\t\r  complementary\t\r  formats\t\r  of\t\r  all\t\r  available\t\r  biophysical\t\r  variables.\t\r  New\t\r  data\t\r  products\t\r  that\t\r  would\t\r  be\t\r  useful\t\r  include:\t\r  \n\u003c/p\u003e\n\u003cp\u003e• Improved\t\r  vegetation\t\r  data\t\r  sets;\t\r  \n• Map\t\r  of\t\r  soil\t\r  properties\t\r  across\t\r  the\t\r  ABZ\t\r  using\t\r  satellite\t\r  data,\t\r  the\t\r  available\t\r  sparse\t\r  in-­‐situ\t\r  data\t\r  sets,\t\r  and\t\r  modeling;\t\r  \n• Better\t\r  records\t\r  of\t\r  past\t\r  disturbance\t\r  –\t\r  perhaps\t\r  from\t\r  the\t\r  Landsat\t\r  record\t\r  –\t\r  particularly\t\r  for\t\r  northern\t\r  Eurasia;\t\r  \n• Change\t\r  and\t\r  disturbance\t\r  mapping;\t\r  \n• Near-­‐surface\t\r  hourly\t\r  weather\t\r  drivers,\t\r  at\t\r  the\t\r  highest\t\r  resolution\t\r  possible,\t\r  for\t\r  multiple\t\r  decades;\t\r  \n• Characterization\t\r  of\t\r  fresh\t\r  snow\t\r  density.\t\r  \n\u003c/p\u003e\n\u003cp\u003e\t\r  \u003c/p\u003e\n\u003cp /\u003e\n\u003c/div\u003e\n\u003cdiv class\u003d\"page\"\u003e\u003cp /\u003e\n\u003cp\u003e\t\r  \u003c/p\u003e\n\u003cp\u003e\t\r   36\t\r  \n\u003c/p\u003e\n\u003cp\u003e4.4.3 Model\t\r  input\t\r  to\t\r  planning\t\r  of\t\r  new\t\r  observations\t\r  and\t\r  field\t\r  campaigns\t\r  Modeling\t\r   studies,\t\r   either\t\r   unconstrained\t\r   simulation\t\r   or\t\r   data-­‐constrained\t\r   assimilation\t\r   analyses,\t\r   can\t\r  help\t\r   to\t\r   refine\t\r   measurement\t\r   needs.\t\r   For\t\r   example,\t\r   simulations\t\r   that\t\r   quantify\t\r   the\t\r   uncertainty\t\r   in\t\r  transport\t\r   and\t\r   the\t\r   relation\t\r   to\t\r   surface\t\r   emissions\t\r   and\t\r   spatiotemporal\t\r   variability\t\r   can\t\r   be\t\r   used\t\r   to\t\r  identify\t\r   the\t\r   requirements\t\r   (number\t\r  and\t\r  sites)\t\r   for\t\r  an\t\r  expanded\t\r  ground-­‐based\t\r  network\t\r   to\t\r  monitor\t\r  long-­‐term\t\r   changes\t\r   in\t\r   carbon\t\r   flux\t\r   and\t\r   storage.\t\r   Data\t\r   assimilation,\t\r   which\t\r   can\t\r   be\t\r   used\t\r   to\t\r   infer\t\r  unobserved\t\r   parameters\t\r   from\t\r   limited\t\r   observations\t\r   (such\t\r   as\t\r   column-­‐integrated\t\r   CO2),\t\r   can\t\r   be\t\r   used\t\r  with\t\r  samples\t\r  extracted\t\r  from\t\r  high-­‐resolution\t\r  simulations\t\r  to\t\r  determine\t\r  the\t\r  satellite\t\r  measurements\t\r  best\t\r   suited\t\r   to\t\r  observing\t\r  spatial\t\r  and\t\r  shorter\t\r   term\t\r  (seasonal\t\r   to\t\r   interannual)\t\r  variability\t\r   in\t\r  CO2\t\r  and\t\r  CH4\t\r  fluxes\t\r   and\t\r   concentrations.\t\r   Sampling\t\r   studies\t\r   using\t\r   high-­‐resolution\t\r   simulations\t\r   could\t\r   also\t\r   be\t\r  used\t\r  to\t\r  identify\t\r  the\t\r  types\t\r  of\t\r  field\t\r  campaigns\t\r  that\t\r  best\t\r  support\t\r  model\t\r  testing\t\r  and\t\r  what\t\r  observations\t\r  are\t\r  needed\t\r  to\t\r  provide\t\r  a\t\r  comprehensive,\t\r  short\t\r  term\t\r  view\t\r  of\t\r  regional\t\r  carbon\t\r  fluxes,\t\r  examining\t\r  (for\t\r  example)\t\r  the\t\r  benefits\t\r  of\t\r  potential\t\r  UAV\t\r  observations\t\r  versus\t\r  conventional\t\r  in-­‐situ\t\r  aircraft\t\r  sampling.\t\r  \n4.4.4 \t\r  Integrative\t\r  assessments\t\r  The\t\r   balance\t\r   between\t\r   the\t\r   opposing\t\r   processes\t\r   of\t\r   increased\t\r   carbon\t\r   capture\t\r   and\t\r   release\t\r   will\t\r  determine\t\r  future\t\r  changes\t\r  in\t\r  the\t\r  carbon\t\r  feedbacks\t\r  from\t\r  Arctic-­‐Boreal\t\r  ecosystems\t\r  to\t\r  global\t\r  climate.\t\r  However,\t\r  there\t\r  are\t\r  large\t\r  uncertainties\t\r  in\t\r  calculating\t\r  this\t\r  balance\t\r  across\t\r  permafrost,\t\r  terrestrial\t\r  soil,\t\r  vegetation,\t\r  ocean,\t\r  and\t\r  freshwater\t\r  systems.\t\r  Integrative\t\r  assessments\t\r  are\t\r  urgently\t\r  needed\t\r  to\t\r  advance\t\r  state-­‐of-­‐the-­‐art\t\r  modeling.\t\r  An\t\r  important\t\r  step\t\r  forward\t\r  would\t\r  be\t\r  to\t\r  establish\t\r  an\t\r  Arctic-­‐Boreal\t\r  System\t\r  Synthesis\t\r  Center.\t\r  At\t\r  a\t\r  minimum,\t\r  having\t\r  a\t\r  devoted\t\r  multi-­‐year\t\r  program\t\r  to\t\r  synthesize\t\r  and\t\r  integrate\t\r  the\t\r  numerous\t\r  previously\t\r  funded\t\r  Arctic-­‐Boreal\t\r  projects\t\r  would\t\r  yield\t\r  an\t\r  advanced\t\r  understanding\t\r  of\t\r  feedback\t\r   and\t\r   scaling\t\r   processes\t\r   and\t\r   interactions.\t\r   The\t\r   effort\t\r   would\t\r   include\t\r   ABLE,\t\r   BOREAS,\t\r  ICESCAPE,\t\r   IceBridge,\t\r  ARCTAS,\t\r  etc.,\t\r   the\t\r   integration\t\r  of\t\r  multiple\t\r  remotely\t\r  sensed\t\r  products\t\r   from\t\r  the\t\r  EOS\t\r   satellites,\t\r   and\t\r   other\t\r   resources.\t\r   In\t\r   either\t\r   case,\t\r   it\t\r   would\t\r   be\t\r   a\t\r   very\t\r   reasonable\t\r   investment\t\r   to\t\r  integrate\t\r  the\t\r  many\t\r  existing\t\r  parts\t\r  into\t\r  a\t\r  whole\t\r  and\t\r  discover\t\r  that\t\r  we\t\r  know\t\r  more\t\r  than\t\r  we\t\r  realized.\t\r  \t\r  \n5 Next\t\r  steps\t\r  This\t\r   report\t\r   is\t\r   the\t\r   outcome\t\r   of\t\r   a\t\r   small,\t\r   focused\t\r   workshop\t\r   funded\t\r   by\t\r   NASA/HQ\t\r   and\t\r   held\t\r   at\t\r   the\t\r  Goddard\t\r  Space\t\r  Flight\t\r  Center.\t\r  The\t\r  workshop\t\r  benefited\t\r  from\t\r  the\t\r   insights\t\r  gained\t\r  from\t\r  a\t\r  few\t\r  recent\t\r  workshops\t\r  and/or\t\r  planning\t\r  activities,\t\r  some\t\r  initiated\t\r  by\t\r  other\t\r  agencies.\t\r  The\t\r  recommendations\t\r  for\t\r  activities\t\r   –\t\r   field\t\r   campaigns,\t\r   data\t\r   analysis,\t\r   and\t\r  model\t\r   developments\t\r   –\t\r   are\t\r   priorities\t\r   identified\t\r   as\t\r  necessary\t\r   for\t\r   a\t\r   major\t\r   advance\t\r   in\t\r   our\t\r   predictive\t\r   modeling\t\r   capabilities.\t\r   However,\t\r   it\t\r   is\t\r   clear\t\r   that\t\r  these\t\r  proposed\t\r  activities\t\r  have\t\r   to\t\r  be\t\r  considered\t\r   in\t\r   the\t\r   light\t\r  of\t\r  activities\t\r   funded\t\r  by\t\r  other\t\r  agencies\t\r  and\t\r   would\t\r   both\t\r   leverage\t\r   those\t\r   activities\t\r   and\t\r   potentially\t\r   contribute\t\r   to\t\r   them.\t\r   Thus,\t\r   one\t\r   of\t\r   the\t\r  desired\t\r  steps\t\r  forward\t\r  is\t\r  the\t\r  formation\t\r  of\t\r  a\t\r  small\t\r  interdisciplinary,\t\r  interagency\t\r  team\t\r  to\t\r  1) Assess\t\r  current\t\r  and\t\r  planned\t\r  activities\t\r  in\t\r  the\t\r  context\t\r  of\t\r  this\t\r  and\t\r  other\t\r  study\t\r  reports,\t\r  and\t\r  2) Assess\t\r  priorities,\t\r  feasibility\t\r  and\t\r  resources\t\r  required\t\r  to\t\r  conduct\t\r  the\t\r  recommended\t\r  activities.\t\r  NASA\t\r  has\t\r  the\t\r  expertise\t\r  –\t\r  satellite\t\r  data,\t\r  field\t\r  campaigns,\t\r  and\t\r  models\t\r  –\t\r  to\t\r  lead\t\r  the\t\r  formation\t\r  of\t\r  such\t\r  a\t\r  team.\t\r  Although\t\r  careful\t\r  consideration\t\r  has\t\r  to\t\r  go\t\r  into\t\r  the\t\r  development\t\r  of\t\r  a\t\r  phased\t\r  plan\t\r  of\t\r  activities\t\r  and\t\r  the\t\r  required\t\r  funding\t\r  profiles,\t\r  several\t\r  activities\t\r  could\t\r  be\t\r  initiated\t\r  early\t\r  since\t\r  they\t\r  are\t\r  relatively\t\r  low-­‐cost\t\r   tasks\t\r   that\t\r   can\t\r   proceed\t\r   without\t\r   new\t\r   observations\t\r   and\t\r   can\t\r   provide\t\r   information\t\r   for\t\r  planning\t\r  campaigns\t\r  and\t\r  new\t\r  observational\t\r  sites.\t\r  These\t\r  tasks\t\r  inlcude\t\r  data\t\r  mining\t\r  and\t\r  analysis,\t\r  new\t\r  product\t\r  development,\t\r  data\t\r  assimilation\t\r  synthesis\t\r  of\t\r  existing\t\r  observations,\t\r  observing\t\r  system\t\r  design,\t\r  and\t\r  model\t\r  development.\t\r   \t\r  \u003c/p\u003e\n\u003cp /\u003e\n\u003c/div\u003e\n\u003cdiv class\u003d\"page\"\u003e\u003cp /\u003e\n\u003cp\u003e\t\r  \u003c/p\u003e\n\u003cp\u003e\t\r   37\t\r  \n\u003c/p\u003e\n\u003cp\u003e6 References\t\r  Alexander,\t\r  V.,\t\r  and\t\r  H.J.\t\r  Niebauer,\t\r  1981:\t\r  Oceanography\t\r  of\t\r  the\t\r  Eastern\t\r  Bering\t\r  Sea\t\r  ice-­‐edge\t\r  zone\t\r  in\t\r  Spring.\t\r  Limnol.\t\r  Oceanogr.,\t\r  26,\t\r  1111-­‐1125.\t\r  Arrigo,\t\r  K.R.,\t\r  P.A.\t\r  Matrai,\t\r  and\t\r  G.L.\t\r  van\t\r  Dijken,\t\r  2011:\t\r  Primary\t\r  productivity\t\r  in\t\r  the\t\r  Arctic\t\r  Ocean:\t\r  Impacts\t\r  of\t\r  complex\t\r  optical\t\r  properties\t\r  and\t\r  subsurface\t\r  chlorophyll\t\r  maxima\t\r  on\t\r  large-­‐scale\t\r  estimates.\t\r  J.\t\r  Geophys.\t\r  Res.,\t\r  116,\t\r  C11022,\t\r  doi:10.1029/2011JC007273.\t\r  Arrigo,\t\r  K.R.,\t\r  and\t\r  G.L.\t\r  van\t\r  Dijken,\t\r  2011:\t\r  Secular\t\r  trends\t\r  in\t\r  Arctic\t\r  Ocean\t\r  net\t\r  primary\t\r  production.\t\r  J.\t\r  \nGeophys.\t\r  Res.,\t\r  116,\t\r  C09011,\t\r  doi:10.1029/2011JC007151.\t\r  Arrigo,\t\r  K.,\t\r  and\t\r  co-­‐authors,\t\r  2012:\t\r  Massive\t\r  phytoplankton\t\r  blooms\t\r  under\t\r  Arctic\t\r  sea\t\r  ice.\t\r  Science,\t\r  336,\t\r  1408.\t\r  Avramov,\t\r  A.,\t\r  and\t\r  co-­‐authors,\t\r  2011:\t\r  Towards\t\r  ice\t\r  formation\t\r  closure\t\r  in\t\r  Arctic\t\r  mixed-­‐phase\t\r  boundary\t\r  layer\t\r  clouds\t\r  during\t\r  ISDAC.\t\r  J.\t\r  Geophys.\t\r  Res.,\t\r  116,\t\r  D00T08,\t\r  doi:10.1029/2011JD015910.\t\r  Balshi,\t\r  M.S.,\t\r  A.D.\t\r  McGuire,\t\r  P.\t\r  Duffy,\t\r  M.\t\r  Flannigan,\t\r  J.\t\r  Walsh,\t\r  and\t\r  J.\t\r  Melillo,\t\r  2009a:\t\r  Assessing\t\r  the\t\r  response\t\r  of\t\r  area\t\r  burned\t\r  to\t\r  changing\t\r  climate\t\r  in\t\r  western\t\r  boreal\t\r  North\t\r  America\t\r  using\t\r  a\t\r  Multivariate\t\r  Adaptive\t\r  Regression\t\r  Splines\t\r  (MARS)\t\r  approach.\t\r  Global\t\r  Change\t\r  Biol.,\t\r  15,\t\r  578-­‐600.\t\r  Balshi,\t\r  M.S.,\t\r  A.D.\t\r  McGuire,\t\r  P.\t\r  Duffy,\t\r  M.\t\r  Flannigan,\t\r  D.W.\t\r  Kicklighter,\t\r  and\t\r  J.\t\r  Mellilo,\t\r  2009b:\t\r  Vulnerability\t\r  of\t\r  carbon\t\r  storage\t\r  in\t\r  North\t\r  American\t\r  boreal\t\r  forests\t\r  to\t\r  wildfires\t\r  during\t\r  the\t\r  21st\t\r  Century.\t\r  Global\t\r  Change\t\r  Biol.,\t\r  15,\t\r  1491-­‐1510.\t\r  Barahona,\t\r  D.\t\r  2012:\t\r  On\t\r  the\t\r  ice\t\r  nucleation\t\r  spectrum.\t\r  Atmos.\t\r  Chem.\t\r  Phys.\t\r  12,\t\r  3733-­‐3752.\t\r  Betts,\t\r  A.K.,\t\r  and\t\r  J.H.\t\r  Ball,\t\r  1997:\t\r  Albedo\t\r  over\t\r  the\t\r  boreal\t\r  forest.\t\r  J.\t\r  Geophys.\t\r  Res.,\t\r  102,\t\r  28901-­‐28909.\t\r  Betts,\t\r  A.K.,\t\r  J.H.\t\r  Ball,\t\r  and\t\r  J.H.\t\r  McCaughey,\t\r  2001:\t\r  Near-­‐surface\t\r  climate\t\r  in\t\r  the\t\r  boreal\t\r  forest.\t\r  J.\t\r  Geophys.\t\r  \nRes.,\t\r  106,\t\r  33529-­‐33541.\t\r  Bhatt,\t\r  U.S.,\t\r  and\t\r  co-­‐authors,\t\r  2010:\t\r  Circumpolar\t\r  Arctic\t\r  tundra\t\r  vegetation\t\r  change\t\r  is\t\r  linked\t\r  to\t\r  sea-­‐ice\t\r  decline.\t\r  Earth\t\r  Interactions,\t\r  14,\t\r  1-­‐20,\t\r  doi:10.1175/2010EI315.1.\t\r  Boé\t\r  ,\t\r  J.,\t\r  A.\t\r  Hall,\t\r  and\t\r  X.\t\r  Qu,\t\r  2009:\t\r  Current\t\r  GCMs’\t\r  unrealistic\t\r  negative\t\r  feedback\t\r  in\t\r  the\t\r  Arctic.\t\r  J.\t\r  Climate,\t\r  \n22,\t\r  4682–4695.\t\r  \n\u003c/p\u003e\n\u003cp\u003eChan, M.A., and J.C. Comiso, 2011: Cloud features detected by MODIS but not by CloudSat and  \n         CALIOP. Geophys. Res. Letters, 38, 1-8. \t\r  \t\r  Chapin,\t\r  F.\t\r  S.,\t\r  III,\t\r  and\t\r  co-­‐authors,\t\r  2000:\t\r  Arctic\t\r  and\t\r  boreal\t\r  ecosystems\t\r  of\t\r  western\t\r  North\t\r  America\t\r  as\t\r  components\t\r  of\t\r  the\t\r  climate\t\r  system.\t\r  Global\t\r  Change\t\r  Biol.,\t\r  6,\t\r  211\t\r  –223.\t\r  Chevallier,\t\r  F.,\t\r  and\t\r  co-­‐authors,\t\r  2011:\t\r  Global\t\r  CO2\t\r  fluxes\t\r  inferred\t\r  from\t\r  surface\t\r  air-­‐sample\t\r  measurements\t\r  and\t\r  from\t\r  TCCON\t\r  retrievals\t\r  of\t\r  the\t\r  CO2\t\r  total\t\r  column.\t\r  Geophys.\t\r  Res.\t\r  Lett.,\t\r  38,\t\r  L24810,\t\r  doi:10.1029/2011GL049899.\t\r  \nComiso, J.C., 2012: Large decadal decline of the Arctic multiyear ice cover. J. Climate, 25, 1176-1193. \t\r  Curry,\t\r  J.A.,\t\r  W.B.\t\r  Rossow,\t\r  D.\t\r  Randall,\t\r  and\t\r  J.\t\r  L.\t\r  Schramm,\t\r  1996:\t\r  Overview\t\r  of\t\r  Arctic\t\r  cloud\t\r  and\t\r  radiation\t\r  characteristics.\t\r  J.\t\r  Climate,\t\r  9,\t\r  1731–1764.\t\r  Curry,\t\r  J.A.,\t\r  J.O.\t\r  Pinto,\t\r  T.\t\r  Benner,\t\r  and\t\r  M.\t\r  Tschudi,\t\r  1997:\t\r  Evolution\t\r  of\t\r  the\t\r  cloudy\t\r  boundary\t\r  layer\t\r  during\t\r  the\t\r  autumnal\t\r  freezing\t\r  of\t\r  the\t\r  Beaufort\t\r  Sea.\t\r  J.\t\r  Geophys.\t\r  Res.,\t\r  102,\t\r  13\t\r  851–13\t\r  860.\t\r  Desjardins,\t\r  R.L.,\t\r  and\t\r  co-­‐authors,\t\r  1997:\t\r  Scaling\t\r  up\t\r  flux\t\r  measurements\t\r  for\t\r  the\t\r  boreal\t\r  forest\t\r  using\t\r  aircraft-­‐tower\t\r  combinations.\t\r  J.\t\r  Geophys.\t\r  Res.,\t\r  \t\r  102,\t\r  29,125-­‐29,133.\t\r  Ebbesmeyer,\t\r  C.C.,\t\r  D.R.\t\r  Cayan,\t\r  D.R.\t\r  McLain,\t\r  F.H.\t\r  Nichols,\t\r  D.H.\t\r  Peterson\t\r  and\t\r  K.T.\t\r  Redmond,\t\r  1991:\t\r  1976\t\r  step\t\r  in\t\r  the\t\r  Pacific\t\r  climate:\t\r  forty\t\r  environmental\t\r  changes\t\r  between\t\r  1968–1975\t\r  and\t\r  1977–1984.\t\r  In:\t\r  J.L.\t\r  Betancourt\t\r  and\t\r  V.L.\t\r  Tharp\t\r  (eds).\t\r  Proceedings\t\r  of\t\r  the\t\r  Seventh\t\r  Annual\t\r  Pacific\t\r  \u003c/p\u003e\n\u003cp /\u003e\n\u003c/div\u003e\n\u003cdiv class\u003d\"page\"\u003e\u003cp /\u003e\n\u003cp\u003e\t\r  \u003c/p\u003e\n\u003cp\u003e\t\r   38\t\r  \n\u003c/p\u003e\n\u003cp\u003eClimate\t\r  (PACLIM)\t\r  Workshop,\t\r  April\t\r  1990.\t\r  California\t\r  Dept.\t\r  of\t\r  Water\t\r  Resources.\t\r  Interagency\t\r  Ecological\t\r  Studies\t\r  Program,\t\r  Technical\t\r  Report\t\r  26.\t\r  Eisenman,\t\r  I.,\t\r  N.\t\r  Untersteiner,\t\r  and\t\r  J.S.\t\r  Wettlaufer,\t\r  2007:\t\r  On\t\r  the\t\r  reliability\t\r  of\t\r  simulated\t\r  Arctic\t\r  sea\t\r  ice\t\r  in\t\r  global\t\r  climate\t\r  models.\t\r  Geophys.\t\r  Res.\t\r  Lett.,\t\r  34,\t\r  L10501,\t\r  doi:10.1029/2007GL029914.\t\r  Elliott,\t\r  S.,\t\r  C.\t\r  Deal,\t\r  G.\t\r  Humphries,\t\r  E.\t\r  Hunke,\t\r  N.\t\r  Jeffery,\t\r  M.\t\r  Jin,\t\r  M.\t\r  Levasseur,\t\r  and\t\r  J.\t\r  Stefels,\t\r  2012:\t\r  Pan-­‐Arctic\t\r  simulation\t\r  of\t\r  coupled\t\r  nutrient-­‐sulfur\t\r  cycling\t\r  due\t\r  to\t\r  sea\t\r  ice\t\r  biology:\t\r  Preliminary\t\r  results.\t\r  \nJ.\t\r  Geophys.\t\r  Res.,\t\r  117,\t\r  G01016,\t\r  doi:10.1029/2011JG001649.\t\r  Esau,\t\r  I.\t\r  and\t\r  S.\t\r  Zilitinkevich,\t\r  2010:\t\r  On\t\r  the\t\r  role\t\r  of\t\r  the\t\r  planetary\t\r  boundary\t\r  layer\t\r  depth\t\r  in\t\r  the\t\r  climate\t\r  system.\t\r  Adv.\t\r  Sci.\t\r  Res.,\t\r  4,\t\r  63–69,\t\r  doi:10.5194/asr-­‐4-­‐63-­‐2010.\t\r  Fisher,\t\r  J.A.,\t\r  and\t\r  co-­‐authors,\t\r  2011:\t\r  Sources,\t\r  distribution,\t\r  and\t\r  acidity\t\r  of\t\r  sulfate-­‐ammonium\t\r  aerosol\t\r  in\t\r  the\t\r  Arctic\t\r  in\t\r  winter-­‐spring.\t\r  Atmospheric\t\r  Environment,\t\r  45,\t\r  7301-­‐7318.\t\r  Fisher,\t\r  R.,\t\r  N.\t\r  McDowell,\t\r  D.\t\r  Purves,\t\r  P.\t\r  Moorcroft,\t\r  S.\t\r  Sitch,\t\r  P.\t\r  Cox,\t\r  C.\t\r  Huntingford,\t\r  P.\t\r  Meir,\t\r  F.I.\t\r  Woodward,\t\r  2010:\t\r  Assessing\t\r  uncertainties\t\r  in\t\r  a\t\r  second-­‐generation\t\r  dynamic\t\r  vegetation\t\r  model\t\r  due\t\r  to\t\r  ecological\t\r  scale\t\r  limitations.\t\r  New\t\r  Phytologist,\t\r  187,\t\r  666–681.\t\r  Flanner,\t\r  M.G.,\t\r  C.S.\t\r  Zender,\t\r  P.G.\t\r  Hess,\t\r  N.M.\t\r  Mahowald,\t\r  T.H.\t\r  Painter,\t\r  V.\t\r  Ramanathan,\t\r  V.,\t\r  and\t\r  P.J.\t\r  Rasch,\t\r  2009:\t\r  Springtime\t\r  warming\t\r  and\t\r  reduced\t\r  snow\t\r  cover\t\r  from\t\r  carbonaceous\t\r  particles.\t\r  Atmos.\t\r  \nChem.\t\r  Phys.,\t\r  9,\t\r  2481–2497,\t\r  doi:10.5194/acp-­‐9-­‐2481-­‐2009.\t\r  Fridlind,\t\r  A.M.,\t\r  A.S.\t\r  Ackerman,\t\r  G.\t\r  McFarquhar,\t\r  G.\t\r  Zhang,\t\r  M.R.\t\r  Poellot,\t\r  P.J.\t\r  DeMott,\t\r  A.J.\t\r  Prenni,\t\r  and\t\r  A.J.\t\r  Heymsfield,\t\r  2007:\t\r  Ice\t\r  properties\t\r  of\t\r  single-­‐layer\t\r  stratocumulus\t\r  during\t\r  the\t\r  Mixed-­‐Phase\t\r  Arctic\t\r  Cloud\t\r  Experiment\t\r  (M-­‐PACE):\t\r  Part\t\r  II,\t\r  Model\t\r  results.\t\r  J.\t\r  Geophys.\t\r  Res.,\t\r  112,\t\r  D24202,\t\r  doi:10.1029/2007JD008646.\t\r  Fridlind,\t\r  A.M.,\t\r  B.\t\r  van\t\r  Diedenhoven,\t\r  A.S.\t\r  Ackerman,\t\r  A.\t\r  Avramov,\t\r  A.\t\r  Mrowiec,\t\r  H.\t\r  Morrison,\t\r  P.\t\r  Zuidema,\t\r  and\t\r  M.D.\t\r  Shupe,\t\r  2012:\t\r  A\t\r  FIRE-­‐ACE/SHEBA\t\r  case\t\r  study\t\r  of\t\r  mixed-­‐phase\t\r  Arctic\t\r  boundary-­‐layer\t\r  clouds:\t\r  Entrainment\t\r  rate\t\r  limitations\t\r  on\t\r  rapid\t\r  primary\t\r  ice\t\r  nucleation\t\r  processes.\t\r  J.\t\r  Atmos.\t\r  Sci.,\t\r  69,\t\r  365-­‐389,\t\r  doi:10.1175/JAS-­‐D-­‐11-­‐052.1.\t\r  Friedlingstein,\t\r  P.,\t\r  and\t\r  co-­‐authors,\t\r  2006:\t\r  Results\t\r  from\t\r  the\t\r  C4MIP\t\r  model\t\r  intercomparison.\t\r  J.\t\r  Climate,\t\r  \n19,\t\r  3337–3353.\t\r  Frolking,\t\r  S.,\t\r  M.W.\t\r  Palace,\t\r  D.B.\t\r  Clark,\t\r  J.Q.\t\r  Chambers,\t\r  H.H.\t\r  Shugart,\t\r  and\t\r  G.C.\t\r  Hurtt,\t\r  2009:\t\r  Forest\t\r  disturbance\t\r  and\t\r  recovery:\t\r  A\t\r  general\t\r  review\t\r  in\t\r  the\t\r  context\t\r  of\t\r  spaceborne\t\r  remote\t\r  sensing\t\r  of\t\r  impacts\t\r  on\t\r  aboveground\t\r  biomass\t\r  and\t\r  canopy\t\r  structure.\t\r  J.\t\r  Geophys.\t\r  Res.,\t\r  114,\t\r  G00E02,\t\r  doi:10.1029/2008JG000911.\t\r  Frolking\t\r  S.,\t\r  J.\t\r  Talbot,\t\r  M.\t\r  Jones,\t\r  C.C.\t\r  Treat,\t\r  J.B.\t\r  Kauffman,\t\r  E.S.\t\r  Tuittila,\t\r  N.T.\t\r  Roulet,\t\r  2011:\t\r  \t\r  Peatlands\t\r  in\t\r  the\t\r  Earth’s\t\r  21st\t\r  century\t\r  climate\t\r  system.\t\r  Environ.\t\r  Rev.,\t\r  19,\t\r  371-­‐396.\t\r  Garrett,\t\r  T.J.,\t\r  S.\t\r  Brattström,\t\r  S.\t\r  Sharma,\t\r  D.E.J.\t\r  Worthy,\t\r  and\t\r  P.\t\r  Novelli,\t\r  2011:\t\r  The\t\r  role\t\r  of\t\r  scavenging\t\r  in\t\r  the\t\r  seasonal\t\r  transport\t\r  of\t\r  black\t\r  carbon\t\r  and\t\r  sulfate\t\r  to\t\r  the\t\r  Arctic.\t\r  Geophys.\t\r  Res.\t\r  Lett.,\t\r  38,\t\r  L16805,\t\r  doi:10.1029/2011GL048221.\t\r  \t\r  Glooschenko,\t\r  W.\t\r  A.,\t\r  and\t\r  co-­‐authors,\t\r  1994:\t\r  The\t\r  Northern\t\r  Wetlands\t\r  Study\t\r  (NOWES):\t\r  An\t\r  overview.\t\r  J.\t\r  \nGeophys.\t\r  Res.,\t\r  99,\t\r  1423-­‐1428.\t\r  Göckede,\t\r  M.,\t\r  A.M.\t\r  Michalak,\t\r  D.\t\r  Vickers,\t\r  D.P.\t\r  Turner,\t\r  and\t\r  B.E.\t\r  Law,\t\r  2010:\t\r  Atmospheric\t\r  inverse\t\r  modeling\t\r  to\t\r  constrain\t\r  regional-­‐scale\t\r  CO2\t\r  budgets\t\r  at\t\r  high\t\r  spatial\t\r  and\t\r  temporal\t\r  resolution.\t\r  J.\t\r  \nGeophys.\t\r  Res.,\t\r  115,\t\r  D15113,\t\r  doi:10.1029/2009JD012257.\t\r  Goetz,\t\r  S.J.,\t\r  M.C.\t\r  Mack,\t\r  K.R.\t\r  Gurkey,\t\r  J.T.\t\r  Randerson,\t\r  and\t\r  R.A.\t\r  Houghton,\t\r  2007:\t\r  Ecosystem\t\r  responses\t\r  to\t\r  recent\t\r  climate\t\r  change\t\r  and\t\r  fire\t\r  disturbance\t\r  at\t\r  northern\t\r  high\t\r  latitudes:\t\r  observations\t\r  and\t\r  model\t\r  results\t\r  contrasting\t\r  northern\t\r  Eurasia\t\r  and\t\r  North\t\r  America.\t\r  Environ.\t\r  Res.\t\r  Lett.,\t\r  2,\t\r  doi:10.1088/1748-­‐9326/2/4/045031.\t\r  \u003c/p\u003e\n\u003cp /\u003e\n\u003c/div\u003e\n\u003cdiv class\u003d\"page\"\u003e\u003cp /\u003e\n\u003cp\u003e\t\r  \u003c/p\u003e\n\u003cp\u003e\t\r   39\t\r  \n\u003c/p\u003e\n\u003cp\u003eGoetz,\t\r  S.J.,\t\r  and\t\r  co-­‐authors,\t\r  2012:\t\r  Observations\t\r  and\t\r  assessment\t\r  of\t\r  forest\t\r  carbon\t\r  dynamics\t\r  following\t\r  disturbance\t\r  in\t\r  North\t\r  America.\t\r  J.\t\r  Geophys.\t\r  Res.,\t\r  117,\t\r  G02022,\t\r  doi:10.1029/2011JG001733.\t\r  Gourdji,\t\r  S.M.,\t\r  A.I.\t\r  Hirsch,\t\r  K.L.\t\r  Mueller,\t\r  V.\t\r  Yadav,\t\r  A.E.\t\r  Andrews,\t\r  and\t\r  A.M.\t\r  Michalak,\t\r  2010:\t\r  Regional-­‐scale\t\r  geostatistical\t\r  inverse\t\r  modeling\t\r  of\t\r  North\t\r  American\t\r  CO_2\t\r  fluxes:\t\r  a\t\r  synthetic\t\r  data\t\r  study.\t\r  \nAtmos.\t\r  Chem.\t\r  Phys.,\t\r  10,\t\r  6151-­‐6167.\t\r  Gouttevin,\t\r  I.,\t\r  M.\t\r  Menegoz,\t\r  F.\t\r  Dominé,\t\r  G.\t\r  Krinner,\t\r  C.\t\r  Koven,\t\r  P.\t\r  Ciais,\t\r  C.\t\r  Tarnocai,\t\r  and\t\r  J.\t\r  Boike,\t\r  2012:\t\r  How\t\r  the\t\r  insulating\t\r  properties\t\r  of\t\r  snow\t\r  affect\t\r  soil\t\r  carbon\t\r  distribution\t\r  in\t\r  the\t\r  continental\t\r  pan-­‐Arctic\t\r  area.\t\r  J.\t\r  Geophys.\t\r  Res.,\t\r  117,\t\r  G02020,\t\r  doi:10.1029/2011JG001916.\t\r  Govind,\t\r  A.,\t\r  J.M.\t\r  Chen,\t\r  J.\t\r  McDonnell,\t\r  J.\t\r  Kumari,\t\r  and\t\r  O.\t\r  Sonnentag,\t\r  2011:\t\r  Effects\t\r  of\t\r  lateral\t\r  hydrological\t\r  processes\t\r  on\t\r  photosynthesis\t\r  and\t\r  evapotranspiration\t\r  in\t\r  a\t\r  boreal\t\r  ecosystem.\t\r  Ecohydrology,\t\r  4,\t\r  394-­‐410.\t\r  Grosse,\t\r  G.,\t\r  and\t\r  co-­‐authors,\t\r  2011:\t\r  Vulnerability\t\r  of\t\r  high-­‐latitude\t\r  soil\t\r  organic\t\r  carbon\t\r  in\t\r  North\t\r  America\t\r  to\t\r  disturbance.\t\r  J.\t\r  Geophys.\t\r  Res.,\t\r  116,\t\r  G00K06,\t\r  doi:10.1029/2010JG001507.\t\r  Hall,\t\r  F.G.,\t\r  D.B.\t\r  Botkin,\t\r  D.E.\t\r  Strebel,\t\r  K.D.\t\r  Woods,\t\r  and\t\r  S.J.\t\r  Goetz,\t\r  1991:\t\r  Large-­‐Scale\t\r  Patterns\t\r  of\t\r  Forest\t\r  Succession\t\r  as\t\r  Determined\t\r  by\t\r  Remote\t\r  Sensing.\t\r  Ecology,\t\r  72,\t\r  628–640,\t\r  http://dx.doi.org/10.2307/2937203\t\r  Hansen,\t\r  J.,\t\r  D.\t\r  Johnson,\t\r  A.\t\r  Lacis,\t\r  S.\t\r  Lebedeff,\t\r  P.\t\r  Lee,\t\r  D.\t\r  Rind,\t\r  and\t\r  G.\t\r  Russell,\t\r  1981:\t\r  Climate\t\r  impact\t\r  of\t\r  increasing\t\r  atmospheric\t\r  carbon\t\r  dioxide.\t\r  Science,\t\r  213,\t\r  957-­‐966,\t\r  doi:10.1126/science.213.4511.957.\t\r  Hansen,\t\r  J.,\t\r  A.\t\r  Lacis,\t\r  D.\t\r  Rind,\t\r  G.\t\r  Russell,\t\r  P.\t\r  Stone,\t\r  I.\t\r  Fung,\t\r  R.\t\r  Ruedy,\t\r  and\t\r  J.\t\r  Lerner,\t\r  1984:\t\r  Climate\t\r  sensitivity:\t\r  Analysis\t\r  of\t\r  feedback\t\r  mechanisms.\t\r  In\t\r  Climate\t\r  Processes\t\r  and\t\r  Climate\t\r  Sensitivity,\t\r  AGU\t\r  Geophysical\t\r  Monograph\t\r  29,\t\r  Maurice\t\r  Ewing\t\r  Vol.\t\r  5.\t\r  J.E.\t\r  Hansen\t\r  and\t\r  T.\t\r  Takahashi,\t\r  Eds.\t\r  American\t\r  Geophysical\t\r  Union,\t\r  pp.\t\r  130-­‐163.\t\r  Hansen,\t\r  J.,\t\r  R.\t\r  Ruedy,\t\r  M.\t\r  Sato,\t\r  and\t\r  K.\t\r  Lo,\t\r  2010:\t\r  Global\t\r  surface\t\r  temperature\t\r  change.\t\r  Rev.\t\r  Geophys.,\t\r  48,\t\r  RG4004,\t\r  doi:10.1029/2010RG000345.\t\r  Harden,\t\r  J.W.,\t\r  and\t\r  co-­‐authors,\t\r  2012:\t\r  Field\t\r  information\t\r  links\t\r  permafrost\t\r  carbon\t\r  to\t\r  physical\t\r  vulnerabilities\t\r  of\t\r  thawing.\t\r  Geophys.\t\r  Res.\t\r  Lett.,\t\r  39,\t\r  L15704,\t\r  doi:10.1029/2012GL051958.\t\r  Harriss,\t\r  R.C.,\t\r  and\t\r  co-­‐authors,\t\r  1992:\t\r  The\t\r  Arctic\t\r  Boundary\t\r  Layer\t\r  Expedition\t\r  (ABLE-­‐3A):\t\r  July-­‐August\t\r  1988.\t\r  J.\t\r  Geophys.\t\r  Res.,\t\r  97,\t\r  16,383-­‐16,394.\t\r  Harriss,\t\r  R.C.,\t\r  and\t\r  co-­‐authors,\t\r  1994:\t\r  The\t\r  Arctic\t\r  Boundary\t\r  Layer\t\r  Expedition\t\r  (ABLE-­‐3B):\t\r  July-­‐August\t\r  1990.\t\r  J.\t\r  Geophys.\t\r  Res.,\t\r  99,\t\r  1635-­‐1643.\t\r  Hegg,\t\r  D.A.,\t\r  S.G.\t\r  Warren,\t\r  T.C.\t\r  Grenfell,\t\r  S.J.\t\r  Doherty,\t\r  and\t\r  A.D.\t\r  Clarke,\t\r  2010:\t\r  Sources\t\r  of\t\r  light-absorbing\t\r  aerosol\t\r  in\t\r  Arctic\t\r  snow\t\r  and\t\r  their\t\r  seasonal\t\r  variation.\t\r  Atmos.\t\r  Chem.\t\r  Phys.,\t\r  10,\t\r  10,923–10,938,\t\r  doi:10.5194/acp-­‐10-­‐10923-­‐2010.\t\r  Heimann,\t\r  M.,\t\r  and\t\r  M.\t\r  Reichstein,\t\r  2008:\t\r  Terrestrial\t\r  ecosystem\t\r  carbon\t\r  dynamics\t\r  and\t\r  climate\t\r  feedbacks.\t\r  Nature,\t\r  451,\t\r  289-­‐292.\t\r  Hicke,\t\r  J.A.,\t\r  and\t\r  co-­‐authors,\t\r  2012:\t\r  The\t\r  effects\t\r  of\t\r  biotic\t\r  disturbances\t\r  on\t\r  carbon\t\r  budgets\t\r  of\t\r  North\t\r  American\t\r  forests.\t\r  Glob.\t\r  Change\t\r  Biol.,\t\r  18,\t\r  7-­‐34.\t\r  Holland,\t\r  M.M.,\t\r  D.A.\t\r  Bailey,\t\r  B.P.\t\r  Briegleb,\t\r  B.\t\r  Light,\t\r  and\t\r  E.\t\r  Hunke,\t\r  2012:\t\r  Improved\t\r  sea\t\r  ice\t\r  shortwave\t\r  radiation\t\r  physics\t\r  in\t\r  CCSM4:\t\r  The\t\r  impact\t\r  of\t\r  melt\t\r  ponds\t\r  and\t\r  aerosols\t\r  on\t\r  Arctic\t\r  sea\t\r  ice.\t\r  J.\t\r  \nClimate,\t\r  25,\t\r  1413–1430.\t\r  Holland,\t\r  M.M.,\t\r  and\t\r  C.M.\t\r  Bitz,\t\r  2003:\t\r  Polar\t\r  amplification\t\r  of\t\r  climate\t\r  change\t\r  in\t\r  coupled\t\r  models.\t\r  Climate\t\r  \nDyn.,\t\r  21,\t\r  221–232,\t\r  doi:10.1007/s00382-­‐003-­‐0332-­‐6.\t\r  Intrieri,\t\r  J.\t\r  M.,\t\r  M.D.\t\r  Shupe,\t\r  T.\t\r  Uttal,\t\r  and\t\r  B.\t\r  J.\t\r  McCarty,\t\r  \u003c/p\u003e\n\u003cp /\u003e\n\u003c/div\u003e\n\u003cdiv class\u003d\"page\"\u003e\u003cp /\u003e\n\u003cp\u003e\t\r  \u003c/p\u003e\n\u003cp\u003e\t\r   40\t\r  \n\u003c/p\u003e\n\u003cp\u003echaracteristics\t\r  observed\t\r  by\t\r  radar\t\r  and\t\r  lidar\t\r  at\t\r  SHEBA.\t\r  J.\t\r  Geophys.\t\r  Res.,\t\r  107,\t\r  8030,\t\r  doi:10.1029/2000JC000423.\t\r  IPCC\t\r  (2007)\t\r  Climate\t\r  Change\t\r  2007:\t\r  The\t\r  Physical\t\r  Science\t\r  Basis.\t\r  Contribution\t\r  of\t\r  Working\t\r  Group\t\r  I\t\r  to\t\r  the\t\r  Fourth\t\r  Assessment\t\r  Report\t\r  of\t\r  the\t\r  Intergovernmental\t\r  Panel\t\r  on\t\r  Climate\t\r  Change.\t\r  WMO/UNEP,\t\r  Cambridge\t\r  University\t\r  Press,\t\r  Cambridge,\t\r  996\t\r  pp.\t\r  Jin,\t\r  Y.,\t\r  J.T.\t\r  Randerson,\t\r  M.L.\t\r  Goulden,\t\r  and\t\r  S.J.\t\r  Goetz,\t\r  2012:\t\r  Post-­‐fire\t\r  changes\t\r  in\t\r  net\t\r  shortwave\t\r  radiation\t\r  along\t\r  a\t\r  latitudinal\t\r  gradient\t\r  in\t\r  boreal\t\r  North\t\r  America.\t\r  Geophys.\t\r  Res.\t\r  Lett.,\t\r  39,\t\r  L13403,\t\r  doi:10.1029/2012GL051790.\t\r  Kasischke,\t\r  E.\t\r  S.,\t\r  and\t\r  M.R.\t\r  Turetsky,\t\r  2006:\t\r  Recent\t\r  changes\t\r  in\t\r  the\t\r  fire\t\r  regime\t\r  across\t\r  the\t\r  North\t\r  American\t\r  boreal\t\r  region—Spatial\t\r  and\t\r  temporal\t\r  patterns\t\r  of\t\r  burning\t\r  across\t\r  Canada\t\r  and\t\r  Alaska\t\r  \nGeophys.\t\r  Res.\t\r  Lett.,\t\r  33,\t\r  L09703.\t\r  Kasischke,\t\r  E.\t\r  S.,\t\r  and\t\r  co-­‐authors,\t\r  2010:\t\r  Alaska’s\t\r  changing\t\r  fire\t\r  regime—Implications\t\r  for\t\r  the\t\r  vulnerability\t\r  of\t\r  its\t\r  boreal\t\r  forests.\t\r  Can.\t\r  J.\t\r  For.\t\r  Res.,\t\r  \t\r  40(7),\t\r  1313–1324,\t\r  doi:10.1139/X10-­‐098.\t\r  Kattsov,\t\r  V.M.,\t\r  J.E.\t\r  Walsh,\t\r  W.L.\t\r  Chapman,\t\r  V.A.\t\r  Govorkova,\t\r  T.V.\t\r  Pavlova,\t\r  and\t\r  X.\t\r  Zhang,\t\r  2007:\t\r  Simulation\t\r  and\t\r  projection\t\r  of\t\r  Arctic\t\r  freshwater\t\r  budget\t\r  components\t\r  by\t\r  the\t\r  IPCC\t\r  AR4\t\r  global\t\r  climate\t\r  models.\t\r  J.\t\r  Hydrometeorol.,\t\r  8,\t\r  571–589.\t\r  Kay,\t\r  J.E.,\t\r  and\t\r  A.\t\r  Gettelman,\t\r  2009:\t\r  Cloud\t\r  influence\t\r  on\t\r  and\t\r  response\t\r  to\t\r  seasonal\t\r  Arctic\t\r  sea\t\r  ice\t\r  loss.\t\r  J.\t\r  \nGeophys.\t\r  Res.,\t\r  114,\t\r  D18204,\t\r  doi:10.1029/2009JD011773.\t\r  Kay,\t\r  J.E.,\t\r  M.M.\t\r  Holland,\t\r  and\t\r  A.\t\r  Jahn,\t\r  2011:\t\r  Inter-­‐annual\t\r  to\t\r  multi-­‐decadal\t\r  Arctic\t\r  sea\t\r  ice\t\r  extent\t\r  trends\t\r  in\t\r  a\t\r  warming\t\r  world.\t\r  Geophys.\t\r  Res.\t\r  Lett.,\t\r  38,\t\r  L15708,\t\r  doi:10.1029/2011GL048008.\t\r  Kay,\t\r  J.E.,\t\r  and\t\r  co-­‐authors,\t\r  2012:\t\r  Exposing\t\r  global\t\r  cloud\t\r  biases\t\r  in\t\r  the\t\r  Community\t\r  Atmospheric\t\r  Model\t\r  (CAM)\t\r  using\t\r  satellite\t\r  observations\t\r  and\t\r  their\t\r  corresponding\t\r  instrument\t\r  simulators.\t\r  J.\t\r  Climate,\t\r  \n25,\t\r  5190-­‐5207.\t\r  Klein,\t\r  S.A.,\t\r  and\t\r  co-­‐authors,\t\r  2009:\t\r  Intercomparison\t\r  of\t\r  model\t\r  simulations\t\r  of\t\r  mixed-­‐phase\t\r  clouds\t\r  observed\t\r  during\t\r  the\t\r  ARM\t\r  Mixed-­‐Phase\t\r  Arctic\t\r  Cloud\t\r  Experiment.\t\r  I:\t\r  Single-­‐layer\t\r  cloud.\t\r  Q.\t\r  J.\t\r  R.\t\r  \nMeteorol.\t\r  Soc.,\t\r  135,\t\r  979–1002.\t\r  Knight,\t\r  C.G.,\t\r  S.H.E.\t\r  Knight,\t\r  N.\t\r  Massey,\t\r  T.\t\r  Aina,\t\r  C.\t\r  Christensen,\t\r  D.J.\t\r  Frame,\t\r  J.A.\t\r  Kettleborough,\t\r  A.\t\r  Martin,\t\r  S.\t\r  Pascoe,\t\r  B.\t\r  Sanderson,\t\r  D.A.\t\r  Stainforth,\t\r  and\t\r  M.R.\t\r  Allen,\t\r  2007:\t\r  Association\t\r  of\t\r  parameter,\t\r  software,\t\r  and\t\r  hardware\t\r  variation\t\r  with\t\r  large-­‐\t\r  scale\t\r  behaviour\t\r  across\t\r  57,000\t\r  climate\t\r  models.\t\r  PNAS,\t\r  104(30),\t\r  12259–12264.\t\r  Koch,\t\r  D.,\t\r  and\t\r  co-­‐authors,\t\r  2009:\t\r  Evaluation\t\r  of\t\r  black\t\r  carbon\t\r  estimations\t\r  in\t\r  global\t\r  aerosol\t\r  models.\t\r  \nAtmos.\t\r  Chem.\t\r  Phys.,\t\r  9,\t\r  9001-­‐9026,\t\r  doi:10.5194/acp-­‐9-­‐9001-­‐2009.\t\r  \t\r  Koster,\t\r  R.D.,\t\r  M.J.\t\r  Suárez,\t\r  A.\t\r  Ducharne,\t\r  M.\t\r  Stieglitz,\t\r  and\t\r  P.\t\r  Kumar,\t\r  2000:\t\r  A\t\r  catchment-­‐based\t\r  approach\t\r  to\t\r  modeling\t\r  land\t\r  surface\t\r  processes\t\r  in\t\r  a\t\r  GCM,\t\r  Part\t\r  1,\t\r  Model\t\r  Structure.\t\r  \t\r  J.\t\r  Geophys.\t\r  Res.,\t\r  105,\t\r  24809-­‐24822.\t\r  Koven,\t\r  C.,\t\r  P.\t\r  Friedlingstein,\t\r  P.\t\r  Ciais,\t\r  D.Khvorostyanov,\t\r  G.\t\r  Krinner,\t\r  and\t\r  C.\t\r  Tarnocai,\t\r  2009:\t\r  On\t\r  the\t\r  formation\t\r  of\t\r  high\t\r  latitude\t\r  soil\t\r  carbon\t\r  stocks:\t\r  Effects\t\r  of\t\r  cryoturbation\t\r  and\t\r  insulation\t\r  by\t\r  organic\t\r  matter\t\r  in\t\r  a\t\r  land\t\r  surface\t\r  model.\t\r  Geophys.\t\r  Res.\t\r  Lett.,\t\r  36,\t\r  L21501,\t\r  doi:10.1029/2009GL040150.\t\r  Koven,\t\r  C.D.,\t\r  B.\t\r  Ringeval,\t\r  P.\t\r  Friedlingstein,\t\r  P.\t\r  Ciais,\t\r  P.\t\r  Cadule,\t\r  D.\t\r  Khvorostyanov,\t\r  G.\t\r  Krinner,\t\r  G.,\t\r  and\t\r  C.\t\r  Tarnocai,\t\r  2011:\t\r  Permafrost\t\r  carbon-­‐climate\t\r  feedbacks\t\r  accelerate\t\r  global\t\r  warming.\t\r  P.\t\r  Natl.\t\r  \nAcad.\t\r  Sci.,\t\r  108,\t\r  14769–14774,\t\r  doi:10.1073/pnas.1103910108.\t\r  Khvorostyanov,\t\r  D.V.,\t\r  P.\t\r  Ciais,\t\r  G.\t\r  Krinner,\t\r  S.A.\t\r  Zimov,\t\r  C.\t\r  Corradi,\t\r  G.\t\r  Guggenberger,\t\r  2008:\t\r  Vulnerability\t\r  of\t\r  permafrost\t\r  carbon\t\r  to\t\r  global\t\r  warming.\t\r  Part\t\r  2:\t\r  sensitivity\t\r  of\t\r  permafrost\t\r  carbon\t\r  stock\t\r  to\t\r  global\t\r  warming.\t\r  Tellus,\t\r  60B,\t\r  250–264.\t\r  \u003c/p\u003e\n\u003cp /\u003e\n\u003c/div\u003e\n\u003cdiv class\u003d\"page\"\u003e\u003cp /\u003e\n\u003cp\u003e\t\r  \u003c/p\u003e\n\u003cp\u003e\t\r   41\t\r  \n\u003c/p\u003e\n\u003cp\u003eKurz,\t\r  W.A.,\t\r  C.C.\t\r  Dymond,\t\r  G.\t\r  Stinson,\t\r  G.J.\t\r  Rampley,\t\r  E.T.\t\r  Neilson,\t\r  A.L.\t\r  Carroll,\t\r  T.\t\r  Ebata,\t\r  and\t\r  L.\t\r  Safranyik,\t\r  2008a:\t\r  Mountain\t\r  pine\t\r  beetle\t\r  and\t\r  forest\t\r  carbon\t\r  feedback\t\r  to\t\r  climate\t\r  change.\t\r  Nature,\t\r  \n452,\t\r  987-­‐990.\t\r  Kurz,\t\r  W.A.,\t\r  G.\t\r  Stinson,\t\r  G.J.\t\r  Rampley,\t\r  C.C.\t\r  Dymond,\t\r  and\t\r  E.T.\t\r  Neilson,\t\r  2008b:\t\r  Risk\t\r  of\t\r  natural\t\r  disturbances\t\r  makes\t\r  future\t\r  contribution\t\r  of\t\r  Canada\u0027s\t\r  forests\t\r  to\t\r  the\t\r  global\t\r  carbon\t\r  cycle\t\r  highly\t\r  uncertain.\t\r  Proc.\t\r  Nat.\t\r  Acad.\t\r  Sci.,\t\r  105,\t\r  1551-­‐1555.\t\r  Kwok,\t\r  R.,\t\r  2011:\t\r  Observational\t\r  assessment\t\r  of\t\r  Arctic\t\r  Ocean\t\r  sea\t\r  ice\t\r  motion,\t\r  export,\t\r  and\t\r  thickness\t\r  in\t\r  CMIP3\t\r  climate\t\r  simulations.\t\r  J.\t\r  Geophys.\t\r  Res.,\t\r  116,\t\r  C00D05.\t\r  Law,\t\r  K.\t\r  S.\t\r  and\t\r  A.\t\r  Stohl,\t\r  2007:\t\r  Arctic\t\r  air\t\r  pollution:\t\r  Origins\t\r  and\t\r  impacts.\t\r  Science,\t\r  315(5818),\t\r  1537–1540,\t\r  doi:10.1126/science.1137695.\t\r  \t\r  Lawrence,\t\r  D.M.,\t\r  and\t\r  A.G.\t\r  Slater,\t\r  2005:\t\r  A\t\r  projection\t\r  of\t\r  severe\t\r  near\t\r  surface\t\r  permafrost\t\r  degradation\t\r  during\t\r  the\t\r  21st\t\r  century.\t\r  Geophys.\t\r  Res.\t\r  Lett.\t\r  32,\t\r  doi:10.1029/2005GL025080.\t\r  Lawrence,\t\r  D.\t\r  M.,\t\r  A.\t\r  G.\t\r  Slater,\t\r  V.\t\r  E.\t\r  Romanovsky,\t\r  and\t\r  D.\t\r  J.\t\r  Nicolsky,\t\r  2008:\t\r  Sensitivity\t\r  of\t\r  a\t\r  model\t\r  projection\t\r  of\t\r  near-­‐surface\t\r  permafrost\t\r  degradation\t\r  to\t\r  soil\t\r  column\t\r  depth\t\r  and\t\r  representation\t\r  of\t\r  soil\t\r  organic\t\r  matter.\t\r  J.\t\r  Geophys.\t\r  Res.,\t\r  113,\t\r  F02011,\t\r  doi:10.1029/2007JF000883.\t\r  Lawrence,\t\r  D.M.,\t\r  A.G.\t\r  Slater,\t\r  and\t\r  S.C.\t\r  Swenson,\t\r  2012:\t\r  Simulation\t\r  of\t\r  Present-­‐Day\t\r  and\t\r  Future\t\r  Permafrost\t\r  and\t\r  Seasonally\t\r  Frozen\t\r  Ground\t\r  Conditions\t\r  in\t\r  CCSM4.\t\r  J.\t\r  Climate,\t\r  25,\t\r  2207-­‐2225.\t\r  Levis,\t\r  S.,\t\r  2010:\t\r  Modeling\t\r  vegetation\t\r  and\t\r  land\t\r  use\t\r  in\t\r  models\t\r  of\t\r  the\t\r  Earth\t\r  System.\t\r  WIREs\t\r  Clim\t\r  Change,\t\r  \n1,\t\r  840–856\t\r  DOI:\t\r  10.1002/wcc.83.\t\r  Liu,\t\r  L.,\t\r  K.\t\r  Schaefer,\t\r  T.\t\r  Zhang,\t\r  and\t\r  J.\t\r  Wahr,\t\r  2012:\t\r  Estimating\t\r  1992–2000\t\r  average\t\r  active\t\r  layer\t\r  thickness\t\r  on\t\r  the\t\r  Alaskan\t\r  North\t\r  Slope\t\r  from\t\r  remotely\t\r  sensed\t\r  surface\t\r  subsidence.\t\r  J.\t\r  Geophys.\t\r  \nRes.,\t\r  117,\t\r  F01005,\t\r  doi:10.1029/2011JF002041\t\r  Liu,\t\r  S.,\t\r  and\t\r  co-­‐authors,\t\r  2011:\t\r  Simulating\t\r  the\t\r  impacts\t\r  of\t\r  disturbances\t\r  on\t\r  forest\t\r  carbon\t\r  cycling\t\r  in\t\r  North\t\r  America:\t\r  processes,\t\r  data,\t\r  models,\t\r  and\t\r  challenges.\t\r  J.\t\r  Geophy.\t\r  Res.,\t\r  116,\t\r  G00K08,\t\r  doi:10.1029/2010JG001585\t\r  Liu,\t\r  Y.,\t\r  S.A.\t\r  Ackerman,\t\r  B.C.\t\r  Maddux,\t\r  J.R.\t\r  Key,\t\r  and\t\r  R.A.\t\r  Frey,\t\r  2010:\t\r  Errors\t\r  in\t\r  cloud\t\r  detection\t\r  over\t\r  the\t\r  Arctic\t\r  and\t\r  implications\t\r  for\t\r  observing\t\r  feedback\t\r  mechanisms.\t\r  J.\t\r  Climate,\t\r  23,\t\r  1894-­‐1907.\t\r  \t\r  McFarquhar,\t\r  G.M.,\t\r  G.\t\r  Zhang,\t\r  M.R.\t\r  Poellot,\t\r  G.L.\t\r  Kok,\t\r  R.\t\r  McCoy,\t\r  T.\t\r  Tooman,\t\r  A.\t\r  Fridlind,\t\r  and\t\r  A.J.\t\r  Heymsfield,\t\r  2007:\t\r  Ice\t\r  properties\t\r  of\t\r  single-­‐layer\t\r  stratocumulus\t\r  during\t\r  the\t\r  Mixed-­‐Phase\t\r  Arctic\t\r  Cloud\t\r  Experiment\t\r  (MPACE):\t\r  Part\t\r  I,\t\r  Observations.\t\r  J.\t\r  Geophys.\t\r  Res.,\t\r  112,\t\r  D24201,\t\r  doi:10.1029/2007JD008633.\t\r  McGeehan,\t\r  T.,\t\r  and\t\r  W.\t\r  Maslowski,\t\r  2012:\t\r  Evaluation\t\r  and\t\r  control\t\r  mechanisms\t\r  of\t\r  volume\t\r  and\t\r  freshwater\t\r  export\t\r  through\t\r  the\t\r  Canadian\t\r  Arctic\t\r  Archipelago\t\r  in\t\r  a\t\r  high-­‐resolution\t\r  pan-­‐Arctic\t\r  ice-­‐ocean\t\r  model.\t\r  J.\t\r  Geophys.\t\r  Res.,\t\r  117,\t\r  doi:10.1029/2011JC007261\t\r  (in\t\r  press).\t\r  McGuire,\t\r  A.D.,\t\r  and\t\r  co-­‐authors,\t\r  2010:\t\r  An\t\r  analysis\t\r  of\t\r  the\t\r  carbon\t\r  balance\t\r  of\t\r  the\t\r  Arctic\t\r  Basin\t\r  from\t\r  1997\t\r  to\t\r  2006.\t\r  Tellus\t\r  B,\t\r  62,\t\r  455-­‐474.\t\r  Mack\t\r  MC,\t\r  MS\t\r  Bret-­‐Harte,\t\r  TN\t\r  Hollingsworth,\t\r  RR\t\r  Jandt,\t\r  EAG\t\r  Schuur,\t\r  GR\t\r  Schaver,\t\r  DL\t\r  Verbyla.\t\r  2011.\t\r  Carbon\t\r  loss\t\r  from\t\r  an\t\r  unprecedented\t\r  Arctic\t\r  tundra\t\r  wildfire,\t\r  Nature,\t\r  475,\t\r  489–492.\t\r  Manabe,\t\r  S.,\t\r  and\t\r  R.T.\t\r  Wetherald,\t\r  1975:\t\r  The\t\r  effects\t\r  of\t\r  doubling\t\r  the\t\r  CO2\t\r  concentration\t\r  on\t\r  the\t\r  climate\t\r  of\t\r  a\t\r  general\t\r  circulation\t\r  model.\t\r  J.\t\r  Atmos.\t\r  Sci,\t\r  32,\t\r  3-­‐15.\t\r  Macias-­‐Furia\t\r  M.,\t\r  B.C.\t\r  Forbes,\t\r  P.\t\r  Zetterberg,\t\r  and\t\r  T.\t\r  Kumpula,\t\r  2012:\t\r  Eurasian\t\r  Arctic\t\r  greening\t\r  reveals\t\r  teleconnections\t\r  and\t\r  the\t\r  potential\t\r  for\t\r  structurally\t\r  novel\t\r  ecosystems.\t\r  Nature\t\r  Climate\t\r  Change,\t\r  2,\t\r  613-­‐618.\t\r  Maslowski,\t\r  W.,\t\r  J.\t\r  Clement\t\r  Kinney,\t\r  M.\t\r  Higgins,\t\r  A.F.\t\r  Roberts,\t\r  2012:\t\r  The\t\r  Future\t\r  of\t\r  Arctic\t\r  Sea\t\r  Ice.\t\r  Ann.\t\r  \u003c/p\u003e\n\u003cp /\u003e\n\u003c/div\u003e\n\u003cdiv class\u003d\"page\"\u003e\u003cp /\u003e\n\u003cp\u003e\t\r  \u003c/p\u003e\n\u003cp\u003e\t\r   42\t\r  \n\u003c/p\u003e\n\u003cp\u003eRev.\t\r  Earth\t\r  Planet.\t\r  Sci.,\t\r  40,\t\r  625-­‐654.\t\r  Maslowski,\t\r  W.,\t\r  J.\t\r  Clement\t\r  Kinney,\t\r  D.C.\t\r  Marble,\t\r  J.\t\r  Jakacki,\t\r  2008:\t\r  Towards\t\r  eddy-­‐resolving\t\r  models\t\r  of\t\r  the\t\r  Arctic\t\r  Ocean.\t\r  In\t\r  Ocean\t\r  Modeling\t\r  in\t\r  an\t\r  Eddying\t\r  Regime,\t\r  M.W.\t\r  Hecht\t\r  and\t\r  H\t\r  Hasumi\t\r  (Eds),\t\r  pp.\t\r  241–64.\t\r  Geophys.\t\r  Monogr.\t\r  Ser.,\t\r  177.\t\r  Washington,\t\r  DC:\t\r  Am.\t\r  Geophys.\t\r  Union.\t\r  Maslowski,\t\r  W.,\t\r  and\t\r  W.\t\r  Walczowski,\t\r  2002:\t\r  On\t\r  the\t\r  circulation\t\r  of\t\r  the\t\r  Baltic\t\r  Sea\t\r  and\t\r  its\t\r  connection\t\r  to\t\r  the\t\r  pan-­‐Arctic\t\r  region:\t\r  a\t\r  large\t\r  scale\t\r  and\t\r  high-­‐resolution\t\r  modeling\t\r  approach.\t\r  Boreal\t\r  Environ.\t\r  \nRes.,\t\r  7,\t\r  319–325.\t\r  Medeiros,\t\r  B.,\t\r  C.\t\r  Deser,\t\r  R.\t\r  Tomas,\t\r  and\t\r  J.\t\r  Kay,\t\r  2011:\t\r  Arctic\t\r  inversion\t\r  strength\t\r  in\t\r  climate\t\r  models.\t\r  J.\t\r  \nClimate,\t\r  24,\t\r  4733–4740.\t\r  Menon,\t\r  S.,\t\r  N.\t\r  Unger,\t\r  D.\t\r  Koch,\t\r  J.\t\r  Francis,\t\r  T.\t\r  Garrett,\t\r  I.\t\r  Sednev,\t\r  D.\t\r  Shindell,\t\r  and\t\r  D.\t\r  Streets,\t\r  2008:\t\r  Aerosol\t\r  climate\t\r  effects\t\r  and\t\r  air\t\r  quality\t\r  impacts\t\r  from\t\r  1980\t\r  to\t\r  2030.\t\r  Environ.\t\r  Res.\t\r  Lett.,\t\r  3,\t\r  024004,\t\r  doi:10.1088/1748-­‐9326/3/2/024004.\t\r  Minsley,\t\r  B.J.,\t\r  and\t\r  co-­‐authors,\t\r  2012:\t\r  Airborne\t\r  electromagnetic\t\r  imaging\t\r  of\t\r  discontinuous\t\r  permafrost.\t\r  \nGeophys.\t\r  Res.\t\r  Lett.,\t\r  39,\t\r  L02503,\t\r  doi:10.1029/2011GL050079.\t\r  Morrison\t\r  H.,\t\r  and\t\r  J.O.\t\r  Pinto,\t\r  2006:\t\r  Intercomparison\t\r  of\t\r  bulk\t\r  cloud\t\r  microphysics\t\r  schemes\t\r  in\t\r  mesoscale\t\r  simulations\t\r  of\t\r  springtime\t\r  Arctic\t\r  mixed-­‐phase\t\r  stratiform\t\r  clouds.\t\r  Mon.\t\r  Weather\t\r  Rev.,\t\r  \n134,\t\r  1880–1900.\t\r  Morrison,\t\r  H.,\t\r  and\t\r  co-­‐authors,\t\r  2011:\t\r  Intercomparison\t\r  of\t\r  cloud\t\r  model\t\r  simulations\t\r  of\t\r  Arctic\t\r  mixed-phase\t\r  boundary\t\r  layer\t\r  clouds\t\r  observed\t\r  during\t\r  SHEBA.\t\r  J.\t\r  Adv.\t\r  Model.\t\r  Earth\t\r  Syst.,\t\r  3,\t\r  M06003,\t\r  doi:10.1029/2011MS000066.\t\r  Muir,\t\r  D.C.G.,\t\r  R.\t\r  Wagemann,\t\r  B.T.\t\r  Hargrave,\t\r  D.J.\t\r  Thomas,\t\r  D.B.\t\r  Peakall,\t\r  and\t\r  R.J.\t\r  Norstrom,\t\r  1992:\t\r  Arctic\t\r  marine\t\r  ecosystem\t\r  contamination.\t\r  Sci.\t\r  Total\t\r  Environ.,\t\r  1,\t\r  75–134,\t\r  doi:10.1016/0048-­‐9697(92)90246-­‐O.\t\r  Neilson,\t\r  R.P.,\t\r  L.F.\t\r  Pitelka,\t\r  A.M.\t\r  Solomon,\t\r  R.\t\r  Nathan,\t\r  G.F.\t\r  Midgley,\t\r  J.M.V.\t\r  Fragoso,\t\r  H.\t\r  Lischke,\t\r  and\t\r  K.\t\r  Thompson,\t\r  2005:\t\r  Forecasting\t\r  regional\t\r  to\t\r  global\t\r  plant\t\r  migration\t\r  in\t\r  response\t\r  to\t\r  climate\t\r  change.\t\r  BioScience,\t\r  55,\t\r  749–759.\t\r  Ovchinnikov,\t\r  M.,\t\r  A.\t\r  Korolev,\t\r  and\t\r  J.\t\r  Fan,\t\r  2011:\t\r  Effects\t\r  of\t\r  ice\t\r  number\t\r  concentration\t\r  on\t\r  dynamics\t\r  of\t\r  a\t\r  shallow\t\r  mixed-phase\t\r  stratiform\t\r  cloud.\t\r  J.\t\r  Geophys.\t\r  Res.,\t\r  116,\t\r  D00T06,\t\r  doi:10.1029/2011JD015888.\t\r  Overeem,\t\r  I.,\t\r  R.S.\t\r  Anderson,\t\r  C.W.\t\r  Wobus,\t\r  G.D.\t\r  Clow,\t\r  F.E.\t\r  Urban,\t\r  and\t\r  N.\t\r  Matell,\t\r  2011:\t\r  Sea\t\r  ice\t\r  loss\t\r  enhances\t\r  wave\t\r  action\t\r  at\t\r  the\t\r  Arctic\t\r  coast.\t\r  Geophys.\t\r  Res.\t\r  Lett.,\t\r  38,\t\r  L17503,\t\r  doi:10.1029/2011GL048681.\t\r  Palm,\t\r  S.P.,\t\r  S.T.\t\r  Strey,\t\r  J.\t\r  Spinhirne,\t\r  and\t\r  T.\t\r  Markus,\t\r  2010:\t\r  Influence\t\r  of\t\r  Arctic\t\r  sea\t\r  ice\t\r  extent\t\r  on\t\r  polar\t\r  cloud\t\r  fraction\t\r  and\t\r  vertical\t\r  structure\t\r  and\t\r  implications\t\r  for\t\r  regional\t\r  climate.\t\r  J.\t\r  Geophys.\t\r  Res.,\t\r  \n115,\t\r  D21209,\t\r  doi:10.1029/2010JD013900.\t\r  Perovich,\t\r  D.K.,\t\r  T.C.\t\r  Grenfell,\t\r  B.\t\r  Light,\t\r  and\t\r  P.V.\t\r  Hobbs,\t\r  2002:\t\r  Seasonal\t\r  evolution\t\r  of\t\r  the\t\r  albedo\t\r  of\t\r  multiyear\t\r  Arctic\t\r  sea\t\r  ice.\t\r  J.\t\r  Geophys.\t\r  Res.,\t\r  107,\t\r  8044.\t\r  doi:10.1029/2000JC000438.\t\r  Popova,\t\r  E.E.,\t\r  A.\t\r  Yool,\t\r  A.C.\t\r  Coward,\t\r  F.\t\r  Dupont,\t\r  C.\t\r  Deal,\t\r  S.\t\r  Elliott,\t\r  E.\t\r  Hunke,\t\r  M.\t\r  Jin,\t\r  M.\t\r  Steele,\t\r  and\t\r  J.\t\r  Zhang,\t\r  2012:\t\r  What\t\r  controls\t\r  primary\t\r  production\t\r  in\t\r  the\t\r  Arctic\t\r  Ocean?\t\r  Results\t\r  from\t\r  an\t\r  intercomparison\t\r  of\t\r  five\t\r  general\t\r  circulation\t\r  models\t\r  with\t\r  biogeochemistry.\t\r  J.\t\r  Geophys.\t\r  Res.,\t\r  \n117,\t\r  C00D12,\t\r  doi:10.1029/2011JC007112.\t\r  Prenni,\t\r  A.J.,\t\r  J.Y.\t\r  Harrington,\t\r  M.\t\r  Tjenrström,\t\r  .J.\t\r  DeMott,\t\r  A.\t\r  Avramov,\t\r  C.N.\t\r  Long,\t\r  S.M.\t\r  Kreidneweis,\t\r  P.Q.\t\r  Olsson,\t\r  and\t\r  J.\t\r  Verlinde,\t\r  2007:\t\r  Can\t\r  ice-­‐nucleating\t\r  aerosols\t\r  affect\t\r  Arctic\t\r  seasonal\t\r  climate?\t\r  Bull.\t\r  \nAmer.\t\r  Meteorol.\t\r  Soc.,\t\r  88,\t\r  541-­‐550.\t\r  Qian,\t\r  H.,\t\r  R.\t\r  Joseph,\t\r  and\t\r  N.\t\r  Zeng,\t\r  2010:\t\r  Enhanced\t\r  terrestrial\t\r  carbon\t\r  uptake\t\r  in\t\r  the\t\r  Northern\t\r  High\t\r  \u003c/p\u003e\n\u003cp /\u003e\n\u003c/div\u003e\n\u003cdiv class\u003d\"page\"\u003e\u003cp /\u003e\n\u003cp\u003e\t\r  \u003c/p\u003e\n\u003cp\u003e\t\r   43\t\r  \n\u003c/p\u003e\n\u003cp\u003eLatitudes\t\r  in\t\r  the\t\r  21st\t\r  century\t\r  from\t\r  the\t\r  Coupled\t\r  Carbon\t\r  Cycle\t\r  Climate\t\r  Model\t\r  Intercomparison\t\r  Project\t\r  model\t\r  projections.\t\r  Global\t\r  Change\t\r  Biol.\t\r  16,\t\r  641–656,\t\r  doi:10.1111/j.13652486.2009.01989.x.\t\r  Qian,\t\r  Y.,\t\r  C,\t\r  Long,\t\r  H.\t\r  Wang,\t\r  J.\t\r  Comstock,\t\r  S.A.\t\r  McFarlane,\t\r  and\t\r  S.\t\r  Xie,\t\r  2012:\t\r  Evaluation\t\r  of\t\r  cloud\t\r  fraction\t\r  and\t\r  its\t\r  radiative\t\r  effect\t\r  simulated\t\r  by\t\r  IPCC\t\r  AR4\t\r  global\t\r  models\t\r  against\t\r  ARM\t\r  surface\t\r  observations.\t\r  Atmos.\t\r  Chem.\t\r  Phys.,\t\r  12,\t\r  1785-­‐1810,\t\r  doi:10.5194/acp-­‐12-­‐1785-­‐2012.\t\r  \t\r  Quinn,\t\r  P.K.,\t\r  G.\t\r  Shaw,\t\r  E.\t\r  Andrews,\t\r  E.G.\t\r  Dutton,\t\r  T.\t\r  Ruoho-­‐Airola,\t\r  and\t\r  S.L.\t\r  Gong,\t\r  2007:\t\r  Arctic\t\r  haze:\t\r  Current\t\r  trends\t\r  and\t\r  knowledge\t\r  gaps.\t\r  Tellus\t\r  B,\t\r  59(1),\t\r  99–114,\t\r  doi:10.1111/j.1600-­‐0889.2006.00238.x.\t\r  \t\r  Rahn,\t\r  K.\t\r  A.,\t\r  R.D.\t\r  Borys,\t\r  and\t\r  G.E.\t\r  Shaw,\t\r  1977:\t\r  The\t\r  Asian\t\r  source\t\r  of\t\r  Arctic\t\r  haze\t\r  bands.\t\r  Nature,\t\r  268,\t\r  713–715.\t\r  Randall,\t\r  D.A.,\t\r  R.A.\t\r  Wood,\t\r  S.\t\r  Bony,\t\r  R.\t\r  Colman,\t\r  T.\t\r  Fichefet,\t\r  J.\t\r  Fyfe,\t\r  V.\t\r  Kattsov,\t\r  A.\t\r  Pitman,\t\r  J.\t\r  Shukla,\t\r  J.\t\r  Srinivasan,\t\r  R.J.\t\r  Stouffer,\t\r  A.\t\r  Sumi\t\r  and\t\r  K.E.\t\r  Taylor,\t\r  2007:\t\r  Climate\t\r  Models\t\r  and\t\r  Their\t\r  Evaluation.\t\r  In:\t\r  Climate\t\r  Change\t\r  2007:\t\r  The\t\r  Physical\t\r  Science\t\r  Basis.\t\r  Contribution\t\r  of\t\r  Working\t\r  Group\t\r  I\t\r  to\t\r  the\t\r  \nFourth\t\r  Assessment\t\r  Report\t\r  of\t\r  the\t\r  Intergovernmental\t\r  Panel\t\r  on\t\r  Climate\t\r  Change\t\r  [Solomon,\t\r  S.,\t\r  D.\t\r  Qin,\t\r  M.\t\r  Manning,\t\r  Z.\t\r  Chen,\t\r  M.\t\r  Marquis,\t\r  K.B.\t\r  Averyt,\t\r  M.Tignor\t\r  and\t\r  H.L.\t\r  Miller\t\r  (eds.)].\t\r  Cambridge\t\r  University\t\r  Press,\t\r  Cambridge,\t\r  United\t\r  Kingdom\t\r  and\t\r  New\t\r  York,\t\r  NY,\t\r  USA.\t\r  Raynolds,\t\r  M.K.,\t\r  D.A.\t\r  Walker,\t\r  H.E.\t\r  Epstein,\t\r  J.E.\t\r  Pinzon,\t\r  and\t\r  C.J.\t\r  Tucker,\t\r  2012:\t\r  A\t\r  new\t\r  estimate\t\r  of\t\r  tundra-­‐biome\t\r  phytomass\t\r  from\t\r  trans-­‐Arctic\t\r  field\t\r  data\t\r  and\t\r  AVHRR\t\r  NDVI.\t\r  Rem.\t\r  Sens.\t\r  Lett.,\t\r  3(5),\t\r  403-­‐411.\t\r  \t\r  Richardson,\t\r  A.D.,\t\r  and\t\r  co-­‐authors,\t\r  2010:\t\r  Evaluation\t\r  of\t\r  Land\t\r  Surface\t\r  Model\t\r  Representation\t\r  of\t\r  Phenology:\t\r  An\t\r  Analysis\t\r  of\t\r  Model\t\r  Runs\t\r  Submitted\t\r  to\t\r  the\t\r  NACP\t\r  Interim\t\r  Site\t\r  Synthesis,\t\r  AGU\t\r  \npresentation,\t\r  available\t\r  at\t\r  http://nacp.ornl.gov/int_synthesis.shtml.\t\r  Richardson,\t\r  A.D.,\t\r  and\t\r  co-­‐authors,\t\r  2012:\t\r  Terrestrial\t\r  biosphere\t\r  models\t\r  need\t\r  better\t\r  representation\t\r  of\t\r  vegetation\t\r  phenology:\t\r  results\t\r  from\t\r  the\t\r  North\t\r  American\t\r  Carbon\t\r  Program\t\r  Site\t\r  Synthesis.\t\r  Global\t\r  \nChange\t\r  Biol.,\t\r  18\t\r  566-­‐584,\t\r  doi:\t\r  10.1111/j.1365-­‐2486.2011.02562.x.\t\r  Rind\t\r  D.\t\r  2008:\t\r  The\t\r  consequences\t\r  of\t\r  not\t\r  knowing\t\r  low-­‐\t\r  and\t\r  high-­‐latitude\t\r  climate\t\r  sensitivity.\t\r  Bull.\t\r  \nAm.Meteorol.\t\r  Soc.,\t\r  89,\t\r  855–864.\t\r  Robinson,\t\r  S.D.,\t\r  and\t\r  T.R.\t\r  Moore,\t\r  2000:\t\r  The\t\r  influence\t\r  of\t\r  permafrost\t\r  and\t\r  fire\t\r  upon\t\r  carbon\t\r  accumulation\t\r  in\t\r  high\t\r  boreal\t\r  peatlands,\t\r  Northwest\t\r  Territories,\t\r  Canada.\t\r  Arct.\t\r  Antarct.\t\r  Alp.\t\r  Res.,\t\r  \n32(2),\t\r  155–166,\t\r  doi:10.2307/1552447.\t\r  Rouse,\t\r  W.R.,\t\r  and\t\r  co-­‐authors,\t\r  1997:\t\r  Effects\t\r  of\t\r  climate\t\r  change\t\r  on\t\r  the\t\r  freshwaters\t\r  of\t\r  arctic\t\r  and\t\r  subarctic\t\r  North\t\r  America.\t\r  Hydrol.\t\r  Process.,\t\r  11(8),\t\r  873–\t\r  902.\t\r  Samuelsson,\t\r  P.,\t\r  E.\t\r  Kourzeneva,\t\r  and\t\r  D.\t\r  Mironov,\t\r  2010:\t\r  The\t\r  impact\t\r  of\t\r  lakes\t\r  on\t\r  the\t\r  European\t\r  climate\t\r  as\t\r  simulated\t\r  by\t\r  a\t\r  regional\t\r  climate\t\r  model.\t\r  Boreal\t\r  Environ.\t\r  Res.,\t\r  15,\t\r  113–129.\t\r  Schaefer,\t\r  K.,\t\r  T.\t\r  Zhang,\t\r  L.\t\r  Bruhwiler,\t\r  and\t\r  A.P.\t\r  Barrett,\t\r  2011:\t\r  Amount\t\r  and\t\r  timing\t\r  of\t\r  permafrost\t\r  carbon\t\r  release\t\r  in\t\r  response\t\r  to\t\r  climate\t\r  warming.\t\r  Tellus,\t\r  63B,\t\r  165–180.\t\r  Schaefer,\t\r  K.\t\r  and\t\r  co-­‐authors,\t\r  2012:\t\r  A\t\r  Model-­‐Data\t\r  Comparison\t\r  of\t\r  Gross\t\r  Primary\t\r  Productivity:\t\r  Results\t\r  from\t\r  the\t\r  North\t\r  American\t\r  Carbon\t\r  Program\t\r  Site\t\r  Synthesis.\t\r  J.\t\r  Geophys.\t\r  Res.,\t\r  117,\t\r  G03010,\t\r  doi:10.1029/2012JG001960.\t\r  Schneider,\t\r  B.,\t\r  L.\t\r  Bopp,\t\r  M.\t\r  Gehlen,\t\r  J.\t\r  Segschneider,\t\r  T.L.\t\r  Frlicher,\t\r  P.\t\r  Cadule,\t\r  P.\t\r  Friedlingstein,\t\r  S.C.\t\r  Doney,\t\r  M.J.\t\r  Behrenfeld,\t\r  and\t\r  F.\t\r  Joos,\t\r  2008:\t\r  Climate-­‐induced\t\r  interannual\t\r  variability\t\r  of\t\r  marine\t\r  primary\t\r  and\t\r  export\t\r  production\t\r  in\t\r  three\t\r  global\t\r  coupled\t\r  climate\t\r  carbon\t\r  cycle\t\r  models.\t\r  \nBiogeosciences,\t\r  5,\t\r  597–614.\t\r  Schneider\t\r  von\t\r  Deimling,\t\r  T.,\t\r  M.\t\r  Meinshausen,\t\r  A.\t\r  Levermann,\t\r  V.\t\r  Huber,\t\r  K.\t\r  Frieler,\t\r  D.M.\t\r  Lawrence,\t\r  and\t\r  \u003c/p\u003e\n\u003cp /\u003e\n\u003c/div\u003e\n\u003cdiv class\u003d\"page\"\u003e\u003cp /\u003e\n\u003cp\u003e\t\r  \u003c/p\u003e\n\u003cp\u003e\t\r   44\t\r  \n\u003c/p\u003e\n\u003cp\u003eV.\t\r  Brovkin,\t\r  2012:\t\r  Estimating\t\r  the\t\r  near-­‐surface\t\r  permafrost-­‐carbon\t\r  feedback\t\r  on\t\r  global\t\r  warming.\t\r  Biogeosciences,\t\r  9,\t\r  649–665,\t\r  doi:10.5194/bg-­‐9-­‐649-­‐2012.\t\r  Screen,\t\r  J.A.,\t\r  and\t\r  I.\t\r  Simmonds,\t\r  2010:\t\r  The\t\r  central\t\r  role\t\r  of\t\r  diminishing\t\r  sea\t\r  ice\t\r  in\t\r  recent\t\r  Arctic\t\r  temperature\t\r  amplification.\t\r  Nature,\t\r  464,\t\r  1334-­‐1337,\t\r  doi:10.1038/nature09051.\t\r  Seferian,\t\r  R.,\t\r  and\t\r  co-­‐authors,\t\r  2012:\t\r  Skill\t\r  assessment\t\r  of\t\r  three\t\r  earth\t\r  system\t\r  models\t\r  with\t\r  common\t\r  marine\t\r  biogeochemistry.\t\r  Clim\t\r  Dyn,\t\r  DOI\t\r  10.1007/s00382-­‐012-­‐1362-­‐8.\t\r  Serreze,\t\r  M.C.,\t\r  A.P.\t\r  Barrett,\t\r  J.C.\t\r  Stroeve,\t\r  D.N.\t\r  Kindig,\t\r  and\t\r  M.M.\t\r  Holland,\t\r  2009:\t\r  The\t\r  Emergence\t\r  of\t\r  Surface-­‐Based\t\r  Arctic\t\r  Amplification.\t\r  The\t\r  Cryosphere,\t\r  3,\t\r  11–19.\t\r  \t\r  \t\r  Serreze,\t\r  M.C.,\t\r  and\t\r  R.G.\t\r  Barry,\t\r  2011.\t\r  Processes\t\r  and\t\r  Impacts\t\r  of\t\r  Arctic\t\r  Amplification:\t\r  A\t\r  Research\t\r  Synthesis.\t\r  Global\t\r  and\t\r  Planetary\t\r  Change,\t\r  77,\t\r  85–96.\t\r  Sedlar,\t\r  J.,\t\r  M.D.\t\r  Shupe,\t\r  and\t\r  M.\t\r  Tjernstrom,\t\r  2012:\t\r  On\t\r  the\t\r  relationship\t\r  between\t\r  thermodynamic\t\r  structure,\t\r  cloud\t\r  top,\t\r  and\t\r  climate\t\r  significance\t\r  in\t\r  the\t\r  Arctic.\t\r  J.\t\r  Climate,\t\r  25,\t\r  2374-­‐2393.\t\r  Sharma,\t\r  S.,\t\r  E.\t\r  Andrews,\t\r  L.A.\t\r  Barrie,\t\r  J\t\r  A.,\t\r  Ogren,\t\r  and\t\r  D.\t\r  Lavoué,\t\r  2006:\t\r  Variations\t\r  and\t\r  sources\t\r  of\t\r  the\t\r  equivalent\t\r  black\t\r  carbon\t\r  in\t\r  the\t\r  high\t\r  Arctic\t\r  revealed\t\r  by\t\r  long-­‐term\t\r  observations\t\r  at\t\r  Alert\t\r  and\t\r  Barrow:\t\r  1989–2003.\t\r  J.\t\r  Geophys.\t\r  Res.,\t\r  111,\t\r  D14208,\t\r  doi:10.1029/2005JD006581.\t\r  \t\r  Shindell,\t\r  D.T.,\t\r  and\t\r  co-­‐authors,\t\r  2008:\t\r  A\t\r  multi-­‐model\t\r  assessment\t\r  of\t\r  pollution\t\r  transport\t\r  to\t\r  the\t\r  Arctic.\t\r  \nAtmos.\t\r  Chem.\t\r  Phys.,\t\r  8,\t\r  5353-­‐5372,\t\r  doi:10.5194/acp-­‐8-­‐5353-­‐2008.\t\r  \t\r  Shupe,\t\r  M.D\t\r  and\t\r  J.M.\t\r  Intrieri,\t\r  2004:\t\r  Cloud\t\r  radiative\t\r  forcing\t\r  of\t\r  the\t\r  Arctic\t\r  surface:\t\r  The\t\r  influence\t\r  of\t\r  cloud\t\r  properties,\t\r  surface\t\r  albedo,\t\r  and\t\r  solar\t\r  zenith\t\r  angle.\t\r  J.\t\r  Climate,\t\r  17,\t\r  616–628.\t\r  Shupe,\t\r  M.D.,\t\r  2011:\t\r  Clouds at Arctic atmospheric observatories. Part II: Thermodynamic phase \ncharacteristics. J. Appl. Met. Climatol., 50, 645-61.\t\r  Shupe,\t\r  M.D.,\t\r  V.P.\t\r  Walden,\t\r  E.\t\r  Eloranta,\t\r  T.\t\r  Uttal,\t\r  J.R.\t\r  Campbell,\t\r  S.M.\t\r  Starkweather,\t\r  and\t\r  M.\t\r  Shiobara,\t\r  2011:\t\r  Clouds\t\r  at\t\r  Arctic\t\r  Atmospheric\t\r  Observatories,\t\r  Part\t\r  I:\t\r  Occurrence\t\r  and\t\r  macrophysical\t\r  properties.\t\r  J.\t\r  Appl.\t\r  Meteor.\t\r  Clim.,\t\r  50,\t\r  626-­‐644.\t\r  Sitch,\t\r  S.,\t\r  and\t\r  co-­‐authors,\t\r  2008:\t\r  Evaluation\t\r  of\t\r  the\t\r  terrestrial\t\r  carbon\t\r  cycle,\t\r  future\t\r  plant\t\r  geography\t\r  and\t\r  climate-­‐carbon\t\r  cycle\t\r  feedbacks\t\r  using\t\r  5\t\r  dynamic\t\r  global\t\r  vegetation\t\r  models\t\r  (DGVMs).\t\r  Glob.\t\r  \nChang.\t\r  Biol.,\t\r  14,\t\r  2015–2039,\t\r  doi:10.1111/j.1365-­‐\t\r  2486.2008.01626.x.\t\r  Smith,\t\r  Jr.\t\r  W.,\t\r  and\t\r  J.C.\t\r  Comiso,\t\r  2008:\t\r  The\t\r  influence\t\r  of\t\r  sea\t\r  ice\t\r  on\t\r  primary\t\r  production\t\r  in\t\r  the\t\r  Southern\t\r  Ocean:\t\r  \t\r  A\t\r  satellite\t\r  perspective.\t\r  J.\t\r  Geophys.\t\r  Res.,\t\r  113,\t\r  C05S93,\t\r  doi:10.1029/2007JC004251.\t\r  Sonnentag,\t\r  O.,\t\r  J.M.\t\r  Chen,\t\r  N.T.\t\r  Roulet,\t\r  W.\t\r  Ju,\t\r  and\t\r  A.\t\r  Govind,\t\r  2008:\t\r  Spatially\t\r  explicit\t\r  simulation\t\r  of\t\r  peatland\t\r  hydrology\t\r  and\t\r  carbon\t\r  dioxide\t\r  exchange:\t\r  Influence\t\r  of\t\r  mesoscale\t\r  topography.\t\r  J.\t\r  \nGeophys.\t\r  Res.,\t\r  113,\t\r  G02005,\t\r  doi:10.1029/2007JG000605.\t\r  Steffen,\t\r  K.,\t\r  J.\t\r  Comiso,\t\r  K.S.\t\r  Gemain,\t\r  P.\t\r  Gloersen,\t\r  J.\t\r  Key,\t\r  and\t\r  I.\t\r  Rubenstein,\t\r  1992:\t\r  The\t\r  estimation\t\r  of\t\r  geophysical\t\r  parameters\t\r  using\t\r  passive\t\r  microwave\t\r  algorithms.\t\r  Microwave\t\r  Remote\t\r  Sensing\t\r  of\t\r  \nSea\t\r  Ice,\t\r  F.\t\r  D.\t\r  Carsey,\t\r  Ed.,\t\r  Amer.\t\r  Geophys.\t\r  Union,\t\r  201–228.\t\r  Steinacher,\t\r  M.,\t\r  and\t\r  co-­‐authors,\t\r  2010:\t\r  Projected\t\r  21st\t\r  century\t\r  decrease\t\r  in\t\r  marine\t\r  productivity:\t\r  a\t\r  multi-­‐model\t\r  analysis.\t\r  Biogeosciences,\t\r  7,\t\r  979–1005.\t\r  Stroeve,\t\r  J.,\t\r  M.M.\t\r  Holland,\t\r  W.\t\r  Meier,\t\r  T.\t\r  Scambos,\t\r  and\t\r  M.\t\r  Serreze,\t\r  2007:\t\r  Arctic\t\r  se\t\r  ice\t\r  decline:\t\r  faster\t\r  than\t\r  forecast.\t\r  Geophys.\t\r  Res.\t\r  Lett.\t\r  34:L09501.\t\r  Stroeve,\t\r  J.C.,\t\r  V.\t\r  Kattsov,\t\r  A.\t\r  Barrett,\t\r  M.\t\r  Serreze,\t\r  T.\t\r  Pavlova,\t\r  M.\t\r  Holland,\t\r  and\t\r  W\t\r  N.\t\r  Meier,\t\r  2012:\t\r  Trends\t\r  in\t\r  Arctic\t\r  sea\t\r  ice\t\r  extent\t\r  from\t\r  CMIP5,\t\r  CMIP3\t\r  and\t\r  observations.\t\r  Geophys.\t\r  Res.\t\r  Lett.,\t\r  39,\t\r  L16502,\t\r  doi:10.1029/2012GL052676.\t\r  Subin,\t\r  Z.\t\r  M.,\t\r  L.\t\r  N.\t\r  Murphy,\t\r  F.\t\r  Li,\t\r  C.\t\r  Bonfils,\t\r  and\t\r  W.\t\r  J.\t\r  Riley,\t\r  2012a:\t\r  Boreal\t\r  lakes\t\r  moderate\t\r  seasonal\t\r  and\t\r  diurnal\t\r  temperature\t\r  variation\t\r  and\t\r  perturb\t\r  atmospheric\t\r  circulation:\t\r  Analyses\t\r  in\t\r  CESM1.\t\r  \u003c/p\u003e\n\u003cp /\u003e\n\u003c/div\u003e\n\u003cdiv class\u003d\"page\"\u003e\u003cp /\u003e\n\u003cp\u003e\t\r  \u003c/p\u003e\n\u003cp\u003e\t\r   45\t\r  \n\u003c/p\u003e\n\u003cp\u003eTellus,\t\r  Ser.\t\r  A,\t\r  64,\t\r  15639,\t\r  DOI:\t\r  10.3402/tellusa.v64i0.15639.\t\r  Subin,\t\r  Z.M.,\t\r  W.J.\t\r  Riley\t\r  and\t\r  D.\t\r  Mironov,\t\r  2012b:\t\r  Improved\t\r  lake\t\r  model\t\r  for\t\r  climate\t\r  simulations.\t\r  J.\t\r  Adv.\t\r  \nModel.\t\r  Earth\t\r  Syst.,\t\r  4,\t\r  M02001,\t\r  doi:10.1029/2011MS000072.\t\r  Turetsky,\t\r  M.R.,\t\r  W.F.\t\r  Donahue,\t\r  and\t\r  B.W.\t\r  Benscoter,\t\r  2011:\t\r  Experimental\t\r  drying\t\r  intensifies\t\r  burning\t\r  and\t\r  carbon\t\r  loss\t\r  in\t\r  a\t\r  northern\t\r  peatland.\t\r  Nature\t\r  Communications,\t\r  doi:\t\r  10.1038/ncomms1523.\t\r  Vavrus,\t\r  S.,\t\r  2004:\t\r  The\t\r  impact\t\r  of\t\r  cloud\t\r  feedbacks\t\r  on\t\r  Arctic\t\r  climate\t\r  under\t\r  greenhouse\t\r  forcing.\t\r  J.\t\r  \nClimate,\t\r  17,\t\r  603–615.\t\r  Vavrus,\t\r  S.,\t\r  and\t\r  D.\t\r  Waliser,\t\r  2008:\t\r  An\t\r  Improved\t\r  Parameterization\t\r  for\t\r  Simulating\t\r  Arctic\t\r  Cloud\t\r  Amount\t\r  in\t\r  the\t\r  CCSM3\t\r  Climate\t\r  Model.\t\r  J.\t\r  Climate,\t\r  21,\t\r  5673–5687,\t\r  doi:\t\r  10.1175/2008JCLI2299.1.\t\r  \t\r  Vavrus,\t\r  S.,\t\r  D.\t\r  Waliser,\t\r  A.\t\r  Schweiger,\t\r  and\t\r  J.\t\r  Francis,\t\r  2009:\t\r  Simulations\t\r  of\t\r  20th\t\r  and\t\r  21st\t\r  century\t\r  Arctic\t\r  cloud\t\r  amount\t\r  in\t\r  the\t\r  global\t\r  climate\t\r  models\t\r  assessed\t\r  in\t\r  the\t\r  IPCC\t\r  AR4.\t\r  Climate\t\r  Dyn.,\t\r  33,\t\r  1099–1115.\t\r  doi:10.1007/s00382-­‐008-­‐0475-­‐6.\t\r  Vavrus,\t\r  S.J.,\t\r  M.M.\t\r  Holland,\t\r  A.\t\r  Jahn,\t\r  D.A.\t\r  Bailey,\t\r  and\t\r  B.A.\t\r  Blazey,\t\r  2012:\t\r  Twenty-­‐first-­‐century\t\r  Arctic\t\r  climate\t\r  change\t\r  in\t\r  CCSM4.\t\r  J.\t\r  Climate,\t\r  25,\t\r  2696-­‐2710.\t\r  Walsh,\t\r  J.E.,\t\r  V.M.\t\r  Kattsov,\t\r  W.L.\t\r  Chapman,\t\r  V.\t\r  Govorkova,\t\r  and\t\r  T.\t\r  Pavlova,\t\r  2002:\t\r  Comparison\t\r  of\t\r  Arctic\t\r  climate\t\r  simulations\t\r  by\t\r  uncoupled\t\r  and\t\r  coupled\t\r  global\t\r  models.\t\r  J.\t\r  Climate,\t\r  15,\t\r  1429-­‐1446.\t\r  Walter,\t\r  K.M.,\t\r  S.A.\t\r  Zimov,\t\r  J.P.\t\r  Chanton,\t\r  D.\t\r  Verbyla,\t\r  and\t\r  F.S.\t\r  Chapin,\t\r  2006:\t\r  Methane\t\r  bubbling\t\r  from\t\r  Siberian\t\r  thaw\t\r  lakes\t\r  as\t\r  a\t\r  positive\t\r  feedback\t\r  to\t\r  climate\t\r  warming.\t\r  Nature,\t\r  443,\t\r  71–75,\t\r  doi:10.1038/nature05040.\t\r  Wania,\t\r  R.,\t\r  I.\t\r  Ross,\t\r  and\t\r  I.C.\t\r  Prentice,\t\r  2009:\t\r  Integrating\t\r  peatlands\t\r  and\t\r  permafrost\t\r  into\t\r  a\t\r  dynamic\t\r  global\t\r  vegetation\t\r  model:\t\r  1.\t\r  Evaluation\t\r  and\t\r  sensitivity\t\r  of\t\r  physical\t\r  land\t\r  surface\t\r  processes.\t\r  \nGlobal\t\r  Biogeochem.\t\r  Cycles,\t\r  23,\t\r  GB3014,\t\r  doi:10.1029/2008GB003412.\t\r  Wang,\t\r  H.,\t\r  and\t\r  co-­‐authors,\t\r  2012:\t\r  Improving\t\r  aerosol\t\r  transport\t\r  to\t\r  high-­‐latitudes\t\r  in\t\r  the\t\r  Community\t\r  Atmosphere\t\r  Model\t\r  CAM5,\t\r  Atmos.\t\r  Chem.\t\r  Phys.\t\r  (submitted).\t\r  \t\r  Wang,\t\r  Q.,\t\r  and\t\r  co-­‐authors,\t\r  2011:\t\r  Sources\t\r  of\t\r  carbonaceous\t\r  aerosols\t\r  and\t\r  deposited\t\r  black\t\r  carbon\t\r  in\t\r  the\t\r  Arctic\t\r  in\t\r  winter-­‐spring:\t\r  implications\t\r  for\t\r  radiative\t\r  forcing.\t\r  Atmos.\t\r  Chem.\t\r  Phys.,\t\r  11,\t\r  12453-­‐12473,\t\r  doi:10.5194/acp-­‐11-­‐12453-­‐2011.\t\r  \t\r  Warren,\t\r  S.G.,\t\r  and\t\r  W.J.\t\r  Wiscombe,\t\r  1980:\t\r  A\t\r  model\t\r  for\t\r  the\t\r  spectral\t\r  albedo\t\r  of\t\r  snow.\t\r  II:\t\r  Snow\t\r  containing\t\r  atmospheric\t\r  aerosols,\t\r  J.\t\r  Atmos.\t\r  Sci.,\t\r  37,\t\r  2734–2745.\t\r  \t\r  Weng,\t\r  E.,\t\r  Y.\t\r  Luo,\t\r  W.\t\r  Wang,\t\r  H.\t\r  Wang,\t\r  D.J.\t\r  Hayes,\t\r  A.D.\t\r  McGuire,\t\r  A.\t\r  Hastings,\t\r  and\t\r  D.S.\t\r  Schimel,\t\r  2012:\t\r  Ecosystem\t\r  carbon\t\r  storage\t\r  capacity\t\r  as\t\r  affected\t\r  by\t\r  disturbance\t\r  regimes:\t\r  A\t\r  general\t\r  theoretical\t\r  model.\t\r  J.\t\r  Geophys.\t\r  Res.,\t\r  117,\t\r  G03014,\t\r  doi:10.1029/2012JG002040\t\r  Wookey,\t\r  P.A.,\t\r  and\t\r  co-­‐authors,\t\r  2009:\t\r  Ecosystem\t\r  Feedbacks\t\r  and\t\r  cascade\t\r  processes:\t\r  understanding\t\r  their\t\r  role\t\r  in\t\r  the\t\r  responses\t\r  of\t\r  arctic\t\r  and\t\r  alpine\t\r  ecosystems\t\r  to\t\r  environmental\t\r  change.\t\r  Global\t\r  \nChange\t\r  Biology,\t\r  15,\t\r  1153-­‐1172.\t\r  Wu,\t\r  D.L.,\t\r  and\t\r  J.N.\t\r  Lee,\t\r  2012:\t\r  Arctic\t\r  low\t\r  cloud\t\r  changes\t\r  as\t\r  observed\t\r  by\t\r  MISR\t\r  and\t\r  CALIOP:\t\r  Implication\t\r  for\t\r  the\t\r  enhanced\t\r  autumnal\t\r  warming\t\r  and\t\r  sea\t\r  ice\t\r  loss,\t\r  J.\t\r  Geophys.\t\r  Res.,\t\r  117,\t\r  D07107,\t\r  doi:10.1029/2011JD017050.\t\r  Zhang,\t\r  X.D.,\t\r  and\t\r  J.E.\t\r  Walsh,\t\r  2006:\t\r  Toward\t\r  a\t\r  seasonally\t\r  ice-­‐covered\t\r  Arctic\t\r  Ocean:\t\r  scenarios\t\r  from\t\r  the\t\r  IPCC\t\r  AR4\t\r  model\t\r  simulations.\t\r  J.\t\r  Climate,\t\r  19,\t\r  1730–1747.\t\r  \t\r   \t\r  \u003c/p\u003e\n\u003cp /\u003e\n\u003c/div\u003e\n\u003cdiv class\u003d\"page\"\u003e\u003cp /\u003e\n\u003cp\u003e\t\r  \u003c/p\u003e\n\u003cp\u003e\t\r   46\t\r  \n\u003c/p\u003e\n\u003cp\u003eAppendix\t\r  A:\t\r  Acronyms\t\r  3-­‐D\t\r   \t\r   Three-­‐dimensional\t\r  4DDA\t\r   \t\r   Four-­‐Dimensional\t\r  Data\t\r  Assimilation\t\r  ABLE\t\r   \t\r   Arctic\t\r  Boundary\t\r  Layer\t\r  Expedition\t\r  ABoVE\t\r   \t\r   Arctic-­‐Boreal\t\r  Vulnerability\t\r  Experiment\t\r  ABZ\t\r   \t\r   Arctic-­‐Boreal\t\r  Zone\t\r  ADAPT\t\r  \t\r   Arctic\t\r  Development\t\r  and\t\r  Adaptation\t\r  to\t\r  Permafrost\t\r  in\t\r  Transition\t\r  AEROCAN\t\r   AERONET\t\r  Canada\t\r  AERONET\t\r   AErosol\t\r  RObotic\t\r  NETwork\t\r  AGCM\t\r   \t\r   Atmospheric\t\r  General\t\r  Circulation\t\r  Model\t\r  AIRS\t\r   \t\r   Atmospheric\t\r  Infrared\t\r  Sounder\t\r  AMSU\t\r   \t\r   Advanced\t\r  Microwave\t\r  Sounding\t\r  Unit\t\r  AMSR-­‐E\t\r   Advanced\t\r  Microwave\t\r  Scanning\t\r  Radiometer\t\r  -­‐\t\r  Earth\t\r  Observing\t\r  System\t\r  AOD\t\r   \t\r   Aerosol\t\r  Optical\t\r  Depth\t\r  AOMIP\t\r  \t\r   Arctic\t\r  Ocean\t\r  Model\t\r  Intercomparison\t\r  Project\t\r  AON\t\r   \t\r   Arctic\t\r  Observing\t\r  Network\t\r  AR4\t\r  (5)\t\r   Fourth\t\r  (Fifth)\t\r  Assessment\t\r  Report\t\r  of\t\r  the\t\r  IPCC\t\r  ARCTAS\t\r   Arctic\t\r  Research\t\r  of\t\r  the\t\r  Composition\t\r  of\t\r  the\t\r  Troposphere\t\r  from\t\r  Aircraft\t\r  and\t\r  Satellites\t\r  ARM\t\r   \t\r   Atmospheric\t\r  Radiation\t\r  Measurement\t\r  ASCENDS\t\r   Active\t\r  Sensing\t\r  of\t\r  CO2\t\r  Emissions\t\r  over\t\r  Nights,\t\r  Days,\t\r  and\t\r  Seasons\t\r  ASOF\t\r  \t\r   \t\r   Arctic/Subarctic\t\r  Ocean\t\r  Fluxes\t\r  ATMS\t\r   \t\r   Advanced\t\r  Technology\t\r  Microwave\t\r  Sounder\t\r  AVHRR\t\r  \t\r   Advanced\t\r  Very\t\r  High\t\r  Resolution\t\r  Radiometer\t\r  BC\t\r   \t\r   Black\t\r  carbon\t\r  BERMS\t\r  \t\r   Boreal\t\r  Ecosystem\t\r  Research\t\r  and\t\r  Monitoring\t\r  Sites\t\r  BGC\t\r   \t\r   Biogeochemical\t\r  BL\t\r   \t\r   Boundary\t\r  Layer\t\r  BOREAS\t\r  \t\r   Boreal\t\r  Ecosystem–Atmosphere\t\r  Study\t\r  CADIS\t\r   \t\r   Cooperative\t\r  Arctic\t\r  Data\t\r  and\t\r  Information\t\r  Service\t\r  CALIOP\t\r  \t\r   Cloud-­‐Aerosol\t\r  Lidar\t\r  with\t\r  Orthogonal\t\r  Polarisation\t\r  CALIPSO\t\r   Cloud-­‐Aerosol\t\r  Lidar\t\r  and\t\r  Infrared\t\r  Pathfinder\t\r  Satellite\t\r  Observations\t\r  CALM\t\r  \t\r   \t\r   Circumpolar\t\r  Active\t\r  Layer\t\r  Monitoring\t\r  program\t\r  \t\r  CARVE\t\r  \t\r   Carbon\t\r  in\t\r  Arctic\t\r  Reservoirs\t\r  Vulnerability\t\r  Experiment\t\r  C4MIP\t\r  \t\r   \t\r   Coupled\t\r  Climate–Carbon\t\r  Cycle\t\r  Model\t\r  Intercomparison\t\r  Project\t\r  \t\r  CCN\t\r   \t\r   Cloud\t\r  Condensation\t\r  Nuclei\t\r  CCSM4\t\r  \t\r   Community\t\r  Climate\t\r  System\t\r  Model\t\r  version\t\r  4\t\r  CERES\t\r   \t\r   Clouds\t\r  and\t\r  Earth\u0027s\t\r  Radiant\t\r  Energy\t\r  System\t\r  CFMIP\t\r   \t\r   Cloud\t\r  Feedbacks\t\r  Model\t\r  Intercomparison\t\r  Project\t\r  CGCM\t\r   \t\r   Coupled\t\r  General\t\r  Circulation\t\r  Model\t\r  CliC\t\r   \t\r   Climate\t\r  and\t\r  Cryosphere\t\r  CLM4\t\r   \t\r   Community\t\r  Land\t\r  Surface\t\r  Model,\t\r  Version\t\r  4\t\r  CMIP3(5)\t\r   Coupled\t\r  Model\t\r  Intercomparison\t\r  Project,\t\r  Phase\t\r  3\t\r  (5)\t\r  COSP\t\r   \t\r   CFMIP\t\r  Observation\t\r  Simulator\t\r  Package\t\r  CPR\t\r   \t\r   Cloud\t\r  Profiling\t\r  Radar\t\r  CrIS\t\r   \t\r   Cross-­‐track\t\r  Infrared\t\r  Sounder\t\r  DIC\t\r   \t\r   Dissolved\t\r  Inorganic\t\r  Carbon\t\r  DMS\t\r   \t\r   Dimethylsulfide\t\r  DoE\t\r   \t\r   Department\t\r  of\t\r  Energy\t\r  DGVM\t\r   \t\r   Dynamic\t\r  Global\t\r  Vegetation\t\r  Model\t\r  \u003c/p\u003e\n\u003cp /\u003e\n\u003c/div\u003e\n\u003cdiv class\u003d\"page\"\u003e\u003cp /\u003e\n\u003cp\u003e\t\r  \u003c/p\u003e\n\u003cp\u003e\t\r   47\t\r  \n\u003c/p\u003e\n\u003cp\u003eEM\t\r   \t\r   Electro-­‐Magnetic\t\r  EP\t\r   \t\r   Export\t\r  of\t\r  POC\t\r  ERA\t\r   \t\r   ECMWF\t\r  Re-­‐Analysis\t\r  ESM\t\r   \t\r   Earth\t\r  System\t\r  Model\t\r  ESMR\t\r   \t\r   Electrically\t\r  Scanning\t\r  Microwave\t\r  Radiometer\t\r  ESRL\t\r   \t\r   Earth\t\r  System\t\r  Research\t\r  Laboratory\t\r  GCM\t\r   \t\r   Global\t\r  Climate\t\r  Model\t\r  GHG\t\r   \t\r   Greenhouse\t\r  Gas\t\r  GOSAT\t\r  \t\r   Greenhouse\t\r  gases\t\r  Observing\t\r  SATellite\t\r  GPP\t\r   \t\r   Gross\t\r  Primary\t\r  Productivity\t\r  GRACE\t\r  \t\r   Gravity\t\r  Recovery\t\r  and\t\r  Climate\t\r  Experiment\t\r  IASC\t\r   \t\r   International\t\r  Arctic\t\r  Science\t\r  Committee\t\r  IASI\t\r   \t\r   Infrared\t\r  Atmospheric\t\r  Sounding\t\r  Interferometer\t\r  ICECAPS\t\r  \t\r   Integrated\t\r  Characterization\t\r  of\t\r  Energy,\t\r  Clouds,\t\r  Atmospheric\t\r  State,\t\r  and\t\r  Precipitation\t\r  over\t\r  Summit\t\r  ICESCAPE\t\r   Impacts\t\r  of\t\r  Climate\t\r  on\t\r  EcoSystems\t\r  and\t\r  Chemistry\t\r  of\t\r  the\t\r  Arctic\t\r  Pacific\t\r  Environment\t\r  IMPROVE\t\r   Interagency\t\r  Monitoring\t\r  of\t\r  Protected\t\r  Visual\t\r  Environments\t\r  IN\t\r   \t\r   Ice\t\r  Nuclei\t\r  InSAR\t\r   \t\r   Interferometric\t\r  Synthetic\t\r  Aperture\t\r  Radar\t\r  IPCC\t\r   \t\r   Intergovernmental\t\r  Panel\t\r  on\t\r  Climate\t\r  Change\t\r  ISCCP\t\r   \t\r   International\t\r  Satellite\t\r  Cloud\t\r  Climatology\t\r  Project\t\r  ITEX\t\r   \t\r   International Tundra Experiment\t\r  LIDAR\t\r   \t\r   Light\t\r  Detection\t\r  and\t\r  Ranging\t\r  LSM\t\r   \t\r   Land\t\r  Surface\t\r  Model\t\r  LTER\t\r   \t\r   Long\t\r  Term\t\r  Ecological\t\r  Research\t\r  LW\t\r   \t\r   Longwave\t\r  MISR\t\r   \t\r   Multi-­‐angle\t\r  Imaging\t\r  SpectroRadiometer\t\r  MLS\t\r   \t\r   Microwave\t\r  Limb\t\r  Sounder\t\r  MODIS\t\r   \t\r   Moderate\t\r  Resolution\t\r  Imaging\t\r  Spectroradiometer\t\r  MOSAiC\t\r   Multi-­‐disciplinary\t\r  drifting\t\r  Observatory\t\r  for\t\r  the\t\r  Study\t\r  of\t\r  the\t\r  Arctic\t\r  Climate\t\r  M-­‐PACE\t\r   Mixed-­‐Phase\t\r  Arctic\t\r  Cloud\t\r  Experiment\t\r  MsTMIP\t\r   Multi-­‐scale\t\r  Synthesis\t\r  and\t\r  Terrestrial\t\r  Model\t\r  Intercomparison\t\r  Project\t\r  NACP\t\r   \t\r   North\t\r  American\t\r  Carbon\t\r  Program\t\r  NADW\t\r   \t\r   North\t\r  Atlantic\t\r  Deep\t\r  Water\t\r  NASA\t\r   \t\r   National\t\r  Aeronautics\t\r  and\t\r  Space\t\r  Administration\t\r  NCSCD\t\r  \t\r  \t\r   Northern\t\r  Circumpolar\t\r  Soil\t\r  Carbon\t\r  Database\t\r  NEE\t\r   \t\r   Net\t\r  Ecosystem\t\r  Exchange\t\r  \t\r  NGEE\t\r   \t\r   Next\t\r  Generation\t\r  Ecosystem\t\r  Experiments\t\r  NH\t\r   \t\r   Northern\t\r  Hemisphere\t\r  NIR\t\r   \t\r   Near\t\r  Infra-­‐Red\t\r  NOAA\t\r   \t\r   National\t\r  Oceanic\t\r  and\t\r  Atmospheric\t\r  Administration\t\r  NOWES\t\r   Northern\t\r  Wetlands\t\r  Study\t\r  NPP\t\r   \t\r   National\t\r  Polar-­‐orbiting\t\r  Partnership\t\r  NPP\t\r   \t\r   Net\t\r  Primary\t\r  Productivity\t\r  (context\t\r  provides\t\r  the\t\r  distinction\t\r  from\t\r  the\t\r  above)\t\r  NSA\t\r   \t\r   North\t\r  Slope\t\r  of\t\r  Alaska\t\r  \t\r  NSIDC\t\r   \t\r   National\t\r  Snow\t\r  and\t\r  Ice\t\r  Data\t\r  Center\t\r  NSF\t\r   \t\r   National\t\r  Science\t\r  Foundation\t\r  OC\t\r   \t\r   Organic\t\r  Carbon\t\r  OCO\t\r   \t\r   Orbiting\t\r  Carbon\t\r  Observatory\t\r  OGCM\t\r   \t\r   Ocean\t\r  General\t\r  Circulation\t\r  Model\t\r  \u003c/p\u003e\n\u003cp /\u003e\n\u003c/div\u003e\n\u003cdiv class\u003d\"page\"\u003e\u003cp /\u003e\n\u003cp\u003e\t\r  \u003c/p\u003e\n\u003cp\u003e\t\r   48\t\r  \n\u003c/p\u003e\n\u003cp\u003eOPP\t\r   \t\r   Office\t\r  of\t\r  Polar\t\r  Programs\t\r  OSSE\t\r   \t\r   Observing\t\r  System\t\r  Simulation\t\r  Experiment\t\r  PARASOL\t\r   Polarization\t\r  and\t\r  Anisotropy\t\r  of\t\r  Reflectances\t\r  for\t\r  Atmospheric\t\r  Sciences\t\r  coupled\t\r  with\t\r  Observations\t\r  from\t\r  a\t\r  lidar\t\r  \t\r  PBL\t\r   \t\r   Planetary\t\r  Boundary\t\r  Layer\t\r  PCS\t\r   \t\r   Physical\t\r  Climate\t\r  System\t\r  PP\t\r   \t\r   Primary\t\r  Productivity\t\r  RS\t\r   \t\r   Remote\t\r  Sensing\t\r  SAR\t\r   \t\r   Synthetic\t\r  Aperture\t\r  Radar\t\r  \t\r  SAT\t\r   \t\r   Surface\t\r  Air\t\r  Temperature\t\r  SEARCH\t\r   Study\t\r  of\t\r  Environmental\t\r  Arctic\t\r  Change\t\r  SeaWIFS\t\r   Sea-­‐viewing\t\r  Wide\t\r  Field-­‐of-­‐view\t\r  Sensor\t\r  SHEBA\t\r  \t\r   Surface\t\r  Heat\t\r  Budget\t\r  of\t\r  Arctic\t\r  Ocean\t\r  SLP\t\r   \t\r   Sea\t\r  Level\t\r  Pressure\t\r  SMAP\t\r   \t\r   Soil\t\r  Moisture\t\r  Active\t\r  Passive\t\r  mission\t\r  SMMR\t\r   \t\r   Scanning\t\r  Multichannel\t\r  Microwave\t\r  Radiometer\t\r  SMOS\t\r   \t\r   Soil\t\r  Moisture\t\r  and\t\r  Ocean\t\r  Salinity\t\r  mission\t\r  SOC\t\r   \t\r   Soil\t\r  Organic\t\r  Carbon\t\r  SOM\t\r   \t\r   Soil\t\r  Organic\t\r  Matter\t\r  SRES\t\r   \t\r   Special\t\r  Report\t\r  Emissions\t\r  Scenario\t\r  SSMI/S\t\r  \t\r   Special\t\r  Sensor\t\r  Microwave\t\r  Imager\t\r  /\t\r  Sounder\t\r   \t\r   \t\r  SW\t\r   \t\r   Shortwave\t\r  SWE\t\r   \t\r   Snow\t\r  Water\t\r  Equivalent\t\r  SWOT\t\r   \t\r   Surface\t\r  Water\t\r  Ocean\t\r  Topography\t\r  mission\t\r  TCCON\t\r  \t\r  \t\r   Total\t\r  Carbon\t\r  Column\t\r  Observing\t\r  Network\t\r  TES\t\r   \t\r   Tropospheric\t\r  Emission\t\r  Spectrometer\t\r  TransCom\t\r   Atmospheric\t\r  Tracer\t\r  Transport\t\r  Model\t\r  Intercomparison\t\r  Project\t\r  UAV\t\r   \t\r   Unmanned\t\r  Aerial\t\r  Vehicle\t\r  VIIRS\t\r   \t\r   Visible\t\r  Infrared\t\r  Imaging\t\r  Radiometer\t\r  Suite\t\r  \t\r  WWRP\t\r  \t\r   World\t\r  Weather\t\r  Research\t\r  Program\t\r  YOPP\t\r   \t\r   Year\t\r  of\t\r  Polar\t\r  Prediction\t\r  \t\r   \t\r  \u003c/p\u003e\n\u003cp /\u003e\n\u003c/div\u003e\n\u003cdiv class\u003d\"page\"\u003e\u003cp /\u003e\n\u003cp\u003e\t\r  \u003c/p\u003e\n\u003cp\u003e\t\r   49\t\r  \n\u003c/p\u003e\n\u003cp\u003eAppendix\t\r  B:\t\r  Relevant\t\r  Field\t\r  Campaigns\t\r  and\t\r  Measurement\t\r  Programs\t\r  \t\r  \nABoVE\t\r  –\t\r  the\t\r  Arctic-­‐Boreal\t\r  Vulnerability\t\r  Experiment\t\r  (NASA)\t\r  http://cce.nasa.gov/terrestrial_ecology/scoping.html#above\t\r  ABoVE\t\r  will\t\r  be\t\r  an\t\r  international\t\r  research\t\r  initiative\t\r  led\t\r  by\t\r  NASA.\t\r  ABoVE\t\r  is\t\r  designed\t\r  to\t\r  produce\t\r  new\t\r  knowledge\t\r   needed\t\r   to\t\r   understand\t\r   how\t\r   climate\t\r   change\t\r   impacts\t\r   ecosystems\t\r   in\t\r   the\t\r   High\t\r   Northern\t\r  Latitude\t\r   region,\t\r   and\t\r   how\t\r   these\t\r   changes\t\r   produce\t\r   feedbacks\t\r   to\t\r   climate\t\r   and\t\r   are\t\r   influencing\t\r  ecosystem\t\r   services.\t\r   ABoVE\t\r  was\t\r   scoped\t\r   to\t\r   focus\t\r   on\t\r  processes,\t\r   feedbacks\t\r  and\t\r   interactions\t\r   that\t\r   are\t\r  regulated\t\r  by\t\r  climate\t\r  and\t\r  influence\t\r  the\t\r  vulnerability\t\r  and\t\r  resilience\t\r  of\t\r  Arctic\t\r  and\t\r  Boreal\t\r  ecosystems\t\r  and\t\r   landscapes.\t\r   Particular\t\r   focus\t\r   is\t\r   placed\t\r   on\t\r   the\t\r   roles\t\r   of\t\r   and\t\r   interactions\t\r   between\t\r   disturbance,\t\r  permafrost,\t\r  and\t\r  surface\t\r  hydrology\t\r  –\t\r  processes\t\r  that\t\r  are\t\r  key\t\r  to\t\r  high\t\r  northern\t\r  latitude\t\r  biomes.\t\r  \t\r  ABoVE\t\r   is\t\r   designed\t\r   around\t\r   intensive\t\r   study\t\r   sites\t\r   located\t\r   in\t\r   areas\t\r   that\t\r   (a)\t\r   represent\t\r   major\t\r  ecosystem/landscape\t\r   types;\t\r   (b)\t\r   span\t\r   gradients\t\r   in\t\r   permafrost\t\r   and\t\r   surface\t\r   hydrology;\t\r   (c)\t\r   include\t\r  areas\t\r   where\t\r   disturbances\t\r   are\t\r   common;\t\r   and\t\r   (d)\t\r   include\t\r   ongoing\t\r   intensive\t\r   and/or\t\r   long\t\r   term\t\r  research\t\r  projects\t\r   (such\t\r  as\t\r  LTERs)\t\r   sponsored\t\r  by\t\r   the\t\r  Canadian,\t\r   Japanese,\t\r  and\t\r  U.S.\t\r  agencies.\t\r  These\t\r  intensive\t\r  study\t\r  sites\t\r  will\t\r  be\t\r  located\t\r  along\t\r  three\t\r  N-­‐S\t\r  transects\t\r  (western\t\r  Alaska,\t\r  central\t\r  Alaska\t\r  and\t\r  western\t\r  Canada.\t\r  The\t\r  field\t\r  campaign\t\r  will\t\r  focus\t\r  on\t\r  collection\t\r  of\t\r  a\t\r  similar\t\r  suite\t\r  of\t\r  measurements\t\r  and\t\r  observations\t\r  in\t\r  each\t\r  intensive\t\r  study\t\r  area\t\r  to\t\r  enable\t\r  the\t\r  improvement\t\r  and\t\r  validation\t\r  of\t\r  key\t\r  models.\t\r  The\t\r  field\t\r  campaign\t\r  will\t\r  also\t\r  include\t\r  experiments\t\r  and\t\r  studies\t\r  of\t\r  key\t\r  processes.\t\r  Many\t\r  of\t\r  experiments\t\r  and\t\r  studies\t\r  at\t\r  intensive\t\r  sites\t\r  will\t\r  be\t\r  based\t\r  on\t\r  research\t\r  being\t\r  sponsored\t\r  by\t\r  collaborating\t\r  agencies\t\r  and\t\r  organizations.\t\r  Secondary\t\r  study\t\r  sites\t\r  will\t\r  be\t\r  established\t\r  to\t\r  address\t\r  knowledge\t\r  gaps\t\r  that\t\r  focus\t\r  on\t\r  a\t\r  specific\t\r  area\t\r  (e.g.,\t\r  impacts\t\r  of\t\r  insects).\t\r  \nAERONET\t\r  (AErosol\t\r  RObotic\t\r  NETwork)\t\r  \t\r  http://aeronet.gsfc.nasa.gov/\t\r  AERONET\t\r   is\t\r   a\t\r   network\t\r   of\t\r   ground-­‐based\t\r   sun\t\r   photometers,\t\r   which\t\r   measure\t\r   atmospheric\t\r   aerosol\t\r  properties,\t\r   providing\t\r   continuous\t\r   cloud-­‐screened\t\r   observations\t\r   of\t\r   spectral\t\r   aerosol\t\r   optical\t\r   depth\t\r  (AOD),\t\r   precipitable\t\r   water,\t\r   and\t\r   inversion\t\r   aerosol\t\r   products\t\r   in\t\r   diverse\t\r   aerosol\t\r   regimes.\t\r   For\t\r   more\t\r  than\t\r  a\t\r  decade\t\r  the\t\r  AEROCAN\t\r  sun\t\r  photometry\t\r  network\t\r  has\t\r  generated\t\r  aerosol\t\r  concentration\t\r  and\t\r  size\t\r  information\t\r  at\t\r  sites\t\r  across\t\r  Canada.\t\r  \nArctic\t\r  Boundary\t\r  Layer\t\r  Expedition\t\r  (ABLE-­‐3\t\r  A,\t\r  ABLE-­‐3B,\t\r  NASA),\t\r  July-­‐August\t\r  1988\t\r  and\t\r  1990\t\r  The\t\r   Arctic\t\r   Boundary\t\r   Layer\t\r   Expeditions\t\r   (ABLE)\t\r   3A\t\r   and\t\r   3B\t\r   were\t\r   conducted\t\r   in\t\r   arctic\t\r   and\t\r   boreal\t\r  North\t\r   America.\t\r   \t\r   ABLE-­‐3A\t\r   used\t\r   ground,\t\r   aircraft\t\r   and\t\r   satellite\t\r   measurements\t\r   to\t\r   characterize\t\r   the\t\r  chemistry\t\r  and\t\r  dynamics\t\r  of\t\r  the\t\r  lower\t\r  atmosphere\t\r  during\t\r  July-­‐August\t\r  1988,\t\r  with\t\r  research\t\r  areas\t\r  in\t\r  Alaska’s\t\r   North\t\r   Slope\t\r   and\t\r   Yukon-­‐Kuskokwim\t\r   Delta\t\r   regions.\t\r   \t\r   ABLE-­‐3B\t\r   was\t\r   focused\t\r   on\t\r   the\t\r   north\t\r  central\t\r  and\t\r  northeastern\t\r  regions\t\r  of\t\r  Canada\t\r  during\t\r  July-­‐August\t\r  1990,\t\r  co-­‐incident\t\r  with\t\r  the\t\r  Northern\t\r  Wetlands\t\r   Study\t\r   (NOWES)\t\r   in\t\r   the\t\r   Hudson\t\r   Bay\t\r   Lowlands\t\r   (Glooschenko\t\r   et\t\r   al.\t\r   1994).\t\r   A\t\r   latitudinal\t\r  study\t\r  of\t\r  tropospheric\t\r  trace\t\r  gas\t\r  and\t\r  aerosol\t\r  composition\t\r  was\t\r  also\t\r  conducted\t\r  along\t\r  the\t\r  east\t\r  coast\t\r  of\t\r  North\t\r   America\t\r   from\t\r   37°N\t\r   to\t\r   65°N.\t\r   The\t\r   expedition\t\r   used\t\r   ground,\t\r   aircraft,\t\r   and\t\r   satellite\t\r  measurements\t\r  to\t\r  study\t\r  source,\t\r  sink,\t\r  and\t\r  transport\t\r  processes\t\r  that\t\r  influence\t\r  the\t\r  chemical\t\r  climate\t\r  of\t\r  subarctic\t\r  and\t\r  Arctic\t\r  regions\t\r  of\t\r  Canada.\t\r  Intensive\t\r  studies,\t\r  involving\t\r  coordinated\t\r  ground\t\r  and\t\r  aircraft\t\r  measurements,\t\r   were\t\r   centered\t\r   on\t\r   Kinosheo\t\r   Lake\t\r   in\t\r   the\t\r   Hudson\t\r   Bay\t\r   lowlands\t\r   on\t\r   and\t\r  forest/wetland\t\r   sites\t\r   near\t\r   Schefferville,\t\r   Quebec.\t\r   The\t\r   emphases\t\r   placed\t\r   in\t\r   the\t\r   experimental\t\r   design\t\r  included\t\r  (1)\t\r  biosphere-­‐atmosphere\t\r  interactions\t\r  on\t\r  the\t\r  atmospheric\t\r  biogeochemical\t\r  cycles\t\r  of\t\r  CO2,\t\r  CO,\t\r  CH4\t\r  and\t\r  other\t\r  chemical\t\r  species,\t\r  and\t\r  (2)\t\r  the\t\r  importance\t\r  of\t\r   long-­‐range\t\r  transport\t\r  as\t\r  a\t\r  source\t\r  of\t\r  airborne\t\r  pollutants.\t\r  More\t\r  information\t\r  on\t\r  ABLE-­‐3A\t\r  and\t\r  ABLE-­‐3B\t\r  is\t\r  available\t\r  in\t\r  Harriss\t\r  et\t\r  al.\t\r  (1992,\t\r  \u003c/p\u003e\n\u003cp /\u003e\n\u003c/div\u003e\n\u003cdiv class\u003d\"page\"\u003e\u003cp /\u003e\n\u003cp\u003e\t\r  \u003c/p\u003e\n\u003cp\u003e\t\r   50\t\r  \n\u003c/p\u003e\n\u003cp\u003e1994).\t\r  \nArctic\t\r  Observing\t\r  Network\t\r  (AON,\t\r  NSF)\t\r  http://www.arcus.org/search/aon\t\r  AON\t\r   is\t\r   an\t\r   integral\t\r   part\t\r   of\t\r   the\t\r   SEARCH\t\r   program,\t\r   as\t\r   an\t\r   NSF\t\r   initiative\t\r   growing\t\r   out\t\r   of\t\r   the\t\r  International\t\r  Polar\t\r  Year\t\r  (IPY)\t\r  to\t\r  improve\t\r  observational\t\r  capabilities\t\r  in\t\r  the\t\r  Arctic\t\r  and\t\r  leave\t\r  a\t\r  long-­‐term\t\r   legacy\t\r   for\t\r   the\t\r  benefit\t\r   of\t\r   science\t\r  and\t\r   society.\t\r  AON\t\r  data\t\r  will\t\r   contribute\t\r   to\t\r   scientific\t\r   research\t\r  leading\t\r   to\t\r   (1)\t\r   increased\t\r   knowledge\t\r   and\t\r   understanding\t\r   of\t\r   the\t\r   regional\t\r   and\t\r   global\t\r   causes\t\r   and\t\r  consequences\t\r  of\t\r  present-­‐day\t\r  environmental\t\r  arctic\t\r  change,\t\r   (2)\t\r  scenarios\t\r   for\t\r  and\t\r  prediction\t\r  of\t\r   the\t\r  course\t\r  of\t\r  future\t\r  arctic\t\r  change\t\r  and\t\r  its\t\r  regional\t\r  and\t\r  global\t\r  consequences,\t\r  and\t\r  (3)\t\r  the\t\r  development\t\r  of\t\r  adaptive\t\r  responses\t\r  to\t\r  arctic\t\r  change.\t\r  AON\t\r  currently\t\r  consists\t\r  of\t\r  51\t\r  projects\t\r  funded\t\r  by\t\r  the\t\r  NSF\t\r  Office\t\r  of\t\r   Polar\t\r   Programs.\t\r   The\t\r   AON\t\r   projects\t\r   fall\t\r   into\t\r   the\t\r   following\t\r   SEARCH\t\r   Implementation\t\r   Plan\t\r  categories:\t\r   Atmosphere;\t\r   Ocean\t\r   and\t\r   Sea\t\r   Ice;\t\r   Hydrology/Cryosphere;\t\r   Terrestrial\t\r   Ecosystems;\t\r   and\t\r  Human\t\r  Dimensions.\t\r  The\t\r  Cooperative\t\r  Arctic\t\r  Data\t\r  and\t\r  Information\t\r  Service\t\r  (CADIS)\t\r  supports\t\r  AON\t\r  by\t\r  providing\t\r   portal\t\r   for\t\r   data\t\r   discovery,\t\r   provide\t\r   near-­‐real-­‐time\t\r   data\t\r   delivery,\t\r   a\t\r   repository\t\r   for\t\r   data\t\r  storage,\t\r  and\t\r  tools\t\r  to\t\r  manipulate\t\r  data.\t\r  \t\r  \t\r  \nADAPT\t\r  http://www.cen.ulaval.ca/adapt/index.php\t\r  The\t\r  Canadian\t\r  ADAPT\t\r  mission\t\r  is\t\r  to\t\r  produce\t\r  an\t\r  ‘Integrated\t\r  Permafrost\t\r  Systems\t\r  Science’\t\r  framework\t\r  that\t\r  will\t\r  be\t\r  used\t\r  to\t\r  help\t\r  generate\t\r  sustainable\t\r  development\t\r  and\t\r  adaptation\t\r  strategies\t\r  for\t\r  the\t\r  North\t\r  in\t\r   the\t\r   context\t\r  of\t\r   rapid\t\r   socio-­‐economic\t\r  and\t\r   climate\t\r   change.\t\r   It\t\r  will\t\r  work\t\r  at\t\r  numerous\t\r   sites\t\r   across\t\r  northern\t\r  Canada,\t\r  from\t\r  Yukon\t\r  to\t\r  Labrador,\t\r  to\t\r  study\t\r  the\t\r  impact\t\r  of\t\r  changing\t\r  permafrost\t\r  and\t\r  snowfall\t\r  on\t\r  landscapes,\t\r  wildlife,\t\r  northern\t\r  communities\t\r  and\t\r  northern\t\r  industries.\t\r  ADAPT\t\r  is\t\r  organized\t\r  as\t\r  four\t\r  interlocking\t\r  research\t\r  modules\t\r  to\t\r  address\t\r  a\t\r  broad,\t\r  representative\t\r  spectrum\t\r  of\t\r  natural\t\r  science\t\r  and\t\r  engineering\t\r  issues\t\r  within\t\r  the\t\r  Integrated\t\r  Permafrost\t\r  Systems\t\r  framework:\t\r  (1) Permafrost\t\r  dynamics\t\r  in\t\r  natural\t\r  and\t\r  engineered\t\r  environments;\t\r  (2) Permafrost\t\r  and\t\r  aquatic\t\r  ecosystems;\t\r  (3) Microbes\t\r  and\t\r  biogeochemical\t\r  fluxes\t\r  of\t\r  nutrients\t\r  and\t\r  carbon;\t\r  and\t\r  (4) Tundra\t\r  ecosystems:\t\r  vegetation\t\r  and\t\r  wildlife.\t\r  The\t\r  project,\t\r  funded\t\r  under\t\r  NSERC’s\t\r  Discovery\t\r  Frontiers\t\r  initiative,\t\r  is\t\r  led\t\r  by\t\r  Université\t\r  Laval\t\r  ecologist\t\r  Warwick\t\r  Vincent.\t\r  \nArctic/Subarctic\t\r  Ocean\t\r  Fluxes\t\r  (ASOF)\t\r  http://www.asof.awi.de/en/home/\t\r  ASOF\t\r   is\t\r  an\t\r   international\t\r  program\t\r  on\t\r   the\t\r  oceanography\t\r  of\t\r   the\t\r  Arctic\t\r  and\t\r  Subarctic\t\r  seas\t\r  and\t\r   their\t\r  role\t\r   in\t\r   climate.\t\r  ASOF\t\r   focuses\t\r  on\t\r  ocean\t\r   fluxes\t\r  of\t\r  mass,\t\r  heat,\t\r   freshwater,\t\r   and\t\r   ice\t\r   in\t\r   the\t\r  Arctic\t\r   and\t\r  subarctic\t\r   oceans.\t\r   The\t\r   program\t\r   was\t\r   established\t\r   in\t\r   2000\t\r   and\t\r   the\t\r   first\t\r   phase\t\r   from\t\r   2000-­‐2008\t\r  coordinated\t\r   novel\t\r  measurements\t\r   in\t\r   novel\t\r   places\t\r   in\t\r   order\t\r   to\t\r   produce\t\r   a\t\r   baseline\t\r   freshwater\t\r   flux\t\r  budget\t\r   for\t\r  Arctic\t\r   inflows\t\r  and\t\r  outflows.\t\r  Since\t\r  2008,\t\r  the\t\r  second\t\r  phase,\t\r  ASOF\t\r  II,\t\r  still\t\r  has\t\r  a\t\r   focus\t\r  on\t\r  fluxes,\t\r  but\t\r  now\t\r  has\t\r  a\t\r  charge\t\r  to\t\r  apply\t\r  the\t\r  knowledge\t\r  gained\t\r  during\t\r  the\t\r  first\t\r  phase\t\r  to\t\r  broader\t\r  issues\t\r  of\t\r  high\t\r  scientific\t\r  and\t\r  societal\t\r  importance.\t\r  ASOF\t\r  has\t\r  strong\t\r  links\t\r  to\t\r  SEARCH\t\r  (ASOF\t\r  is\t\r  a\t\r  sub-­‐program\t\r  of\t\r   International\t\r   SEARCH),\t\r   CLIVAR\t\r   (an\t\r   endorsed\t\r   program),\t\r   CliC\t\r   (an\t\r   endorsed\t\r   program),\t\r   and\t\r  DAMOCLES\t\r  (which\t\r  has\t\r  substantial\t\r  overlap\t\r  with\t\r  ASOF).\t\r  \t\r  \n\t\r  \u003c/p\u003e\n\u003cp /\u003e\n\u003c/div\u003e\n\u003cdiv class\u003d\"page\"\u003e\u003cp /\u003e\n\u003cp\u003e\t\r  \u003c/p\u003e\n\u003cp\u003e\t\r   51\t\r  \n\u003c/p\u003e\n\u003cp\u003eAtmospheric\t\r  Radiation\t\r  Measurement\t\r  (ARM,\t\r  DOE)\t\r  http://www.arm.gov\t\r  ARM’s\t\r  North\t\r   Slope\t\r   of\t\r  Alaska\t\r   (NSA)\t\r   site\t\r   is\t\r   providing\t\r  data\t\r   about\t\r   cloud\t\r   and\t\r   radiative\t\r  processes\t\r   at\t\r  high\t\r  latitudes.\t\r  Centered\t\r  at\t\r  Barrow\t\r  and\t\r  extending\t\r  to\t\r  the\t\r  south\t\r  (to\t\r  the\t\r  vicinity\t\r  of\t\r  Atqasuk),\t\r  west\t\r  (to\t\r  the\t\r  vicinity\t\r  of\t\r  Wainwright),\t\r  and\t\r  east\t\r  (towards\t\r  Oliktok),\t\r   the\t\r  NSA\t\r  site\t\r  has\t\r  become\t\r  a\t\r   focal\t\r  point\t\r   for\t\r  atmospheric\t\r  and\t\r  ecological\t\r  research\t\r  activity\t\r  on\t\r  the\t\r  North\t\r  Slope.\t\r  The\t\r  principal\t\r  instrumented\t\r  facility\t\r  was\t\r   installed\t\r  near\t\r  Barrow\t\r   in\t\r  1997,\t\r   followed\t\r  by\t\r   a\t\r   smaller\t\r   remote\t\r   site\t\r   in\t\r  Atqasuk\t\r   in\t\r  1999,\t\r  which\t\r  operated\t\r  through\t\r  2010.\t\r  Ongoing\t\r  ARM\t\r  campaigns\t\r  in\t\r  the\t\r  ABZ\t\r  are:\t\r  Arctic\t\r  Cloud\t\r  Infrared\t\r  Imaging,\t\r  2012.07.16\t\r  -­‐\t\r  2013.09.30,\t\r  at\t\r  or\t\r  close\t\r  to\t\r  the\t\r  Great\t\r  White\t\r  facility\t\r  at\t\r  the\t\r  North\t\r  Slope\t\r  of\t\r  Alaska\t\r  site\t\r  ARM\t\r  Radiosondes\t\r  for\t\r  NPOESS/NPP\t\r  Validation,\t\r  2012.07.09\t\r  -­‐\t\r  2015.12.31\t\r  Barrow\t\r  Black\t\r  Carbon\t\r  Source\t\r  and\t\r  Impact\t\r  Study,\t\r  2012.07.01\t\r  -­‐\t\r  2013.06.30\t\r  Lidar\t\r  support\t\r  for\t\r  ICECAPS\t\r  at\t\r  Summit,\t\r  Greenland,\t\r  2010.04.15\t\r  -­‐\t\r  2014.10.31\t\r  \nBoreal\t\r  Ecosystem\t\r  Research\t\r  and\t\r  Monitoring\t\r  Sites\t\r  (BERMS,\t\r  Canada)\t\r  http://berms.ccrp.ec.gc.ca/Overview/e-­‐overview-­‐about.htm\t\r  The\t\r  BERMS\t\r  program\t\r   is\t\r  a\t\r   joint\t\r   initiative\t\r  of\t\r  Canadian\t\r  government\t\r  agencies,\t\r  universities\t\r  and\t\r  other\t\r  research\t\r  partners.\t\r  \t\r  Their\t\r  main\t\r  objective\t\r  is\t\r  to\t\r  study\t\r  the\t\r  role\t\r  that\t\r  Canadian\t\r  boreal\t\r  forest\t\r  plays\t\r  in\t\r  the\t\r  global\t\r   carbon\t\r  budget\t\r   and\t\r   climate\t\r   change.\t\r  From\t\r  1996\t\r   to\t\r  2006,\t\r   the\t\r  program\t\r  continued\t\r  where\t\r   the\t\r  field\t\r  phase\t\r  of\t\r  BOREAS\t\r  left\t\r  off.\t\r   \t\r  New\t\r  research\t\r  projects\t\r  were\t\r  conducted\t\r  at\t\r  the\t\r  three\t\r  previous\t\r  study\t\r  sites\t\r   in\t\r   the\t\r   southern\t\r  boreal\t\r   forest\t\r  of\t\r  Saskatchewan\t\r   (Old\t\r  Aspen,\t\r  Old\t\r   Jack\t\r  Pine,\t\r  Old\t\r  Black\t\r  Spruce).\t\r  Younger\t\r   forest\t\r   sites\t\r   associated\t\r  with\t\r   the\t\r  main\t\r   sites\t\r  have\t\r  been\t\r   included.\t\r  The\t\r  BERMS\t\r  sites\t\r   are\t\r   the\t\r  flagship\t\r  sites\t\r  in\t\r  the\t\r  Fluxnet-­‐Canada\t\r  network.\t\r  \t\r  \nBoreal\t\r  Ecosystem-­‐Atmosphere\t\r  Study\t\r  (BOREAS)\t\r  \t\r  http://daac.ornl.gov/BOREAS/boreas.shtml\t\r  BOREAS\t\r   was\t\r   a\t\r   large-­‐scale\t\r   experiment\t\r   initiated\t\r   in\t\r   1990\t\r   to\t\r   investigate\t\r   interactions\t\r   between\t\r   the\t\r  boreal\t\r   forest\t\r  biome\t\r  and\t\r  the\t\r  atmosphere.\t\r  Surface,\t\r  airborne,\t\r  and\t\r  satellite-­‐based\t\r  observations\t\r  were\t\r  collected\t\r  at\t\r  representative\t\r  sites\t\r  in\t\r  the\t\r  boreal\t\r  forest\t\r  of\t\r  central\t\r  Canada\t\r  from\t\r  1993\t\r  through\t\r  1996\t\r  to\t\r  study\t\r  the\t\r  biological\t\r  and\t\r  physical\t\r  processes\t\r  and\t\r  conditions\t\r  that\t\r  govern\t\r  the\t\r  exchanges\t\r  of\t\r  radiative\t\r  energy,\t\r  water,\t\r  heat,\t\r  carbon,\t\r  and\t\r  trace\t\r  gases\t\r  between\t\r  boreal\t\r  forest\t\r  ecosystems\t\r  and\t\r  the\t\r  atmosphere,\t\r  particularly\t\r  those\t\r  processes\t\r  that\t\r  may\t\r  be\t\r  sensitive\t\r  to\t\r  global\t\r  change.\t\r  The\t\r  objectives\t\r  of\t\r  the\t\r  BOREAS\t\r  project\t\r  were:\t\r  (1)\t\r  to\t\r  improve\t\r  process\t\r  models\t\r  that\t\r  describe\t\r  the\t\r  exchanges\t\r  of\t\r  radiative\t\r  energy,\t\r  water,\t\r  heat,\t\r   carbon,\t\r   and\t\r   trace\t\r   constituents\t\r   between\t\r   the\t\r   boreal\t\r   forest\t\r   and\t\r   the\t\r   atmosphere;\t\r   and\t\r   (2)\t\r   to\t\r  develop\t\r  methods\t\r   for\t\r   applying\t\r   the\t\r   process\t\r  models\t\r   over\t\r   large\t\r   spatial\t\r   scales\t\r   using\t\r   remote\t\r   sensing\t\r  and\t\r  other\t\r  integrative\t\r  modeling\t\r  techniques.\t\r  \t\r  The\t\r  BOREAS\t\r  Follow-­‐On\t\r  project\t\r  extended\t\r  and\t\r  built\t\r  upon\t\r  the\t\r  original\t\r  BOREAS\t\r  goal\t\r  of\t\r  investigating\t\r  interactions\t\r   between\t\r   the\t\r   boreal\t\r   forest\t\r   biome\t\r   and\t\r   the\t\r   atmosphere\t\r   to\t\r   clarify\t\r   their\t\r   roles\t\r   in\t\r   global\t\r  change.\t\r  A\t\r   common\t\r   set\t\r   of\t\r   existing\t\r  BOREAS\t\r   in\t\r   situ\t\r   and\t\r   remote-­‐sensing\t\r  data\t\r   from\t\r  1993-­‐1996\t\r  was\t\r  compiled\t\r  at\t\r  point,\t\r   study\t\r  area,\t\r   and\t\r   regional\t\r   scales\t\r   for\t\r  use\t\r  by\t\r  Follow-­‐On\t\r   investigators.\t\r   In\t\r   addition\t\r  new\t\r  data\t\r  were\t\r  compiled\t\r  for\t\r  1997-­‐1998.\t\r  \n\t\r  \n\u003c/p\u003e\n\u003cp\u003e\t\r  \u003c/p\u003e\n\u003cp /\u003e\n\u003c/div\u003e\n\u003cdiv class\u003d\"page\"\u003e\u003cp /\u003e\n\u003cp\u003e\t\r  \u003c/p\u003e\n\u003cp\u003e\t\r   52\t\r  \n\u003c/p\u003e\n\u003cp\u003eCircumpolar\t\r  Active\t\r  Layer\t\r  Monitoring\t\r  (CALM,\t\r  NSF)\t\r  http://www.gwu.edu/~calm/\t\r  The\t\r   primary\t\r   goal\t\r   of\t\r   the\t\r   CALM\t\r  program\t\r   is\t\r   to\t\r   observe\t\r   the\t\r   response\t\r   of\t\r   the\t\r   active\t\r   layer\t\r   and\t\r   near-­‐surface\t\r   permafrost\t\r   to\t\r   climate\t\r   change\t\r   over\t\r   long\t\r   (multi-­‐decadal)\t\r   time\t\r   scales.\t\r   The\t\r   CALM\t\r  observational\t\r   network,\t\r   established\t\r   in\t\r   the\t\r   1990s,\t\r   observes\t\r   the\t\r   long-­‐term\t\r   response\t\r   of\t\r   the\t\r   active\t\r  layer\t\r  and\t\r  near-­‐surface\t\r  permafrost\t\r   to\t\r  changes\t\r  and\t\r  variations\t\r   in\t\r  climate\t\r  at\t\r  more\t\r   than\t\r  200\t\r  sites\t\r   in\t\r  both\t\r  hemispheres.\t\r   CALM\t\r   currently\t\r   has\t\r   participants\t\r   from\t\r  15\t\r   countries.\t\r  Majority\t\r   of\t\r   sites\t\r  measure\t\r  active-­‐layer\t\r   thickness\t\r   on\t\r   grids\t\r   ranging\t\r   from\t\r  1\t\r  ha\t\r   to\t\r   1\t\r   km²,\t\r   and\t\r  observe\t\r   soil\t\r   temperatures.\t\r  Most\t\r  sites\t\r  in\t\r  the\t\r  CALM\t\r  network\t\r  are\t\r  located\t\r  in\t\r  Arctic\t\r  and\t\r  Subarctic\t\r  lowlands.\t\r  \t\r  The\t\r  CALM\t\r  program\t\r  began\t\r  in\t\r  1991.\t\r   It\t\r  was\t\r   initially\t\r   affiliated\t\r  with\t\r   the\t\r   International\t\r  Tundra\t\r  Experiment.\t\r   Since\t\r  2009\t\r  CALM\t\r   is\t\r  part\t\r  of\t\r  the\t\r  NSF\t\r  Arctic\t\r  Observing\t\r  Network\t\r  (AON)\t\r  Program.\t\r  \t\r  \nCARVE\t\r  (NASA)\t\r  http://science.nasa.gov/missions/carve/\t\r  The\t\r   Carbon\t\r   in\t\r   Arctic\t\r   Reservoirs\t\r   Vulnerability\t\r   Experiment\t\r   (CARVE)\t\r   is\t\r   one\t\r   of\t\r   the\t\r   first\t\r   of\t\r   NASA’s\t\r  Earth\t\r  Ventures\t\r  (EV-­‐1)\t\r  investigations.\t\r  CARVE\t\r  is\t\r  a\t\r  5-­‐year\t\r  mission\t\r  designed\t\r  to\t\r  quantify\t\r  correlations\t\r  between\t\r   atmospheric\t\r   concentrations\t\r   of\t\r   CO2\t\r   and\t\r   CH4\t\r  with\t\r   surface-­‐atmosphere\t\r   carbon\t\r   fluxes\t\r   and\t\r  surface\t\r   state\t\r   control\t\r   variables\t\r   (soil\t\r   moisture,\t\r   freeze-­‐thaw\t\r   state,\t\r   inundation\t\r   state,\t\r   surface\t\r   soil\t\r  temperature)\t\r   and\t\r   elucidate\t\r   the\t\r   sensitivities\t\r   of\t\r   Arctic\t\r   carbon\t\r   cycle\t\r   processes\t\r   to\t\r   climate\t\r   change.\t\r  CARVE\t\r  will\t\r  use\t\r  the\t\r  Arctic-­‐proven\t\r  C-­‐23\t\r  Sherpa\t\r  aircraft\t\r  to\t\r  fly\t\r  an\t\r  innovative\t\r  airborne\t\r  remote\t\r  sensing\t\r  payload.\t\r   It\t\r   includes\t\r  an\t\r  L-­‐band\t\r  radiometer/radar\t\r  and\t\r  a\t\r  nadir-­‐viewing\t\r  spectrometer\t\r   to\t\r  deliver\t\r   the\t\r  first\t\r   simultaneous\t\r   measurements\t\r   of\t\r   surface\t\r   parameters\t\r   that\t\r   control\t\r   gas\t\r   emissions\t\r   (i.e.,\t\r   soil\t\r  moisture,\t\r  freeze/thaw\t\r  state,\t\r  surface\t\r  temperature)\t\r  and\t\r  total\t\r  atmospheric\t\r  columns\t\r  of\t\r  carbon\t\r  dioxide,\t\r  methane,\t\r   and\t\r   carbon\t\r   monoxide.\t\r   The\t\r   aircraft\t\r   payload\t\r   also\t\r   includes\t\r   a\t\r   gas\t\r   analyzer\t\r   that\t\r   links\t\r  greenhouse\t\r   gas\t\r   measurements\t\r   directly\t\r   to\t\r   WMO\t\r   standards.\t\r   Deployments\t\r   will\t\r   occur\t\r   during\t\r   the\t\r  spring,\t\r  summer\t\r  and\t\r  early\t\r   fall\t\r  when\t\r  Arctic\t\r  carbon\t\r   fluxes\t\r  are\t\r   large\t\r  and\t\r  change\t\r  rapidly.\t\r  Further,\t\r  at\t\r  these\t\r  times,\t\r  the\t\r  sensitivities\t\r  of\t\r  ecosystems\t\r  to\t\r  external\t\r  forces\t\r  such\t\r  as\t\r  fire\t\r  and\t\r  anomalous\t\r  variability\t\r  of\t\r  temperature\t\r  and\t\r  precipitation\t\r  are\t\r  maximized.\t\r  Continuous\t\r  ground-­‐based\t\r  measurements\t\r  provide\t\r  temporal\t\r   and\t\r   regional\t\r   context\t\r   as\t\r  well\t\r   as\t\r   calibration\t\r   for\t\r   CARVE\t\r   airborne\t\r  measurements.\t\r   Science\t\r  operations\t\r  are\t\r  scheduled\t\r  for\t\r  2012-­‐2015.\t\r  \t\r  \nGlobal\t\r  Rivers\t\r  Project\t\r  http://www.whoi.edu/page.do?pid\u003d19735\t\r  This\t\r   is\t\r   an\t\r   NSF-­‐funded\t\r   effort\t\r   of\t\r   WHOI\t\r   and\t\r   WHRC\t\r   to\t\r   characterize\t\r   the\t\r   sources,\t\r   pathways\t\r   and\t\r  timescales\t\r   of\t\r   riverine\t\r   export\t\r   of\t\r   organic\t\r   and\t\r   inorganic\t\r   carbon\t\r   from\t\r   land\t\r   to\t\r   the\t\r   ocean.\t\r   \t\r   This\t\r   is\t\r  accomplished\t\r  by\t\r  integrating\t\r  detailed\t\r  geochemical\t\r  information\t\r  on\t\r  temporal\t\r  and\t\r  spatial\t\r  changes\t\r  in\t\r  the\t\r  composition\t\r  of\t\r  the\t\r  dissolved\t\r  and\t\r  particulate\t\r  river\t\r  loads\t\r  with\t\r  spatially\t\r  and\t\r  temporally\t\r  resolved\t\r  data\t\r  on\t\r  relevant\t\r  ecosystem,\t\r  hydrologic,\t\r  geologic,\t\r  geomorphologic\t\r  and\t\r  climatologic\t\r  characteristics\t\r  derived\t\r   from\t\r  remote\t\r  sensing\t\r  and\t\r  GIS\t\r  mapping.\t\r   \t\r  The\t\r  study\t\r   is\t\r   conducted\t\r  on\t\r  six\t\r   large\t\r  river\t\r  basins.\t\r  Rivers\t\r  relevant\t\r  to\t\r  the\t\r  ABZ\t\r  are\t\r  the\t\r  Lena\t\r  and\t\r  Kolyma\t\r  Rivers\t\r  that\t\r  feed\t\r  the\t\r  Arctic\t\r  and\t\r  Eastern\t\r  Siberian\t\r  Sea,\t\r  respectively.\t\r  \t\r  \nIceBridge\t\r  (NASA)\t\r  http://www.nasa.gov/mission_pages/icebridge/index.html\t\r  Operation\t\r   IceBridge\t\r   images\t\r   Earth\u0027s\t\r   polar\t\r   ice\t\r   in\t\r   unprecedented\t\r   detail\t\r   to\t\r   better\t\r   understand\t\r  processes\t\r  that\t\r  connect\t\r  the\t\r  polar\t\r  regions\t\r  with\t\r  the\t\r  global\t\r  climate\t\r  system.\t\r  IceBridge\t\r  utilizes\t\r  a\t\r  highly\t\r  \u003c/p\u003e\n\u003cp /\u003e\n\u003c/div\u003e\n\u003cdiv class\u003d\"page\"\u003e\u003cp /\u003e\n\u003cp\u003e\t\r  \u003c/p\u003e\n\u003cp\u003e\t\r   53\t\r  \n\u003c/p\u003e\n\u003cp\u003especialized\t\r   fleet\t\r   of\t\r   research\t\r   aircraft\t\r   and\t\r   the\t\r   most\t\r   sophisticated\t\r   suite\t\r   of\t\r   innovative\t\r   science\t\r  instruments\t\r  ever\t\r  assembled\t\r  to\t\r  characterize\t\r  annual\t\r  changes\t\r  in\t\r  thickness\t\r  of\t\r  sea\t\r  ice,\t\r  glaciers,\t\r  and\t\r  ice\t\r  sheets.\t\r  In\t\r  addition,\t\r  IceBridge\t\r  collects\t\r  critical\t\r  data\t\r  used\t\r  to\t\r  predict\t\r  the\t\r  response\t\r  of\t\r  earth’s\t\r  polar\t\r  ice\t\r  to\t\r   climate\t\r   change\t\r   and\t\r   resulting\t\r   sea-­‐level\t\r   rise.\t\r   IceBridge\t\r   also\t\r   helps\t\r   bridge\t\r   the\t\r   gap\t\r   in\t\r   polar\t\r  observations\t\r  between\t\r  NASA\u0027s\t\r  ICESat\t\r  satellite\t\r  missions.\t\r  \t\r  \nICECAPS\t\r  (NSF)\t\r  The\t\r   Integrated\t\r   Characterization\t\r   of\t\r   Energy,\t\r   Clouds,\t\r   Atmospheric\t\r   State,\t\r   and\t\r   Precipitation\t\r   over\t\r  Summit\t\r  (ICECAPS)\t\r  project,\t\r  funded\t\r  through\t\r  NSF’s\t\r  Arctic\t\r  Observing\t\r  Network,\t\r  is\t\r  deploying\t\r  a\t\r  suite\t\r  of\t\r  remote\t\r   sensors\t\r   at\t\r   Summit,\t\r   Greenland,\t\r   for\t\r   four\t\r   years,\t\r   beginning\t\r  May\t\r   2010.\t\r   The\t\r   instrument\t\r   suite\t\r  includes\t\r  a\t\r  millimeter-­‐wave\t\r  cloud\t\r  radar,\t\r  Atmospheric\t\r  Emitted\t\r  Radiance\t\r  Interferometer,\t\r  microwave\t\r  radiometer\t\r  profiler,\t\r  a\t\r  high-­‐frequency\t\r  microwave\t\r  radiometer,\t\r  microwave\t\r  precipitation\t\r  sensor,\t\r  and\t\r  other\t\r  instruments.\t\r  The\t\r  project\t\r  also\t\r  includes\t\r  twice-­‐daily\t\r  radiosonde\t\r  launches.\t\r  ARM\t\r  is\t\r  contributing\t\r  to\t\r   this\t\r   campaign\t\r   with\t\r   a\t\r   micropulse\t\r   lidar\t\r   and\t\r   Vaisala\t\r   ceilometer\t\r   to\t\r   gather\t\r   information\t\r   about\t\r  optically\t\r  thin\t\r  clouds\t\r  commonly\t\r  found\t\r  above\t\r  the\t\r  Summit\t\r  site.\t\r  Combined\t\r  measurements\t\r  from\t\r  these\t\r  sensors\t\r  and\t\r   instruments\t\r  will\t\r   result\t\r   in\t\r  a\t\r  comprehensive\t\r  data\t\r  set\t\r  of\t\r  cloud\t\r  properties,\t\r  atmospheric\t\r  state,\t\r  precipitation,\t\r  and\t\r  radiation.\t\r  Data\t\r  from\t\r  ICECAPS\t\r  data\t\r  will\t\r  provide\t\r  a\t\r  complementary\t\r  data\t\r  set\t\r  to\t\r  ongoing\t\r  measurements\t\r  gathered\t\r  at\t\r  ARMs\t\r  North\t\r  Slope\t\r  of\t\r  Alaska\t\r  site\t\r  in\t\r  Barrow,\t\r  and\t\r  the\t\r  SEARCH\t\r  site\t\r  in\t\r  Eureka,\t\r  Canada.\t\r  \nITEX\t\r  –\t\r  International\t\r  Tundra\t\r  Experiment\t\r  http://www.geog.ubc.ca/itex/\t\r  The\t\r  International\t\r  Tundra\t\r  Experiment\t\r  is\t\r  a\t\r  scientific\t\r  network\t\r  of\t\r  experiments\t\r  focusing\t\r  on\t\r  the\t\r  impact\t\r  of\t\r   climate\t\r   change\t\r   on\t\r   selected\t\r   plant\t\r   species\t\r   in\t\r   tundra\t\r   and\t\r   alpine\t\r   vegetation.\t\r   Currently,\t\r   research\t\r  teams\t\r   at\t\r   more\t\r   than\t\r   24\t\r   circumpolar\t\r   sites\t\r   carry\t\r   out\t\r   similar,\t\r   multi-­‐year\t\r   plant\t\r   manipulation\t\r  experiments\t\r   that\t\r   allow\t\r   them\t\r   to\t\r   compare\t\r   annual\t\r   variation\t\r   in\t\r   plant\t\r   performance\t\r   with\t\r   respect\t\r   to\t\r  phenological\t\r  response\t\r  to\t\r  climate\t\r  conditions.\t\r  \t\r  \nMOSAiC\t\r  -­‐\t\r  Multi-­‐disciplinary\t\r  drifting\t\r  Observatory\t\r  for\t\r  the\t\r  Study\t\r  of\t\r  the\t\r  Arctic\t\r  Climate\t\r  http://www.iasc.info\t\r  MOSAiC\t\r   is\t\r   an\t\r   activity\t\r   being\t\r   organized\t\r   under\t\r   the\t\r   auspices\t\r   of\t\r   the\t\r   International\t\r   Arctic\t\r   Science\t\r  Committee\t\r   (IASC).\t\r   It\t\r   will\t\r   be\t\r   fashioned\t\r   after\t\r   SHEBA,\t\r   but\t\r   the\t\r   goal\t\r   is\t\r   to\t\r   substantially\t\r   improve\t\r   on\t\r  SHEBA\t\r   in\t\r   terms\t\r   of\t\r   spatial\t\r   context,\t\r   and\t\r   observations\t\r   of\t\r   aerosols,\t\r   boundary\t\r   layer\t\r   structure,\t\r   and\t\r  measurement\t\r  technology.\t\r  \t\r  \t\r  There\t\r  will\t\r  be\t\r  intensive\t\r  measurements\t\r  in\t\r  the\t\r  atmosphere,\t\r  sea-­‐ice,\t\r  ocean,\t\r  and\t\r  biosphere.\t\r  An\t\r   initial\t\r  deployment,\t\r   targeted\t\r   for\t\r   the\t\r  2017\t\r  timeframe,\t\r   is\t\r  being\t\r  coordinated\t\r  with\t\r  the\t\r  WWRP\t\r   Year\t\r   of\t\r   Polar\t\r   Prediction\t\r   (YOPP)\t\r   activities.\t\r   MOSAiC\t\r   Overview\t\r   Statement:\t\r   “Multi-­‐year,\t\r  detailed,\t\r   and\t\r   comprehensive\t\r  measurements,\t\r   extending\t\r   from\t\r   the\t\r   atmosphere\t\r   through\t\r   the\t\r   sea-­‐ice\t\r  and\t\r   into\t\r   the\t\r   ocean\t\r   of\t\r   the\t\r   central\t\r   Arctic\t\r   Basin\t\r   are\t\r   needed\t\r   to\t\r   improve\t\r   our\t\r   understanding\t\r   and\t\r  modeling\t\r  of\t\r  Arctic\t\r  climate\t\r  and\t\r  weather,\t\r  and\t\r  enhance\t\r  Arctic\t\r  sea-­‐ice\t\r  predictive\t\r  capabilities.\t\r   \t\r  These\t\r  observations\t\r  will\t\r   be\t\r  designed\t\r   to\t\r  provide\t\r  a\t\r  process-­‐level\t\r  understanding\t\r  of\t\r   the\t\r  new\t\r  central\t\r  Arctic\t\r  climate\t\r  system,\t\r  consisting\t\r  of\t\r  dramatically\t\r  less\t\r  and\t\r  thinner\t\r  sea-­‐ice\t\r  than\t\r  in\t\r  the\t\r  recent\t\r  past,\t\r  as\t\r  well\t\r  as\t\r  a\t\r   more\t\r   detailed\t\r   understanding\t\r   of\t\r   the\t\r   processes\t\r   leading\t\r   to\t\r   these\t\r   sea-­‐ice\t\r   changes.\t\r   \t\r   Scientific\t\r  emphasis\t\r  will\t\r  be\t\r  placed\t\r  on\t\r  processes\t\r  that\t\r  transfer\t\r  heat,\t\r  moisture,\t\r  density,\t\r  and\t\r  momentum\t\r  through\t\r  the\t\r   system.\t\r   \t\r   To\t\r   obtain\t\r   the\t\r   needed\t\r   measurements,\t\r   a\t\r   manned,\t\r   transpolar\t\r   drifting\t\r   observatory\t\r   is\t\r  proposed,\t\r   wherein\t\r   an\t\r   ice-­‐hardened\t\r   ship\t\r   serves\t\r   as\t\r   a\t\r   central\t\r   hub\t\r   for\t\r   intensive\t\r   observations\t\r   of\t\r  atmospheric,\t\r  oceanic,\t\r  and\t\r  sea-­‐ice\t\r  properties\t\r  over\t\r  1-­‐2\t\r  years’\t\r  time.\t\r  \t\r  The\t\r  comprehensive\t\r  information\t\r  from\t\r  this\t\r  central\t\r   facility\t\r  will\t\r  be\t\r  expanded\t\r   to\t\r   larger\t\r  spatial\t\r   scales\t\r  using\t\r  a\t\r  coordinated\t\r  network\t\r  of\t\r  distributed\t\r  measurements\t\r  made\t\r  using\t\r  buoys,\t\r  unmanned\t\r  aerial\t\r   systems,\t\r  autonomous\t\r  underwater\t\r  \u003c/p\u003e\n\u003cp /\u003e\n\u003c/div\u003e\n\u003cdiv class\u003d\"page\"\u003e\u003cp /\u003e\n\u003cp\u003e\t\r  \u003c/p\u003e\n\u003cp\u003e\t\r   54\t\r  \n\u003c/p\u003e\n\u003cp\u003evehicles,\t\r   additional\t\r   ships,\t\r   aircraft,\t\r   and\t\r   satellites.\t\r   \t\r   A\t\r   broad\t\r   consortium\t\r   of\t\r   nations\t\r   and\t\r   funding\t\r  agencies\t\r   is\t\r   needed\t\r   to\t\r   facilitate,\t\r   coordinate,\t\r   and\t\r   support\t\r   such\t\r   a\t\r   constellation\t\r   of\t\r   central\t\r   Arctic\t\r  observations.”\t\r  \nNGEE-­‐Arctic\t\r  (DOE)\t\r  http://ngee.ornl.gov/\t\r  The\t\r  Next-­‐Generation\t\r  Ecosystem\t\r  Experiments\t\r  (NGEE)\t\r  project\t\r  will\t\r  use\t\r  observations\t\r  and\t\r  models\t\r  to\t\r  quantify\t\r   the\t\r   response\t\r   of\t\r   physical,\t\r   ecological,\t\r   and\t\r   biogeochemical\t\r   processes\t\r   to\t\r   climatic\t\r   change\t\r  across\t\r  molecular\t\r   to\t\r   landscape\t\r  scales.\t\r  Their\t\r  approach\t\r  addresses\t\r  how\t\r  permafrost\t\r  degradation\t\r   in\t\r  a\t\r  warming\t\r  Arctic,\t\r  and\t\r  the\t\r  associated\t\r  changes\t\r  in\t\r  landscape\t\r  evolution,\t\r  hydrology,\t\r  soil\t\r  biogeochemical\t\r  processes,\t\r  and\t\r  plant\t\r  community\t\r  succession,\t\r  will\t\r  affect\t\r   feedbacks\t\r   to\t\r   the\t\r  climate\t\r  system.\t\r  Field\t\r  and\t\r  lab\t\r  research\t\r  will\t\r  focus\t\r  on\t\r  interactions\t\r  that\t\r  drive\t\r  ecosystem-­‐climate\t\r  feedbacks\t\r  through\t\r  greenhouse\t\r  gas\t\r  fluxes\t\r  and\t\r  changes\t\r  in\t\r  surface\t\r  energy\t\r  balance.\t\r  \t\r  NGEE\t\r   Phase\t\r   1\t\r   includes\t\r   a\t\r   series\t\r   of\t\r   integrated\t\r   field\t\r   observations,\t\r   lab\t\r   experiments,\t\r   and\t\r  modeling\t\r  activities.\t\r   Permafrost\t\r   degradation\t\r   and\t\r   its\t\r   impact\t\r   on\t\r  water,\t\r   nitrogen,\t\r   carbon,\t\r   and\t\r   energy-­‐related\t\r  processes\t\r   will\t\r   be\t\r   investigated\t\r   across\t\r   a\t\r   hierarchy\t\r   of\t\r   scales,\t\r   including\t\r   the\t\r   pore/core,\t\r   plot,\t\r   and\t\r  landscape\t\r   scales.\t\r   Field\t\r   research\t\r   will\t\r   be\t\r   conducted\t\r   in\t\r   Alaska\t\r   on\t\r   the\t\r   North\t\r   Slope\t\r   (Barrow)\t\r   and\t\r  Seward\t\r  Peninsula\t\r  (Council).\t\r  Phase\t\r  1\t\r  modeling\t\r  efforts\t\r  will\t\r  focus\t\r  on\t\r  application\t\r  of\t\r  existing\t\r  models\t\r  to\t\r  evaluate\t\r   their\t\r  predictive\t\r   capability\t\r   across\t\r  a\t\r   range\t\r  of\t\r   spatial\t\r   scales,\t\r   from\t\r  single-­‐column\t\r   to\t\r  plot\t\r   to\t\r  landscape\t\r   scales.\t\r   Model\t\r   results\t\r   will\t\r   be\t\r   compared\t\r   with\t\r   laboratory\t\r   experiments\t\r   and\t\r   field\t\r  observations\t\r  at\t\r  the\t\r  Barrow\t\r  and\t\r  Council\t\r  sites.\t\r  NGEE\t\r   is\t\r   sponsored\t\r   by\t\r   the\t\r   Office\t\r   of\t\r   Biological\t\r   and\t\r   Environmental\t\r   Research\t\r   within\t\r   the\t\r   U.S.\t\r  Department\t\r  of\t\r  Energy’s\t\r  Office\t\r  of\t\r  Science.\t\r  \t\r  \nSEARCH\t\r  –\t\r  Study\t\r  of\t\r  Environmental\t\r  Arctic\t\r  Change\t\r  –\t\r  Arctic\t\r  Atmospheric\t\r  Observatories\t\r  (NOAA)\t\r  http://www.esrl.noaa.gov/psd/arctic/observatories/\t\r  The\t\r  NOAA\t\r  Atmospheric\t\r  Observatory\t\r  program\t\r  has\t\r  established\t\r  long-­‐term,\t\r  intensive\t\r  measurements\t\r  of\t\r  clouds,\t\r  radiation,\t\r  aerosols,\t\r  surface\t\r  energy\t\r  fluxes\t\r  and\t\r  chemistry\t\r  in\t\r  Eureka/Alert\t\r  Canada\t\r  and\t\r  Tiksi,\t\r  Russia.\t\r  These\t\r  measurements\t\r  allow\t\r  comparison\t\r  with\t\r  similar\t\r  observatory\t\r  measurements\t\r  in\t\r  Barrow,\t\r  Alaska.\t\r  \t\r  \nSHEBA\t\r  –\t\r  Surface\t\r  Heat\t\r  Budget\t\r  of\t\r  the\t\r  Arctic\t\r  Ocean,\t\r  September\t\r  1997-­‐October\t\r  1998\t\r  The\t\r  SHEBA\t\r  (Surface\t\r  Heat\t\r  Budget\t\r  of\t\r  the\t\r  Arctic\t\r  Ocean)\t\r  project,\t\r  which\t\r  was\t\r  sponsored\t\r  jointly\t\r  by\t\r  the\t\r  National\t\r   Science\t\r   Foundation’s\t\r   Office\t\r   of\t\r   Polar\t\r   Programs\t\r   Arctic\t\r   System\t\r   Science\t\r   program\t\r   and\t\r   the\t\r  Office\t\r   of\t\r   Naval\t\r   Research’s\t\r   High\t\r   Latitude\t\r   Dynamics\t\r   program,\t\r   included\t\r   a\t\r   field\t\r   experiment\t\r   from\t\r  September\t\r  1997\t\r  through\t\r  October\t\r  1998.\t\r  SHEBA\t\r  was\t\r  governed\t\r  by\t\r  two\t\r  broad\t\r  goals:\t\r  understand\t\r  the\t\r  ice–albedo\t\r  and\t\r  cloud–radiation\t\r   feedback\t\r  mechanisms\t\r  and\t\r  use\t\r   that\t\r  understanding\t\r   to\t\r   improve\t\r   the\t\r  treatment\t\r  of\t\r  the\t\r  Arctic\t\r  in\t\r  large-­‐scale\t\r  climate\t\r  models.\t\r  A\t\r  unique\t\r  aspect\t\r  of\t\r  the\t\r  field\t\r  program\t\r  was\t\r  the\t\r  concurrent\t\r  measurement\t\r  of\t\r  characteristics\t\r  and\t\r  physical\t\r  properties\t\r  of\t\r  the\t\r  atmosphere,\t\r  sea\t\r  ice\t\r  and\t\r  upper\t\r  ocean,\t\r  including\t\r  the\t\r  fluxes\t\r  that\t\r  occur\t\r  at\t\r  the\t\r  air-­‐ice,\t\r  ice-­‐ocean,\t\r  and\t\r  air-­‐ocean\t\r  interfaces.\t\r  \nTCCON\t\r  –\t\r  the\t\r  Total\t\r  Carbon\t\r  Column\t\r  Observing\t\r  Network\t\r  http://tccon-­‐wiki.caltech.edu/\t\r  TCCON\t\r   is\t\r   a\t\r   network\t\r   of\t\r   ground-­‐based\t\r   Fourier\t\r   Transform\t\r   Spectrometers\t\r   recording\t\r   direct\t\r   solar\t\r  spectra\t\r   in\t\r   the\t\r   near-­‐infrared\t\r   spectral\t\r   region.\t\r   From\t\r   these\t\r   spectra,\t\r   accurate\t\r   and\t\r   precise\t\r   column-­‐averaged\t\r   abundance\t\r   of\t\r   CO2,\t\r   CH4,\t\r  N2O,\t\r  HF,\t\r   CO,\t\r  H2O,\t\r   and\t\r  HDO\t\r  are\t\r   retrieved.\t\r   The\t\r  web\t\r   site\t\r   lists\t\r   19\t\r  \u003c/p\u003e\n\u003cp /\u003e\n\u003c/div\u003e\n\u003cdiv class\u003d\"page\"\u003e\u003cp /\u003e\n\u003cp\u003e\t\r  \u003c/p\u003e\n\u003cp\u003e\t\r   55\t\r  \n\u003c/p\u003e\n\u003cp\u003eoperational\t\r  sites;\t\r  three\t\r  sites\t\r  are\t\r  north\t\r  of\t\r  60°N,\t\r  but\t\r  only\t\r  two\t\r  are\t\r  operational.\t\r  \t\r  \nTransCom\t\r  http://transcom.project.asu.edu/index.php\t\r  The\t\r   Atmospheric\t\r   Tracer\t\r   Transport\t\r   Model\t\r   Intercomparison\t\r   Project\t\r   (TransCom)\t\r   was\t\r   created\t\r   to\t\r  quantify\t\r   and\t\r   diagnose\t\r   the\t\r   uncertainty\t\r   in\t\r   inversion\t\r   calculations\t\r   of\t\r   the\t\r   global\t\r   carbon\t\r   budget\t\r   that\t\r  result\t\r  from\t\r  errors\t\r  in\t\r  simulated\t\r  atmospheric\t\r  transport.\t\r  \t\r  \t\r  \t\r   \t\r  \u003c/p\u003e\n\u003cp /\u003e\n\u003c/div\u003e\n\u003cdiv class\u003d\"page\"\u003e\u003cp /\u003e\n\u003cp\u003e\t\r  \u003c/p\u003e\n\u003cp\u003e\t\r   56\t\r  \n\u003c/p\u003e\n\u003cp\u003eAppendix\t\r  C:\t\r  Contributors\t\r  to\t\r  this\t\r  Report\t\r  David\t\r  Adamec,\t\r  NASA/Goddard\t\r  Space\t\r  Flight\t\r  Center\t\r  Kevin\t\r  Arrigo,\t\r  Stanford\t\r  University\t\r  Jeff\t\r  Bowman,\t\r  University\t\r  of\t\r  Washington\t\r  Jing\t\r  Chen,\t\r  University\t\r  of\t\r  Toronto\t\r  Michael\t\r  Coe,\t\r  Woods\t\r  Hole\t\r  Research\t\r  Center\t\r  Jim\t\r  Collatz,\t\r  NASA/Goddard\t\r  Space\t\r  Flight\t\r  Center\t\r  Josefino\t\r  Comiso,\t\r  NASA/Goddard\t\r  Space\t\r  Flight\t\r  Center\t\r  Clara\t\r  Deal,\t\r  International\t\r  Arctic\t\r  Research\t\r  Center,\t\r  University\t\r  of\t\r  Alaska,\t\r  Fairbanks.\t\r  Anthony\t\r  del\t\r  Genio,\t\r  NASA/GISS\t\r  Ray\t\r  Desjardins,\t\r  Agriculture\t\r  \u0026amp;\t\r  Agri-­‐Food\t\r  Canada\t\r  Ian\t\r  Eisenman,\t\r  California\t\r  Institute\t\r  of\t\r  Technology\t\r  and\t\r  University\t\r  of\t\r  Washington\t\r  Scott\t\r  Elliot,\t\r  Los\t\r  Alamos\t\r  National\t\r  Laboratory\t\r  Ann\t\r  Fridlind,\t\r  NASA/GISS\t\r  Steve\t\r  Frolking,\t\r  University\t\r  of\t\r  New\t\r  Hampshire\t\r  Scott\t\r  Goetz,\t\r  Woods\t\r  Hole\t\r  Research\t\r  Center\t\r  Robert\t\r  Harriss,\t\r  Houston\t\r  Advanced\t\r  Research\t\r  Ctr.\t\r  Daniel\t\r  Jacob,\t\r  Harvard\t\r  University\t\r  Eric\t\r  Kasischke,\t\r  University\t\r  of\t\r  Maryland\t\r  Randal\t\r  Koster,\t\r  NASA/Goddard\t\r  Space\t\r  Flight\t\r  Center\t\r  Robin\t\r  Kovach,\t\r  NASA/Goddard\t\r  Space\t\r  Flight\t\r  Center\t\r  Charles\t\r  Koven,\t\r  Lawrence\t\r  Berkeley\t\r  National\t\r  Lab.\t\r  Dennis\t\r  Lettenmaier,\t\r  University\t\r  of\t\r  Washington\t\r  Sergei\t\r  Marchenko,\t\r  University\t\r  of\t\r  Alaska\t\r  Wieslaw\t\r  Maslowski,\t\r  Naval\t\r  Postgraduate\t\r  School\t\r  Andrea\t\r  Molod,\t\r  NASA/Goddard\t\r  Space\t\r  Flight\t\r  Center\t\r  Elizabeth\t\r  Nelson,\t\r  NASA/Goddard\t\r  Space\t\r  Flight\t\r  Center\t\r  Lesley\t\r  Ott,\t\r  NASA/Goddard\t\r  Space\t\r  Flight\t\r  Center\t\r  Steven\t\r  Pawson,\t\r  NASA/Goddard\t\r  Space\t\r  Flight\t\r  Center\t\r  \t\r  Andrey\t\r  Proshutinsky,\t\r  Woods\t\r  Hole\t\r  Oceanographic\t\r  Institution\t\r  David\t\r  Randall,\t\r  Colorado\t\r  State\t\r  University\t\r  Andrew\t\r  Richardson,\t\r  Harvard\t\r  University\t\r  Michele\t\r  Rienecker,\t\r  NASA/Goddard\t\r  Space\t\r  Flight\t\r  Center\t\r  Gavin\t\r  Schmidt,\t\r  NASA/GISS\t\r  Piers\t\r  Sellers,\t\r  NASA/Goddard\t\r  Space\t\r  Flight\t\r  Center\t\r  Elena\t\r  Shevliakova,\t\r  Princeton\t\r  University\t\r  Matthew\t\r  Shupe,\t\r  NOAA/Earth\t\r  System\t\r  Research\t\r  Laboratory\t\r  Julienne\t\r  Stroeve,\t\r  National\t\r  Snow\t\r  and\t\r  Ice\t\r  Data\t\r  Center\t\r  Max\t\r  Suarez,\t\r  NASA/Goddard\t\r  Space\t\r  Flight\t\r  Center\t\r  Peter\t\r  Thornton,\t\r  Oak\t\r  Ridge\t\r  National\t\r  Laboratory\t\r  Compton\t\r  Tucker,\t\r  NASA/Goddard\t\r  Space\t\r  Flight\t\r  Center\t\r  Steve\t\r  Vavrus,\t\r  University\t\r  of\t\r  Wisconsin-­‐Madison\t\r  Hailong\t\r  Wang,\t\r  Pacific\t\r  Northwest\t\r  National\t\r  Laboratory\t\r  \t\r  \t\r  Support\t\r  was\t\r  provided\t\r  by\t\r  NASA/HQ\t\r  program\t\r  managers\t\r  –\t\r  Jack\t\r  Kaye,\t\r  Diane\t\r  Wickland,\t\r  Jay\t\r  Al-­‐Saadi,\t\r  Paula\t\r  Bontempi,\t\r  David\t\r  Considine,\t\r  Hal\t\r  Maring\t\r  and\t\r  Tom\t\r  Wagner\t\r  \t\r  –\t\r  and\t\r  is\t\r  gratefully\t\r  acknowledged.\t\r  \u003c/p\u003e\n\u003cp /\u003e\n\u003c/div\u003e\n\u003cdiv class\u003d\"page\"\u003e\u003cp /\u003e\n\u003cp\u003e\t\r  \u003c/p\u003e\n\u003cp\u003e\t\r   57\t\r  \n\u003c/p\u003e\n\u003cp\u003eAppendix\t\r  D:\t\r  Workshop\t\r  Agenda\t\r  \nMay 22  \n\u003c/p\u003e\n\u003cp\u003e9:00 AM Welcome (R. Harriss and D. Wickland) \n9:15 AM Logistics (D. Adamec) \n9:20 AM Physical Climate System Overview  (D. Randall) \n10:00 AM Biogeochemical Climate System  (S. Frolking) \n10:40 AM BREAK \n11:00 AM ABoVE  (S. Goetz) \n11:15 AM NGEE  (P. Thornton) \n11:30 AM ARCTAS (D. Jacob) \n11:45 AM Report for NSF (W. Maslowski) \n12:00 PM Charge to Working Groups (P. Sellers) \n \n12:15 PM LUNCH \n\u003c/p\u003e\n\u003cp\u003eBreakout Sessions  \n\u003c/p\u003e\n\u003cp\u003e1:15PM Biogeochemical \u0026amp; Physical Climate Breakout Session \n\u003c/p\u003e\n\u003cp\u003e2:45PM BREAK \n\u003c/p\u003e\n\u003cp\u003e3:00PM Biogeochemical \u0026amp; Physical Climate Breakout Session \n4:30PM Plenary Discussion – Summary, Issues and concerns  \n5:00PM Adjourn \n\u003c/p\u003e\n\u003cp\u003e5:30PM Social at GSFC Recreational Center \n\u003c/p\u003e\n\u003cp\u003eMay 23  \n\u003c/p\u003e\n\u003cp\u003e9:00 AM Biogeochemical \u0026amp; Physical Climate Breakout Session \n\u003c/p\u003e\n\u003cp\u003e10:20 AM BREAK \n\u003c/p\u003e\n\u003cp\u003e10:40 AM Biogeochemical \u0026amp; Physical Climate Breakout Session \n\u003c/p\u003e\n\u003cp\u003e11:30 AM LUNCH \n\u003c/p\u003e\n\u003cp\u003e1:30 PM Plenary Discussion -  Progress Report, Q\u0026amp;A \n\u003c/p\u003e\n\u003cp\u003e2:30 PM BREAK \n\u003c/p\u003e\n\u003cp\u003e3:00 PM Biogeochemical \u0026amp; Physical Climate Breakout Session \n\u003c/p\u003e\n\u003cp\u003e5:00 PM Adjourn \n\u003c/p\u003e\n\u003cp\u003eMay 24  \n\u003c/p\u003e\n\u003cp\u003e9:00 AM Report Writing (Breakout session leads and all interested parties) \n\u003c/p\u003e\n\u003cp\u003e10:20 AM BREAK \n\u003c/p\u003e\n\u003cp\u003e10:40 AM Report Writing (Breakout session leads and all interested parties) \n11:40 AM Final Issues and Assignments \n\u003c/p\u003e\n\u003cp\u003e12:00PM Workshop Adjourns \t\r   \t\r  \u003c/p\u003e\n\u003cp /\u003e\n\u003c/div\u003e\n\u003cdiv class\u003d\"page\"\u003e\u003cp /\u003e\n\u003cp\u003e\t\r  \u003c/p\u003e\n\u003cp\u003e\t\r   58\t\r  \n\u003c/p\u003e\n\u003cp\u003eAppendix\t\r  D:\t\r  Workshop\t\r  Attendees\t\r  David\t\r  Adamec\t\r  Earth\t\r  Sciences\t\r  Division,\t\r  Code\t\r  610\t\r  NASA/Goddard\t\r  Space\t\r  Flight\t\r  Center\t\r  Greenbelt,\t\r  MD\t\r  20771\t\r  \n Melissa\t\r  Burt\t\r  221\t\r  Atmospheric\t\r  Science\t\r  West\t\r  Colorado\t\r  State\t\r  University\t\r  Fort\t\r  Collins,\t\r  CO\t\r  80523\t\r  \t\r  Jing\t\r  Chen\t\r  Dept.\t\r  of\t\r  Geography\t\r  and\t\r  Program\t\r  in\t\r  Planning\t\r  University\t\r  of\t\r  Toronto\t\r  Toronto,\t\r  Ontario\t\r  M5S\t\r  3G3\t\r  CANADA\t\r  \t\r  Michael\t\r  T.\t\r  Coe\t\r  Woods\t\r  Hole\t\r  Research\t\r  Center\t\r  149\t\r  Woods\t\r  Hole\t\r  Road\t\r  Falmouth,\t\r  MA\t\r  \t\r  02540-­‐1644\t\r  \t\r  Jim\t\r  Collatz\t\r  Biospheric\t\r  Sciences\t\r  Laboratory,\t\r  Code\t\r  618\t\r  NASA/Goddard\t\r  Space\t\r  Flight\t\r  Center\t\r  Greenbelt,\t\r  MD\t\r  20771\t\r  \t\r  Ray\t\r  Desjardins\t\r  960\t\r  Carling\t\r  Avenue,\t\r  Room\t\r  3020\t\r  Eastern\t\r  Cereal\t\r  and\t\r  Oilseed\t\r  Research\t\r  Centre\t\r  Ottawa,\t\r  Ontario\t\r  K1A\t\r  0C6\t\r  CANADA\t\r  \t\r  Steve\t\r  Frolking\t\r  Institute\t\r  for\t\r  the\t\r  Study\t\r  of\t\r  Earth,\t\r  Oceans,\t\r  and\t\r  Space\t\r  Morse\t\r  Hall\t\r  \t\r  University\t\r  of\t\r  New\t\r  Hampshire\t\r  Durham,\t\r  NH\t\r  03824-­‐3525\t\r  \t\r  Scott\t\r  Goetz\t\r  Woods\t\r  Hole\t\r  Research\t\r  Center\t\r  149\t\r  Woods\t\r  Hole\t\r  Road\t\r  Falmouth,\t\r  MA\t\r  \t\r  02540-­‐1644\t\r  \t\r  Robert\t\r  Harriss\t\r  Houston\t\r  Advanced\t\r  Research\t\r  Center\t\r  4800\t\r  Research\t\r  Forest\t\r  Drive\t\r  The\t\r  Woodlands,\t\r  TX\t\r  \t\r  77381\t\r  \n\u003c/p\u003e\n\u003cp\u003eDaniel\t\r  Jacob\t\r  Division\t\r  of\t\r  Engineering\t\r  and\t\r  Applied\t\r  Science\t\r  \u0026amp;\t\r  Dept.\t\r  of\t\r  Earth\t\r  \u0026amp;\t\r  Planetary\t\r  Sciences\t\r  Pierce\t\r  Hall\t\r  Harvard\t\r  University\t\r  Cambridge,\t\r  MA\t\r  \t\r  02138\t\r  \t\r  Randal\t\r  Koster\t\r  GMAO,\t\r  Code\t\r  610.1\t\r  NASA/Goddard\t\r  Space\t\r  Flight\t\r  Center\t\r  Greenbelt,\t\r  MD\t\r  20771\t\r  \n Charles\t\r  Koven\t\r  Lawrence\t\r  Berkeley\t\r  National\t\r  Lab\t\r  1\t\r  Cyclotron\t\r  Road\t\r  Mail\t\r  Stop\t\r  90-­‐1116\t\r  Berkeley,\t\r  CA\t\r  94720\t\r  \t\r  Dennis\t\r  Lettenmaier\t\r  Civil\t\r  \u0026amp;\t\r  Environmental\t\r  Engineering\t\r  University\t\r  of\t\r  Washington\t\r  Seattle,\t\r  WA\t\r  98195\t\r  \t\r  Sergei\t\r  Marchenko\t\r  Geophysical\t\r  Institute\t\r  University\t\r  of\t\r  Alaska\t\r  Fairbanks\t\r  Fairbanks,\t\r  AK\t\r  99775\t\r  \t\r  Wieslaw\t\r  Maslowski\t\r  Department\t\r  of\t\r  Oceanography\t\r  Naval\t\r  Postgraduate\t\r  School\t\r  Monterey,\t\r  CA,\t\r  93943-­‐5122\t\r  \t\r  Andrea\t\r  Molod\t\r  GMAO,\t\r  Code\t\r  610.1\t\r  NASA/Goddard\t\r  Space\t\r  Flight\t\r  Center\t\r  Greenbelt,\t\r  MD\t\r  20771\t\r  \t\r  Lesley\t\r  Ott\t\r  GMAO,\t\r  Code\t\r  610.1\t\r  NASA/Goddard\t\r  Space\t\r  Flight\t\r  Center\t\r  Greenbelt,\t\r  MD\t\r  20771\t\r  \t\r  \t\r  Steven\t\r  Pawson\t\r  GMAO,\t\r  Code\t\r  610.1\t\r  NASA/Goddard\t\r  Space\t\r  Flight\t\r  Center\t\r  Greenbelt,\t\r  MD\t\r  20771\t\r  \t\r  \u003c/p\u003e\n\u003cp /\u003e\n\u003c/div\u003e\n\u003cdiv class\u003d\"page\"\u003e\u003cp /\u003e\n\u003cp\u003e\t\r  \u003c/p\u003e\n\u003cp\u003e\t\r   59\t\r  \n\u003c/p\u003e\n\u003cp\u003eAndrey\t\r  Proshutinsky\t\r  Woods\t\r  Hole\t\r  Oceanographic\t\r  Institution\t\r  \t\r  266\t\r  Woods\t\r  Hole\t\r  Rd.\t\r  MS#\t\r  29\t\r  \t\r  Woods\t\r  Hole,\t\r  MA\t\r  02543-­‐1050\t\r  \n David\t\r  Randall\t\r  Department\t\r  of\t\r  Atmospheric\t\r  Science\t\r  Colorado\t\r  State\t\r  University\t\r  Fort\t\r  Collins,\t\r  CO\t\r  80523-­‐1371\t\r  \t\r  Michele\t\r  Rienecker\t\r  GMAO,\t\r  Code\t\r  610.1\t\r  NASA/Goddard\t\r  Space\t\r  Flight\t\r  Center\t\r  Greenbelt,\t\r  MD\t\r  20771\t\r  \t\r  Piers\t\r  Sellers\t\r  \t\r  Sciences\t\r  \u0026amp;\t\r  Exploration\t\r  Directorate,\t\r  Code\t\r  600\t\r  NASA/Goddard\t\r  Space\t\r  Flight\t\r  Center\t\r  Greenbelt,\t\r  MD\t\r  20771\t\r  \t\r  Elana\t\r  Shevliakova\t\r  Dept.\t\r  of\t\r  Ecology\t\r  and\t\r  Evolutionary\t\r  Biology\t\r  Guyot\t\r  Hall\t\r  \t\r  Princeton\t\r  University\t\r  Princeton,\t\r  NJ\t\r  \t\r  08544\t\r  \t\r  Gavin\t\r  Schmidt,\t\r  \t\r  GISS,\t\r  Code\t\r  611\t\r  NASA/Goddard\t\r  Space\t\r  Flight\t\r  Center\t\r  Greenbelt,\t\r  MD\t\r  20771\t\r  \n\u003c/p\u003e\n\u003cp\u003eMax\t\r  Suarez\t\r  GMAO,\t\r  Code\t\r  610.1\t\r  NASA/Goddard\t\r  Space\t\r  Flight\t\r  Center\t\r  Greenbelt,\t\r  MD\t\r  20771\t\r  \t\r  Peter\t\r  Thornton\t\r  ORNL\t\r  Climate\t\r  Change\t\r  Science\t\r  Institute\t\r  PO\t\r  BOX\t\r  2800,\t\r  MS-­‐6301\t\r  Oak\t\r  Ridge,\t\r  TN\t\r  37831-­‐6301\t\r  \t\r  Compton\t\r  Tucker\t\r  Earth\t\r  Sciences\t\r  Division,\t\r  Code\t\r  610\t\r  NASA/Goddard\t\r  Space\t\r  Flight\t\r  Center\t\r  \nGreenbelt, MD 20771\t\r  \t\r  Hailong\t\r  Wang\t\r  Pacific\t\r  Northwest\t\r  National\t\r  Laboratory\t\r  PO\t\r  Box\t\r  999\t\r  Richland,\t\r  WA\t\r  99352\t\r  \t\r  \t\r  Diane\t\r  Wickland\t\r  SMD,\t\r  Earth\t\r  Science\t\r  Division\t\r  NASA\t\r  Headquarters\t\r  Washington,\t\r  DC,\t\r  20546-­‐0001\t\r  \t\r  \t\r  \t\r  \t\r  \t\r  \t\r  \t\r  \n\u003c/p\u003e\n\u003cp\u003e  \u003c/p\u003e\n\u003cp /\u003e\n\u003c/div\u003e\n\u003cdiv class\u003d\"page\"\u003e\u003cp /\u003e\n\u003cp\u003e\t\r  \u003c/p\u003e\n\u003cp\u003e\t\r  \n\u003c/p\u003e\n\u003cp\u003e  \u003c/p\u003e\n\u003cp /\u003e\n\u003c/div\u003e\n\u003cdiv class\u003d\"page\"\u003e\u003cp /\u003e\n\u003cp\u003e\t\r  \u003c/p\u003e\n\u003cp\u003e\t\r  \n\u003c/p\u003e\n\u003cp\u003e \u003c/p\u003e\n\u003cp /\u003e\n\u003c/div\u003e\n\u003cdiv class\u003d\"page\"\u003e\u003cp /\u003e\n\u003cp\u003e\t\r  \u003c/p\u003e\n\u003cp\u003e\t\r  \n\u003c/p\u003e\n\u003cp\u003e \u003c/p\u003e\n\u003cp /\u003e\n\u003c/div\u003e\n\u003c/body\u003e\u003c/html\u003e","X-TIKA:parse_time_millis":"3239","access_permission:assemble_document":"true","access_permission:can_modify":"true","access_permission:can_print":"true","access_permission:can_print_degraded":"true","access_permission:extract_content":"true","access_permission:extract_for_accessibility":"true","access_permission:fill_in_form":"true","access_permission:modify_annotations":"true","created":"Fri Nov 23 13:17:44 PST 2012","creator":"Rienecker, Michele M. (GSFC-6101)","date":"2012-11-23T21:17:44Z","dc:creator":"Rienecker, Michele M. (GSFC-6101)","dc:format":"application/pdf; version\u003d1.4","dc:subject":"","dc:title":"Microsoft Word - ABZ_Workshop_Report_Draft_Nov23.docx","dcterms:created":"2012-11-23T21:17:44Z","dcterms:modified":"2012-11-23T21:17:44Z","grobid:header_Address":"null, null null null ","grobid:header_Affiliation":"1","grobid:header_Authors":"Piers  Sellers 1 Michele  Rienecker 1 Steve  Frolking 1 David  Randall 1 ","grobid:header_Class":"org.apache.tika.metadata.Metadata","grobid:header_FullAffiliations":"[Affiliation {orgName\u003d, address\u003dnull, null null null}[Affiliation {orgName\u003d, address\u003dnull, null null null}]","grobid:header_TEIJSONSource":"{\"TEI\":{\"xmlns\":\"http://www.tei-c.org/ns/1.0\",\"teiHeader\":{\"xml:lang\":\"en\",\"profileDesc\":{\"abstract\":\"\"},\"encodingDesc\":{\"appInfo\":{\"application\":{\"ref\":{\"content\":\"GROBID - A machine learning software for extracting information from scholarly documents\",\"target\":\"https://github.com/kermitt2/grobid\"},\"ident\":\"GROBID\",\"version\":\"0.4.1\",\"when\":\"2016-03-25T04:57+0000\"}}},\"fileDesc\":{\"titleStmt\":{\"title\":{\"level\":\"a\",\"type\":\"main\",\"content\":\"Earth System Modeling and Field Experiments in the Arctic-­\\u2010Boreal Zone NASA Workshop Report\"}},\"sourceDesc\":{\"biblStruct\":{\"analytic\":{\"author\":[{\"affiliation\":{\"orgName\":{\"type\":\"laboratory\",\"content\":\"National Aeronautics and Space Administration\"}},\"persName\":{\"forename\":{\"type\":\"first\",\"content\":\"Piers\"},\"surname\":\"Sellers\"}},{\"affiliation\":{\"orgName\":{\"type\":\"laboratory\",\"content\":\"National Aeronautics and Space Administration\"}},\"persName\":{\"forename\":{\"type\":\"first\",\"content\":\"Michele\"},\"surname\":\"Rienecker\"}},{\"affiliation\":{\"orgName\":{\"type\":\"laboratory\",\"content\":\"National Aeronautics and Space Administration\"}},\"persName\":{\"forename\":{\"type\":\"first\",\"content\":\"Steve\"},\"surname\":\"Frolking\"}},{\"affiliation\":{\"orgName\":{\"type\":\"laboratory\",\"content\":\"National Aeronautics and Space Administration\"}},\"persName\":{\"forename\":{\"type\":\"first\",\"content\":\"David\"},\"surname\":\"Randall\"}}],\"title\":{\"level\":\"a\",\"type\":\"main\",\"content\":\"Earth System Modeling and Field Experiments in the Arctic-­\\u2010Boreal Zone NASA Workshop Report\"}},\"monogr\":{\"imprint\":{\"date\":{\"type\":\"published\",\"content\":\"22-­\\u201024 May 2012 November 2012\"}}}}},\"publicationStmt\":{\"date\":\"22-­\\u201024 May 2012 November 2012\",\"publisher\":\"\",\"availability\":{\"licence\":\"\",\"status\":\"unknown\"}}}},\"xsi:schemaLocation\":\"http://www.tei-c.org/ns/1.0 /Users/Shashank/src/grobid/grobid-home/schemas/xsd/Grobid.xsd\",\"xmlns:xlink\":\"http://www.w3.org/1999/xlink\",\"xmlns:xsi\":\"http://www.w3.org/2001/XMLSchema-instance\",\"text\":{\"xml:lang\":\"en\"}}}","grobid:header_TEIXMLSource":"\u003c?xml version\u003d\"1.0\" encoding\u003d\"UTF-8\"?\u003e\n\u003cTEI xmlns\u003d\"http://www.tei-c.org/ns/1.0\" \nxmlns:xsi\u003d\"http://www.w3.org/2001/XMLSchema-instance\" \nxsi:schemaLocation\u003d\"http://www.tei-c.org/ns/1.0 /Users/Shashank/src/grobid/grobid-home/schemas/xsd/Grobid.xsd\"\n xmlns:xlink\u003d\"http://www.w3.org/1999/xlink\"\u003e\n\t\u003cteiHeader xml:lang\u003d\"en\"\u003e\n\t\t\u003cencodingDesc\u003e\n\t\t\t\u003cappInfo\u003e\n\t\t\t\t\u003capplication version\u003d\"0.4.1\" ident\u003d\"GROBID\" when\u003d\"2016-03-25T04:57+0000\"\u003e\n\t\t\t\t\t\u003cref target\u003d\"https://github.com/kermitt2/grobid\"\u003eGROBID - A machine learning software for extracting information from scholarly documents\u003c/ref\u003e\n\t\t\t\t\u003c/application\u003e\n\t\t\t\u003c/appInfo\u003e\n\t\t\u003c/encodingDesc\u003e\n\t\t\u003cfileDesc\u003e\n\t\t\t\u003ctitleStmt\u003e\n\t\t\t\t\u003ctitle level\u003d\"a\" type\u003d\"main\"\u003eEarth System Modeling and Field Experiments in the Arctic-­‐Boreal Zone NASA Workshop Report\u003c/title\u003e\n\t\t\t\u003c/titleStmt\u003e\n\t\t\t\u003cpublicationStmt\u003e\n\t\t\t\t\u003cpublisher/\u003e\n\t\t\t\t\u003cavailability status\u003d\"unknown\"\u003e\u003clicence/\u003e\u003c/availability\u003e\n\t\t\t\t\u003cdate\u003e22-­‐24 May 2012 November 2012\u003c/date\u003e\n\t\t\t\u003c/publicationStmt\u003e\n\t\t\t\u003csourceDesc\u003e\n\t\t\t\t\u003cbiblStruct\u003e\n\t\t\t\t\t\u003canalytic\u003e\n\t\t\t\t\t\t\u003cauthor\u003e\n\t\t\t\t\t\t\t\u003cpersName\u003e\n\t\t\t\t\t\t\t\t\u003cforename type\u003d\"first\"\u003ePiers\u003c/forename\u003e\n\t\t\t\t\t\t\t\t\u003csurname\u003eSellers\u003c/surname\u003e\n\t\t\t\t\t\t\t\u003c/persName\u003e\n\t\t\t\t\t\t\t\u003caffiliation\u003e\n\t\t\t\t\t\t\t\t\u003corgName type\u003d\"laboratory\"\u003eNational Aeronautics and Space Administration\u003c/orgName\u003e\n\t\t\t\t\t\t\t\u003c/affiliation\u003e\n\t\t\t\t\t\t\u003c/author\u003e\n\t\t\t\t\t\t\u003cauthor\u003e\n\t\t\t\t\t\t\t\u003cpersName\u003e\n\t\t\t\t\t\t\t\t\u003cforename type\u003d\"first\"\u003eMichele\u003c/forename\u003e\n\t\t\t\t\t\t\t\t\u003csurname\u003eRienecker\u003c/surname\u003e\n\t\t\t\t\t\t\t\u003c/persName\u003e\n\t\t\t\t\t\t\t\u003caffiliation\u003e\n\t\t\t\t\t\t\t\t\u003corgName type\u003d\"laboratory\"\u003eNational Aeronautics and Space Administration\u003c/orgName\u003e\n\t\t\t\t\t\t\t\u003c/affiliation\u003e\n\t\t\t\t\t\t\u003c/author\u003e\n\t\t\t\t\t\t\u003cauthor\u003e\n\t\t\t\t\t\t\t\u003cpersName\u003e\n\t\t\t\t\t\t\t\t\u003cforename type\u003d\"first\"\u003eSteve\u003c/forename\u003e\n\t\t\t\t\t\t\t\t\u003csurname\u003eFrolking\u003c/surname\u003e\n\t\t\t\t\t\t\t\u003c/persName\u003e\n\t\t\t\t\t\t\t\u003caffiliation\u003e\n\t\t\t\t\t\t\t\t\u003corgName type\u003d\"laboratory\"\u003eNational Aeronautics and Space Administration\u003c/orgName\u003e\n\t\t\t\t\t\t\t\u003c/affiliation\u003e\n\t\t\t\t\t\t\u003c/author\u003e\n\t\t\t\t\t\t\u003cauthor\u003e\n\t\t\t\t\t\t\t\u003cpersName\u003e\n\t\t\t\t\t\t\t\t\u003cforename type\u003d\"first\"\u003eDavid\u003c/forename\u003e\n\t\t\t\t\t\t\t\t\u003csurname\u003eRandall\u003c/surname\u003e\n\t\t\t\t\t\t\t\u003c/persName\u003e\n\t\t\t\t\t\t\t\u003caffiliation\u003e\n\t\t\t\t\t\t\t\t\u003corgName type\u003d\"laboratory\"\u003eNational Aeronautics and Space Administration\u003c/orgName\u003e\n\t\t\t\t\t\t\t\u003c/affiliation\u003e\n\t\t\t\t\t\t\u003c/author\u003e\n\t\t\t\t\t\t\u003ctitle level\u003d\"a\" type\u003d\"main\"\u003eEarth System Modeling and Field Experiments in the Arctic-­‐Boreal Zone NASA Workshop Report\u003c/title\u003e\n\t\t\t\t\t\u003c/analytic\u003e\n\t\t\t\t\t\u003cmonogr\u003e\n\t\t\t\t\t\t\u003cimprint\u003e\n\t\t\t\t\t\t\t\u003cdate type\u003d\"published\"\u003e22-­‐24 May 2012 November 2012\u003c/date\u003e\n\t\t\t\t\t\t\u003c/imprint\u003e\n\t\t\t\t\t\u003c/monogr\u003e\n\t\t\t\t\u003c/biblStruct\u003e\n\t\t\t\u003c/sourceDesc\u003e\n\t\t\u003c/fileDesc\u003e\n\t\t\u003cprofileDesc\u003e\n\t\t\t\u003cabstract/\u003e\n\t\t\u003c/profileDesc\u003e\n\t\u003c/teiHeader\u003e\n\t\u003ctext xml:lang\u003d\"en\"\u003e\n\t\u003c/text\u003e\n\u003c/TEI\u003e\n","grobid:header_Title":"Earth System Modeling and Field Experiments in the Arctic-­‐Boreal Zone NASA Workshop Report","meta:author":"Rienecker, Michele M. (GSFC-6101)","meta:creation-date":"2012-11-23T21:17:44Z","meta:keyword":"","meta:save-date":"2012-11-23T21:17:44Z","modified":"2012-11-23T21:17:44Z","pdf:PDFVersion":"1.4","pdf:encrypted":"false","producer":"Mac OS X 10.7.5 Quartz PDFContext","resourceName":"DC83BF75177C2A4828762BA4E8362E24117BB624D8EC510CF56A2DF347450194","subject":"","title":"Microsoft Word - ABZ_Workshop_Report_Draft_Nov23.docx","xmp:CreatorTool":"Word","xmpTPg:NPages":"74"}]